Workbook
Name enum_aa_booleanstatus: [1]importDropDownContent!$C$2:$C$3
Name enum_bd_assetmanage: [1]importDropDownContent!$A$2:$A$6
Name enum_taxDeductible: [1]importDropDownContent!$B$2:$B$3
Name refer_ucf_org_center.org_pure_tree_ref0: [1]参照!$C$3:$C$3

Sheet 资金报表科目
A1: 一级 | B1: 二级 | C1: 名词解释
A2: 业务收入 | B2: 平台硬件销售收入 | C2: 各个平台货款收入-退款部分。
B3: 服务收款 | C3: 目前业务暂不涉及，主要是后续用户达到一定量级后，会给用户提供其他AI服务
B4: 平台补贴收入
A5: 售后收入 | B5: 客户赔偿款 | C5: 用户因为机器以及零配件损坏，支付的赔偿款
B6: 供应商赔偿款 | C6: 供应商（合作商、物流、仓储供应商、员工等）因为机器以及零配件损坏，支付的赔偿款
A7: 营业外收入 | B7: 政府补贴收入 | C7: 从政府部门获取的各类补贴收益，包含注册资本金返还、房租补贴、研发补贴、高新技术补助等
B8: 利息收入 | C8: 理财收入、利息收入
B9: 其他收入 | C9: 验证款项等
B10: 收入合计
A11: 往来款项收入 | B11: 内部往来收入 | C11: 合并内关联方的往来款项
B12: 外部往来收入 | C12: 合并报表外的往来款项
A13: 投资款收入 | B13: 内部投资款收入 | C13: 合并内关联方的投资款，包含香港公司的对内投资
B14: 外部投资款收入
B15: 收款合计
A16: 往来款项支出 | B16: 内部往来支出 | C16: 合并内关联方的往来款项
B17: 外部往来支出 | C17: 合并报表外的往来款项
A18: 投资款支出 | B18: 内部投资款支出 | C18: 合并内关联方的投资款，包含香港公司的对内投资
A19: 人工成本 | B19: 实发工资 | C19: 销售、客服提成包含其中
B20: 奖金 | C20: 特殊项目奖金或者年终奖
B21: 社保（单位+个人）
B22: 公积金（单位+个人）
B23: 个税
B24: 福利费
B25: 补偿金
B26: 派遣费用 | C26: 支付给外包劳务公司的
B27: 顾问费 | C27: 支付给提供个人劳务的服务费
B28: 其他人工成本
A29: BONG MAX | B29: TCL平板电脑款项 | C29: TCL提货的款项支出，不包含前期的研发支出
B30: 保护套 | C30: 提货的款项支出，不包含模具等前期开发费用
B31: 包装盒 | C31: 提货的款项支出，不包含前期开发费用
B32: 充电器费用 | C32: 提货的款项支出，不包含前期开发费用
B33: 指学镜 | C33: 提货的款项支出，不包含前期开发费用
B34: 学习机系统授权费 | C34: 九学王等系统授权，该授权费用是根据学习机的装机数量确定
A35: BONG PRO | B35: BOE平板电脑款项 | C35: 提货的款项支出，不包含前期开发费用
B36: 保护套 | C36: 提货的款项支出，不包含前期开发费用
B37: 包装盒 | C37: 提货的款项支出，不包含前期开发费用
B38: 充电器费用 | C38: 提货的款项支出，不包含前期开发费用
B39: 指学镜 | C39: 提货的款项支出，不包含前期开发费用
B40: 学习机系统授权费 | C40: 九学王等系统授权，该授权费用是根据学习机的装机数量确定
A41: 其他硬件成本 | B41: 电容笔 | C41: 没办法区分支付的款项，是属于MAX还是Pro时，记录在其他硬件成本中
B42: 支架 | C42: 没办法区分支付的款项，是属于MAX还是Pro时，记录在其他硬件成本中
B43: 硬件支出合计
A44: 产品开发-MAX | B44: 检测费
B45: 认证费 | C45: 硬件认证相关的支出，包含各项资质认证等
B46: 设计费 | C46: 产品外包装设计、电容笔设计费等
B47: OTA费用 | C47: 软件升级的服务费
B48: 模具费用
B49: TCL研发费 | C49: 研发产品的产品开发支出，是产品量产前的研发费用
B50: 唤醒功能开发 | C50: 思必驰的机器唤醒功能开发
B51: 题库费 | C51: 供应商-菁优，
A52: 产品开发-PRO | B52: 检测费
B53: 认证费 | C53: 硬件认证相关的支出，包含各项资质认证等
B54: 设计费 | C54: 产品外包装设计、电容笔设计费等
B55: OTA费用 | C55: 软件升级的服务费
B56: 模具费用
B57: BOE研发费 | C57: 研发产品的产品开发支出，是产品量产前的研发费用
B58: 题库费 | C58: 供应商-菁优，
A59: 其他产品开发 | B59: 员工报销
B60: 软件使用费
A61: 服务器算法充值 | B61: 阿里云充值费用 | C61: 充值至阿里云网站的费用，包含服务器租赁费用/GPU费用
B62: 微软充值费用 | C62: 语音服务（可燃）
B63: kimi充值费用
B64: 智普AI充值费用
B65: 硅基流动充值费用
B66: 无问芯穹充值费用
B67: 其他服务器算法充值 | C67: 其他接口费用，要是金额较大，也可以列示二级项目
A68: 研发-服务费 | B68: 设计外包服务费 | C68: 是软件产品需要外包给其他人的设计服务，软件的UI设计、软件中人物设计等费用
B69: AI技术外包服务费 | C69: 主要是包含中山市虚实之间网络科技工作室供应商的服务
B70: 知识产权服务费 | C70: 商标、软著、专利等，全部包括
A71: 研发-费用报销 | B71: 员工报销 | C71: 研发部门产生的差旅费，包括杭州市内的打车费和杭州市外的机票、住宿、打车费
B72: 研发支出合计
A73: 品牌建设 | B73: 媒体采购 | C73: 发布新闻稿、公众号等媒体服务
B74: 舆情服务 | C74: 对公共舆论进行监测、危机管理的服务
B75: 会务服务 | C75: 指为会议、展览、商务活动等提供的专业服务，它涵盖了会议策划、组织、执行以及相关配套服务的全过程。包含会议策划、接待、餐饮、车马费等
B76: 场地搭建 | C76: 公司参加各种展会而产生的场地建设费用，包括展台架、易拉宝、供应商服务费等，如：云栖大会展台搭建
B77: 素材拍摄 | C77: 通过和影楼、媒体公司合作，让供应商提供模特，后续拍摄视频、图像、语音，以便公司或者相关部门对外宣传时有素材可用而产生的费用
B78: 背书合作费用 | C78: 支付给高校或其他有名的品牌方，寻求业内知名机构背书而产生的费用。（如：李睿的服务费）
A79: 内容种草 | B79: 抖音平台种草-GD广告 | C79: 指在抖音平台推广中使用了GD广告，这是一种按照广告主的投放需求，在指定的时间、曝光量内，确保广告投放完成的广告形式
B80: 抖音平台种草-种草通 | C80: 指在抖音千川账户中下单，与相关领域具有一定影响力和粉丝基础的抖音用户合作，这些用户会创作并发布关于产品的使用体验、评测、展示等内容，以吸引更多用户的关注和兴趣，进而促进产品的销售和品牌的推广。
B81: 抖音平台种草-达人合作 | C81: 直接与达人供应商进行合作，达人主要发布在抖音的种草视频，以吸引更多用户的关注和兴趣，进而促进产品的销售和品牌的推广。
B82: 小红书平台种草-达人合作 | C82: 达人只在小红书端发帖，或者主要合作目的是小红书的宣发。
B83: 全平台种草-达人合作 | C83: 达人会在抖音、小红书、视频号等都发布相关作品，进行宣传
B84: 小红书种草充值 | C84: 指公司为了给已经发布的小红书作品而产生的投流而产生的“红薯币”的充值费用
A85: 投放转化 | B85: 信息流视频制作 | C85: 通过和供应商合作，让供应商通过结合视频、音频、图像、文字等元素，达到给用户种草的目的，以便后续在直播时对这个视频进行投流，后续完成对用户的收割
B86: 抖音投放充值 | C86: 支付给在抖音平台充值的推广费用和购买流量的费用，目前主要供应商为“湖北巨量引擎科技有限公司”。奈斯
B87: 京东平台投放充值 | C87: 直接在京东平台充值的推广费用，工具包括但不限于“品销宝”、“引力魔方”、“钻石展位”、“万象台”等推广充值费用
B88: 视频号投放充值 | C88: 支付给在微信视频号平台的充值推广费用和购买流量的费用，目前主要供应商为“润和（深圳）互联网有限公司”
B89: 天猫平台投放充值 | C89: 直接在淘宝、天猫平台充值的推广费用，工具包括但不限于“品销宝”、“引力魔方”、“钻石展位”、“万象台”等推广充值费用
A90: 直播间运营 | B90: DP-有熊团队服务费 | C90: 核算公司直播间代运营服务商【上海粒资信息科技有限公司】，即“有熊&周扬扬”直播间的服务费
B91: DP-黑哥团队服务费 | C91: 核算公司直播间代运营服务商【杭州小百灵网络科技有限公司】，即“黑哥”直播间的服务费+佣金费用
B92: DP-小太阳团队服务费 | C92: 核算公司直播间代运营服务商【杭州辰上星辰信息科技有限公司】，即“小太阳”直播间的服务费
B93: 直播间搭建费用 | C93: 给供应商直播间场景建设、软装、硬装、零星设备采买而支付的费用
A94: 平台运营 | B94: 分期服务费 | C94: 抖音月付与商家联合贴息活动、代收白条网络推广技术服务费、花呗分期服务费、信用卡服务费
B95: 平台服务费 | C95: 平台佣金、软件服务费、技术服务费年费、交易服务费
B96: 权益保险
B97: 消费者赔付 | C97: 因发货延迟给客户的赔款
B98: 平台积分扣款 | C98: 代扣积分、京东京豆
B99: 平台推荐佣金 | C99: 京东联盟扣款、淘宝客佣金
B100: 保证金及认证费用 | C100: 核算店铺在抖音、京东、天猫等线上平台为开设电商店铺而支付的保证金，认证费用
...

Sheet 科目编码
A1: 手工码 | B1: *业务单元 | C1: 编码 | D1: *名称 | E1: 费用项目类型编码 | F1: 费用项目类型 | G1: 上级费用项目编码 | H1: 上级费用项目 | I1: 备注 | J1: 状态 | K1: 资产业务 | L1: 供应链业务 | M1: 费控业务 | N1: 营销业务 | O1: 财资业务 | P1: 资产业务分类 | Q1: 资产对应物料编码 | R1: 资产对应物料 | S1: 是否开票 | T1: 更新成本 | U1: 供应链对应物料编码 | V1: 供应链对应物料 | W1: 是否分摊 | X1: 排序
A2: 2236674769572331525 | B2: 企业账号级 | C2: Else01 | D2: 中转 | G2: Else | H2: 其他 | J2: 启用 | K2: 否 | L2: 否 | M2: 否 | N2: 否 | O2: 否 | S2: 否 | T2: 否 | V2: 0 | W2: 否 | X2: 999
A3: 2236674142531747845 | B3: 企业账号级 | C3: Else | D3: 其他 | J3: 启用 | K3: 否 | L3: 否 | M3: 否 | N3: 否 | O3: 否 | S3: 否 | T3: 否 | V3: 0 | W3: 否 | X3: 999
A4: 2225580121718259712 | B4: 企业账号级 | C4: Q3301 | D4: 理财收支 | G4: Q33 | H4: 理财 | J4: 启用 | K4: 否 | L4: 否 | M4: 否 | N4: 否 | O4: 否 | S4: 否 | T4: 否 | V4: 0 | W4: 否 | X4: 999
A5: 2225579984277733378 | B5: 企业账号级 | C5: Q33 | D5: 理财 | J5: 启用 | K5: 否 | L5: 否 | M5: 否 | N5: 否 | O5: 否 | S5: 否 | T5: 否 | V5: 0 | W5: 否 | X5: 999
A6: 2225576187526643714 | B6: 企业账号级 | C6: Q3209 | D6: 笔尖 | G6: Q32 | H6: 生产成本 | J6: 启用 | K6: 否 | L6: 否 | M6: 否 | N6: 否 | O6: 否 | S6: 否 | T6: 否 | V6: 0 | W6: 否 | X6: 999
A7: 2225576084447428617 | B7: 企业账号级 | C7: Q3208 | D7: 贴纸/说明书 | G7: Q32 | H7: 生产成本 | J7: 启用 | K7: 否 | L7: 否 | M7: 否 | N7: 否 | O7: 否 | S7: 否 | T7: 否 | V7: 0 | W7: 否 | X7: 999
A8: 2225575921240244228 | B8: 企业账号级 | C8: Q3207 | D8: 包机膜 | G8: Q32 | H8: 生产成本 | J8: 启用 | K8: 否 | L8: 否 | M8: 否 | N8: 否 | O8: 否 | S8: 否 | T8: 否 | V8: 0 | W8: 否 | X8: 999
A9: 2225575792421109769 | B9: 企业账号级 | C9: Q3206 | D9: 生产成本-员工报销 | G9: Q32 | H9: 生产成本 | J9: 启用 | K9: 否 | L9: 否 | M9: 否 | N9: 否 | O9: 否 | S9: 否 | T9: 否 | V9: 0 | W9: 否 | X9: 999
A10: 2225575637772402693 | B10: 企业账号级 | C10: Q3205 | D10: 低值易耗品采购 | G10: Q32 | H10: 生产成本 | J10: 启用 | K10: 否 | L10: 否 | M10: 否 | N10: 否 | O10: 否 | S10: 否 | T10: 否 | V10: 0 | W10: 否 | X10: 999
A11: 2225575508923383812 | B11: 企业账号级 | C11: Q3204 | D11: 运输费 | G11: Q32 | H11: 生产成本 | J11: 启用 | K11: 否 | L11: 否 | M11: 否 | N11: 否 | O11: 否 | S11: 否 | T11: 否 | V11: 0 | W11: 否 | X11: 999
A12: 2225575362894495751 | B12: 企业账号级 | C12: Q3203 | D12: 西溪首座仓库装修费 | G12: Q32 | H12: 生产成本 | J12: 启用 | K12: 否 | L12: 否 | M12: 否 | N12: 否 | O12: 否 | S12: 否 | T12: 否 | V12: 0 | W12: 否 | X12: 999
A13: 2225575199685738502 | B13: 企业账号级 | C13: Q3202 | D13: 西溪首座仓库物业水电费 | G13: Q32 | H13: 生产成本 | J13: 启用 | K13: 否 | L13: 否 | M13: 否 | N13: 否 | O13: 否 | S13: 否 | T13: 否 | V13: 0 | W13: 否 | X13: 999
A14: 2225574692909481986 | B14: 企业账号级 | C14: Q3201 | D14: 西溪首座仓库租金 | G14: Q32 | H14: 生产成本 | J14: 启用 | K14: 否 | L14: 否 | M14: 否 | N14: 否 | O14: 否 | S14: 否 | T14: 否 | V14: 0 | W14: 否 | X14: 999
A15: 2225574443801378816 | B15: 企业账号级 | C15: Q32 | D15: 生产成本 | J15: 启用 | K15: 否 | L15: 否 | M15: 否 | N15: 否 | O15: 否 | S15: 否 | T15: 否 | V15: 0 | W15: 否 | X15: 999
A16: 2225570054313345030 | B16: 企业账号级 | C16: Q3104 | D16: 违约金支出 | G16: Q31 | H16: 营业外支出 | J16: 启用 | K16: 否 | L16: 否 | M16: 否 | N16: 否 | O16: 否 | S16: 否 | T16: 否 | V16: 0 | W16: 否 | X16: 999
A17: 2225569444459446277 | B17: 企业账号级 | C17: Q2807 | D17: 软件服务费 | G17: Q28 | H17: 服务费 | J17: 启用 | K17: 否 | L17: 否 | M17: 否 | N17: 否 | O17: 否 | S17: 否 | T17: 否 | V17: 0 | W17: 否 | X17: 999
A18: 2225547351117791241 | B18: 企业账号级 | C18: Q2209 | D18: 其他平台扣款 | G18: Q22 | H18: 平台运营 | J18: 启用 | K18: 否 | L18: 否 | M18: 否 | N18: 否 | O18: 否 | S18: 否 | T18: 否 | V18: 0 | W18: 否 | X18: 999
A19: 2225547144959361032 | B19: 企业账号级 | C19: Q2208 | D19: 平台推荐佣金 | G19: Q22 | H19: 平台运营 | J19: 启用 | K19: 否 | L19: 否 | M19: 否 | N19: 否 | O19: 否 | S19: 否 | T19: 否 | V19: 0 | W19: 否 | X19: 999
A20: 2225546973190553601 | B20: 企业账号级 | C20: Q2207 | D20: 平台积分扣款 | G20: Q22 | H20: 平台运营 | J20: 启用 | K20: 否 | L20: 否 | M20: 否 | N20: 否 | O20: 否 | S20: 否 | T20: 否 | V20: 0 | W20: 否 | X20: 999
A21: 2225546715461058564 | B21: 企业账号级 | C21: Q2206 | D21: 消费者赔付 | G21: Q22 | H21: 平台运营 | J21: 启用 | K21: 否 | L21: 否 | M21: 否 | N21: 否 | O21: 否 | S21: 否 | T21: 否 | V21: 0 | W21: 否 | X21: 999
A22: 2225546612413300736 | B22: 企业账号级 | C22: Q2205 | D22: 权益保险 | G22: Q22 | H22: 平台运营 | J22: 启用 | K22: 否 | L22: 否 | M22: 否 | N22: 否 | O22: 否 | S22: 否 | T22: 否 | V22: 0 | W22: 否 | X22: 999
A23: 2225546423434739718 | B23: 企业账号级 | C23: Q2204 | D23: 分期服务费 | G23: Q22 | H23: 平台运营 | J23: 启用 | K23: 否 | L23: 否 | M23: 否 | N23: 否 | O23: 否 | S23: 否 | T23: 否 | V23: 0 | W23: 否 | X23: 999
A24: 2225498637598720000 | B24: 企业账号级 | C24: Q1507 | D24: 无问芯穹充值费用 | G24: Q15 | H24: 服务器算法充值 | J24: 启用 | K24: 否 | L24: 否 | M24: 否 | N24: 否 | O24: 否 | S24: 否 | T24: 否 | V24: 0 | W24: 否 | X24: 999
A25: 2225498491599716358 | B25: 企业账号级 | C25: Q1506 | D25: 硅基流动充值费用 | G25: Q15 | H25: 服务器算法充值 | J25: 启用 | K25: 否 | L25: 否 | M25: 否 | N25: 否 | O25: 否 | S25: 否 | T25: 否 | V25: 0 | W25: 否 | X25: 999
A26: 2225497855944556547 | B26: 企业账号级 | C26: Q1402 | D26: 产品开发-员工报销 | G26: Q14 | H26: 其他产品开发 | J26: 启用 | K26: 否 | L26: 否 | M26: 否 | N26: 否 | O26: 否 | S26: 否 | T26: 否 | V26: 0 | W26: 否 | X26: 999
A27: 2225337902772518913 | B27: 企业账号级 | C27: Q0103 | D27: 平台补贴收入 | G27: Q01 | H27: 业务收入 | J27: 启用 | K27: 否 | L27: 否 | M27: 否 | N27: 否 | O27: 否 | S27: 否 | T27: 否 | W27: 否 | X27: 999
A28: 2200402851648241672 | B28: 企业账号级 | C28: Q2302 | D28: 转介绍佣金 | G28: Q23 | H28: 私域运营 | J28: 启用 | K28: 否 | L28: 否 | M28: 否 | N28: 否 | O28: 否 | S28: 否 | T28: 否 | W28: 否 | X28: 999
A29: 2184633380988518407 | B29: 企业账号级 | C29: Q3103 | D29: 滞纳金支出 | G29: Q31 | H29: 营业外支出 | J29: 启用 | K29: 是 | L29: 是 | M29: 是 | N29: 是 | O29: 是 | S29: 否 | T29: 否 | W29: 否 | X29: 999
A30: 2184633380988518406 | B30: 企业账号级 | C30: Q3102 | D30: 罚款支出 | G30: Q31 | H30: 营业外支出 | J30: 启用 | K30: 是 | L30: 是 | M30: 是 | N30: 是 | O30: 是 | S30: 否 | T30: 否 | W30: 否 | X30: 999
A31: 2184633380988518405 | B31: 企业账号级 | C31: Q3101 | D31: 手续费 | G31: Q31 | H31: 营业外支出 | J31: 启用 | K31: 是 | L31: 是 | M31: 是 | N31: 是 | O31: 是 | S31: 否 | T31: 否 | W31: 否 | X31: 999
A32: 2184633380988518404 | B32: 企业账号级 | C32: Q3004 | D32: 企业所得税 | G32: Q30 | H32: 税费成本 | J32: 启用 | K32: 是 | L32: 是 | M32: 是 | N32: 是 | O32: 是 | S32: 否 | T32: 否 | W32: 否 | X32: 999
A33: 2184633380988518403 | B33: 企业账号级 | C33: Q3003 | D33: 印花税 | G33: Q30 | H33: 税费成本 | J33: 启用 | K33: 是 | L33: 是 | M33: 是 | N33: 是 | O33: 是 | S33: 否 | T33: 否 | W33: 否 | X33: 999
A34: 2184633372398583822 | B34: 企业账号级 | C34: Q3002 | D34: 附加税 | G34: Q30 | H34: 税费成本 | J34: 启用 | K34: 是 | L34: 是 | M34: 是 | N34: 是 | O34: 是 | S34: 否 | T34: 否 | W34: 否 | X34: 999
A35: 2184633372398583821 | B35: 企业账号级 | C35: Q3001 | D35: 增值税 | G35: Q30 | H35: 税费成本 | J35: 启用 | K35: 是 | L35: 是 | M35: 是 | N35: 是 | O35: 是 | S35: 否 | T35: 否 | W35: 否 | X35: 999
A36: 2184633372398583820 | B36: 企业账号级 | C36: Q29010 | D36: 其他办公费用 | G36: Q29 | H36: 办公费用 | J36: 启用 | K36: 是 | L36: 是 | M36: 是 | N36: 是 | O36: 是 | S36: 否 | T36: 否 | W36: 否 | X36: 999
A37: 2184633372398583819 | B37: 企业账号级 | C37: Q2909 | D37: 总经办报销费用 | G37: Q29 | H37: 办公费用 | J37: 启用 | K37: 是 | L37: 是 | M37: 是 | N37: 是 | O37: 是 | S37: 否 | T37: 否 | W37: 否 | X37: 999
A38: 2184633372398583818 | B38: 企业账号级 | C38: Q2908 | D38: 办公设备租赁费 | G38: Q29 | H38: 办公费用 | J38: 启用 | K38: 是 | L38: 是 | M38: 是 | N38: 是 | O38: 是 | S38: 否 | T38: 否 | W38: 否 | X38: 999
... A152: 2184633192009957380 | B152: 企业账号级 | C152: Q0101 | D152: 平台硬件销售收入 | G152: Q01 | H152: 业务收入 | J152: 启用 | K152: 是 | L152: 是 | M152: 是 | N152: 是 | O152: 是 | S152: 否 | T152: 否 | W152: 否 | X152: 999
A153: 2184632444685647874 | B153: 企业账号级 | C153: Q31 | D153: 营业外支出 | J153: 启用 | K153: 是 | L153: 是 | M153: 是 | N153: 是 | O153: 是 | S153: 否 | T153: 否 | W153: 否 | X153: 999
A154: 2184632444685647873 | B154: 企业账号级 | C154: Q30 | D154: 税费成本 | J154: 启用 | K154: 是 | L154: 是 | M154: 是 | N154: 是 | O154: 是 | S154: 否 | T154: 否 | W154: 否 | X154: 999
A155: 2184632444685647872 | B155: 企业账号级 | C155: Q27 | D155: 办公场地使用费 | J155: 启用 | K155: 是 | L155: 是 | M155: 是 | N155: 是 | O155: 是 | S155: 否 | T155: 否 | W155: 否 | X155: 999
A156: 2184632436095713287 | B156: 企业账号级 | C156: Q26 | D156: 品销-费用报销 | J156: 启用 | K156: 是 | L156: 是 | M156: 是 | N156: 是 | O156: 是 | S156: 否 | T156: 否 | W156: 否 | X156: 999
A157: 2184632436095713286 | B157: 企业账号级 | C157: Q25 | D157: 发货成本 | J157: 启用 | K157: 是 | L157: 是 | M157: 是 | N157: 是 | O157: 是 | S157: 否 | T157: 否 | W157: 否 | X157: 999
A158: 2184632436095713285 | B158: 企业账号级 | C158: Q24 | D158: 达人带货 | J158: 启用 | K158: 是 | L158: 是 | M158: 是 | N158: 是 | O158: 是 | S158: 否 | T158: 否 | W158: 否 | X158: 999
A159: 2184632436095713284 | B159: 企业账号级 | C159: Q23 | D159: 私域运营 | J159: 启用 | K159: 是 | L159: 是 | M159: 是 | N159: 是 | O159: 是 | S159: 否 | T159: 否 | W159: 否 | X159: 999
A160: 2184632436095713283 | B160: 企业账号级 | C160: Q22 | D160: 平台运营 | J160: 启用 | K160: 是 | L160: 是 | M160: 是 | N160: 是 | O160: 是 | S160: 否 | T160: 否 | W160: 否 | X160: 999
A161: 2184632436095713282 | B161: 企业账号级 | C161: Q21 | D161: 直播间运营 | J161: 启用 | K161: 是 | L161: 是 | M161: 是 | N161: 是 | O161: 是 | S161: 否 | T161: 否 | W161: 否 | X161: 999
A162: 2184632436095713281 | B162: 企业账号级 | C162: Q20 | D162: 投放转化 | J162: 启用 | K162: 是 | L162: 是 | M162: 是 | N162: 是 | O162: 是 | S162: 否 | T162: 否 | W162: 否 | X162: 999
A163: 2184632427505778699 | B163: 企业账号级 | C163: Q19 | D163: 内容种草 | J163: 启用 | K163: 是 | L163: 是 | M163: 是 | N163: 是 | O163: 是 | S163: 否 | T163: 否 | W163: 否 | X163: 999
A164: 2184632427505778698 | B164: 企业账号级 | C164: Q18 | D164: 品牌建设 | J164: 启用 | K164: 是 | L164: 是 | M164: 是 | N164: 是 | O164: 是 | S164: 否 | T164: 否 | W164: 否 | X164: 999
... A183: 2184014424687247371 | B183: 企业账号级 | C183: Q28 | D183: 服务费 | J183: 启用 | K183: 是 | L183: 是 | M183: 是 | N183: 是 | O183: 是 | S183: 否 | T183: 否 | W183: 否 | X183: 999
A184: 2180202014143152464 | B184: 企业账号级 | C184: Cost_PU | D184: 入库费用 | I184: 入库时发生的运费、关税等各项费用 | J184: 停用 | K184: 否 | L184: 否 | M184: 否 | N184: 否 | O184: 否 | S184: 否 | T184: 否 | W184: 否 | X184: 999
A185: 2180202014143152463 | B185: 企业账号级 | C185: Fee_PU | D185: 采购成本 | I185: 采购材料成本 | J185: 停用 | K185: 否 | L185: 是 | M185: 否 | N185: 否 | O185: 否 | S185: 否 | T185: 是 | W185: 否 | X185: 999
A186: 2180202014143152462 | B186: 企业账号级 | C186: Fee_OS | D186: 委外加工费 | I186: 委外生产的结算加工费 | J186: 停用 | K186: 否 | L186: 是 | M186: 否 | N186: 否 | O186: 否 | S186: 否 | T186: 是 | W186: 否 | X186: 999
C187: Q3105 | D187: 汇兑损益 | G187: Q31 | H187: 营业外支出

Sheet 问题
A1: 1、 | B1: 理财的利息收入，目前费用项目放在利息收入里，王妍的表里是单独在最后加了一行理财收支，这个费用项目只包括本金部分
A2: 2、 | B2: 汇兑损益的费用项目修改为手续费
P4: 统一修改为汇兑损益
P8: 统一修改为汇兑损益
A11: 3、 | B11: 这两个应该是外部往来支出？
A17: 4、 | B17: 理财收支是否要分开
A23: 5、 | B23: 这样会导致该项目支出金额为负数，是否要紧
A32: 6、 | B32: 合并抵消的要单独标注
A34: 7、 | B34: 这个业务是啥
A40: 8、 | B40: 其他还有一些费用项目会存在退款导致资金流出为负数的情况，比方物业费退款、抖音投放退款
A42: 9、 | B42: 费用项目应该是社保（单位+个人）
R45: 已修改
A49: 10、 | B49: 2楼的费用项目应该是生产成本下面的Q3201，现在Q2702是归在管理费用里了
A56: 11、 | B56: 2楼应该是制造费用
A73: 12、 | B73: 公司内部不同账户之间划款费用名称应改为内部往来收入

Sheet 合并抵消
A1: 月份 | B1: 科目编码 | C1: 科目名称 | D1: 日期 | E1: 费用项目编码 | F1: 费用项目名称 | G1: 核算账簿 | H1: 凭证号 | I1: 摘要 | J1: 借方本币 | K1: 贷方本币
A2: 1月 | B2: 100201 | D2: 2025-01-21 | E2: Q0401 | H2: 记-1
A3: 1月 | B3: 100201 | D3: 2025-01-23 | E3: Q0401 | H3: 记-33
A4: 1月 | B4: 100201 | D4: 2025-01-21 | E4: Q0601 | H4: 记-81
A5: 1月 | B5: 100201 | D5: 2025-01-23 | E5: Q0601 | H5: 记-117
A6: 2月 | B6: 100201 | D6: 2025-02-28 | E6: Q0401 | H6: 记-98
A7: 2月 | B7: 100201 | D7: 2025-02-27 | E7: Q0401 | H7: 记-84
A8: 2月 | B8: 100201 | D8: 2025-02-26 | E8: Q0401 | H8: 记-77
A9: 2月 | B9: 100201 | D9: 2025-02-14 | E9: Q0401 | H9: 记-41
A10: 2月 | B10: 100201 | D10: 2025-02-28 | E10: Q0601 | H10: 记-35
A11: 2月 | B11: 100201 | D11: 2025-02-26 | E11: Q0601 | H11: 记-25
A12: 2月 | B12: 100201 | D12: 2025-02-28 | E12: Q0601 | H12: 记-99
A13: 2月 | B13: 100201 | D13: 2025-02-14 | E13: Q0601 | H13: 记-10
... A97: 7月 | B97: 100202 | D97: 2025-07-09 | E97: Q0501 | H97: 记-82
A98: 9月 | B98: 100201 | C98: 银行存款_人民币户 | D98: 2025-09-24 | E98: Q0401 | F98: 内部往来收入 | G98: 浙江精准学科技有限公司 | H98: 记-2 | I98: 关联交易-123456 | J98: 19999 | K98: 0

Sheet 分月实际收支-集团合并
A1: 公司：集团合并
A2: 一级 | B2: 辅助列 | C2: 二级 | D2: 三级 | E2: 三级科目对应编码 | F2: 1月 | G2: 2月 | H2: 3月 | I2: 4月 | J2: 5月 | K2: 6月 | L2: 7月 | M2: 8月 | N2: 9月 | O2: 10月 | P2: 11月 | Q2: 12月 | R2: 本年合计
A3: 收入 | B3: 学习机销售收入 | C3: 业务收入 | D3: 平台硬件销售收入 | E3: Q0101 | F3: =浙江精准学!F3+知识跳跳!F3+海南精准学!F3+实时查!F3+目标准!F3+'SMART LEARNING HOLDING'!F3+'SMART AI LIMITED'!F3+'HK01'!F3-(SUMIFS(合并抵消!$J:$J,合并抵消!$E:$E,$E3,合并抵消!$A:$A,F$2)-SUMIFS(合并抵消!$K:$K,合并抵消!$E:$E,$E3,合并抵消!$A:$A,F$2)) | G3: =浙江精准学!G3+知识跳跳!G3+海南精准学!G3+实时查!G3+目标准!G3+'SMART LEARNING HOLDING'!G3+'SMART AI LIMITED'!G3+'HK01'!G3-(SUMIFS(合并抵消!$J:$J,合并抵消!$E:$E,$E3,合并抵消!$A:$A,G$2)-SUMIFS(合并抵消!$K:$K,合并抵消!$E:$E,$E3,合并抵消!$A:$A,G$2)) | H3: =浙江精准学!H3+知识跳跳!H3+海南精准学!H3+实时查!H3+目标准!H3+'SMART LEARNING HOLDING'!H3+'SMART AI LIMITED'!H3+'HK01'!H3-(SUMIFS(合并抵消!$J:$J,合并抵消!$E:$E,$E3,合并抵消!$A:$A,H$2)-SUMIFS(合并抵消!$K:$K,合并抵消!$E:$E,$E3,合并抵消!$A:$A,H$2)) | I3: =浙江精准学!I3+知识跳跳!I3+海南精准学!I3+实时查!I3+目标准!I3+'SMART LEARNING HOLDING'!I3+'SMART AI LIMITED'!I3+'HK01'!I3-(SUMIFS(合并抵消!$J:$J,合并抵消!$E:$E,$E3,合并抵消!$A:$A,I$2)-SUMIFS(合并抵消!$K:$K,合并抵消!$E:$E,$E3,合并抵消!$A:$A,I$2)) | J3: =浙江精准学!J3+知识跳跳!J3+海南精准学!J3+实时查!J3+目标准!J3+'SMART LEARNING HOLDING'!J3+'SMART AI LIMITED'!J3+'HK01'!J3-(SUMIFS(合并抵消!$J:$J,合并抵消!$E:$E,$E3,合并抵消!$A:$A,J$2)-SUMIFS(合并抵消!$K:$K,合并抵消!$E:$E,$E3,合并抵消!$A:$A,J$2)) | K3: =浙江精准学!K3+知识跳跳!K3+海南精准学!K3+实时查!K3+目标准!K3+'SMART LEARNING HOLDING'!K3+'SMART AI LIMITED'!K3+'HK01'!K3-(SUMIFS(合并抵消!$J:$J,合并抵消!$E:$E,$E3,合并抵消!$A:$A,K$2)-SUMIFS(合并抵消!$K:$K,合并抵消!$E:$E,$E3,合并抵消!$A:$A,K$2)) | L3: =浙江精准学!L3+知识跳跳!L3+海南精准学!L3+实时查!L3+目标准!L3+'SMART LEARNING HOLDING'!L3+'SMART AI LIMITED'!L3+'HK01'!L3-(SUMIFS(合并抵消!$J:$J,合并抵消!$E:$E,$E3,合并抵消!$A:$A,L$2)-SUMIFS(合并抵消!$K:$K,合并抵消!$E:$E,$E3,合并抵消!$A:$A,L$2)) | M3: =浙江精准学!M3+知识跳跳!M3+海南精准学!M3+实时查!M3+目标准!M3+'SMART LEARNING HOLDING'!M3+'SMART AI LIMITED'!M3+'HK01'!M3-(SUMIFS(合并抵消!$J:$J,合并抵消!$E:$E,$E3,合并抵消!$A:$A,M$2)-SUMIFS(合并抵消!$K:$K,合并抵消!$E:$E,$E3,合并抵消!$A:$A,M$2)) | ... Q3: =浙江精准学!Q3+知识跳跳!Q3+海南精准学!Q3+实时查!Q3+目标准!Q3+'SMART LEARNING HOLDING'!Q3+'SMART AI LIMITED'!Q3+'HK01'!Q3-(SUMIFS(合并抵消!$J:$J,合并抵消!$E:$E,$E3,合并抵消!$A:$A,Q$2)-SUMIFS(合并抵消!$K:$K,合并抵消!$E:$E,$E3,合并抵消!$A:$A,Q$2)) | R3: =SUM(F3:Q3)
A4: 收入 | B4: 学习机销售收入 | D4: 服务收款 | E4: Q0102 | F4: =浙江精准学!F4+知识跳跳!F4+海南精准学!F4+实时查!F4+目标准!F4+'SMART LEARNING HOLDING'!F4+'SMART AI LIMITED'!F4+'HK01'!F4-(SUMIFS(合并抵消!$J:$J,合并抵消!$E:$E,$E4,合并抵消!$A:$A,F$2)-SUMIFS(合并抵消!$K:$K,合并抵消!$E:$E,$E4,合并抵消!$A:$A,F$2)) | G4: =浙江精准学!G4+知识跳跳!G4+海南精准学!G4+实时查!G4+目标准!G4+'SMART LEARNING HOLDING'!G4+'SMART AI LIMITED'!G4+'HK01'!G4-(SUMIFS(合并抵消!$J:$J,合并抵消!$E:$E,$E4,合并抵消!$A:$A,G$2)-SUMIFS(合并抵消!$K:$K,合并抵消!$E:$E,$E4,合并抵消!$A:$A,G$2)) | H4: =浙江精准学!H4+知识跳跳!H4+海南精准学!H4+实时查!H4+目标准!H4+'SMART LEARNING HOLDING'!H4+'SMART AI LIMITED'!H4+'HK01'!H4-(SUMIFS(合并抵消!$J:$J,合并抵消!$E:$E,$E4,合并抵消!$A:$A,H$2)-SUMIFS(合并抵消!$K:$K,合并抵消!$E:$E,$E4,合并抵消!$A:$A,H$2)) | I4: =浙江精准学!I4+知识跳跳!I4+海南精准学!I4+实时查!I4+目标准!I4+'SMART LEARNING HOLDING'!I4+'SMART AI LIMITED'!I4+'HK01'!I4-(SUMIFS(合并抵消!$J:$J,合并抵消!$E:$E,$E4,合并抵消!$A:$A,I$2)-SUMIFS(合并抵消!$K:$K,合并抵消!$E:$E,$E4,合并抵消!$A:$A,I$2)) | J4: =浙江精准学!J4+知识跳跳!J4+海南精准学!J4+实时查!J4+目标准!J4+'SMART LEARNING HOLDING'!J4+'SMART AI LIMITED'!J4+'HK01'!J4-(SUMIFS(合并抵消!$J:$J,合并抵消!$E:$E,$E4,合并抵消!$A:$A,J$2)-SUMIFS(合并抵消!$K:$K,合并抵消!$E:$E,$E4,合并抵消!$A:$A,J$2)) | K4: =浙江精准学!K4+知识跳跳!K4+海南精准学!K4+实时查!K4+目标准!K4+'SMART LEARNING HOLDING'!K4+'SMART AI LIMITED'!K4+'HK01'!K4-(SUMIFS(合并抵消!$J:$J,合并抵消!$E:$E,$E4,合并抵消!$A:$A,K$2)-SUMIFS(合并抵消!$K:$K,合并抵消!$E:$E,$E4,合并抵消!$A:$A,K$2)) | L4: =浙江精准学!L4+知识跳跳!L4+海南精准学!L4+实时查!L4+目标准!L4+'SMART LEARNING HOLDING'!L4+'SMART AI LIMITED'!L4+'HK01'!L4-(SUMIFS(合并抵消!$J:$J,合并抵消!$E:$E,$E4,合并抵消!$A:$A,L$2)-SUMIFS(合并抵消!$K:$K,合并抵消!$E:$E,$E4,合并抵消!$A:$A,L$2)) | M4: =浙江精准学!M4+知识跳跳!M4+海南精准学!M4+实时查!M4+目标准!M4+'SMART LEARNING HOLDING'!M4+'SMART AI LIMITED'!M4+'HK01'!M4-(SUMIFS(合并抵消!$J:$J,合并抵消!$E:$E,$E4,合并抵消!$A:$A,M$2)-SUMIFS(合并抵消!$K:$K,合并抵消!$E:$E,$E4,合并抵消!$A:$A,M$2)) | ... Q4: =浙江精准学!Q4+知识跳跳!Q4+海南精准学!Q4+实时查!Q4+目标准!Q4+'SMART LEARNING HOLDING'!Q4+'SMART AI LIMITED'!Q4+'HK01'!Q4-(SUMIFS(合并抵消!$J:$J,合并抵消!$E:$E,$E4,合并抵消!$A:$A,Q$2)-SUMIFS(合并抵消!$K:$K,合并抵消!$E:$E,$E4,合并抵消!$A:$A,Q$2)) | R4: =SUM(F4:Q4)
A5: 收入 | B5: 学习机销售收入 | D5: 平台补贴收入 | E5: Q0103 | F5: =浙江精准学!F5+知识跳跳!F5+海南精准学!F5+实时查!F5+目标准!F5+'SMART LEARNING HOLDING'!F5+'SMART AI LIMITED'!F5+'HK01'!F5-(SUMIFS(合并抵消!$J:$J,合并抵消!$E:$E,$E5,合并抵消!$A:$A,F$2)-SUMIFS(合并抵消!$K:$K,合并抵消!$E:$E,$E5,合并抵消!$A:$A,F$2)) | G5: =浙江精准学!G5+知识跳跳!G5+海南精准学!G5+实时查!G5+目标准!G5+'SMART LEARNING HOLDING'!G5+'SMART AI LIMITED'!G5+'HK01'!G5-(SUMIFS(合并抵消!$J:$J,合并抵消!$E:$E,$E5,合并抵消!$A:$A,G$2)-SUMIFS(合并抵消!$K:$K,合并抵消!$E:$E,$E5,合并抵消!$A:$A,G$2)) | H5: =浙江精准学!H5+知识跳跳!H5+海南精准学!H5+实时查!H5+目标准!H5+'SMART LEARNING HOLDING'!H5+'SMART AI LIMITED'!H5+'HK01'!H5-(SUMIFS(合并抵消!$J:$J,合并抵消!$E:$E,$E5,合并抵消!$A:$A,H$2)-SUMIFS(合并抵消!$K:$K,合并抵消!$E:$E,$E5,合并抵消!$A:$A,H$2)) | I5: =浙江精准学!I5+知识跳跳!I5+海南精准学!I5+实时查!I5+目标准!I5+'SMART LEARNING HOLDING'!I5+'SMART AI LIMITED'!I5+'HK01'!I5-(SUMIFS(合并抵消!$J:$J,合并抵消!$E:$E,$E5,合并抵消!$A:$A,I$2)-SUMIFS(合并抵消!$K:$K,合并抵消!$E:$E,$E5,合并抵消!$A:$A,I$2)) | J5: =浙江精准学!J5+知识跳跳!J5+海南精准学!J5+实时查!J5+目标准!J5+'SMART LEARNING HOLDING'!J5+'SMART AI LIMITED'!J5+'HK01'!J5-(SUMIFS(合并抵消!$J:$J,合并抵消!$E:$E,$E5,合并抵消!$A:$A,J$2)-SUMIFS(合并抵消!$K:$K,合并抵消!$E:$E,$E5,合并抵消!$A:$A,J$2)) | K5: =浙江精准学!K5+知识跳跳!K5+海南精准学!K5+实时查!K5+目标准!K5+'SMART LEARNING HOLDING'!K5+'SMART AI LIMITED'!K5+'HK01'!K5-(SUMIFS(合并抵消!$J:$J,合并抵消!$E:$E,$E5,合并抵消!$A:$A,K$2)-SUMIFS(合并抵消!$K:$K,合并抵消!$E:$E,$E5,合并抵消!$A:$A,K$2)) | L5: =浙江精准学!L5+知识跳跳!L5+海南精准学!L5+实时查!L5+目标准!L5+'SMART LEARNING HOLDING'!L5+'SMART AI LIMITED'!L5+'HK01'!L5-(SUMIFS(合并抵消!$J:$J,合并抵消!$E:$E,$E5,合并抵消!$A:$A,L$2)-SUMIFS(合并抵消!$K:$K,合并抵消!$E:$E,$E5,合并抵消!$A:$A,L$2)) | M5: =浙江精准学!M5+知识跳跳!M5+海南精准学!M5+实时查!M5+目标准!M5+'SMART LEARNING HOLDING'!M5+'SMART AI LIMITED'!M5+'HK01'!M5-(SUMIFS(合并抵消!$J:$J,合并抵消!$E:$E,$E5,合并抵消!$A:$A,M$2)-SUMIFS(合并抵消!$K:$K,合并抵消!$E:$E,$E5,合并抵消!$A:$A,M$2)) | ... Q5: =浙江精准学!Q5+知识跳跳!Q5+海南精准学!Q5+实时查!Q5+目标准!Q5+'SMART LEARNING HOLDING'!Q5+'SMART AI LIMITED'!Q5+'HK01'!Q5-(SUMIFS(合并抵消!$J:$J,合并抵消!$E:$E,$E5,合并抵消!$A:$A,Q$2)-SUMIFS(合并抵消!$K:$K,合并抵消!$E:$E,$E5,合并抵消!$A:$A,Q$2)) | R5: =SUM(F5:Q5)
A6: 收入 | B6: 自习室收入 | D6: 自习室收入 | E6: Q0104 | F6: =浙江精准学!F6+知识跳跳!F6+海南精准学!F6+实时查!F6+目标准!F6+'SMART LEARNING HOLDING'!F6+'SMART AI LIMITED'!F6+'HK01'!F6-(SUMIFS(合并抵消!$J:$J,合并抵消!$E:$E,$E6,合并抵消!$A:$A,F$2)-SUMIFS(合并抵消!$K:$K,合并抵消!$E:$E,$E6,合并抵消!$A:$A,F$2)) | G6: =浙江精准学!G6+知识跳跳!G6+海南精准学!G6+实时查!G6+目标准!G6+'SMART LEARNING HOLDING'!G6+'SMART AI LIMITED'!G6+'HK01'!G6-(SUMIFS(合并抵消!$J:$J,合并抵消!$E:$E,$E6,合并抵消!$A:$A,G$2)-SUMIFS(合并抵消!$K:$K,合并抵消!$E:$E,$E6,合并抵消!$A:$A,G$2)) | H6: =浙江精准学!H6+知识跳跳!H6+海南精准学!H6+实时查!H6+目标准!H6+'SMART LEARNING HOLDING'!H6+'SMART AI LIMITED'!H6+'HK01'!H6-(SUMIFS(合并抵消!$J:$J,合并抵消!$E:$E,$E6,合并抵消!$A:$A,H$2)-SUMIFS(合并抵消!$K:$K,合并抵消!$E:$E,$E6,合并抵消!$A:$A,H$2)) | I6: =浙江精准学!I6+知识跳跳!I6+海南精准学!I6+实时查!I6+目标准!I6+'SMART LEARNING HOLDING'!I6+'SMART AI LIMITED'!I6+'HK01'!I6-(SUMIFS(合并抵消!$J:$J,合并抵消!$E:$E,$E6,合并抵消!$A:$A,I$2)-SUMIFS(合并抵消!$K:$K,合并抵消!$E:$E,$E6,合并抵消!$A:$A,I$2)) | J6: =浙江精准学!J6+知识跳跳!J6+海南精准学!J6+实时查!J6+目标准!J6+'SMART LEARNING HOLDING'!J6+'SMART AI LIMITED'!J6+'HK01'!J6-(SUMIFS(合并抵消!$J:$J,合并抵消!$E:$E,$E6,合并抵消!$A:$A,J$2)-SUMIFS(合并抵消!$K:$K,合并抵消!$E:$E,$E6,合并抵消!$A:$A,J$2)) | K6: =浙江精准学!K6+知识跳跳!K6+海南精准学!K6+实时查!K6+目标准!K6+'SMART LEARNING HOLDING'!K6+'SMART AI LIMITED'!K6+'HK01'!K6-(SUMIFS(合并抵消!$J:$J,合并抵消!$E:$E,$E6,合并抵消!$A:$A,K$2)-SUMIFS(合并抵消!$K:$K,合并抵消!$E:$E,$E6,合并抵消!$A:$A,K$2)) | L6: =浙江精准学!L6+知识跳跳!L6+海南精准学!L6+实时查!L6+目标准!L6+'SMART LEARNING HOLDING'!L6+'SMART AI LIMITED'!L6+'HK01'!L6-(SUMIFS(合并抵消!$J:$J,合并抵消!$E:$E,$E6,合并抵消!$A:$A,L$2)-SUMIFS(合并抵消!$K:$K,合并抵消!$E:$E,$E6,合并抵消!$A:$A,L$2)) | M6: =浙江精准学!M6+知识跳跳!M6+海南精准学!M6+实时查!M6+目标准!M6+'SMART LEARNING HOLDING'!M6+'SMART AI LIMITED'!M6+'HK01'!M6-(SUMIFS(合并抵消!$J:$J,合并抵消!$E:$E,$E6,合并抵消!$A:$A,M$2)-SUMIFS(合并抵消!$K:$K,合并抵消!$E:$E,$E6,合并抵消!$A:$A,M$2)) | ... Q6: =浙江精准学!Q6+知识跳跳!Q6+海南精准学!Q6+实时查!Q6+目标准!Q6+'SMART LEARNING HOLDING'!Q6+'SMART AI LIMITED'!Q6+'HK01'!Q6-(SUMIFS(合并抵消!$J:$J,合并抵消!$E:$E,$E6,合并抵消!$A:$A,Q$2)-SUMIFS(合并抵消!$K:$K,合并抵消!$E:$E,$E6,合并抵消!$A:$A,Q$2))
A7: 收入 | B7: 售后收入 | C7: 售后收入 | D7: 客户赔偿款 | E7: Q0201 | F7: =浙江精准学!F7+知识跳跳!F7+海南精准学!F7+实时查!F7+目标准!F7+'SMART LEARNING HOLDING'!F7+'SMART AI LIMITED'!F7+'HK01'!F7-(SUMIFS(合并抵消!$J:$J,合并抵消!$E:$E,$E7,合并抵消!$A:$A,F$2)-SUMIFS(合并抵消!$K:$K,合并抵消!$E:$E,$E7,合并抵消!$A:$A,F$2)) | G7: =浙江精准学!G7+知识跳跳!G7+海南精准学!G7+实时查!G7+目标准!G7+'SMART LEARNING HOLDING'!G7+'SMART AI LIMITED'!G7+'HK01'!G7-(SUMIFS(合并抵消!$J:$J,合并抵消!$E:$E,$E7,合并抵消!$A:$A,G$2)-SUMIFS(合并抵消!$K:$K,合并抵消!$E:$E,$E7,合并抵消!$A:$A,G$2)) | H7: =浙江精准学!H7+知识跳跳!H7+海南精准学!H7+实时查!H7+目标准!H7+'SMART LEARNING HOLDING'!H7+'SMART AI LIMITED'!H7+'HK01'!H7-(SUMIFS(合并抵消!$J:$J,合并抵消!$E:$E,$E7,合并抵消!$A:$A,H$2)-SUMIFS(合并抵消!$K:$K,合并抵消!$E:$E,$E7,合并抵消!$A:$A,H$2)) | I7: =浙江精准学!I7+知识跳跳!I7+海南精准学!I7+实时查!I7+目标准!I7+'SMART LEARNING HOLDING'!I7+'SMART AI LIMITED'!I7+'HK01'!I7-(SUMIFS(合并抵消!$J:$J,合并抵消!$E:$E,$E7,合并抵消!$A:$A,I$2)-SUMIFS(合并抵消!$K:$K,合并抵消!$E:$E,$E7,合并抵消!$A:$A,I$2)) | J7: =浙江精准学!J7+知识跳跳!J7+海南精准学!J7+实时查!J7+目标准!J7+'SMART LEARNING HOLDING'!J7+'SMART AI LIMITED'!J7+'HK01'!J7-(SUMIFS(合并抵消!$J:$J,合并抵消!$E:$E,$E7,合并抵消!$A:$A,J$2)-SUMIFS(合并抵消!$K:$K,合并抵消!$E:$E,$E7,合并抵消!$A:$A,J$2)) | K7: =浙江精准学!K7+知识跳跳!K7+海南精准学!K7+实时查!K7+目标准!K7+'SMART LEARNING HOLDING'!K7+'SMART AI LIMITED'!K7+'HK01'!K7-(SUMIFS(合并抵消!$J:$J,合并抵消!$E:$E,$E7,合并抵消!$A:$A,K$2)-SUMIFS(合并抵消!$K:$K,合并抵消!$E:$E,$E7,合并抵消!$A:$A,K$2)) | L7: =浙江精准学!L7+知识跳跳!L7+海南精准学!L7+实时查!L7+目标准!L7+'SMART LEARNING HOLDING'!L7+'SMART AI LIMITED'!L7+'HK01'!L7-(SUMIFS(合并抵消!$J:$J,合并抵消!$E:$E,$E7,合并抵消!$A:$A,L$2)-SUMIFS(合并抵消!$K:$K,合并抵消!$E:$E,$E7,合并抵消!$A:$A,L$2)) | M7: =浙江精准学!M7+知识跳跳!M7+海南精准学!M7+实时查!M7+目标准!M7+'SMART LEARNING HOLDING'!M7+'SMART AI LIMITED'!M7+'HK01'!M7-(SUMIFS(合并抵消!$J:$J,合并抵消!$E:$E,$E7,合并抵消!$A:$A,M$2)-SUMIFS(合并抵消!$K:$K,合并抵消!$E:$E,$E7,合并抵消!$A:$A,M$2)) | ... Q7: =浙江精准学!Q7+知识跳跳!Q7+海南精准学!Q7+实时查!Q7+目标准!Q7+'SMART LEARNING HOLDING'!Q7+'SMART AI LIMITED'!Q7+'HK01'!Q7-(SUMIFS(合并抵消!$J:$J,合并抵消!$E:$E,$E7,合并抵消!$A:$A,Q$2)-SUMIFS(合并抵消!$K:$K,合并抵消!$E:$E,$E7,合并抵消!$A:$A,Q$2)) | R7: =SUM(F7:Q7)
A8: 收入 | B8: 售后收入 | D8: 供应商赔偿款 | E8: Q0202 | F8: =浙江精准学!F8+知识跳跳!F8+海南精准学!F8+实时查!F8+目标准!F8+'SMART LEARNING HOLDING'!F8+'SMART AI LIMITED'!F8+'HK01'!F8-(SUMIFS(合并抵消!$J:$J,合并抵消!$E:$E,$E8,合并抵消!$A:$A,F$2)-SUMIFS(合并抵消!$K:$K,合并抵消!$E:$E,$E8,合并抵消!$A:$A,F$2)) | G8: =浙江精准学!G8+知识跳跳!G8+海南精准学!G8+实时查!G8+目标准!G8+'SMART LEARNING HOLDING'!G8+'SMART AI LIMITED'!G8+'HK01'!G8-(SUMIFS(合并抵消!$J:$J,合并抵消!$E:$E,$E8,合并抵消!$A:$A,G$2)-SUMIFS(合并抵消!$K:$K,合并抵消!$E:$E,$E8,合并抵消!$A:$A,G$2)) | H8: =浙江精准学!H8+知识跳跳!H8+海南精准学!H8+实时查!H8+目标准!H8+'SMART LEARNING HOLDING'!H8+'SMART AI LIMITED'!H8+'HK01'!H8-(SUMIFS(合并抵消!$J:$J,合并抵消!$E:$E,$E8,合并抵消!$A:$A,H$2)-SUMIFS(合并抵消!$K:$K,合并抵消!$E:$E,$E8,合并抵消!$A:$A,H$2)) | I8: =浙江精准学!I8+知识跳跳!I8+海南精准学!I8+实时查!I8+目标准!I8+'SMART LEARNING HOLDING'!I8+'SMART AI LIMITED'!I8+'HK01'!I8-(SUMIFS(合并抵消!$J:$J,合并抵消!$E:$E,$E8,合并抵消!$A:$A,I$2)-SUMIFS(合并抵消!$K:$K,合并抵消!$E:$E,$E8,合并抵消!$A:$A,I$2)) | J8: =浙江精准学!J8+知识跳跳!J8+海南精准学!J8+实时查!J8+目标准!J8+'SMART LEARNING HOLDING'!J8+'SMART AI LIMITED'!J8+'HK01'!J8-(SUMIFS(合并抵消!$J:$J,合并抵消!$E:$E,$E8,合并抵消!$A:$A,J$2)-SUMIFS(合并抵消!$K:$K,合并抵消!$E:$E,$E8,合并抵消!$A:$A,J$2)) | K8: =浙江精准学!K8+知识跳跳!K8+海南精准学!K8+实时查!K8+目标准!K8+'SMART LEARNING HOLDING'!K8+'SMART AI LIMITED'!K8+'HK01'!K8-(SUMIFS(合并抵消!$J:$J,合并抵消!$E:$E,$E8,合并抵消!$A:$A,K$2)-SUMIFS(合并抵消!$K:$K,合并抵消!$E:$E,$E8,合并抵消!$A:$A,K$2)) | L8: =浙江精准学!L8+知识跳跳!L8+海南精准学!L8+实时查!L8+目标准!L8+'SMART LEARNING HOLDING'!L8+'SMART AI LIMITED'!L8+'HK01'!L8-(SUMIFS(合并抵消!$J:$J,合并抵消!$E:$E,$E8,合并抵消!$A:$A,L$2)-SUMIFS(合并抵消!$K:$K,合并抵消!$E:$E,$E8,合并抵消!$A:$A,L$2)) | M8: =浙江精准学!M8+知识跳跳!M8+海南精准学!M8+实时查!M8+目标准!M8+'SMART LEARNING HOLDING'!M8+'SMART AI LIMITED'!M8+'HK01'!M8-(SUMIFS(合并抵消!$J:$J,合并抵消!$E:$E,$E8,合并抵消!$A:$A,M$2)-SUMIFS(合并抵消!$K:$K,合并抵消!$E:$E,$E8,合并抵消!$A:$A,M$2)) | ... Q8: =浙江精准学!Q8+知识跳跳!Q8+海南精准学!Q8+实时查!Q8+目标准!Q8+'SMART LEARNING HOLDING'!Q8+'SMART AI LIMITED'!Q8+'HK01'!Q8-(SUMIFS(合并抵消!$J:$J,合并抵消!$E:$E,$E8,合并抵消!$A:$A,Q$2)-SUMIFS(合并抵消!$K:$K,合并抵消!$E:$E,$E8,合并抵消!$A:$A,Q$2)) | R8: =SUM(F8:Q8)
A9: 收入 | B9: 政府补贴收入 | C9: 营业外收入 | D9: 政府补贴收入 | E9: Q0301 | F9: =浙江精准学!F9+知识跳跳!F9+海南精准学!F9+实时查!F9+目标准!F9+'SMART LEARNING HOLDING'!F9+'SMART AI LIMITED'!F9+'HK01'!F9-(SUMIFS(合并抵消!$J:$J,合并抵消!$E:$E,$E9,合并抵消!$A:$A,F$2)-SUMIFS(合并抵消!$K:$K,合并抵消!$E:$E,$E9,合并抵消!$A:$A,F$2)) | G9: =浙江精准学!G9+知识跳跳!G9+海南精准学!G9+实时查!G9+目标准!G9+'SMART LEARNING HOLDING'!G9+'SMART AI LIMITED'!G9+'HK01'!G9-(SUMIFS(合并抵消!$J:$J,合并抵消!$E:$E,$E9,合并抵消!$A:$A,G$2)-SUMIFS(合并抵消!$K:$K,合并抵消!$E:$E,$E9,合并抵消!$A:$A,G$2)) | H9: =浙江精准学!H9+知识跳跳!H9+海南精准学!H9+实时查!H9+目标准!H9+'SMART LEARNING HOLDING'!H9+'SMART AI LIMITED'!H9+'HK01'!H9-(SUMIFS(合并抵消!$J:$J,合并抵消!$E:$E,$E9,合并抵消!$A:$A,H$2)-SUMIFS(合并抵消!$K:$K,合并抵消!$E:$E,$E9,合并抵消!$A:$A,H$2)) | I9: =浙江精准学!I9+知识跳跳!I9+海南精准学!I9+实时查!I9+目标准!I9+'SMART LEARNING HOLDING'!I9+'SMART AI LIMITED'!I9+'HK01'!I9-(SUMIFS(合并抵消!$J:$J,合并抵消!$E:$E,$E9,合并抵消!$A:$A,I$2)-SUMIFS(合并抵消!$K:$K,合并抵消!$E:$E,$E9,合并抵消!$A:$A,I$2)) | J9: =浙江精准学!J9+知识跳跳!J9+海南精准学!J9+实时查!J9+目标准!J9+'SMART LEARNING HOLDING'!J9+'SMART AI LIMITED'!J9+'HK01'!J9-(SUMIFS(合并抵消!$J:$J,合并抵消!$E:$E,$E9,合并抵消!$A:$A,J$2)-SUMIFS(合并抵消!$K:$K,合并抵消!$E:$E,$E9,合并抵消!$A:$A,J$2)) | K9: =浙江精准学!K9+知识跳跳!K9+海南精准学!K9+实时查!K9+目标准!K9+'SMART LEARNING HOLDING'!K9+'SMART AI LIMITED'!K9+'HK01'!K9-(SUMIFS(合并抵消!$J:$J,合并抵消!$E:$E,$E9,合并抵消!$A:$A,K$2)-SUMIFS(合并抵消!$K:$K,合并抵消!$E:$E,$E9,合并抵消!$A:$A,K$2)) | L9: =浙江精准学!L9+知识跳跳!L9+海南精准学!L9+实时查!L9+目标准!L9+'SMART LEARNING HOLDING'!L9+'SMART AI LIMITED'!L9+'HK01'!L9-(SUMIFS(合并抵消!$J:$J,合并抵消!$E:$E,$E9,合并抵消!$A:$A,L$2)-SUMIFS(合并抵消!$K:$K,合并抵消!$E:$E,$E9,合并抵消!$A:$A,L$2)) | M9: =浙江精准学!M9+知识跳跳!M9+海南精准学!M9+实时查!M9+目标准!M9+'SMART LEARNING HOLDING'!M9+'SMART AI LIMITED'!M9+'HK01'!M9-(SUMIFS(合并抵消!$J:$J,合并抵消!$E:$E,$E9,合并抵消!$A:$A,M$2)-SUMIFS(合并抵消!$K:$K,合并抵消!$E:$E,$E9,合并抵消!$A:$A,M$2)) | ... Q9: =浙江精准学!Q9+知识跳跳!Q9+海南精准学!Q9+实时查!Q9+目标准!Q9+'SMART LEARNING HOLDING'!Q9+'SMART AI LIMITED'!Q9+'HK01'!Q9-(SUMIFS(合并抵消!$J:$J,合并抵消!$E:$E,$E9,合并抵消!$A:$A,Q$2)-SUMIFS(合并抵消!$K:$K,合并抵消!$E:$E,$E9,合并抵消!$A:$A,Q$2)) | R9: =SUM(F9:Q9)
A10: 收入 | B10: 利息收入 | D10: 利息收入 | E10: Q0302 | F10: =浙江精准学!F10+知识跳跳!F10+海南精准学!F10+实时查!F10+目标准!F10+'SMART LEARNING HOLDING'!F10+'SMART AI LIMITED'!F10+'HK01'!F10-(SUMIFS(合并抵消!$J:$J,合并抵消!$E:$E,$E10,合并抵消!$A:$A,F$2)-SUMIFS(合并抵消!$K:$K,合并抵消!$E:$E,$E10,合并抵消!$A:$A,F$2)) | G10: =浙江精准学!G10+知识跳跳!G10+海南精准学!G10+实时查!G10+目标准!G10+'SMART LEARNING HOLDING'!G10+'SMART AI LIMITED'!G10+'HK01'!G10-(SUMIFS(合并抵消!$J:$J,合并抵消!$E:$E,$E10,合并抵消!$A:$A,G$2)-SUMIFS(合并抵消!$K:$K,合并抵消!$E:$E,$E10,合并抵消!$A:$A,G$2)) | H10: =浙江精准学!H10+知识跳跳!H10+海南精准学!H10+实时查!H10+目标准!H10+'SMART LEARNING HOLDING'!H10+'SMART AI LIMITED'!H10+'HK01'!H10-(SUMIFS(合并抵消!$J:$J,合并抵消!$E:$E,$E10,合并抵消!$A:$A,H$2)-SUMIFS(合并抵消!$K:$K,合并抵消!$E:$E,$E10,合并抵消!$A:$A,H$2)) | I10: =浙江精准学!I10+知识跳跳!I10+海南精准学!I10+实时查!I10+目标准!I10+'SMART LEARNING HOLDING'!I10+'SMART AI LIMITED'!I10+'HK01'!I10-(SUMIFS(合并抵消!$J:$J,合并抵消!$E:$E,$E10,合并抵消!$A:$A,I$2)-SUMIFS(合并抵消!$K:$K,合并抵消!$E:$E,$E10,合并抵消!$A:$A,I$2)) | J10: =浙江精准学!J10+知识跳跳!J10+海南精准学!J10+实时查!J10+目标准!J10+'SMART LEARNING HOLDING'!J10+'SMART AI LIMITED'!J10+'HK01'!J10-(SUMIFS(合并抵消!$J:$J,合并抵消!$E:$E,$E10,合并抵消!$A:$A,J$2)-SUMIFS(合并抵消!$K:$K,合并抵消!$E:$E,$E10,合并抵消!$A:$A,J$2)) | K10: =浙江精准学!K10+知识跳跳!K10+海南精准学!K10+实时查!K10+目标准!K10+'SMART LEARNING HOLDING'!K10+'SMART AI LIMITED'!K10+'HK01'!K10-(SUMIFS(合并抵消!$J:$J,合并抵消!$E:$E,$E10,合并抵消!$A:$A,K$2)-SUMIFS(合并抵消!$K:$K,合并抵消!$E:$E,$E10,合并抵消!$A:$A,K$2)) | L10: =浙江精准学!L10+知识跳跳!L10+海南精准学!L10+实时查!L10+目标准!L10+'SMART LEARNING HOLDING'!L10+'SMART AI LIMITED'!L10+'HK01'!L10-(SUMIFS(合并抵消!$J:$J,合并抵消!$E:$E,$E10,合并抵消!$A:$A,L$2)-SUMIFS(合并抵消!$K:$K,合并抵消!$E:$E,$E10,合并抵消!$A:$A,L$2)) | M10: =浙江精准学!M10+知识跳跳!M10+海南精准学!M10+实时查!M10+目标准!M10+'SMART LEARNING HOLDING'!M10+'SMART AI LIMITED'!M10+'HK01'!M10-(SUMIFS(合并抵消!$J:$J,合并抵消!$E:$E,$E10,合并抵消!$A:$A,M$2)-SUMIFS(合并抵消!$K:$K,合并抵消!$E:$E,$E10,合并抵消!$A:$A,M$2)) | ... Q10: =浙江精准学!Q10+知识跳跳!Q10+海南精准学!Q10+实时查!Q10+目标准!Q10+'SMART LEARNING HOLDING'!Q10+'SMART AI LIMITED'!Q10+'HK01'!Q10-(SUMIFS(合并抵消!$J:$J,合并抵消!$E:$E,$E10,合并抵消!$A:$A,Q$2)-SUMIFS(合并抵消!$K:$K,合并抵消!$E:$E,$E10,合并抵消!$A:$A,Q$2)) | R10: =SUM(F10:Q10)
A11: 收入 | B11: 营业外收入 | D11: 其他收入 | E11: Q0303 | F11: =浙江精准学!F11+知识跳跳!F11+海南精准学!F11+实时查!F11+目标准!F11+'SMART LEARNING HOLDING'!F11+'SMART AI LIMITED'!F11+'HK01'!F11-(SUMIFS(合并抵消!$J:$J,合并抵消!$E:$E,$E11,合并抵消!$A:$A,F$2)-SUMIFS(合并抵消!$K:$K,合并抵消!$E:$E,$E11,合并抵消!$A:$A,F$2)) | G11: =浙江精准学!G11+知识跳跳!G11+海南精准学!G11+实时查!G11+目标准!G11+'SMART LEARNING HOLDING'!G11+'SMART AI LIMITED'!G11+'HK01'!G11-(SUMIFS(合并抵消!$J:$J,合并抵消!$E:$E,$E11,合并抵消!$A:$A,G$2)-SUMIFS(合并抵消!$K:$K,合并抵消!$E:$E,$E11,合并抵消!$A:$A,G$2)) | H11: =浙江精准学!H11+知识跳跳!H11+海南精准学!H11+实时查!H11+目标准!H11+'SMART LEARNING HOLDING'!H11+'SMART AI LIMITED'!H11+'HK01'!H11-(SUMIFS(合并抵消!$J:$J,合并抵消!$E:$E,$E11,合并抵消!$A:$A,H$2)-SUMIFS(合并抵消!$K:$K,合并抵消!$E:$E,$E11,合并抵消!$A:$A,H$2)) | I11: =浙江精准学!I11+知识跳跳!I11+海南精准学!I11+实时查!I11+目标准!I11+'SMART LEARNING HOLDING'!I11+'SMART AI LIMITED'!I11+'HK01'!I11-(SUMIFS(合并抵消!$J:$J,合并抵消!$E:$E,$E11,合并抵消!$A:$A,I$2)-SUMIFS(合并抵消!$K:$K,合并抵消!$E:$E,$E11,合并抵消!$A:$A,I$2)) | J11: =浙江精准学!J11+知识跳跳!J11+海南精准学!J11+实时查!J11+目标准!J11+'SMART LEARNING HOLDING'!J11+'SMART AI LIMITED'!J11+'HK01'!J11-(SUMIFS(合并抵消!$J:$J,合并抵消!$E:$E,$E11,合并抵消!$A:$A,J$2)-SUMIFS(合并抵消!$K:$K,合并抵消!$E:$E,$E11,合并抵消!$A:$A,J$2)) | K11: =浙江精准学!K11+知识跳跳!K11+海南精准学!K11+实时查!K11+目标准!K11+'SMART LEARNING HOLDING'!K11+'SMART AI LIMITED'!K11+'HK01'!K11-(SUMIFS(合并抵消!$J:$J,合并抵消!$E:$E,$E11,合并抵消!$A:$A,K$2)-SUMIFS(合并抵消!$K:$K,合并抵消!$E:$E,$E11,合并抵消!$A:$A,K$2)) | L11: =浙江精准学!L11+知识跳跳!L11+海南精准学!L11+实时查!L11+目标准!L11+'SMART LEARNING HOLDING'!L11+'SMART AI LIMITED'!L11+'HK01'!L11-(SUMIFS(合并抵消!$J:$J,合并抵消!$E:$E,$E11,合并抵消!$A:$A,L$2)-SUMIFS(合并抵消!$K:$K,合并抵消!$E:$E,$E11,合并抵消!$A:$A,L$2)) | M11: =浙江精准学!M11+知识跳跳!M11+海南精准学!M11+实时查!M11+目标准!M11+'SMART LEARNING HOLDING'!M11+'SMART AI LIMITED'!M11+'HK01'!M11-(SUMIFS(合并抵消!$J:$J,合并抵消!$E:$E,$E11,合并抵消!$A:$A,M$2)-SUMIFS(合并抵消!$K:$K,合并抵消!$E:$E,$E11,合并抵消!$A:$A,M$2)) | ... Q11: =浙江精准学!Q11+知识跳跳!Q11+海南精准学!Q11+实时查!Q11+目标准!Q11+'SMART LEARNING HOLDING'!Q11+'SMART AI LIMITED'!Q11+'HK01'!Q11-(SUMIFS(合并抵消!$J:$J,合并抵消!$E:$E,$E11,合并抵消!$A:$A,Q$2)-SUMIFS(合并抵消!$K:$K,合并抵消!$E:$E,$E11,合并抵消!$A:$A,Q$2)) | R11: =SUM(F11:Q11)
A12: 收入合计 | F12: =SUM(F3:F11) | G12: =SUM(G3:G11) | H12: =SUM(H3:H11) | I12: =SUM(I3:I11) | J12: =SUM(J3:J11) | K12: =SUM(K3:K11) | L12: =SUM(L3:L11) | M12: =SUM(M3:M11) | ... Q12: =SUM(Q3:Q11) | R12: =SUM(F12:Q12)
A13: 往来款项收入 | B13: 往来款项收入 | C13: 往来款项收入 | D13: 内部往来收入 | E13: Q0401 | F13: =浙江精准学!F13+知识跳跳!F13+海南精准学!F13+实时查!F13+目标准!F13+'SMART LEARNING HOLDING'!F13+'SMART AI LIMITED'!F13+'HK01'!F13-(SUMIFS(合并抵消!$J:$J,合并抵消!$E:$E,$E13,合并抵消!$A:$A,F$2)-SUMIFS(合并抵消!$K:$K,合并抵消!$E:$E,$E13,合并抵消!$A:$A,F$2)) | G13: =浙江精准学!G13+知识跳跳!G13+海南精准学!G13+实时查!G13+目标准!G13+'SMART LEARNING HOLDING'!G13+'SMART AI LIMITED'!G13+'HK01'!G13-(SUMIFS(合并抵消!$J:$J,合并抵消!$E:$E,$E13,合并抵消!$A:$A,G$2)-SUMIFS(合并抵消!$K:$K,合并抵消!$E:$E,$E13,合并抵消!$A:$A,G$2)) | H13: =浙江精准学!H13+知识跳跳!H13+海南精准学!H13+实时查!H13+目标准!H13+'SMART LEARNING HOLDING'!H13+'SMART AI LIMITED'!H13+'HK01'!H13-(SUMIFS(合并抵消!$J:$J,合并抵消!$E:$E,$E13,合并抵消!$A:$A,H$2)-SUMIFS(合并抵消!$K:$K,合并抵消!$E:$E,$E13,合并抵消!$A:$A,H$2)) | I13: =浙江精准学!I13+知识跳跳!I13+海南精准学!I13+实时查!I13+目标准!I13+'SMART LEARNING HOLDING'!I13+'SMART AI LIMITED'!I13+'HK01'!I13-(SUMIFS(合并抵消!$J:$J,合并抵消!$E:$E,$E13,合并抵消!$A:$A,I$2)-SUMIFS(合并抵消!$K:$K,合并抵消!$E:$E,$E13,合并抵消!$A:$A,I$2)) | J13: =浙江精准学!J13+知识跳跳!J13+海南精准学!J13+实时查!J13+目标准!J13+'SMART LEARNING HOLDING'!J13+'SMART AI LIMITED'!J13+'HK01'!J13-(SUMIFS(合并抵消!$J:$J,合并抵消!$E:$E,$E13,合并抵消!$A:$A,J$2)-SUMIFS(合并抵消!$K:$K,合并抵消!$E:$E,$E13,合并抵消!$A:$A,J$2)) | K13: =浙江精准学!K13+知识跳跳!K13+海南精准学!K13+实时查!K13+目标准!K13+'SMART LEARNING HOLDING'!K13+'SMART AI LIMITED'!K13+'HK01'!K13-(SUMIFS(合并抵消!$J:$J,合并抵消!$E:$E,$E13,合并抵消!$A:$A,K$2)-SUMIFS(合并抵消!$K:$K,合并抵消!$E:$E,$E13,合并抵消!$A:$A,K$2)) | L13: =浙江精准学!L13+知识跳跳!L13+海南精准学!L13+实时查!L13+目标准!L13+'SMART LEARNING HOLDING'!L13+'SMART AI LIMITED'!L13+'HK01'!L13-(SUMIFS(合并抵消!$J:$J,合并抵消!$E:$E,$E13,合并抵消!$A:$A,L$2)-SUMIFS(合并抵消!$K:$K,合并抵消!$E:$E,$E13,合并抵消!$A:$A,L$2)) | M13: =浙江精准学!M13+知识跳跳!M13+海南精准学!M13+实时查!M13+目标准!M13+'SMART LEARNING HOLDING'!M13+'SMART AI LIMITED'!M13+'HK01'!M13-(SUMIFS(合并抵消!$J:$J,合并抵消!$E:$E,$E13,合并抵消!$A:$A,M$2)-SUMIFS(合并抵消!$K:$K,合并抵消!$E:$E,$E13,合并抵消!$A:$A,M$2)) | ... Q13: =浙江精准学!Q13+知识跳跳!Q13+海南精准学!Q13+实时查!Q13+目标准!Q13+'SMART LEARNING HOLDING'!Q13+'SMART AI LIMITED'!Q13+'HK01'!Q13-(SUMIFS(合并抵消!$J:$J,合并抵消!$E:$E,$E13,合并抵消!$A:$A,Q$2)-SUMIFS(合并抵消!$K:$K,合并抵消!$E:$E,$E13,合并抵消!$A:$A,Q$2)) | R13: =SUM(F13:Q13)
A14: 往来款项收入 | B14: 往来款项收入 | D14: 外部往来收入 | E14: Q0402 | F14: =浙江精准学!F14+知识跳跳!F14+海南精准学!F14+实时查!F14+目标准!F14+'SMART LEARNING HOLDING'!F14+'SMART AI LIMITED'!F14+'HK01'!F14-(SUMIFS(合并抵消!$J:$J,合并抵消!$E:$E,$E14,合并抵消!$A:$A,F$2)-SUMIFS(合并抵消!$K:$K,合并抵消!$E:$E,$E14,合并抵消!$A:$A,F$2)) | G14: =浙江精准学!G14+知识跳跳!G14+海南精准学!G14+实时查!G14+目标准!G14+'SMART LEARNING HOLDING'!G14+'SMART AI LIMITED'!G14+'HK01'!G14-(SUMIFS(合并抵消!$J:$J,合并抵消!$E:$E,$E14,合并抵消!$A:$A,G$2)-SUMIFS(合并抵消!$K:$K,合并抵消!$E:$E,$E14,合并抵消!$A:$A,G$2)) | H14: =浙江精准学!H14+知识跳跳!H14+海南精准学!H14+实时查!H14+目标准!H14+'SMART LEARNING HOLDING'!H14+'SMART AI LIMITED'!H14+'HK01'!H14-(SUMIFS(合并抵消!$J:$J,合并抵消!$E:$E,$E14,合并抵消!$A:$A,H$2)-SUMIFS(合并抵消!$K:$K,合并抵消!$E:$E,$E14,合并抵消!$A:$A,H$2)) | I14: =浙江精准学!I14+知识跳跳!I14+海南精准学!I14+实时查!I14+目标准!I14+'SMART LEARNING HOLDING'!I14+'SMART AI LIMITED'!I14+'HK01'!I14-(SUMIFS(合并抵消!$J:$J,合并抵消!$E:$E,$E14,合并抵消!$A:$A,I$2)-SUMIFS(合并抵消!$K:$K,合并抵消!$E:$E,$E14,合并抵消!$A:$A,I$2)) | J14: =浙江精准学!J14+知识跳跳!J14+海南精准学!J14+实时查!J14+目标准!J14+'SMART LEARNING HOLDING'!J14+'SMART AI LIMITED'!J14+'HK01'!J14-(SUMIFS(合并抵消!$J:$J,合并抵消!$E:$E,$E14,合并抵消!$A:$A,J$2)-SUMIFS(合并抵消!$K:$K,合并抵消!$E:$E,$E14,合并抵消!$A:$A,J$2)) | K14: =浙江精准学!K14+知识跳跳!K14+海南精准学!K14+实时查!K14+目标准!K14+'SMART LEARNING HOLDING'!K14+'SMART AI LIMITED'!K14+'HK01'!K14-(SUMIFS(合并抵消!$J:$J,合并抵消!$E:$E,$E14,合并抵消!$A:$A,K$2)-SUMIFS(合并抵消!$K:$K,合并抵消!$E:$E,$E14,合并抵消!$A:$A,K$2)) | L14: =浙江精准学!L14+知识跳跳!L14+海南精准学!L14+实时查!L14+目标准!L14+'SMART LEARNING HOLDING'!L14+'SMART AI LIMITED'!L14+'HK01'!L14-(SUMIFS(合并抵消!$J:$J,合并抵消!$E:$E,$E14,合并抵消!$A:$A,L$2)-SUMIFS(合并抵消!$K:$K,合并抵消!$E:$E,$E14,合并抵消!$A:$A,L$2)) | M14: =浙江精准学!M14+知识跳跳!M14+海南精准学!M14+实时查!M14+目标准!M14+'SMART LEARNING HOLDING'!M14+'SMART AI LIMITED'!M14+'HK01'!M14-(SUMIFS(合并抵消!$J:$J,合并抵消!$E:$E,$E14,合并抵消!$A:$A,M$2)-SUMIFS(合并抵消!$K:$K,合并抵消!$E:$E,$E14,合并抵消!$A:$A,M$2)) | ... Q14: =浙江精准学!Q14+知识跳跳!Q14+海南精准学!Q14+实时查!Q14+目标准!Q14+'SMART LEARNING HOLDING'!Q14+'SMART AI LIMITED'!Q14+'HK01'!Q14-(SUMIFS(合并抵消!$J:$J,合并抵消!$E:$E,$E14,合并抵消!$A:$A,Q$2)-SUMIFS(合并抵消!$K:$K,合并抵消!$E:$E,$E14,合并抵消!$A:$A,Q$2)) | R14: =SUM(F14:Q14)
A15: 往来款项收入合计 | F15: =SUM(F13:F14) | G15: =SUM(G13:G14) | H15: =SUM(H13:H14) | I15: =SUM(I13:I14) | J15: =SUM(J13:J14) | K15: =SUM(K13:K14) | L15: =SUM(L13:L14) | M15: =SUM(M13:M14) | ... Q15: =SUM(Q13:Q14) | R15: =SUM(F15:Q15)
A16: 投资款收入 | B16: 投资款收入 | C16: 投资款收入 | D16: 内部投资款收入 | E16: Q0501 | F16: =浙江精准学!F16+知识跳跳!F16+海南精准学!F16+实时查!F16+目标准!F16+'SMART LEARNING HOLDING'!F16+'SMART AI LIMITED'!F16+'HK01'!F16-(SUMIFS(合并抵消!$J:$J,合并抵消!$E:$E,$E16,合并抵消!$A:$A,F$2)-SUMIFS(合并抵消!$K:$K,合并抵消!$E:$E,$E16,合并抵消!$A:$A,F$2)) | G16: =浙江精准学!G16+知识跳跳!G16+海南精准学!G16+实时查!G16+目标准!G16+'SMART LEARNING HOLDING'!G16+'SMART AI LIMITED'!G16+'HK01'!G16-(SUMIFS(合并抵消!$J:$J,合并抵消!$E:$E,$E16,合并抵消!$A:$A,G$2)-SUMIFS(合并抵消!$K:$K,合并抵消!$E:$E,$E16,合并抵消!$A:$A,G$2)) | H16: =浙江精准学!H16+知识跳跳!H16+海南精准学!H16+实时查!H16+目标准!H16+'SMART LEARNING HOLDING'!H16+'SMART AI LIMITED'!H16+'HK01'!H16-(SUMIFS(合并抵消!$J:$J,合并抵消!$E:$E,$E16,合并抵消!$A:$A,H$2)-SUMIFS(合并抵消!$K:$K,合并抵消!$E:$E,$E16,合并抵消!$A:$A,H$2)) | I16: =浙江精准学!I16+知识跳跳!I16+海南精准学!I16+实时查!I16+目标准!I16+'SMART LEARNING HOLDING'!I16+'SMART AI LIMITED'!I16+'HK01'!I16-(SUMIFS(合并抵消!$J:$J,合并抵消!$E:$E,$E16,合并抵消!$A:$A,I$2)-SUMIFS(合并抵消!$K:$K,合并抵消!$E:$E,$E16,合并抵消!$A:$A,I$2)) | J16: =浙江精准学!J16+知识跳跳!J16+海南精准学!J16+实时查!J16+目标准!J16+'SMART LEARNING HOLDING'!J16+'SMART AI LIMITED'!J16+'HK01'!J16-(SUMIFS(合并抵消!$J:$J,合并抵消!$E:$E,$E16,合并抵消!$A:$A,J$2)-SUMIFS(合并抵消!$K:$K,合并抵消!$E:$E,$E16,合并抵消!$A:$A,J$2)) | K16: =浙江精准学!K16+知识跳跳!K16+海南精准学!K16+实时查!K16+目标准!K16+'SMART LEARNING HOLDING'!K16+'SMART AI LIMITED'!K16+'HK01'!K16-(SUMIFS(合并抵消!$J:$J,合并抵消!$E:$E,$E16,合并抵消!$A:$A,K$2)-SUMIFS(合并抵消!$K:$K,合并抵消!$E:$E,$E16,合并抵消!$A:$A,K$2)) | L16: =浙江精准学!L16+知识跳跳!L16+海南精准学!L16+实时查!L16+目标准!L16+'SMART LEARNING HOLDING'!L16+'SMART AI LIMITED'!L16+'HK01'!L16-(SUMIFS(合并抵消!$J:$J,合并抵消!$E:$E,$E16,合并抵消!$A:$A,L$2)-SUMIFS(合并抵消!$K:$K,合并抵消!$E:$E,$E16,合并抵消!$A:$A,L$2)) | M16: =浙江精准学!M16+知识跳跳!M16+海南精准学!M16+实时查!M16+目标准!M16+'SMART LEARNING HOLDING'!M16+'SMART AI LIMITED'!M16+'HK01'!M16-(SUMIFS(合并抵消!$J:$J,合并抵消!$E:$E,$E16,合并抵消!$A:$A,M$2)-SUMIFS(合并抵消!$K:$K,合并抵消!$E:$E,$E16,合并抵消!$A:$A,M$2)) | ... Q16: =浙江精准学!Q16+知识跳跳!Q16+海南精准学!Q16+实时查!Q16+目标准!Q16+'SMART LEARNING HOLDING'!Q16+'SMART AI LIMITED'!Q16+'HK01'!Q16-(SUMIFS(合并抵消!$J:$J,合并抵消!$E:$E,$E16,合并抵消!$A:$A,Q$2)-SUMIFS(合并抵消!$K:$K,合并抵消!$E:$E,$E16,合并抵消!$A:$A,Q$2)) | R16: =SUM(F16:Q16)
A17: 投资款收入 | B17: 投资款收入 | D17: 外部投资款收入 | E17: Q0502 | F17: =浙江精准学!F17+知识跳跳!F17+海南精准学!F17+实时查!F17+目标准!F17+'SMART LEARNING HOLDING'!F17+'SMART AI LIMITED'!F17+'HK01'!F17-(SUMIFS(合并抵消!$J:$J,合并抵消!$E:$E,$E17,合并抵消!$A:$A,F$2)-SUMIFS(合并抵消!$K:$K,合并抵消!$E:$E,$E17,合并抵消!$A:$A,F$2)) | G17: =浙江精准学!G17+知识跳跳!G17+海南精准学!G17+实时查!G17+目标准!G17+'SMART LEARNING HOLDING'!G17+'SMART AI LIMITED'!G17+'HK01'!G17-(SUMIFS(合并抵消!$J:$J,合并抵消!$E:$E,$E17,合并抵消!$A:$A,G$2)-SUMIFS(合并抵消!$K:$K,合并抵消!$E:$E,$E17,合并抵消!$A:$A,G$2)) | H17: =浙江精准学!H17+知识跳跳!H17+海南精准学!H17+实时查!H17+目标准!H17+'SMART LEARNING HOLDING'!H17+'SMART AI LIMITED'!H17+'HK01'!H17-(SUMIFS(合并抵消!$J:$J,合并抵消!$E:$E,$E17,合并抵消!$A:$A,H$2)-SUMIFS(合并抵消!$K:$K,合并抵消!$E:$E,$E17,合并抵消!$A:$A,H$2)) | I17: =浙江精准学!I17+知识跳跳!I17+海南精准学!I17+实时查!I17+目标准!I17+'SMART LEARNING HOLDING'!I17+'SMART AI LIMITED'!I17+'HK01'!I17-(SUMIFS(合并抵消!$J:$J,合并抵消!$E:$E,$E17,合并抵消!$A:$A,I$2)-SUMIFS(合并抵消!$K:$K,合并抵消!$E:$E,$E17,合并抵消!$A:$A,I$2)) | J17: =浙江精准学!J17+知识跳跳!J17+海南精准学!J17+实时查!J17+目标准!J17+'SMART LEARNING HOLDING'!J17+'SMART AI LIMITED'!J17+'HK01'!J17-(SUMIFS(合并抵消!$J:$J,合并抵消!$E:$E,$E17,合并抵消!$A:$A,J$2)-SUMIFS(合并抵消!$K:$K,合并抵消!$E:$E,$E17,合并抵消!$A:$A,J$2)) | K17: =浙江精准学!K17+知识跳跳!K17+海南精准学!K17+实时查!K17+目标准!K17+'SMART LEARNING HOLDING'!K17+'SMART AI LIMITED'!K17+'HK01'!K17-(SUMIFS(合并抵消!$J:$J,合并抵消!$E:$E,$E17,合并抵消!$A:$A,K$2)-SUMIFS(合并抵消!$K:$K,合并抵消!$E:$E,$E17,合并抵消!$A:$A,K$2)) | L17: =浙江精准学!L17+知识跳跳!L17+海南精准学!L17+实时查!L17+目标准!L17+'SMART LEARNING HOLDING'!L17+'SMART AI LIMITED'!L17+'HK01'!L17-(SUMIFS(合并抵消!$J:$J,合并抵消!$E:$E,$E17,合并抵消!$A:$A,L$2)-SUMIFS(合并抵消!$K:$K,合并抵消!$E:$E,$E17,合并抵消!$A:$A,L$2)) | M17: =浙江精准学!M17+知识跳跳!M17+海南精准学!M17+实时查!M17+目标准!M17+'SMART LEARNING HOLDING'!M17+'SMART AI LIMITED'!M17+'HK01'!M17-(SUMIFS(合并抵消!$J:$J,合并抵消!$E:$E,$E17,合并抵消!$A:$A,M$2)-SUMIFS(合并抵消!$K:$K,合并抵消!$E:$E,$E17,合并抵消!$A:$A,M$2)) | ... Q17: =浙江精准学!Q17+知识跳跳!Q17+海南精准学!Q17+实时查!Q17+目标准!Q17+'SMART LEARNING HOLDING'!Q17+'SMART AI LIMITED'!Q17+'HK01'!Q17-(SUMIFS(合并抵消!$J:$J,合并抵消!$E:$E,$E17,合并抵消!$A:$A,Q$2)-SUMIFS(合并抵消!$K:$K,合并抵消!$E:$E,$E17,合并抵消!$A:$A,Q$2)) | R17: =SUM(F17:Q17)
A18: 投资款收入合计 | F18: =SUM(F16:F17) | G18: =SUM(G16:G17) | H18: =SUM(H16:H17) | I18: =SUM(I16:I17) | J18: =SUM(J16:J17) | K18: =SUM(K16:K17) | L18: =SUM(L16:L17) | M18: =SUM(M16:M17) | ... Q18: =SUM(Q16:Q17) | R18: =SUM(F18:Q18)
A19: 收款合计 | F19: =ROUND(F12+F15+F18,2) | G19: =ROUND(G12+G15+G18,2) | H19: =ROUND(H12+H15+H18,2) | I19: =ROUND(I12+I15+I18,2) | J19: =ROUND(J12+J15+J18,2) | K19: =ROUND(K12+K15+K18,2) | L19: =ROUND(L12+L15+L18,2) | M19: =ROUND(M12+M15+M18,2) | ... Q19: =ROUND(Q12+Q15+Q18,2) | R19: =SUM(F19:Q19)
A20: 往来款项支出 | B20: 往来款项支出 | C20: 往来款项支出 | D20: 内部往来支出 | E20: Q0601 | F20: =浙江精准学!F20+知识跳跳!F20+海南精准学!F20+实时查!F20+目标准!F20+'SMART LEARNING HOLDING'!F20+'SMART AI LIMITED'!F20+'HK01'!F20-(-SUMIFS(合并抵消!$J:$J,合并抵消!$E:$E,$E20,合并抵消!$A:$A,F$2)+SUMIFS(合并抵消!$K:$K,合并抵消!$E:$E,$E20,合并抵消!$A:$A,F$2)) | G20: =浙江精准学!G20+知识跳跳!G20+海南精准学!G20+实时查!G20+目标准!G20+'SMART LEARNING HOLDING'!G20+'SMART AI LIMITED'!G20+'HK01'!G20-(-SUMIFS(合并抵消!$J:$J,合并抵消!$E:$E,$E20,合并抵消!$A:$A,G$2)+SUMIFS(合并抵消!$K:$K,合并抵消!$E:$E,$E20,合并抵消!$A:$A,G$2)) | H20: =浙江精准学!H20+知识跳跳!H20+海南精准学!H20+实时查!H20+目标准!H20+'SMART LEARNING HOLDING'!H20+'SMART AI LIMITED'!H20+'HK01'!H20-(-SUMIFS(合并抵消!$J:$J,合并抵消!$E:$E,$E20,合并抵消!$A:$A,H$2)+SUMIFS(合并抵消!$K:$K,合并抵消!$E:$E,$E20,合并抵消!$A:$A,H$2)) | I20: =浙江精准学!I20+知识跳跳!I20+海南精准学!I20+实时查!I20+目标准!I20+'SMART LEARNING HOLDING'!I20+'SMART AI LIMITED'!I20+'HK01'!I20-(-SUMIFS(合并抵消!$J:$J,合并抵消!$E:$E,$E20,合并抵消!$A:$A,I$2)+SUMIFS(合并抵消!$K:$K,合并抵消!$E:$E,$E20,合并抵消!$A:$A,I$2)) | J20: =浙江精准学!J20+知识跳跳!J20+海南精准学!J20+实时查!J20+目标准!J20+'SMART LEARNING HOLDING'!J20+'SMART AI LIMITED'!J20+'HK01'!J20-(-SUMIFS(合并抵消!$J:$J,合并抵消!$E:$E,$E20,合并抵消!$A:$A,J$2)+SUMIFS(合并抵消!$K:$K,合并抵消!$E:$E,$E20,合并抵消!$A:$A,J$2)) | K20: =浙江精准学!K20+知识跳跳!K20+海南精准学!K20+实时查!K20+目标准!K20+'SMART LEARNING HOLDING'!K20+'SMART AI LIMITED'!K20+'HK01'!K20-(-SUMIFS(合并抵消!$J:$J,合并抵消!$E:$E,$E20,合并抵消!$A:$A,K$2)+SUMIFS(合并抵消!$K:$K,合并抵消!$E:$E,$E20,合并抵消!$A:$A,K$2)) | L20: =浙江精准学!L20+知识跳跳!L20+海南精准学!L20+实时查!L20+目标准!L20+'SMART LEARNING HOLDING'!L20+'SMART AI LIMITED'!L20+'HK01'!L20-(-SUMIFS(合并抵消!$J:$J,合并抵消!$E:$E,$E20,合并抵消!$A:$A,L$2)+SUMIFS(合并抵消!$K:$K,合并抵消!$E:$E,$E20,合并抵消!$A:$A,L$2)) | M20: =浙江精准学!M20+知识跳跳!M20+海南精准学!M20+实时查!M20+目标准!M20+'SMART LEARNING HOLDING'!M20+'SMART AI LIMITED'!M20+'HK01'!M20-(-SUMIFS(合并抵消!$J:$J,合并抵消!$E:$E,$E20,合并抵消!$A:$A,M$2)+SUMIFS(合并抵消!$K:$K,合并抵消!$E:$E,$E20,合并抵消!$A:$A,M$2)) | ... Q20: =浙江精准学!Q20+知识跳跳!Q20+海南精准学!Q20+实时查!Q20+目标准!Q20+'SMART LEARNING HOLDING'!Q20+'SMART AI LIMITED'!Q20+'HK01'!Q20-(-SUMIFS(合并抵消!$J:$J,合并抵消!$E:$E,$E20,合并抵消!$A:$A,Q$2)+SUMIFS(合并抵消!$K:$K,合并抵消!$E:$E,$E20,合并抵消!$A:$A,Q$2)) | R20: =SUM(F20:Q20)
A21: 往来款项支出 | B21: 往来款项支出 | D21: 外部往来支出 | E21: Q0602 | F21: =浙江精准学!F21+知识跳跳!F21+海南精准学!F21+实时查!F21+目标准!F21+'SMART LEARNING HOLDING'!F21+'SMART AI LIMITED'!F21+'HK01'!F21-(-SUMIFS(合并抵消!$J:$J,合并抵消!$E:$E,$E21,合并抵消!$A:$A,F$2)+SUMIFS(合并抵消!$K:$K,合并抵消!$E:$E,$E21,合并抵消!$A:$A,F$2)) | G21: =浙江精准学!G21+知识跳跳!G21+海南精准学!G21+实时查!G21+目标准!G21+'SMART LEARNING HOLDING'!G21+'SMART AI LIMITED'!G21+'HK01'!G21-(-SUMIFS(合并抵消!$J:$J,合并抵消!$E:$E,$E21,合并抵消!$A:$A,G$2)+SUMIFS(合并抵消!$K:$K,合并抵消!$E:$E,$E21,合并抵消!$A:$A,G$2)) | H21: =浙江精准学!H21+知识跳跳!H21+海南精准学!H21+实时查!H21+目标准!H21+'SMART LEARNING HOLDING'!H21+'SMART AI LIMITED'!H21+'HK01'!H21-(-SUMIFS(合并抵消!$J:$J,合并抵消!$E:$E,$E21,合并抵消!$A:$A,H$2)+SUMIFS(合并抵消!$K:$K,合并抵消!$E:$E,$E21,合并抵消!$A:$A,H$2)) | I21: =浙江精准学!I21+知识跳跳!I21+海南精准学!I21+实时查!I21+目标准!I21+'SMART LEARNING HOLDING'!I21+'SMART AI LIMITED'!I21+'HK01'!I21-(-SUMIFS(合并抵消!$J:$J,合并抵消!$E:$E,$E21,合并抵消!$A:$A,I$2)+SUMIFS(合并抵消!$K:$K,合并抵消!$E:$E,$E21,合并抵消!$A:$A,I$2)) | J21: =浙江精准学!J21+知识跳跳!J21+海南精准学!J21+实时查!J21+目标准!J21+'SMART LEARNING HOLDING'!J21+'SMART AI LIMITED'!J21+'HK01'!J21-(-SUMIFS(合并抵消!$J:$J,合并抵消!$E:$E,$E21,合并抵消!$A:$A,J$2)+SUMIFS(合并抵消!$K:$K,合并抵消!$E:$E,$E21,合并抵消!$A:$A,J$2)) | K21: =浙江精准学!K21+知识跳跳!K21+海南精准学!K21+实时查!K21+目标准!K21+'SMART LEARNING HOLDING'!K21+'SMART AI LIMITED'!K21+'HK01'!K21-(-SUMIFS(合并抵消!$J:$J,合并抵消!$E:$E,$E21,合并抵消!$A:$A,K$2)+SUMIFS(合并抵消!$K:$K,合并抵消!$E:$E,$E21,合并抵消!$A:$A,K$2)) | L21: =浙江精准学!L21+知识跳跳!L21+海南精准学!L21+实时查!L21+目标准!L21+'SMART LEARNING HOLDING'!L21+'SMART AI LIMITED'!L21+'HK01'!L21-(-SUMIFS(合并抵消!$J:$J,合并抵消!$E:$E,$E21,合并抵消!$A:$A,L$2)+SUMIFS(合并抵消!$K:$K,合并抵消!$E:$E,$E21,合并抵消!$A:$A,L$2)) | M21: =浙江精准学!M21+知识跳跳!M21+海南精准学!M21+实时查!M21+目标准!M21+'SMART LEARNING HOLDING'!M21+'SMART AI LIMITED'!M21+'HK01'!M21-(-SUMIFS(合并抵消!$J:$J,合并抵消!$E:$E,$E21,合并抵消!$A:$A,M$2)+SUMIFS(合并抵消!$K:$K,合并抵消!$E:$E,$E21,合并抵消!$A:$A,M$2)) | ... Q21: =浙江精准学!Q21+知识跳跳!Q21+海南精准学!Q21+实时查!Q21+目标准!Q21+'SMART LEARNING HOLDING'!Q21+'SMART AI LIMITED'!Q21+'HK01'!Q21-(-SUMIFS(合并抵消!$J:$J,合并抵消!$E:$E,$E21,合并抵消!$A:$A,Q$2)+SUMIFS(合并抵消!$K:$K,合并抵消!$E:$E,$E21,合并抵消!$A:$A,Q$2)) | R21: =SUM(F21:Q21)
A22: 往来款项支出合计 | F22: =SUM(F20:F21) | G22: =SUM(G20:G21) | H22: =SUM(H20:H21) | I22: =SUM(I20:I21) | J22: =SUM(J20:J21) | K22: =SUM(K20:K21) | L22: =SUM(L20:L21) | M22: =SUM(M20:M21) | ... Q22: =SUM(Q20:Q21) | R22: =SUM(F22:Q22)
A23: 投资款支出 | B23: 投资款支出 | C23: 投资款支出 | D23: 内部投资款支出 | E23: Q0701 | F23: =浙江精准学!F23+知识跳跳!F23+海南精准学!F23+实时查!F23+目标准!F23+'SMART LEARNING HOLDING'!F23+'SMART AI LIMITED'!F23+'HK01'!F23-(-SUMIFS(合并抵消!$J:$J,合并抵消!$E:$E,$E23,合并抵消!$A:$A,F$2)+SUMIFS(合并抵消!$K:$K,合并抵消!$E:$E,$E23,合并抵消!$A:$A,F$2)) | G23: =浙江精准学!G23+知识跳跳!G23+海南精准学!G23+实时查!G23+目标准!G23+'SMART LEARNING HOLDING'!G23+'SMART AI LIMITED'!G23+'HK01'!G23-(-SUMIFS(合并抵消!$J:$J,合并抵消!$E:$E,$E23,合并抵消!$A:$A,G$2)+SUMIFS(合并抵消!$K:$K,合并抵消!$E:$E,$E23,合并抵消!$A:$A,G$2)) | H23: =浙江精准学!H23+知识跳跳!H23+海南精准学!H23+实时查!H23+目标准!H23+'SMART LEARNING HOLDING'!H23+'SMART AI LIMITED'!H23+'HK01'!H23-(-SUMIFS(合并抵消!$J:$J,合并抵消!$E:$E,$E23,合并抵消!$A:$A,H$2)+SUMIFS(合并抵消!$K:$K,合并抵消!$E:$E,$E23,合并抵消!$A:$A,H$2)) | I23: =浙江精准学!I23+知识跳跳!I23+海南精准学!I23+实时查!I23+目标准!I23+'SMART LEARNING HOLDING'!I23+'SMART AI LIMITED'!I23+'HK01'!I23-(-SUMIFS(合并抵消!$J:$J,合并抵消!$E:$E,$E23,合并抵消!$A:$A,I$2)+SUMIFS(合并抵消!$K:$K,合并抵消!$E:$E,$E23,合并抵消!$A:$A,I$2)) | J23: =浙江精准学!J23+知识跳跳!J23+海南精准学!J23+实时查!J23+目标准!J23+'SMART LEARNING HOLDING'!J23+'SMART AI LIMITED'!J23+'HK01'!J23-(-SUMIFS(合并抵消!$J:$J,合并抵消!$E:$E,$E23,合并抵消!$A:$A,J$2)+SUMIFS(合并抵消!$K:$K,合并抵消!$E:$E,$E23,合并抵消!$A:$A,J$2)) | K23: =浙江精准学!K23+知识跳跳!K23+海南精准学!K23+实时查!K23+目标准!K23+'SMART LEARNING HOLDING'!K23+'SMART AI LIMITED'!K23+'HK01'!K23-(-SUMIFS(合并抵消!$J:$J,合并抵消!$E:$E,$E23,合并抵消!$A:$A,K$2)+SUMIFS(合并抵消!$K:$K,合并抵消!$E:$E,$E23,合并抵消!$A:$A,K$2)) | L23: =浙江精准学!L23+知识跳跳!L23+海南精准学!L23+实时查!L23+目标准!L23+'SMART LEARNING HOLDING'!L23+'SMART AI LIMITED'!L23+'HK01'!L23-(-SUMIFS(合并抵消!$J:$J,合并抵消!$E:$E,$E23,合并抵消!$A:$A,L$2)+SUMIFS(合并抵消!$K:$K,合并抵消!$E:$E,$E23,合并抵消!$A:$A,L$2)) | M23: =浙江精准学!M23+知识跳跳!M23+海南精准学!M23+实时查!M23+目标准!M23+'SMART LEARNING HOLDING'!M23+'SMART AI LIMITED'!M23+'HK01'!M23-(-SUMIFS(合并抵消!$J:$J,合并抵消!$E:$E,$E23,合并抵消!$A:$A,M$2)+SUMIFS(合并抵消!$K:$K,合并抵消!$E:$E,$E23,合并抵消!$A:$A,M$2)) | ... Q23: =浙江精准学!Q23+知识跳跳!Q23+海南精准学!Q23+实时查!Q23+目标准!Q23+'SMART LEARNING HOLDING'!Q23+'SMART AI LIMITED'!Q23+'HK01'!Q23-(-SUMIFS(合并抵消!$J:$J,合并抵消!$E:$E,$E23,合并抵消!$A:$A,Q$2)+SUMIFS(合并抵消!$K:$K,合并抵消!$E:$E,$E23,合并抵消!$A:$A,Q$2)) | R23: =SUM(F23:Q23)
A24: 投资款支出合计 | F24: =SUM(F23:F23) | G24: =SUM(G23:G23) | H24: =SUM(H23:H23) | I24: =SUM(I23:I23) | J24: =SUM(J23:J23) | K24: =SUM(K23:K23) | L24: =SUM(L23:L23) | M24: =SUM(M23:M23) | ... Q24: =SUM(Q23:Q23) | R24: =SUM(F24:Q24)
A25: 人工成本 | B25: 人工成本 | C25: 人工成本 | D25: 实发工资 | E25: Q0801 | F25: =浙江精准学!F25+知识跳跳!F25+海南精准学!F25+实时查!F25+目标准!F25+'SMART LEARNING HOLDING'!F25+'SMART AI LIMITED'!F25+'HK01'!F25-(-SUMIFS(合并抵消!$J:$J,合并抵消!$E:$E,$E25,合并抵消!$A:$A,F$2)+SUMIFS(合并抵消!$K:$K,合并抵消!$E:$E,$E25,合并抵消!$A:$A,F$2)) | G25: =浙江精准学!G25+知识跳跳!G25+海南精准学!G25+实时查!G25+目标准!G25+'SMART LEARNING HOLDING'!G25+'SMART AI LIMITED'!G25+'HK01'!G25-(-SUMIFS(合并抵消!$J:$J,合并抵消!$E:$E,$E25,合并抵消!$A:$A,G$2)+SUMIFS(合并抵消!$K:$K,合并抵消!$E:$E,$E25,合并抵消!$A:$A,G$2)) | H25: =浙江精准学!H25+知识跳跳!H25+海南精准学!H25+实时查!H25+目标准!H25+'SMART LEARNING HOLDING'!H25+'SMART AI LIMITED'!H25+'HK01'!H25-(-SUMIFS(合并抵消!$J:$J,合并抵消!$E:$E,$E25,合并抵消!$A:$A,H$2)+SUMIFS(合并抵消!$K:$K,合并抵消!$E:$E,$E25,合并抵消!$A:$A,H$2)) | I25: =浙江精准学!I25+知识跳跳!I25+海南精准学!I25+实时查!I25+目标准!I25+'SMART LEARNING HOLDING'!I25+'SMART AI LIMITED'!I25+'HK01'!I25-(-SUMIFS(合并抵消!$J:$J,合并抵消!$E:$E,$E25,合并抵消!$A:$A,I$2)+SUMIFS(合并抵消!$K:$K,合并抵消!$E:$E,$E25,合并抵消!$A:$A,I$2)) | J25: =浙江精准学!J25+知识跳跳!J25+海南精准学!J25+实时查!J25+目标准!J25+'SMART LEARNING HOLDING'!J25+'SMART AI LIMITED'!J25+'HK01'!J25-(-SUMIFS(合并抵消!$J:$J,合并抵消!$E:$E,$E25,合并抵消!$A:$A,J$2)+SUMIFS(合并抵消!$K:$K,合并抵消!$E:$E,$E25,合并抵消!$A:$A,J$2)) | K25: =浙江精准学!K25+知识跳跳!K25+海南精准学!K25+实时查!K25+目标准!K25+'SMART LEARNING HOLDING'!K25+'SMART AI LIMITED'!K25+'HK01'!K25-(-SUMIFS(合并抵消!$J:$J,合并抵消!$E:$E,$E25,合并抵消!$A:$A,K$2)+SUMIFS(合并抵消!$K:$K,合并抵消!$E:$E,$E25,合并抵消!$A:$A,K$2)) | L25: =浙江精准学!L25+知识跳跳!L25+海南精准学!L25+实时查!L25+目标准!L25+'SMART LEARNING HOLDING'!L25+'SMART AI LIMITED'!L25+'HK01'!L25-(-SUMIFS(合并抵消!$J:$J,合并抵消!$E:$E,$E25,合并抵消!$A:$A,L$2)+SUMIFS(合并抵消!$K:$K,合并抵消!$E:$E,$E25,合并抵消!$A:$A,L$2)) | M25: =浙江精准学!M25+知识跳跳!M25+海南精准学!M25+实时查!M25+目标准!M25+'SMART LEARNING HOLDING'!M25+'SMART AI LIMITED'!M25+'HK01'!M25-(-SUMIFS(合并抵消!$J:$J,合并抵消!$E:$E,$E25,合并抵消!$A:$A,M$2)+SUMIFS(合并抵消!$K:$K,合并抵消!$E:$E,$E25,合并抵消!$A:$A,M$2)) | ... Q25: =浙江精准学!Q25+知识跳跳!Q25+海南精准学!Q25+实时查!Q25+目标准!Q25+'SMART LEARNING HOLDING'!Q25+'SMART AI LIMITED'!Q25+'HK01'!Q25-(-SUMIFS(合并抵消!$J:$J,合并抵消!$E:$E,$E25,合并抵消!$A:$A,Q$2)+SUMIFS(合并抵消!$K:$K,合并抵消!$E:$E,$E25,合并抵消!$A:$A,Q$2)) | R25: =SUM(F25:Q25)
A26: 人工成本 | B26: 人工成本 | D26: 奖金 | E26: Q0802 | F26: =浙江精准学!F26+知识跳跳!F26+海南精准学!F26+实时查!F26+目标准!F26+'SMART LEARNING HOLDING'!F26+'SMART AI LIMITED'!F26+'HK01'!F26-(-SUMIFS(合并抵消!$J:$J,合并抵消!$E:$E,$E26,合并抵消!$A:$A,F$2)+SUMIFS(合并抵消!$K:$K,合并抵消!$E:$E,$E26,合并抵消!$A:$A,F$2)) | G26: =浙江精准学!G26+知识跳跳!G26+海南精准学!G26+实时查!G26+目标准!G26+'SMART LEARNING HOLDING'!G26+'SMART AI LIMITED'!G26+'HK01'!G26-(-SUMIFS(合并抵消!$J:$J,合并抵消!$E:$E,$E26,合并抵消!$A:$A,G$2)+SUMIFS(合并抵消!$K:$K,合并抵消!$E:$E,$E26,合并抵消!$A:$A,G$2)) | H26: =浙江精准学!H26+知识跳跳!H26+海南精准学!H26+实时查!H26+目标准!H26+'SMART LEARNING HOLDING'!H26+'SMART AI LIMITED'!H26+'HK01'!H26-(-SUMIFS(合并抵消!$J:$J,合并抵消!$E:$E,$E26,合并抵消!$A:$A,H$2)+SUMIFS(合并抵消!$K:$K,合并抵消!$E:$E,$E26,合并抵消!$A:$A,H$2)) | I26: =浙江精准学!I26+知识跳跳!I26+海南精准学!I26+实时查!I26+目标准!I26+'SMART LEARNING HOLDING'!I26+'SMART AI LIMITED'!I26+'HK01'!I26-(-SUMIFS(合并抵消!$J:$J,合并抵消!$E:$E,$E26,合并抵消!$A:$A,I$2)+SUMIFS(合并抵消!$K:$K,合并抵消!$E:$E,$E26,合并抵消!$A:$A,I$2)) | J26: =浙江精准学!J26+知识跳跳!J26+海南精准学!J26+实时查!J26+目标准!J26+'SMART LEARNING HOLDING'!J26+'SMART AI LIMITED'!J26+'HK01'!J26-(-SUMIFS(合并抵消!$J:$J,合并抵消!$E:$E,$E26,合并抵消!$A:$A,J$2)+SUMIFS(合并抵消!$K:$K,合并抵消!$E:$E,$E26,合并抵消!$A:$A,J$2)) | K26: =浙江精准学!K26+知识跳跳!K26+海南精准学!K26+实时查!K26+目标准!K26+'SMART LEARNING HOLDING'!K26+'SMART AI LIMITED'!K26+'HK01'!K26-(-SUMIFS(合并抵消!$J:$J,合并抵消!$E:$E,$E26,合并抵消!$A:$A,K$2)+SUMIFS(合并抵消!$K:$K,合并抵消!$E:$E,$E26,合并抵消!$A:$A,K$2)) | L26: =浙江精准学!L26+知识跳跳!L26+海南精准学!L26+实时查!L26+目标准!L26+'SMART LEARNING HOLDING'!L26+'SMART AI LIMITED'!L26+'HK01'!L26-(-SUMIFS(合并抵消!$J:$J,合并抵消!$E:$E,$E26,合并抵消!$A:$A,L$2)+SUMIFS(合并抵消!$K:$K,合并抵消!$E:$E,$E26,合并抵消!$A:$A,L$2)) | M26: =浙江精准学!M26+知识跳跳!M26+海南精准学!M26+实时查!M26+目标准!M26+'SMART LEARNING HOLDING'!M26+'SMART AI LIMITED'!M26+'HK01'!M26-(-SUMIFS(合并抵消!$J:$J,合并抵消!$E:$E,$E26,合并抵消!$A:$A,M$2)+SUMIFS(合并抵消!$K:$K,合并抵消!$E:$E,$E26,合并抵消!$A:$A,M$2)) | ... Q26: =浙江精准学!Q26+知识跳跳!Q26+海南精准学!Q26+实时查!Q26+目标准!Q26+'SMART LEARNING HOLDING'!Q26+'SMART AI LIMITED'!Q26+'HK01'!Q26-(-SUMIFS(合并抵消!$J:$J,合并抵消!$E:$E,$E26,合并抵消!$A:$A,Q$2)+SUMIFS(合并抵消!$K:$K,合并抵消!$E:$E,$E26,合并抵消!$A:$A,Q$2)) | R26: =SUM(F26:Q26)
A27: 人工成本 | B27: 人工成本 | D27: 社保（单位+个人） | E27: Q0803 | F27: =浙江精准学!F27+知识跳跳!F27+海南精准学!F27+实时查!F27+目标准!F27+'SMART LEARNING HOLDING'!F27+'SMART AI LIMITED'!F27+'HK01'!F27-(-SUMIFS(合并抵消!$J:$J,合并抵消!$E:$E,$E27,合并抵消!$A:$A,F$2)+SUMIFS(合并抵消!$K:$K,合并抵消!$E:$E,$E27,合并抵消!$A:$A,F$2)) | G27: =浙江精准学!G27+知识跳跳!G27+海南精准学!G27+实时查!G27+目标准!G27+'SMART LEARNING HOLDING'!G27+'SMART AI LIMITED'!G27+'HK01'!G27-(-SUMIFS(合并抵消!$J:$J,合并抵消!$E:$E,$E27,合并抵消!$A:$A,G$2)+SUMIFS(合并抵消!$K:$K,合并抵消!$E:$E,$E27,合并抵消!$A:$A,G$2)) | H27: =浙江精准学!H27+知识跳跳!H27+海南精准学!H27+实时查!H27+目标准!H27+'SMART LEARNING HOLDING'!H27+'SMART AI LIMITED'!H27+'HK01'!H27-(-SUMIFS(合并抵消!$J:$J,合并抵消!$E:$E,$E27,合并抵消!$A:$A,H$2)+SUMIFS(合并抵消!$K:$K,合并抵消!$E:$E,$E27,合并抵消!$A:$A,H$2)) | I27: =浙江精准学!I27+知识跳跳!I27+海南精准学!I27+实时查!I27+目标准!I27+'SMART LEARNING HOLDING'!I27+'SMART AI LIMITED'!I27+'HK01'!I27-(-SUMIFS(合并抵消!$J:$J,合并抵消!$E:$E,$E27,合并抵消!$A:$A,I$2)+SUMIFS(合并抵消!$K:$K,合并抵消!$E:$E,$E27,合并抵消!$A:$A,I$2)) | J27: =浙江精准学!J27+知识跳跳!J27+海南精准学!J27+实时查!J27+目标准!J27+'SMART LEARNING HOLDING'!J27+'SMART AI LIMITED'!J27+'HK01'!J27-(-SUMIFS(合并抵消!$J:$J,合并抵消!$E:$E,$E27,合并抵消!$A:$A,J$2)+SUMIFS(合并抵消!$K:$K,合并抵消!$E:$E,$E27,合并抵消!$A:$A,J$2)) | K27: =浙江精准学!K27+知识跳跳!K27+海南精准学!K27+实时查!K27+目标准!K27+'SMART LEARNING HOLDING'!K27+'SMART AI LIMITED'!K27+'HK01'!K27-(-SUMIFS(合并抵消!$J:$J,合并抵消!$E:$E,$E27,合并抵消!$A:$A,K$2)+SUMIFS(合并抵消!$K:$K,合并抵消!$E:$E,$E27,合并抵消!$A:$A,K$2)) | L27: =浙江精准学!L27+知识跳跳!L27+海南精准学!L27+实时查!L27+目标准!L27+'SMART LEARNING HOLDING'!L27+'SMART AI LIMITED'!L27+'HK01'!L27-(-SUMIFS(合并抵消!$J:$J,合并抵消!$E:$E,$E27,合并抵消!$A:$A,L$2)+SUMIFS(合并抵消!$K:$K,合并抵消!$E:$E,$E27,合并抵消!$A:$A,L$2)) | M27: =浙江精准学!M27+知识跳跳!M27+海南精准学!M27+实时查!M27+目标准!M27+'SMART LEARNING HOLDING'!M27+'SMART AI LIMITED'!M27+'HK01'!M27-(-SUMIFS(合并抵消!$J:$J,合并抵消!$E:$E,$E27,合并抵消!$A:$A,M$2)+SUMIFS(合并抵消!$K:$K,合并抵消!$E:$E,$E27,合并抵消!$A:$A,M$2)) | ... Q27: =浙江精准学!Q27+知识跳跳!Q27+海南精准学!Q27+实时查!Q27+目标准!Q27+'SMART LEARNING HOLDING'!Q27+'SMART AI LIMITED'!Q27+'HK01'!Q27-(-SUMIFS(合并抵消!$J:$J,合并抵消!$E:$E,$E27,合并抵消!$A:$A,Q$2)+SUMIFS(合并抵消!$K:$K,合并抵消!$E:$E,$E27,合并抵消!$A:$A,Q$2)) | R27: =SUM(F27:Q27)
A28: 人工成本 | B28: 人工成本 | D28: 公积金（单位+个人） | E28: Q0804 | F28: =浙江精准学!F28+知识跳跳!F28+海南精准学!F28+实时查!F28+目标准!F28+'SMART LEARNING HOLDING'!F28+'SMART AI LIMITED'!F28+'HK01'!F28-(-SUMIFS(合并抵消!$J:$J,合并抵消!$E:$E,$E28,合并抵消!$A:$A,F$2)+SUMIFS(合并抵消!$K:$K,合并抵消!$E:$E,$E28,合并抵消!$A:$A,F$2)) | G28: =浙江精准学!G28+知识跳跳!G28+海南精准学!G28+实时查!G28+目标准!G28+'SMART LEARNING HOLDING'!G28+'SMART AI LIMITED'!G28+'HK01'!G28-(-SUMIFS(合并抵消!$J:$J,合并抵消!$E:$E,$E28,合并抵消!$A:$A,G$2)+SUMIFS(合并抵消!$K:$K,合并抵消!$E:$E,$E28,合并抵消!$A:$A,G$2)) | H28: =浙江精准学!H28+知识跳跳!H28+海南精准学!H28+实时查!H28+目标准!H28+'SMART LEARNING HOLDING'!H28+'SMART AI LIMITED'!H28+'HK01'!H28-(-SUMIFS(合并抵消!$J:$J,合并抵消!$E:$E,$E28,合并抵消!$A:$A,H$2)+SUMIFS(合并抵消!$K:$K,合并抵消!$E:$E,$E28,合并抵消!$A:$A,H$2)) | I28: =浙江精准学!I28+知识跳跳!I28+海南精准学!I28+实时查!I28+目标准!I28+'SMART LEARNING HOLDING'!I28+'SMART AI LIMITED'!I28+'HK01'!I28-(-SUMIFS(合并抵消!$J:$J,合并抵消!$E:$E,$E28,合并抵消!$A:$A,I$2)+SUMIFS(合并抵消!$K:$K,合并抵消!$E:$E,$E28,合并抵消!$A:$A,I$2)) | J28: =浙江精准学!J28+知识跳跳!J28+海南精准学!J28+实时查!J28+目标准!J28+'SMART LEARNING HOLDING'!J28+'SMART AI LIMITED'!J28+'HK01'!J28-(-SUMIFS(合并抵消!$J:$J,合并抵消!$E:$E,$E28,合并抵消!$A:$A,J$2)+SUMIFS(合并抵消!$K:$K,合并抵消!$E:$E,$E28,合并抵消!$A:$A,J$2)) | K28: =浙江精准学!K28+知识跳跳!K28+海南精准学!K28+实时查!K28+目标准!K28+'SMART LEARNING HOLDING'!K28+'SMART AI LIMITED'!K28+'HK01'!K28-(-SUMIFS(合并抵消!$J:$J,合并抵消!$E:$E,$E28,合并抵消!$A:$A,K$2)+SUMIFS(合并抵消!$K:$K,合并抵消!$E:$E,$E28,合并抵消!$A:$A,K$2)) | L28: =浙江精准学!L28+知识跳跳!L28+海南精准学!L28+实时查!L28+目标准!L28+'SMART LEARNING HOLDING'!L28+'SMART AI LIMITED'!L28+'HK01'!L28-(-SUMIFS(合并抵消!$J:$J,合并抵消!$E:$E,$E28,合并抵消!$A:$A,L$2)+SUMIFS(合并抵消!$K:$K,合并抵消!$E:$E,$E28,合并抵消!$A:$A,L$2)) | M28: =浙江精准学!M28+知识跳跳!M28+海南精准学!M28+实时查!M28+目标准!M28+'SMART LEARNING HOLDING'!M28+'SMART AI LIMITED'!M28+'HK01'!M28-(-SUMIFS(合并抵消!$J:$J,合并抵消!$E:$E,$E28,合并抵消!$A:$A,M$2)+SUMIFS(合并抵消!$K:$K,合并抵消!$E:$E,$E28,合并抵消!$A:$A,M$2)) | ... Q28: =浙江精准学!Q28+知识跳跳!Q28+海南精准学!Q28+实时查!Q28+目标准!Q28+'SMART LEARNING HOLDING'!Q28+'SMART AI LIMITED'!Q28+'HK01'!Q28-(-SUMIFS(合并抵消!$J:$J,合并抵消!$E:$E,$E28,合并抵消!$A:$A,Q$2)+SUMIFS(合并抵消!$K:$K,合并抵消!$E:$E,$E28,合并抵消!$A:$A,Q$2)) | R28: =SUM(F28:Q28)
A29: 人工成本 | B29: 人工成本 | D29: 个税 | E29: Q0805 | F29: =浙江精准学!F29+知识跳跳!F29+海南精准学!F29+实时查!F29+目标准!F29+'SMART LEARNING HOLDING'!F29+'SMART AI LIMITED'!F29+'HK01'!F29-(-SUMIFS(合并抵消!$J:$J,合并抵消!$E:$E,$E29,合并抵消!$A:$A,F$2)+SUMIFS(合并抵消!$K:$K,合并抵消!$E:$E,$E29,合并抵消!$A:$A,F$2)) | G29: =浙江精准学!G29+知识跳跳!G29+海南精准学!G29+实时查!G29+目标准!G29+'SMART LEARNING HOLDING'!G29+'SMART AI LIMITED'!G29+'HK01'!G29-(-SUMIFS(合并抵消!$J:$J,合并抵消!$E:$E,$E29,合并抵消!$A:$A,G$2)+SUMIFS(合并抵消!$K:$K,合并抵消!$E:$E,$E29,合并抵消!$A:$A,G$2)) | H29: =浙江精准学!H29+知识跳跳!H29+海南精准学!H29+实时查!H29+目标准!H29+'SMART LEARNING HOLDING'!H29+'SMART AI LIMITED'!H29+'HK01'!H29-(-SUMIFS(合并抵消!$J:$J,合并抵消!$E:$E,$E29,合并抵消!$A:$A,H$2)+SUMIFS(合并抵消!$K:$K,合并抵消!$E:$E,$E29,合并抵消!$A:$A,H$2)) | I29: =浙江精准学!I29+知识跳跳!I29+海南精准学!I29+实时查!I29+目标准!I29+'SMART LEARNING HOLDING'!I29+'SMART AI LIMITED'!I29+'HK01'!I29-(-SUMIFS(合并抵消!$J:$J,合并抵消!$E:$E,$E29,合并抵消!$A:$A,I$2)+SUMIFS(合并抵消!$K:$K,合并抵消!$E:$E,$E29,合并抵消!$A:$A,I$2)) | J29: =浙江精准学!J29+知识跳跳!J29+海南精准学!J29+实时查!J29+目标准!J29+'SMART LEARNING HOLDING'!J29+'SMART AI LIMITED'!J29+'HK01'!J29-(-SUMIFS(合并抵消!$J:$J,合并抵消!$E:$E,$E29,合并抵消!$A:$A,J$2)+SUMIFS(合并抵消!$K:$K,合并抵消!$E:$E,$E29,合并抵消!$A:$A,J$2)) | K29: =浙江精准学!K29+知识跳跳!K29+海南精准学!K29+实时查!K29+目标准!K29+'SMART LEARNING HOLDING'!K29+'SMART AI LIMITED'!K29+'HK01'!K29-(-SUMIFS(合并抵消!$J:$J,合并抵消!$E:$E,$E29,合并抵消!$A:$A,K$2)+SUMIFS(合并抵消!$K:$K,合并抵消!$E:$E,$E29,合并抵消!$A:$A,K$2)) | L29: =浙江精准学!L29+知识跳跳!L29+海南精准学!L29+实时查!L29+目标准!L29+'SMART LEARNING HOLDING'!L29+'SMART AI LIMITED'!L29+'HK01'!L29-(-SUMIFS(合并抵消!$J:$J,合并抵消!$E:$E,$E29,合并抵消!$A:$A,L$2)+SUMIFS(合并抵消!$K:$K,合并抵消!$E:$E,$E29,合并抵消!$A:$A,L$2)) | M29: =浙江精准学!M29+知识跳跳!M29+海南精准学!M29+实时查!M29+目标准!M29+'SMART LEARNING HOLDING'!M29+'SMART AI LIMITED'!M29+'HK01'!M29-(-SUMIFS(合并抵消!$J:$J,合并抵消!$E:$E,$E29,合并抵消!$A:$A,M$2)+SUMIFS(合并抵消!$K:$K,合并抵消!$E:$E,$E29,合并抵消!$A:$A,M$2)) | ... Q29: =浙江精准学!Q29+知识跳跳!Q29+海南精准学!Q29+实时查!Q29+目标准!Q29+'SMART LEARNING HOLDING'!Q29+'SMART AI LIMITED'!Q29+'HK01'!Q29-(-SUMIFS(合并抵消!$J:$J,合并抵消!$E:$E,$E29,合并抵消!$A:$A,Q$2)+SUMIFS(合并抵消!$K:$K,合并抵消!$E:$E,$E29,合并抵消!$A:$A,Q$2)) | R29: =SUM(F29:Q29)
A30: 人工成本 | B30: 人工成本 | D30: 福利费 | E30: Q0806 | F30: =浙江精准学!F30+知识跳跳!F30+海南精准学!F30+实时查!F30+目标准!F30+'SMART LEARNING HOLDING'!F30+'SMART AI LIMITED'!F30+'HK01'!F30-(-SUMIFS(合并抵消!$J:$J,合并抵消!$E:$E,$E30,合并抵消!$A:$A,F$2)+SUMIFS(合并抵消!$K:$K,合并抵消!$E:$E,$E30,合并抵消!$A:$A,F$2)) | G30: =浙江精准学!G30+知识跳跳!G30+海南精准学!G30+实时查!G30+目标准!G30+'SMART LEARNING HOLDING'!G30+'SMART AI LIMITED'!G30+'HK01'!G30-(-SUMIFS(合并抵消!$J:$J,合并抵消!$E:$E,$E30,合并抵消!$A:$A,G$2)+SUMIFS(合并抵消!$K:$K,合并抵消!$E:$E,$E30,合并抵消!$A:$A,G$2)) | H30: =浙江精准学!H30+知识跳跳!H30+海南精准学!H30+实时查!H30+目标准!H30+'SMART LEARNING HOLDING'!H30+'SMART AI LIMITED'!H30+'HK01'!H30-(-SUMIFS(合并抵消!$J:$J,合并抵消!$E:$E,$E30,合并抵消!$A:$A,H$2)+SUMIFS(合并抵消!$K:$K,合并抵消!$E:$E,$E30,合并抵消!$A:$A,H$2)) | I30: =浙江精准学!I30+知识跳跳!I30+海南精准学!I30+实时查!I30+目标准!I30+'SMART LEARNING HOLDING'!I30+'SMART AI LIMITED'!I30+'HK01'!I30-(-SUMIFS(合并抵消!$J:$J,合并抵消!$E:$E,$E30,合并抵消!$A:$A,I$2)+SUMIFS(合并抵消!$K:$K,合并抵消!$E:$E,$E30,合并抵消!$A:$A,I$2)) | J30: =浙江精准学!J30+知识跳跳!J30+海南精准学!J30+实时查!J30+目标准!J30+'SMART LEARNING HOLDING'!J30+'SMART AI LIMITED'!J30+'HK01'!J30-(-SUMIFS(合并抵消!$J:$J,合并抵消!$E:$E,$E30,合并抵消!$A:$A,J$2)+SUMIFS(合并抵消!$K:$K,合并抵消!$E:$E,$E30,合并抵消!$A:$A,J$2)) | K30: =浙江精准学!K30+知识跳跳!K30+海南精准学!K30+实时查!K30+目标准!K30+'SMART LEARNING HOLDING'!K30+'SMART AI LIMITED'!K30+'HK01'!K30-(-SUMIFS(合并抵消!$J:$J,合并抵消!$E:$E,$E30,合并抵消!$A:$A,K$2)+SUMIFS(合并抵消!$K:$K,合并抵消!$E:$E,$E30,合并抵消!$A:$A,K$2)) | L30: =浙江精准学!L30+知识跳跳!L30+海南精准学!L30+实时查!L30+目标准!L30+'SMART LEARNING HOLDING'!L30+'SMART AI LIMITED'!L30+'HK01'!L30-(-SUMIFS(合并抵消!$J:$J,合并抵消!$E:$E,$E30,合并抵消!$A:$A,L$2)+SUMIFS(合并抵消!$K:$K,合并抵消!$E:$E,$E30,合并抵消!$A:$A,L$2)) | M30: =浙江精准学!M30+知识跳跳!M30+海南精准学!M30+实时查!M30+目标准!M30+'SMART LEARNING HOLDING'!M30+'SMART AI LIMITED'!M30+'HK01'!M30-(-SUMIFS(合并抵消!$J:$J,合并抵消!$E:$E,$E30,合并抵消!$A:$A,M$2)+SUMIFS(合并抵消!$K:$K,合并抵消!$E:$E,$E30,合并抵消!$A:$A,M$2)) | ... Q30: =浙江精准学!Q30+知识跳跳!Q30+海南精准学!Q30+实时查!Q30+目标准!Q30+'SMART LEARNING HOLDING'!Q30+'SMART AI LIMITED'!Q30+'HK01'!Q30-(-SUMIFS(合并抵消!$J:$J,合并抵消!$E:$E,$E30,合并抵消!$A:$A,Q$2)+SUMIFS(合并抵消!$K:$K,合并抵消!$E:$E,$E30,合并抵消!$A:$A,Q$2)) | R30: =SUM(F30:Q30)
A31: 人工成本 | B31: 人工成本 | D31: 补偿金 | E31: Q0807 | F31: =浙江精准学!F31+知识跳跳!F31+海南精准学!F31+实时查!F31+目标准!F31+'SMART LEARNING HOLDING'!F31+'SMART AI LIMITED'!F31+'HK01'!F31-(-SUMIFS(合并抵消!$J:$J,合并抵消!$E:$E,$E31,合并抵消!$A:$A,F$2)+SUMIFS(合并抵消!$K:$K,合并抵消!$E:$E,$E31,合并抵消!$A:$A,F$2)) | G31: =浙江精准学!G31+知识跳跳!G31+海南精准学!G31+实时查!G31+目标准!G31+'SMART LEARNING HOLDING'!G31+'SMART AI LIMITED'!G31+'HK01'!G31-(-SUMIFS(合并抵消!$J:$J,合并抵消!$E:$E,$E31,合并抵消!$A:$A,G$2)+SUMIFS(合并抵消!$K:$K,合并抵消!$E:$E,$E31,合并抵消!$A:$A,G$2)) | H31: =浙江精准学!H31+知识跳跳!H31+海南精准学!H31+实时查!H31+目标准!H31+'SMART LEARNING HOLDING'!H31+'SMART AI LIMITED'!H31+'HK01'!H31-(-SUMIFS(合并抵消!$J:$J,合并抵消!$E:$E,$E31,合并抵消!$A:$A,H$2)+SUMIFS(合并抵消!$K:$K,合并抵消!$E:$E,$E31,合并抵消!$A:$A,H$2)) | I31: =浙江精准学!I31+知识跳跳!I31+海南精准学!I31+实时查!I31+目标准!I31+'SMART LEARNING HOLDING'!I31+'SMART AI LIMITED'!I31+'HK01'!I31-(-SUMIFS(合并抵消!$J:$J,合并抵消!$E:$E,$E31,合并抵消!$A:$A,I$2)+SUMIFS(合并抵消!$K:$K,合并抵消!$E:$E,$E31,合并抵消!$A:$A,I$2)) | J31: =浙江精准学!J31+知识跳跳!J31+海南精准学!J31+实时查!J31+目标准!J31+'SMART LEARNING HOLDING'!J31+'SMART AI LIMITED'!J31+'HK01'!J31-(-SUMIFS(合并抵消!$J:$J,合并抵消!$E:$E,$E31,合并抵消!$A:$A,J$2)+SUMIFS(合并抵消!$K:$K,合并抵消!$E:$E,$E31,合并抵消!$A:$A,J$2)) | K31: =浙江精准学!K31+知识跳跳!K31+海南精准学!K31+实时查!K31+目标准!K31+'SMART LEARNING HOLDING'!K31+'SMART AI LIMITED'!K31+'HK01'!K31-(-SUMIFS(合并抵消!$J:$J,合并抵消!$E:$E,$E31,合并抵消!$A:$A,K$2)+SUMIFS(合并抵消!$K:$K,合并抵消!$E:$E,$E31,合并抵消!$A:$A,K$2)) | L31: =浙江精准学!L31+知识跳跳!L31+海南精准学!L31+实时查!L31+目标准!L31+'SMART LEARNING HOLDING'!L31+'SMART AI LIMITED'!L31+'HK01'!L31-(-SUMIFS(合并抵消!$J:$J,合并抵消!$E:$E,$E31,合并抵消!$A:$A,L$2)+SUMIFS(合并抵消!$K:$K,合并抵消!$E:$E,$E31,合并抵消!$A:$A,L$2)) | M31: =浙江精准学!M31+知识跳跳!M31+海南精准学!M31+实时查!M31+目标准!M31+'SMART LEARNING HOLDING'!M31+'SMART AI LIMITED'!M31+'HK01'!M31-(-SUMIFS(合并抵消!$J:$J,合并抵消!$E:$E,$E31,合并抵消!$A:$A,M$2)+SUMIFS(合并抵消!$K:$K,合并抵消!$E:$E,$E31,合并抵消!$A:$A,M$2)) | ... Q31: =浙江精准学!Q31+知识跳跳!Q31+海南精准学!Q31+实时查!Q31+目标准!Q31+'SMART LEARNING HOLDING'!Q31+'SMART AI LIMITED'!Q31+'HK01'!Q31-(-SUMIFS(合并抵消!$J:$J,合并抵消!$E:$E,$E31,合并抵消!$A:$A,Q$2)+SUMIFS(合并抵消!$K:$K,合并抵消!$E:$E,$E31,合并抵消!$A:$A,Q$2)) | R31: =SUM(F31:Q31)
A32: 人工成本 | B32: 人工成本 | D32: 派遣费用 | E32: Q0808 | F32: =浙江精准学!F32+知识跳跳!F32+海南精准学!F32+实时查!F32+目标准!F32+'SMART LEARNING HOLDING'!F32+'SMART AI LIMITED'!F32+'HK01'!F32-(-SUMIFS(合并抵消!$J:$J,合并抵消!$E:$E,$E32,合并抵消!$A:$A,F$2)+SUMIFS(合并抵消!$K:$K,合并抵消!$E:$E,$E32,合并抵消!$A:$A,F$2)) | G32: =浙江精准学!G32+知识跳跳!G32+海南精准学!G32+实时查!G32+目标准!G32+'SMART LEARNING HOLDING'!G32+'SMART AI LIMITED'!G32+'HK01'!G32-(-SUMIFS(合并抵消!$J:$J,合并抵消!$E:$E,$E32,合并抵消!$A:$A,G$2)+SUMIFS(合并抵消!$K:$K,合并抵消!$E:$E,$E32,合并抵消!$A:$A,G$2)) | H32: =浙江精准学!H32+知识跳跳!H32+海南精准学!H32+实时查!H32+目标准!H32+'SMART LEARNING HOLDING'!H32+'SMART AI LIMITED'!H32+'HK01'!H32-(-SUMIFS(合并抵消!$J:$J,合并抵消!$E:$E,$E32,合并抵消!$A:$A,H$2)+SUMIFS(合并抵消!$K:$K,合并抵消!$E:$E,$E32,合并抵消!$A:$A,H$2)) | I32: =浙江精准学!I32+知识跳跳!I32+海南精准学!I32+实时查!I32+目标准!I32+'SMART LEARNING HOLDING'!I32+'SMART AI LIMITED'!I32+'HK01'!I32-(-SUMIFS(合并抵消!$J:$J,合并抵消!$E:$E,$E32,合并抵消!$A:$A,I$2)+SUMIFS(合并抵消!$K:$K,合并抵消!$E:$E,$E32,合并抵消!$A:$A,I$2)) | J32: =浙江精准学!J32+知识跳跳!J32+海南精准学!J32+实时查!J32+目标准!J32+'SMART LEARNING HOLDING'!J32+'SMART AI LIMITED'!J32+'HK01'!J32-(-SUMIFS(合并抵消!$J:$J,合并抵消!$E:$E,$E32,合并抵消!$A:$A,J$2)+SUMIFS(合并抵消!$K:$K,合并抵消!$E:$E,$E32,合并抵消!$A:$A,J$2)) | K32: =浙江精准学!K32+知识跳跳!K32+海南精准学!K32+实时查!K32+目标准!K32+'SMART LEARNING HOLDING'!K32+'SMART AI LIMITED'!K32+'HK01'!K32-(-SUMIFS(合并抵消!$J:$J,合并抵消!$E:$E,$E32,合并抵消!$A:$A,K$2)+SUMIFS(合并抵消!$K:$K,合并抵消!$E:$E,$E32,合并抵消!$A:$A,K$2)) | L32: =浙江精准学!L32+知识跳跳!L32+海南精准学!L32+实时查!L32+目标准!L32+'SMART LEARNING HOLDING'!L32+'SMART AI LIMITED'!L32+'HK01'!L32-(-SUMIFS(合并抵消!$J:$J,合并抵消!$E:$E,$E32,合并抵消!$A:$A,L$2)+SUMIFS(合并抵消!$K:$K,合并抵消!$E:$E,$E32,合并抵消!$A:$A,L$2)) | M32: =浙江精准学!M32+知识跳跳!M32+海南精准学!M32+实时查!M32+目标准!M32+'SMART LEARNING HOLDING'!M32+'SMART AI LIMITED'!M32+'HK01'!M32-(-SUMIFS(合并抵消!$J:$J,合并抵消!$E:$E,$E32,合并抵消!$A:$A,M$2)+SUMIFS(合并抵消!$K:$K,合并抵消!$E:$E,$E32,合并抵消!$A:$A,M$2)) | ... Q32: =浙江精准学!Q32+知识跳跳!Q32+海南精准学!Q32+实时查!Q32+目标准!Q32+'SMART LEARNING HOLDING'!Q32+'SMART AI LIMITED'!Q32+'HK01'!Q32-(-SUMIFS(合并抵消!$J:$J,合并抵消!$E:$E,$E32,合并抵消!$A:$A,Q$2)+SUMIFS(合并抵消!$K:$K,合并抵消!$E:$E,$E32,合并抵消!$A:$A,Q$2)) | R32: =SUM(F32:Q32)
A33: 人工成本 | B33: 人工成本 | D33: 顾问费 | E33: Q0809 | F33: =浙江精准学!F33+知识跳跳!F33+海南精准学!F33+实时查!F33+目标准!F33+'SMART LEARNING HOLDING'!F33+'SMART AI LIMITED'!F33+'HK01'!F33-(-SUMIFS(合并抵消!$J:$J,合并抵消!$E:$E,$E33,合并抵消!$A:$A,F$2)+SUMIFS(合并抵消!$K:$K,合并抵消!$E:$E,$E33,合并抵消!$A:$A,F$2)) | G33: =浙江精准学!G33+知识跳跳!G33+海南精准学!G33+实时查!G33+目标准!G33+'SMART LEARNING HOLDING'!G33+'SMART AI LIMITED'!G33+'HK01'!G33-(-SUMIFS(合并抵消!$J:$J,合并抵消!$E:$E,$E33,合并抵消!$A:$A,G$2)+SUMIFS(合并抵消!$K:$K,合并抵消!$E:$E,$E33,合并抵消!$A:$A,G$2)) | H33: =浙江精准学!H33+知识跳跳!H33+海南精准学!H33+实时查!H33+目标准!H33+'SMART LEARNING HOLDING'!H33+'SMART AI LIMITED'!H33+'HK01'!H33-(-SUMIFS(合并抵消!$J:$J,合并抵消!$E:$E,$E33,合并抵消!$A:$A,H$2)+SUMIFS(合并抵消!$K:$K,合并抵消!$E:$E,$E33,合并抵消!$A:$A,H$2)) | I33: =浙江精准学!I33+知识跳跳!I33+海南精准学!I33+实时查!I33+目标准!I33+'SMART LEARNING HOLDING'!I33+'SMART AI LIMITED'!I33+'HK01'!I33-(-SUMIFS(合并抵消!$J:$J,合并抵消!$E:$E,$E33,合并抵消!$A:$A,I$2)+SUMIFS(合并抵消!$K:$K,合并抵消!$E:$E,$E33,合并抵消!$A:$A,I$2)) | J33: =浙江精准学!J33+知识跳跳!J33+海南精准学!J33+实时查!J33+目标准!J33+'SMART LEARNING HOLDING'!J33+'SMART AI LIMITED'!J33+'HK01'!J33-(-SUMIFS(合并抵消!$J:$J,合并抵消!$E:$E,$E33,合并抵消!$A:$A,J$2)+SUMIFS(合并抵消!$K:$K,合并抵消!$E:$E,$E33,合并抵消!$A:$A,J$2)) | K33: =浙江精准学!K33+知识跳跳!K33+海南精准学!K33+实时查!K33+目标准!K33+'SMART LEARNING HOLDING'!K33+'SMART AI LIMITED'!K33+'HK01'!K33-(-SUMIFS(合并抵消!$J:$J,合并抵消!$E:$E,$E33,合并抵消!$A:$A,K$2)+SUMIFS(合并抵消!$K:$K,合并抵消!$E:$E,$E33,合并抵消!$A:$A,K$2)) | L33: =浙江精准学!L33+知识跳跳!L33+海南精准学!L33+实时查!L33+目标准!L33+'SMART LEARNING HOLDING'!L33+'SMART AI LIMITED'!L33+'HK01'!L33-(-SUMIFS(合并抵消!$J:$J,合并抵消!$E:$E,$E33,合并抵消!$A:$A,L$2)+SUMIFS(合并抵消!$K:$K,合并抵消!$E:$E,$E33,合并抵消!$A:$A,L$2)) | M33: =浙江精准学!M33+知识跳跳!M33+海南精准学!M33+实时查!M33+目标准!M33+'SMART LEARNING HOLDING'!M33+'SMART AI LIMITED'!M33+'HK01'!M33-(-SUMIFS(合并抵消!$J:$J,合并抵消!$E:$E,$E33,合并抵消!$A:$A,M$2)+SUMIFS(合并抵消!$K:$K,合并抵消!$E:$E,$E33,合并抵消!$A:$A,M$2)) | ... Q33: =浙江精准学!Q33+知识跳跳!Q33+海南精准学!Q33+实时查!Q33+目标准!Q33+'SMART LEARNING HOLDING'!Q33+'SMART AI LIMITED'!Q33+'HK01'!Q33-(-SUMIFS(合并抵消!$J:$J,合并抵消!$E:$E,$E33,合并抵消!$A:$A,Q$2)+SUMIFS(合并抵消!$K:$K,合并抵消!$E:$E,$E33,合并抵消!$A:$A,Q$2)) | R33: =SUM(F33:Q33)
A34: 人工成本 | B34: 人工成本 | D34: 其他人工成本 | E34: Q08010 | F34: =浙江精准学!F34+知识跳跳!F34+海南精准学!F34+实时查!F34+目标准!F34+'SMART LEARNING HOLDING'!F34+'SMART AI LIMITED'!F34+'HK01'!F34-(-SUMIFS(合并抵消!$J:$J,合并抵消!$E:$E,$E34,合并抵消!$A:$A,F$2)+SUMIFS(合并抵消!$K:$K,合并抵消!$E:$E,$E34,合并抵消!$A:$A,F$2)) | G34: =浙江精准学!G34+知识跳跳!G34+海南精准学!G34+实时查!G34+目标准!G34+'SMART LEARNING HOLDING'!G34+'SMART AI LIMITED'!G34+'HK01'!G34-(-SUMIFS(合并抵消!$J:$J,合并抵消!$E:$E,$E34,合并抵消!$A:$A,G$2)+SUMIFS(合并抵消!$K:$K,合并抵消!$E:$E,$E34,合并抵消!$A:$A,G$2)) | H34: =浙江精准学!H34+知识跳跳!H34+海南精准学!H34+实时查!H34+目标准!H34+'SMART LEARNING HOLDING'!H34+'SMART AI LIMITED'!H34+'HK01'!H34-(-SUMIFS(合并抵消!$J:$J,合并抵消!$E:$E,$E34,合并抵消!$A:$A,H$2)+SUMIFS(合并抵消!$K:$K,合并抵消!$E:$E,$E34,合并抵消!$A:$A,H$2)) | I34: =浙江精准学!I34+知识跳跳!I34+海南精准学!I34+实时查!I34+目标准!I34+'SMART LEARNING HOLDING'!I34+'SMART AI LIMITED'!I34+'HK01'!I34-(-SUMIFS(合并抵消!$J:$J,合并抵消!$E:$E,$E34,合并抵消!$A:$A,I$2)+SUMIFS(合并抵消!$K:$K,合并抵消!$E:$E,$E34,合并抵消!$A:$A,I$2)) | J34: =浙江精准学!J34+知识跳跳!J34+海南精准学!J34+实时查!J34+目标准!J34+'SMART LEARNING HOLDING'!J34+'SMART AI LIMITED'!J34+'HK01'!J34-(-SUMIFS(合并抵消!$J:$J,合并抵消!$E:$E,$E34,合并抵消!$A:$A,J$2)+SUMIFS(合并抵消!$K:$K,合并抵消!$E:$E,$E34,合并抵消!$A:$A,J$2)) | K34: =浙江精准学!K34+知识跳跳!K34+海南精准学!K34+实时查!K34+目标准!K34+'SMART LEARNING HOLDING'!K34+'SMART AI LIMITED'!K34+'HK01'!K34-(-SUMIFS(合并抵消!$J:$J,合并抵消!$E:$E,$E34,合并抵消!$A:$A,K$2)+SUMIFS(合并抵消!$K:$K,合并抵消!$E:$E,$E34,合并抵消!$A:$A,K$2)) | L34: =浙江精准学!L34+知识跳跳!L34+海南精准学!L34+实时查!L34+目标准!L34+'SMART LEARNING HOLDING'!L34+'SMART AI LIMITED'!L34+'HK01'!L34-(-SUMIFS(合并抵消!$J:$J,合并抵消!$E:$E,$E34,合并抵消!$A:$A,L$2)+SUMIFS(合并抵消!$K:$K,合并抵消!$E:$E,$E34,合并抵消!$A:$A,L$2)) | M34: =浙江精准学!M34+知识跳跳!M34+海南精准学!M34+实时查!M34+目标准!M34+'SMART LEARNING HOLDING'!M34+'SMART AI LIMITED'!M34+'HK01'!M34-(-SUMIFS(合并抵消!$J:$J,合并抵消!$E:$E,$E34,合并抵消!$A:$A,M$2)+SUMIFS(合并抵消!$K:$K,合并抵消!$E:$E,$E34,合并抵消!$A:$A,M$2)) | ... Q34: =浙江精准学!Q34+知识跳跳!Q34+海南精准学!Q34+实时查!Q34+目标准!Q34+'SMART LEARNING HOLDING'!Q34+'SMART AI LIMITED'!Q34+'HK01'!Q34-(-SUMIFS(合并抵消!$J:$J,合并抵消!$E:$E,$E34,合并抵消!$A:$A,Q$2)+SUMIFS(合并抵消!$K:$K,合并抵消!$E:$E,$E34,合并抵消!$A:$A,Q$2)) | R34: =SUM(F34:Q34)
A35: 人工成本合计 | F35: =SUM(F25:F34) | G35: =SUM(G25:G34) | H35: =SUM(H25:H34) | I35: =SUM(I25:I34) | J35: =SUM(J25:J34) | K35: =SUM(K25:K34) | L35: =SUM(L25:L34) | M35: =SUM(M25:M34) | ... Q35: =SUM(Q25:Q34) | R35: =SUM(F35:Q35)
A36: 硬件支出 | B36: BONG MAX | C36: BONG MAX | D36: TCL平板电脑款项 | E36: Q0901 | F36: =浙江精准学!F36+知识跳跳!F36+海南精准学!F36+实时查!F36+目标准!F36+'SMART LEARNING HOLDING'!F36+'SMART AI LIMITED'!F36+'HK01'!F36-(-SUMIFS(合并抵消!$J:$J,合并抵消!$E:$E,$E36,合并抵消!$A:$A,F$2)+SUMIFS(合并抵消!$K:$K,合并抵消!$E:$E,$E36,合并抵消!$A:$A,F$2)) | G36: =浙江精准学!G36+知识跳跳!G36+海南精准学!G36+实时查!G36+目标准!G36+'SMART LEARNING HOLDING'!G36+'SMART AI LIMITED'!G36+'HK01'!G36-(-SUMIFS(合并抵消!$J:$J,合并抵消!$E:$E,$E36,合并抵消!$A:$A,G$2)+SUMIFS(合并抵消!$K:$K,合并抵消!$E:$E,$E36,合并抵消!$A:$A,G$2)) | H36: =浙江精准学!H36+知识跳跳!H36+海南精准学!H36+实时查!H36+目标准!H36+'SMART LEARNING HOLDING'!H36+'SMART AI LIMITED'!H36+'HK01'!H36-(-SUMIFS(合并抵消!$J:$J,合并抵消!$E:$E,$E36,合并抵消!$A:$A,H$2)+SUMIFS(合并抵消!$K:$K,合并抵消!$E:$E,$E36,合并抵消!$A:$A,H$2)) | I36: =浙江精准学!I36+知识跳跳!I36+海南精准学!I36+实时查!I36+目标准!I36+'SMART LEARNING HOLDING'!I36+'SMART AI LIMITED'!I36+'HK01'!I36-(-SUMIFS(合并抵消!$J:$J,合并抵消!$E:$E,$E36,合并抵消!$A:$A,I$2)+SUMIFS(合并抵消!$K:$K,合并抵消!$E:$E,$E36,合并抵消!$A:$A,I$2)) | J36: =浙江精准学!J36+知识跳跳!J36+海南精准学!J36+实时查!J36+目标准!J36+'SMART LEARNING HOLDING'!J36+'SMART AI LIMITED'!J36+'HK01'!J36-(-SUMIFS(合并抵消!$J:$J,合并抵消!$E:$E,$E36,合并抵消!$A:$A,J$2)+SUMIFS(合并抵消!$K:$K,合并抵消!$E:$E,$E36,合并抵消!$A:$A,J$2)) | K36: =浙江精准学!K36+知识跳跳!K36+海南精准学!K36+实时查!K36+目标准!K36+'SMART LEARNING HOLDING'!K36+'SMART AI LIMITED'!K36+'HK01'!K36-(-SUMIFS(合并抵消!$J:$J,合并抵消!$E:$E,$E36,合并抵消!$A:$A,K$2)+SUMIFS(合并抵消!$K:$K,合并抵消!$E:$E,$E36,合并抵消!$A:$A,K$2)) | L36: =浙江精准学!L36+知识跳跳!L36+海南精准学!L36+实时查!L36+目标准!L36+'SMART LEARNING HOLDING'!L36+'SMART AI LIMITED'!L36+'HK01'!L36-(-SUMIFS(合并抵消!$J:$J,合并抵消!$E:$E,$E36,合并抵消!$A:$A,L$2)+SUMIFS(合并抵消!$K:$K,合并抵消!$E:$E,$E36,合并抵消!$A:$A,L$2)) | M36: =浙江精准学!M36+知识跳跳!M36+海南精准学!M36+实时查!M36+目标准!M36+'SMART LEARNING HOLDING'!M36+'SMART AI LIMITED'!M36+'HK01'!M36-(-SUMIFS(合并抵消!$J:$J,合并抵消!$E:$E,$E36,合并抵消!$A:$A,M$2)+SUMIFS(合并抵消!$K:$K,合并抵消!$E:$E,$E36,合并抵消!$A:$A,M$2)) | ... Q36: =浙江精准学!Q36+知识跳跳!Q36+海南精准学!Q36+实时查!Q36+目标准!Q36+'SMART LEARNING HOLDING'!Q36+'SMART AI LIMITED'!Q36+'HK01'!Q36-(-SUMIFS(合并抵消!$J:$J,合并抵消!$E:$E,$E36,合并抵消!$A:$A,Q$2)+SUMIFS(合并抵消!$K:$K,合并抵消!$E:$E,$E36,合并抵消!$A:$A,Q$2)) | R36: =SUM(F36:Q36)
A37: 硬件支出 | B37: BONG MAX | D37: 保护套 | E37: Q0902 | F37: =浙江精准学!F37+知识跳跳!F37+海南精准学!F37+实时查!F37+目标准!F37+'SMART LEARNING HOLDING'!F37+'SMART AI LIMITED'!F37+'HK01'!F37-(-SUMIFS(合并抵消!$J:$J,合并抵消!$E:$E,$E37,合并抵消!$A:$A,F$2)+SUMIFS(合并抵消!$K:$K,合并抵消!$E:$E,$E37,合并抵消!$A:$A,F$2)) | G37: =浙江精准学!G37+知识跳跳!G37+海南精准学!G37+实时查!G37+目标准!G37+'SMART LEARNING HOLDING'!G37+'SMART AI LIMITED'!G37+'HK01'!G37-(-SUMIFS(合并抵消!$J:$J,合并抵消!$E:$E,$E37,合并抵消!$A:$A,G$2)+SUMIFS(合并抵消!$K:$K,合并抵消!$E:$E,$E37,合并抵消!$A:$A,G$2)) | H37: =浙江精准学!H37+知识跳跳!H37+海南精准学!H37+实时查!H37+目标准!H37+'SMART LEARNING HOLDING'!H37+'SMART AI LIMITED'!H37+'HK01'!H37-(-SUMIFS(合并抵消!$J:$J,合并抵消!$E:$E,$E37,合并抵消!$A:$A,H$2)+SUMIFS(合并抵消!$K:$K,合并抵消!$E:$E,$E37,合并抵消!$A:$A,H$2)) | I37: =浙江精准学!I37+知识跳跳!I37+海南精准学!I37+实时查!I37+目标准!I37+'SMART LEARNING HOLDING'!I37+'SMART AI LIMITED'!I37+'HK01'!I37-(-SUMIFS(合并抵消!$J:$J,合并抵消!$E:$E,$E37,合并抵消!$A:$A,I$2)+SUMIFS(合并抵消!$K:$K,合并抵消!$E:$E,$E37,合并抵消!$A:$A,I$2)) | J37: =浙江精准学!J37+知识跳跳!J37+海南精准学!J37+实时查!J37+目标准!J37+'SMART LEARNING HOLDING'!J37+'SMART AI LIMITED'!J37+'HK01'!J37-(-SUMIFS(合并抵消!$J:$J,合并抵消!$E:$E,$E37,合并抵消!$A:$A,J$2)+SUMIFS(合并抵消!$K:$K,合并抵消!$E:$E,$E37,合并抵消!$A:$A,J$2)) | K37: =浙江精准学!K37+知识跳跳!K37+海南精准学!K37+实时查!K37+目标准!K37+'SMART LEARNING HOLDING'!K37+'SMART AI LIMITED'!K37+'HK01'!K37-(-SUMIFS(合并抵消!$J:$J,合并抵消!$E:$E,$E37,合并抵消!$A:$A,K$2)+SUMIFS(合并抵消!$K:$K,合并抵消!$E:$E,$E37,合并抵消!$A:$A,K$2)) | L37: =浙江精准学!L37+知识跳跳!L37+海南精准学!L37+实时查!L37+目标准!L37+'SMART LEARNING HOLDING'!L37+'SMART AI LIMITED'!L37+'HK01'!L37-(-SUMIFS(合并抵消!$J:$J,合并抵消!$E:$E,$E37,合并抵消!$A:$A,L$2)+SUMIFS(合并抵消!$K:$K,合并抵消!$E:$E,$E37,合并抵消!$A:$A,L$2)) | M37: =浙江精准学!M37+知识跳跳!M37+海南精准学!M37+实时查!M37+目标准!M37+'SMART LEARNING HOLDING'!M37+'SMART AI LIMITED'!M37+'HK01'!M37-(-SUMIFS(合并抵消!$J:$J,合并抵消!$E:$E,$E37,合并抵消!$A:$A,M$2)+SUMIFS(合并抵消!$K:$K,合并抵消!$E:$E,$E37,合并抵消!$A:$A,M$2)) | ... Q37: =浙江精准学!Q37+知识跳跳!Q37+海南精准学!Q37+实时查!Q37+目标准!Q37+'SMART LEARNING HOLDING'!Q37+'SMART AI LIMITED'!Q37+'HK01'!Q37-(-SUMIFS(合并抵消!$J:$J,合并抵消!$E:$E,$E37,合并抵消!$A:$A,Q$2)+SUMIFS(合并抵消!$K:$K,合并抵消!$E:$E,$E37,合并抵消!$A:$A,Q$2)) | R37: =SUM(F37:Q37)
A38: 硬件支出 | B38: BONG MAX | D38: 包装盒 | E38: Q0903 | F38: =浙江精准学!F38+知识跳跳!F38+海南精准学!F38+实时查!F38+目标准!F38+'SMART LEARNING HOLDING'!F38+'SMART AI LIMITED'!F38+'HK01'!F38-(-SUMIFS(合并抵消!$J:$J,合并抵消!$E:$E,$E38,合并抵消!$A:$A,F$2)+SUMIFS(合并抵消!$K:$K,合并抵消!$E:$E,$E38,合并抵消!$A:$A,F$2)) | G38: =浙江精准学!G38+知识跳跳!G38+海南精准学!G38+实时查!G38+目标准!G38+'SMART LEARNING HOLDING'!G38+'SMART AI LIMITED'!G38+'HK01'!G38-(-SUMIFS(合并抵消!$J:$J,合并抵消!$E:$E,$E38,合并抵消!$A:$A,G$2)+SUMIFS(合并抵消!$K:$K,合并抵消!$E:$E,$E38,合并抵消!$A:$A,G$2)) | H38: =浙江精准学!H38+知识跳跳!H38+海南精准学!H38+实时查!H38+目标准!H38+'SMART LEARNING HOLDING'!H38+'SMART AI LIMITED'!H38+'HK01'!H38-(-SUMIFS(合并抵消!$J:$J,合并抵消!$E:$E,$E38,合并抵消!$A:$A,H$2)+SUMIFS(合并抵消!$K:$K,合并抵消!$E:$E,$E38,合并抵消!$A:$A,H$2)) | I38: =浙江精准学!I38+知识跳跳!I38+海南精准学!I38+实时查!I38+目标准!I38+'SMART LEARNING HOLDING'!I38+'SMART AI LIMITED'!I38+'HK01'!I38-(-SUMIFS(合并抵消!$J:$J,合并抵消!$E:$E,$E38,合并抵消!$A:$A,I$2)+SUMIFS(合并抵消!$K:$K,合并抵消!$E:$E,$E38,合并抵消!$A:$A,I$2)) | J38: =浙江精准学!J38+知识跳跳!J38+海南精准学!J38+实时查!J38+目标准!J38+'SMART LEARNING HOLDING'!J38+'SMART AI LIMITED'!J38+'HK01'!J38-(-SUMIFS(合并抵消!$J:$J,合并抵消!$E:$E,$E38,合并抵消!$A:$A,J$2)+SUMIFS(合并抵消!$K:$K,合并抵消!$E:$E,$E38,合并抵消!$A:$A,J$2)) | K38: =浙江精准学!K38+知识跳跳!K38+海南精准学!K38+实时查!K38+目标准!K38+'SMART LEARNING HOLDING'!K38+'SMART AI LIMITED'!K38+'HK01'!K38-(-SUMIFS(合并抵消!$J:$J,合并抵消!$E:$E,$E38,合并抵消!$A:$A,K$2)+SUMIFS(合并抵消!$K:$K,合并抵消!$E:$E,$E38,合并抵消!$A:$A,K$2)) | L38: =浙江精准学!L38+知识跳跳!L38+海南精准学!L38+实时查!L38+目标准!L38+'SMART LEARNING HOLDING'!L38+'SMART AI LIMITED'!L38+'HK01'!L38-(-SUMIFS(合并抵消!$J:$J,合并抵消!$E:$E,$E38,合并抵消!$A:$A,L$2)+SUMIFS(合并抵消!$K:$K,合并抵消!$E:$E,$E38,合并抵消!$A:$A,L$2)) | M38: =浙江精准学!M38+知识跳跳!M38+海南精准学!M38+实时查!M38+目标准!M38+'SMART LEARNING HOLDING'!M38+'SMART AI LIMITED'!M38+'HK01'!M38-(-SUMIFS(合并抵消!$J:$J,合并抵消!$E:$E,$E38,合并抵消!$A:$A,M$2)+SUMIFS(合并抵消!$K:$K,合并抵消!$E:$E,$E38,合并抵消!$A:$A,M$2)) | ... Q38: =浙江精准学!Q38+知识跳跳!Q38+海南精准学!Q38+实时查!Q38+目标准!Q38+'SMART LEARNING HOLDING'!Q38+'SMART AI LIMITED'!Q38+'HK01'!Q38-(-SUMIFS(合并抵消!$J:$J,合并抵消!$E:$E,$E38,合并抵消!$A:$A,Q$2)+SUMIFS(合并抵消!$K:$K,合并抵消!$E:$E,$E38,合并抵消!$A:$A,Q$2)) | R38: =SUM(F38:Q38)
A39: 硬件支出 | B39: BONG MAX | D39: 充电器 | E39: Q0904 | F39: =浙江精准学!F39+知识跳跳!F39+海南精准学!F39+实时查!F39+目标准!F39+'SMART LEARNING HOLDING'!F39+'SMART AI LIMITED'!F39+'HK01'!F39-(-SUMIFS(合并抵消!$J:$J,合并抵消!$E:$E,$E39,合并抵消!$A:$A,F$2)+SUMIFS(合并抵消!$K:$K,合并抵消!$E:$E,$E39,合并抵消!$A:$A,F$2)) | G39: =浙江精准学!G39+知识跳跳!G39+海南精准学!G39+实时查!G39+目标准!G39+'SMART LEARNING HOLDING'!G39+'SMART AI LIMITED'!G39+'HK01'!G39-(-SUMIFS(合并抵消!$J:$J,合并抵消!$E:$E,$E39,合并抵消!$A:$A,G$2)+SUMIFS(合并抵消!$K:$K,合并抵消!$E:$E,$E39,合并抵消!$A:$A,G$2)) | H39: =浙江精准学!H39+知识跳跳!H39+海南精准学!H39+实时查!H39+目标准!H39+'SMART LEARNING HOLDING'!H39+'SMART AI LIMITED'!H39+'HK01'!H39-(-SUMIFS(合并抵消!$J:$J,合并抵消!$E:$E,$E39,合并抵消!$A:$A,H$2)+SUMIFS(合并抵消!$K:$K,合并抵消!$E:$E,$E39,合并抵消!$A:$A,H$2)) | I39: =浙江精准学!I39+知识跳跳!I39+海南精准学!I39+实时查!I39+目标准!I39+'SMART LEARNING HOLDING'!I39+'SMART AI LIMITED'!I39+'HK01'!I39-(-SUMIFS(合并抵消!$J:$J,合并抵消!$E:$E,$E39,合并抵消!$A:$A,I$2)+SUMIFS(合并抵消!$K:$K,合并抵消!$E:$E,$E39,合并抵消!$A:$A,I$2)) | J39: =浙江精准学!J39+知识跳跳!J39+海南精准学!J39+实时查!J39+目标准!J39+'SMART LEARNING HOLDING'!J39+'SMART AI LIMITED'!J39+'HK01'!J39-(-SUMIFS(合并抵消!$J:$J,合并抵消!$E:$E,$E39,合并抵消!$A:$A,J$2)+SUMIFS(合并抵消!$K:$K,合并抵消!$E:$E,$E39,合并抵消!$A:$A,J$2)) | K39: =浙江精准学!K39+知识跳跳!K39+海南精准学!K39+实时查!K39+目标准!K39+'SMART LEARNING HOLDING'!K39+'SMART AI LIMITED'!K39+'HK01'!K39-(-SUMIFS(合并抵消!$J:$J,合并抵消!$E:$E,$E39,合并抵消!$A:$A,K$2)+SUMIFS(合并抵消!$K:$K,合并抵消!$E:$E,$E39,合并抵消!$A:$A,K$2)) | L39: =浙江精准学!L39+知识跳跳!L39+海南精准学!L39+实时查!L39+目标准!L39+'SMART LEARNING HOLDING'!L39+'SMART AI LIMITED'!L39+'HK01'!L39-(-SUMIFS(合并抵消!$J:$J,合并抵消!$E:$E,$E39,合并抵消!$A:$A,L$2)+SUMIFS(合并抵消!$K:$K,合并抵消!$E:$E,$E39,合并抵消!$A:$A,L$2)) | M39: =浙江精准学!M39+知识跳跳!M39+海南精准学!M39+实时查!M39+目标准!M39+'SMART LEARNING HOLDING'!M39+'SMART AI LIMITED'!M39+'HK01'!M39-(-SUMIFS(合并抵消!$J:$J,合并抵消!$E:$E,$E39,合并抵消!$A:$A,M$2)+SUMIFS(合并抵消!$K:$K,合并抵消!$E:$E,$E39,合并抵消!$A:$A,M$2)) | ... Q39: =浙江精准学!Q39+知识跳跳!Q39+海南精准学!Q39+实时查!Q39+目标准!Q39+'SMART LEARNING HOLDING'!Q39+'SMART AI LIMITED'!Q39+'HK01'!Q39-(-SUMIFS(合并抵消!$J:$J,合并抵消!$E:$E,$E39,合并抵消!$A:$A,Q$2)+SUMIFS(合并抵消!$K:$K,合并抵消!$E:$E,$E39,合并抵消!$A:$A,Q$2)) | R39: =SUM(F39:Q39)
A40: 硬件支出 | B40: BONG MAX | D40: 指学镜 | E40: Q0905 | F40: =浙江精准学!F40+知识跳跳!F40+海南精准学!F40+实时查!F40+目标准!F40+'SMART LEARNING HOLDING'!F40+'SMART AI LIMITED'!F40+'HK01'!F40-(-SUMIFS(合并抵消!$J:$J,合并抵消!$E:$E,$E40,合并抵消!$A:$A,F$2)+SUMIFS(合并抵消!$K:$K,合并抵消!$E:$E,$E40,合并抵消!$A:$A,F$2)) | G40: =浙江精准学!G40+知识跳跳!G40+海南精准学!G40+实时查!G40+目标准!G40+'SMART LEARNING HOLDING'!G40+'SMART AI LIMITED'!G40+'HK01'!G40-(-SUMIFS(合并抵消!$J:$J,合并抵消!$E:$E,$E40,合并抵消!$A:$A,G$2)+SUMIFS(合并抵消!$K:$K,合并抵消!$E:$E,$E40,合并抵消!$A:$A,G$2)) | H40: =浙江精准学!H40+知识跳跳!H40+海南精准学!H40+实时查!H40+目标准!H40+'SMART LEARNING HOLDING'!H40+'SMART AI LIMITED'!H40+'HK01'!H40-(-SUMIFS(合并抵消!$J:$J,合并抵消!$E:$E,$E40,合并抵消!$A:$A,H$2)+SUMIFS(合并抵消!$K:$K,合并抵消!$E:$E,$E40,合并抵消!$A:$A,H$2)) | I40: =浙江精准学!I40+知识跳跳!I40+海南精准学!I40+实时查!I40+目标准!I40+'SMART LEARNING HOLDING'!I40+'SMART AI LIMITED'!I40+'HK01'!I40-(-SUMIFS(合并抵消!$J:$J,合并抵消!$E:$E,$E40,合并抵消!$A:$A,I$2)+SUMIFS(合并抵消!$K:$K,合并抵消!$E:$E,$E40,合并抵消!$A:$A,I$2)) | J40: =浙江精准学!J40+知识跳跳!J40+海南精准学!J40+实时查!J40+目标准!J40+'SMART LEARNING HOLDING'!J40+'SMART AI LIMITED'!J40+'HK01'!J40-(-SUMIFS(合并抵消!$J:$J,合并抵消!$E:$E,$E40,合并抵消!$A:$A,J$2)+SUMIFS(合并抵消!$K:$K,合并抵消!$E:$E,$E40,合并抵消!$A:$A,J$2)) | K40: =浙江精准学!K40+知识跳跳!K40+海南精准学!K40+实时查!K40+目标准!K40+'SMART LEARNING HOLDING'!K40+'SMART AI LIMITED'!K40+'HK01'!K40-(-SUMIFS(合并抵消!$J:$J,合并抵消!$E:$E,$E40,合并抵消!$A:$A,K$2)+SUMIFS(合并抵消!$K:$K,合并抵消!$E:$E,$E40,合并抵消!$A:$A,K$2)) | L40: =浙江精准学!L40+知识跳跳!L40+海南精准学!L40+实时查!L40+目标准!L40+'SMART LEARNING HOLDING'!L40+'SMART AI LIMITED'!L40+'HK01'!L40-(-SUMIFS(合并抵消!$J:$J,合并抵消!$E:$E,$E40,合并抵消!$A:$A,L$2)+SUMIFS(合并抵消!$K:$K,合并抵消!$E:$E,$E40,合并抵消!$A:$A,L$2)) | M40: =浙江精准学!M40+知识跳跳!M40+海南精准学!M40+实时查!M40+目标准!M40+'SMART LEARNING HOLDING'!M40+'SMART AI LIMITED'!M40+'HK01'!M40-(-SUMIFS(合并抵消!$J:$J,合并抵消!$E:$E,$E40,合并抵消!$A:$A,M$2)+SUMIFS(合并抵消!$K:$K,合并抵消!$E:$E,$E40,合并抵消!$A:$A,M$2)) | ... Q40: =浙江精准学!Q40+知识跳跳!Q40+海南精准学!Q40+实时查!Q40+目标准!Q40+'SMART LEARNING HOLDING'!Q40+'SMART AI LIMITED'!Q40+'HK01'!Q40-(-SUMIFS(合并抵消!$J:$J,合并抵消!$E:$E,$E40,合并抵消!$A:$A,Q$2)+SUMIFS(合并抵消!$K:$K,合并抵消!$E:$E,$E40,合并抵消!$A:$A,Q$2)) | R40: =SUM(F40:Q40)
A41: 硬件支出 | B41: BONG MAX | D41: 学习机系统授权费 | E41: Q0906 | F41: =浙江精准学!F41+知识跳跳!F41+海南精准学!F41+实时查!F41+目标准!F41+'SMART LEARNING HOLDING'!F41+'SMART AI LIMITED'!F41+'HK01'!F41-(-SUMIFS(合并抵消!$J:$J,合并抵消!$E:$E,$E41,合并抵消!$A:$A,F$2)+SUMIFS(合并抵消!$K:$K,合并抵消!$E:$E,$E41,合并抵消!$A:$A,F$2)) | G41: =浙江精准学!G41+知识跳跳!G41+海南精准学!G41+实时查!G41+目标准!G41+'SMART LEARNING HOLDING'!G41+'SMART AI LIMITED'!G41+'HK01'!G41-(-SUMIFS(合并抵消!$J:$J,合并抵消!$E:$E,$E41,合并抵消!$A:$A,G$2)+SUMIFS(合并抵消!$K:$K,合并抵消!$E:$E,$E41,合并抵消!$A:$A,G$2)) | H41: =浙江精准学!H41+知识跳跳!H41+海南精准学!H41+实时查!H41+目标准!H41+'SMART LEARNING HOLDING'!H41+'SMART AI LIMITED'!H41+'HK01'!H41-(-SUMIFS(合并抵消!$J:$J,合并抵消!$E:$E,$E41,合并抵消!$A:$A,H$2)+SUMIFS(合并抵消!$K:$K,合并抵消!$E:$E,$E41,合并抵消!$A:$A,H$2)) | I41: =浙江精准学!I41+知识跳跳!I41+海南精准学!I41+实时查!I41+目标准!I41+'SMART LEARNING HOLDING'!I41+'SMART AI LIMITED'!I41+'HK01'!I41-(-SUMIFS(合并抵消!$J:$J,合并抵消!$E:$E,$E41,合并抵消!$A:$A,I$2)+SUMIFS(合并抵消!$K:$K,合并抵消!$E:$E,$E41,合并抵消!$A:$A,I$2)) | J41: =浙江精准学!J41+知识跳跳!J41+海南精准学!J41+实时查!J41+目标准!J41+'SMART LEARNING HOLDING'!J41+'SMART AI LIMITED'!J41+'HK01'!J41-(-SUMIFS(合并抵消!$J:$J,合并抵消!$E:$E,$E41,合并抵消!$A:$A,J$2)+SUMIFS(合并抵消!$K:$K,合并抵消!$E:$E,$E41,合并抵消!$A:$A,J$2)) | K41: =浙江精准学!K41+知识跳跳!K41+海南精准学!K41+实时查!K41+目标准!K41+'SMART LEARNING HOLDING'!K41+'SMART AI LIMITED'!K41+'HK01'!K41-(-SUMIFS(合并抵消!$J:$J,合并抵消!$E:$E,$E41,合并抵消!$A:$A,K$2)+SUMIFS(合并抵消!$K:$K,合并抵消!$E:$E,$E41,合并抵消!$A:$A,K$2)) | L41: =浙江精准学!L41+知识跳跳!L41+海南精准学!L41+实时查!L41+目标准!L41+'SMART LEARNING HOLDING'!L41+'SMART AI LIMITED'!L41+'HK01'!L41-(-SUMIFS(合并抵消!$J:$J,合并抵消!$E:$E,$E41,合并抵消!$A:$A,L$2)+SUMIFS(合并抵消!$K:$K,合并抵消!$E:$E,$E41,合并抵消!$A:$A,L$2)) | M41: =浙江精准学!M41+知识跳跳!M41+海南精准学!M41+实时查!M41+目标准!M41+'SMART LEARNING HOLDING'!M41+'SMART AI LIMITED'!M41+'HK01'!M41-(-SUMIFS(合并抵消!$J:$J,合并抵消!$E:$E,$E41,合并抵消!$A:$A,M$2)+SUMIFS(合并抵消!$K:$K,合并抵消!$E:$E,$E41,合并抵消!$A:$A,M$2)) | ... Q41: =浙江精准学!Q41+知识跳跳!Q41+海南精准学!Q41+实时查!Q41+目标准!Q41+'SMART LEARNING HOLDING'!Q41+'SMART AI LIMITED'!Q41+'HK01'!Q41-(-SUMIFS(合并抵消!$J:$J,合并抵消!$E:$E,$E41,合并抵消!$A:$A,Q$2)+SUMIFS(合并抵消!$K:$K,合并抵消!$E:$E,$E41,合并抵消!$A:$A,Q$2)) | R41: =SUM(F41:Q41)
A42: 硬件支出 | B42: BONG PRO | C42: BONG PRO | D42: BOE平板电脑款项 | E42: Q1001 | F42: =浙江精准学!F42+知识跳跳!F42+海南精准学!F42+实时查!F42+目标准!F42+'SMART LEARNING HOLDING'!F42+'SMART AI LIMITED'!F42+'HK01'!F42-(-SUMIFS(合并抵消!$J:$J,合并抵消!$E:$E,$E42,合并抵消!$A:$A,F$2)+SUMIFS(合并抵消!$K:$K,合并抵消!$E:$E,$E42,合并抵消!$A:$A,F$2)) | G42: =浙江精准学!G42+知识跳跳!G42+海南精准学!G42+实时查!G42+目标准!G42+'SMART LEARNING HOLDING'!G42+'SMART AI LIMITED'!G42+'HK01'!G42-(-SUMIFS(合并抵消!$J:$J,合并抵消!$E:$E,$E42,合并抵消!$A:$A,G$2)+SUMIFS(合并抵消!$K:$K,合并抵消!$E:$E,$E42,合并抵消!$A:$A,G$2)) | H42: =浙江精准学!H42+知识跳跳!H42+海南精准学!H42+实时查!H42+目标准!H42+'SMART LEARNING HOLDING'!H42+'SMART AI LIMITED'!H42+'HK01'!H42-(-SUMIFS(合并抵消!$J:$J,合并抵消!$E:$E,$E42,合并抵消!$A:$A,H$2)+SUMIFS(合并抵消!$K:$K,合并抵消!$E:$E,$E42,合并抵消!$A:$A,H$2)) | I42: =浙江精准学!I42+知识跳跳!I42+海南精准学!I42+实时查!I42+目标准!I42+'SMART LEARNING HOLDING'!I42+'SMART AI LIMITED'!I42+'HK01'!I42-(-SUMIFS(合并抵消!$J:$J,合并抵消!$E:$E,$E42,合并抵消!$A:$A,I$2)+SUMIFS(合并抵消!$K:$K,合并抵消!$E:$E,$E42,合并抵消!$A:$A,I$2)) | J42: =浙江精准学!J42+知识跳跳!J42+海南精准学!J42+实时查!J42+目标准!J42+'SMART LEARNING HOLDING'!J42+'SMART AI LIMITED'!J42+'HK01'!J42-(-SUMIFS(合并抵消!$J:$J,合并抵消!$E:$E,$E42,合并抵消!$A:$A,J$2)+SUMIFS(合并抵消!$K:$K,合并抵消!$E:$E,$E42,合并抵消!$A:$A,J$2)) | K42: =浙江精准学!K42+知识跳跳!K42+海南精准学!K42+实时查!K42+目标准!K42+'SMART LEARNING HOLDING'!K42+'SMART AI LIMITED'!K42+'HK01'!K42-(-SUMIFS(合并抵消!$J:$J,合并抵消!$E:$E,$E42,合并抵消!$A:$A,K$2)+SUMIFS(合并抵消!$K:$K,合并抵消!$E:$E,$E42,合并抵消!$A:$A,K$2)) | L42: =浙江精准学!L42+知识跳跳!L42+海南精准学!L42+实时查!L42+目标准!L42+'SMART LEARNING HOLDING'!L42+'SMART AI LIMITED'!L42+'HK01'!L42-(-SUMIFS(合并抵消!$J:$J,合并抵消!$E:$E,$E42,合并抵消!$A:$A,L$2)+SUMIFS(合并抵消!$K:$K,合并抵消!$E:$E,$E42,合并抵消!$A:$A,L$2)) | M42: =浙江精准学!M42+知识跳跳!M42+海南精准学!M42+实时查!M42+目标准!M42+'SMART LEARNING HOLDING'!M42+'SMART AI LIMITED'!M42+'HK01'!M42-(-SUMIFS(合并抵消!$J:$J,合并抵消!$E:$E,$E42,合并抵消!$A:$A,M$2)+SUMIFS(合并抵消!$K:$K,合并抵消!$E:$E,$E42,合并抵消!$A:$A,M$2)) | ... Q42: =浙江精准学!Q42+知识跳跳!Q42+海南精准学!Q42+实时查!Q42+目标准!Q42+'SMART LEARNING HOLDING'!Q42+'SMART AI LIMITED'!Q42+'HK01'!Q42-(-SUMIFS(合并抵消!$J:$J,合并抵消!$E:$E,$E42,合并抵消!$A:$A,Q$2)+SUMIFS(合并抵消!$K:$K,合并抵消!$E:$E,$E42,合并抵消!$A:$A,Q$2)) | R42: =SUM(F42:Q42)
A43: 硬件支出 | B43: BONG PRO | D43: 保护套 | E43: Q1002 | F43: =浙江精准学!F43+知识跳跳!F43+海南精准学!F43+实时查!F43+目标准!F43+'SMART LEARNING HOLDING'!F43+'SMART AI LIMITED'!F43+'HK01'!F43-(-SUMIFS(合并抵消!$J:$J,合并抵消!$E:$E,$E43,合并抵消!$A:$A,F$2)+SUMIFS(合并抵消!$K:$K,合并抵消!$E:$E,$E43,合并抵消!$A:$A,F$2)) | G43: =浙江精准学!G43+知识跳跳!G43+海南精准学!G43+实时查!G43+目标准!G43+'SMART LEARNING HOLDING'!G43+'SMART AI LIMITED'!G43+'HK01'!G43-(-SUMIFS(合并抵消!$J:$J,合并抵消!$E:$E,$E43,合并抵消!$A:$A,G$2)+SUMIFS(合并抵消!$K:$K,合并抵消!$E:$E,$E43,合并抵消!$A:$A,G$2)) | H43: =浙江精准学!H43+知识跳跳!H43+海南精准学!H43+实时查!H43+目标准!H43+'SMART LEARNING HOLDING'!H43+'SMART AI LIMITED'!H43+'HK01'!H43-(-SUMIFS(合并抵消!$J:$J,合并抵消!$E:$E,$E43,合并抵消!$A:$A,H$2)+SUMIFS(合并抵消!$K:$K,合并抵消!$E:$E,$E43,合并抵消!$A:$A,H$2)) | I43: =浙江精准学!I43+知识跳跳!I43+海南精准学!I43+实时查!I43+目标准!I43+'SMART LEARNING HOLDING'!I43+'SMART AI LIMITED'!I43+'HK01'!I43-(-SUMIFS(合并抵消!$J:$J,合并抵消!$E:$E,$E43,合并抵消!$A:$A,I$2)+SUMIFS(合并抵消!$K:$K,合并抵消!$E:$E,$E43,合并抵消!$A:$A,I$2)) | J43: =浙江精准学!J43+知识跳跳!J43+海南精准学!J43+实时查!J43+目标准!J43+'SMART LEARNING HOLDING'!J43+'SMART AI LIMITED'!J43+'HK01'!J43-(-SUMIFS(合并抵消!$J:$J,合并抵消!$E:$E,$E43,合并抵消!$A:$A,J$2)+SUMIFS(合并抵消!$K:$K,合并抵消!$E:$E,$E43,合并抵消!$A:$A,J$2)) | K43: =浙江精准学!K43+知识跳跳!K43+海南精准学!K43+实时查!K43+目标准!K43+'SMART LEARNING HOLDING'!K43+'SMART AI LIMITED'!K43+'HK01'!K43-(-SUMIFS(合并抵消!$J:$J,合并抵消!$E:$E,$E43,合并抵消!$A:$A,K$2)+SUMIFS(合并抵消!$K:$K,合并抵消!$E:$E,$E43,合并抵消!$A:$A,K$2)) | L43: =浙江精准学!L43+知识跳跳!L43+海南精准学!L43+实时查!L43+目标准!L43+'SMART LEARNING HOLDING'!L43+'SMART AI LIMITED'!L43+'HK01'!L43-(-SUMIFS(合并抵消!$J:$J,合并抵消!$E:$E,$E43,合并抵消!$A:$A,L$2)+SUMIFS(合并抵消!$K:$K,合并抵消!$E:$E,$E43,合并抵消!$A:$A,L$2)) | M43: =浙江精准学!M43+知识跳跳!M43+海南精准学!M43+实时查!M43+目标准!M43+'SMART LEARNING HOLDING'!M43+'SMART AI LIMITED'!M43+'HK01'!M43-(-SUMIFS(合并抵消!$J:$J,合并抵消!$E:$E,$E43,合并抵消!$A:$A,M$2)+SUMIFS(合并抵消!$K:$K,合并抵消!$E:$E,$E43,合并抵消!$A:$A,M$2)) | ... Q43: =浙江精准学!Q43+知识跳跳!Q43+海南精准学!Q43+实时查!Q43+目标准!Q43+'SMART LEARNING HOLDING'!Q43+'SMART AI LIMITED'!Q43+'HK01'!Q43-(-SUMIFS(合并抵消!$J:$J,合并抵消!$E:$E,$E43,合并抵消!$A:$A,Q$2)+SUMIFS(合并抵消!$K:$K,合并抵消!$E:$E,$E43,合并抵消!$A:$A,Q$2)) | R43: =SUM(F43:Q43)
A44: 硬件支出 | B44: BONG PRO | D44: 包装盒 | E44: Q1003 | F44: =浙江精准学!F44+知识跳跳!F44+海南精准学!F44+实时查!F44+目标准!F44+'SMART LEARNING HOLDING'!F44+'SMART AI LIMITED'!F44+'HK01'!F44-(-SUMIFS(合并抵消!$J:$J,合并抵消!$E:$E,$E44,合并抵消!$A:$A,F$2)+SUMIFS(合并抵消!$K:$K,合并抵消!$E:$E,$E44,合并抵消!$A:$A,F$2)) | G44: =浙江精准学!G44+知识跳跳!G44+海南精准学!G44+实时查!G44+目标准!G44+'SMART LEARNING HOLDING'!G44+'SMART AI LIMITED'!G44+'HK01'!G44-(-SUMIFS(合并抵消!$J:$J,合并抵消!$E:$E,$E44,合并抵消!$A:$A,G$2)+SUMIFS(合并抵消!$K:$K,合并抵消!$E:$E,$E44,合并抵消!$A:$A,G$2)) | H44: =浙江精准学!H44+知识跳跳!H44+海南精准学!H44+实时查!H44+目标准!H44+'SMART LEARNING HOLDING'!H44+'SMART AI LIMITED'!H44+'HK01'!H44-(-SUMIFS(合并抵消!$J:$J,合并抵消!$E:$E,$E44,合并抵消!$A:$A,H$2)+SUMIFS(合并抵消!$K:$K,合并抵消!$E:$E,$E44,合并抵消!$A:$A,H$2)) | I44: =浙江精准学!I44+知识跳跳!I44+海南精准学!I44+实时查!I44+目标准!I44+'SMART LEARNING HOLDING'!I44+'SMART AI LIMITED'!I44+'HK01'!I44-(-SUMIFS(合并抵消!$J:$J,合并抵消!$E:$E,$E44,合并抵消!$A:$A,I$2)+SUMIFS(合并抵消!$K:$K,合并抵消!$E:$E,$E44,合并抵消!$A:$A,I$2)) | J44: =浙江精准学!J44+知识跳跳!J44+海南精准学!J44+实时查!J44+目标准!J44+'SMART LEARNING HOLDING'!J44+'SMART AI LIMITED'!J44+'HK01'!J44-(-SUMIFS(合并抵消!$J:$J,合并抵消!$E:$E,$E44,合并抵消!$A:$A,J$2)+SUMIFS(合并抵消!$K:$K,合并抵消!$E:$E,$E44,合并抵消!$A:$A,J$2)) | K44: =浙江精准学!K44+知识跳跳!K44+海南精准学!K44+实时查!K44+目标准!K44+'SMART LEARNING HOLDING'!K44+'SMART AI LIMITED'!K44+'HK01'!K44-(-SUMIFS(合并抵消!$J:$J,合并抵消!$E:$E,$E44,合并抵消!$A:$A,K$2)+SUMIFS(合并抵消!$K:$K,合并抵消!$E:$E,$E44,合并抵消!$A:$A,K$2)) | L44: =浙江精准学!L44+知识跳跳!L44+海南精准学!L44+实时查!L44+目标准!L44+'SMART LEARNING HOLDING'!L44+'SMART AI LIMITED'!L44+'HK01'!L44-(-SUMIFS(合并抵消!$J:$J,合并抵消!$E:$E,$E44,合并抵消!$A:$A,L$2)+SUMIFS(合并抵消!$K:$K,合并抵消!$E:$E,$E44,合并抵消!$A:$A,L$2)) | M44: =浙江精准学!M44+知识跳跳!M44+海南精准学!M44+实时查!M44+目标准!M44+'SMART LEARNING HOLDING'!M44+'SMART AI LIMITED'!M44+'HK01'!M44-(-SUMIFS(合并抵消!$J:$J,合并抵消!$E:$E,$E44,合并抵消!$A:$A,M$2)+SUMIFS(合并抵消!$K:$K,合并抵消!$E:$E,$E44,合并抵消!$A:$A,M$2)) | ... Q44: =浙江精准学!Q44+知识跳跳!Q44+海南精准学!Q44+实时查!Q44+目标准!Q44+'SMART LEARNING HOLDING'!Q44+'SMART AI LIMITED'!Q44+'HK01'!Q44-(-SUMIFS(合并抵消!$J:$J,合并抵消!$E:$E,$E44,合并抵消!$A:$A,Q$2)+SUMIFS(合并抵消!$K:$K,合并抵消!$E:$E,$E44,合并抵消!$A:$A,Q$2)) | R44: =SUM(F44:Q44)
A45: 硬件支出 | B45: BONG PRO | D45: 充电器 | E45: Q1004 | F45: =浙江精准学!F45+知识跳跳!F45+海南精准学!F45+实时查!F45+目标准!F45+'SMART LEARNING HOLDING'!F45+'SMART AI LIMITED'!F45+'HK01'!F45-(-SUMIFS(合并抵消!$J:$J,合并抵消!$E:$E,$E45,合并抵消!$A:$A,F$2)+SUMIFS(合并抵消!$K:$K,合并抵消!$E:$E,$E45,合并抵消!$A:$A,F$2)) | G45: =浙江精准学!G45+知识跳跳!G45+海南精准学!G45+实时查!G45+目标准!G45+'SMART LEARNING HOLDING'!G45+'SMART AI LIMITED'!G45+'HK01'!G45-(-SUMIFS(合并抵消!$J:$J,合并抵消!$E:$E,$E45,合并抵消!$A:$A,G$2)+SUMIFS(合并抵消!$K:$K,合并抵消!$E:$E,$E45,合并抵消!$A:$A,G$2)) | H45: =浙江精准学!H45+知识跳跳!H45+海南精准学!H45+实时查!H45+目标准!H45+'SMART LEARNING HOLDING'!H45+'SMART AI LIMITED'!H45+'HK01'!H45-(-SUMIFS(合并抵消!$J:$J,合并抵消!$E:$E,$E45,合并抵消!$A:$A,H$2)+SUMIFS(合并抵消!$K:$K,合并抵消!$E:$E,$E45,合并抵消!$A:$A,H$2)) | I45: =浙江精准学!I45+知识跳跳!I45+海南精准学!I45+实时查!I45+目标准!I45+'SMART LEARNING HOLDING'!I45+'SMART AI LIMITED'!I45+'HK01'!I45-(-SUMIFS(合并抵消!$J:$J,合并抵消!$E:$E,$E45,合并抵消!$A:$A,I$2)+SUMIFS(合并抵消!$K:$K,合并抵消!$E:$E,$E45,合并抵消!$A:$A,I$2)) | J45: =浙江精准学!J45+知识跳跳!J45+海南精准学!J45+实时查!J45+目标准!J45+'SMART LEARNING HOLDING'!J45+'SMART AI LIMITED'!J45+'HK01'!J45-(-SUMIFS(合并抵消!$J:$J,合并抵消!$E:$E,$E45,合并抵消!$A:$A,J$2)+SUMIFS(合并抵消!$K:$K,合并抵消!$E:$E,$E45,合并抵消!$A:$A,J$2)) | K45: =浙江精准学!K45+知识跳跳!K45+海南精准学!K45+实时查!K45+目标准!K45+'SMART LEARNING HOLDING'!K45+'SMART AI LIMITED'!K45+'HK01'!K45-(-SUMIFS(合并抵消!$J:$J,合并抵消!$E:$E,$E45,合并抵消!$A:$A,K$2)+SUMIFS(合并抵消!$K:$K,合并抵消!$E:$E,$E45,合并抵消!$A:$A,K$2)) | L45: =浙江精准学!L45+知识跳跳!L45+海南精准学!L45+实时查!L45+目标准!L45+'SMART LEARNING HOLDING'!L45+'SMART AI LIMITED'!L45+'HK01'!L45-(-SUMIFS(合并抵消!$J:$J,合并抵消!$E:$E,$E45,合并抵消!$A:$A,L$2)+SUMIFS(合并抵消!$K:$K,合并抵消!$E:$E,$E45,合并抵消!$A:$A,L$2)) | M45: =浙江精准学!M45+知识跳跳!M45+海南精准学!M45+实时查!M45+目标准!M45+'SMART LEARNING HOLDING'!M45+'SMART AI LIMITED'!M45+'HK01'!M45-(-SUMIFS(合并抵消!$J:$J,合并抵消!$E:$E,$E45,合并抵消!$A:$A,M$2)+SUMIFS(合并抵消!$K:$K,合并抵消!$E:$E,$E45,合并抵消!$A:$A,M$2)) | ... Q45: =浙江精准学!Q45+知识跳跳!Q45+海南精准学!Q45+实时查!Q45+目标准!Q45+'SMART LEARNING HOLDING'!Q45+'SMART AI LIMITED'!Q45+'HK01'!Q45-(-SUMIFS(合并抵消!$J:$J,合并抵消!$E:$E,$E45,合并抵消!$A:$A,Q$2)+SUMIFS(合并抵消!$K:$K,合并抵消!$E:$E,$E45,合并抵消!$A:$A,Q$2)) | R45: =SUM(F45:Q45)
A46: 硬件支出 | B46: BONG PRO | D46: 指学镜 | E46: Q1005 | F46: =浙江精准学!F46+知识跳跳!F46+海南精准学!F46+实时查!F46+目标准!F46+'SMART LEARNING HOLDING'!F46+'SMART AI LIMITED'!F46+'HK01'!F46-(-SUMIFS(合并抵消!$J:$J,合并抵消!$E:$E,$E46,合并抵消!$A:$A,F$2)+SUMIFS(合并抵消!$K:$K,合并抵消!$E:$E,$E46,合并抵消!$A:$A,F$2)) | G46: =浙江精准学!G46+知识跳跳!G46+海南精准学!G46+实时查!G46+目标准!G46+'SMART LEARNING HOLDING'!G46+'SMART AI LIMITED'!G46+'HK01'!G46-(-SUMIFS(合并抵消!$J:$J,合并抵消!$E:$E,$E46,合并抵消!$A:$A,G$2)+SUMIFS(合并抵消!$K:$K,合并抵消!$E:$E,$E46,合并抵消!$A:$A,G$2)) | H46: =浙江精准学!H46+知识跳跳!H46+海南精准学!H46+实时查!H46+目标准!H46+'SMART LEARNING HOLDING'!H46+'SMART AI LIMITED'!H46+'HK01'!H46-(-SUMIFS(合并抵消!$J:$J,合并抵消!$E:$E,$E46,合并抵消!$A:$A,H$2)+SUMIFS(合并抵消!$K:$K,合并抵消!$E:$E,$E46,合并抵消!$A:$A,H$2)) | I46: =浙江精准学!I46+知识跳跳!I46+海南精准学!I46+实时查!I46+目标准!I46+'SMART LEARNING HOLDING'!I46+'SMART AI LIMITED'!I46+'HK01'!I46-(-SUMIFS(合并抵消!$J:$J,合并抵消!$E:$E,$E46,合并抵消!$A:$A,I$2)+SUMIFS(合并抵消!$K:$K,合并抵消!$E:$E,$E46,合并抵消!$A:$A,I$2)) | J46: =浙江精准学!J46+知识跳跳!J46+海南精准学!J46+实时查!J46+目标准!J46+'SMART LEARNING HOLDING'!J46+'SMART AI LIMITED'!J46+'HK01'!J46-(-SUMIFS(合并抵消!$J:$J,合并抵消!$E:$E,$E46,合并抵消!$A:$A,J$2)+SUMIFS(合并抵消!$K:$K,合并抵消!$E:$E,$E46,合并抵消!$A:$A,J$2)) | K46: =浙江精准学!K46+知识跳跳!K46+海南精准学!K46+实时查!K46+目标准!K46+'SMART LEARNING HOLDING'!K46+'SMART AI LIMITED'!K46+'HK01'!K46-(-SUMIFS(合并抵消!$J:$J,合并抵消!$E:$E,$E46,合并抵消!$A:$A,K$2)+SUMIFS(合并抵消!$K:$K,合并抵消!$E:$E,$E46,合并抵消!$A:$A,K$2)) | L46: =浙江精准学!L46+知识跳跳!L46+海南精准学!L46+实时查!L46+目标准!L46+'SMART LEARNING HOLDING'!L46+'SMART AI LIMITED'!L46+'HK01'!L46-(-SUMIFS(合并抵消!$J:$J,合并抵消!$E:$E,$E46,合并抵消!$A:$A,L$2)+SUMIFS(合并抵消!$K:$K,合并抵消!$E:$E,$E46,合并抵消!$A:$A,L$2)) | M46: =浙江精准学!M46+知识跳跳!M46+海南精准学!M46+实时查!M46+目标准!M46+'SMART LEARNING HOLDING'!M46+'SMART AI LIMITED'!M46+'HK01'!M46-(-SUMIFS(合并抵消!$J:$J,合并抵消!$E:$E,$E46,合并抵消!$A:$A,M$2)+SUMIFS(合并抵消!$K:$K,合并抵消!$E:$E,$E46,合并抵消!$A:$A,M$2)) | ... Q46: =浙江精准学!Q46+知识跳跳!Q46+海南精准学!Q46+实时查!Q46+目标准!Q46+'SMART LEARNING HOLDING'!Q46+'SMART AI LIMITED'!Q46+'HK01'!Q46-(-SUMIFS(合并抵消!$J:$J,合并抵消!$E:$E,$E46,合并抵消!$A:$A,Q$2)+SUMIFS(合并抵消!$K:$K,合并抵消!$E:$E,$E46,合并抵消!$A:$A,Q$2)) | R46: =SUM(F46:Q46)
A47: 硬件支出 | B47: BONG PRO | D47: 学习机系统授权费 | E47: Q1006 | F47: =浙江精准学!F47+知识跳跳!F47+海南精准学!F47+实时查!F47+目标准!F47+'SMART LEARNING HOLDING'!F47+'SMART AI LIMITED'!F47+'HK01'!F47-(-SUMIFS(合并抵消!$J:$J,合并抵消!$E:$E,$E47,合并抵消!$A:$A,F$2)+SUMIFS(合并抵消!$K:$K,合并抵消!$E:$E,$E47,合并抵消!$A:$A,F$2)) | G47: =浙江精准学!G47+知识跳跳!G47+海南精准学!G47+实时查!G47+目标准!G47+'SMART LEARNING HOLDING'!G47+'SMART AI LIMITED'!G47+'HK01'!G47-(-SUMIFS(合并抵消!$J:$J,合并抵消!$E:$E,$E47,合并抵消!$A:$A,G$2)+SUMIFS(合并抵消!$K:$K,合并抵消!$E:$E,$E47,合并抵消!$A:$A,G$2)) | H47: =浙江精准学!H47+知识跳跳!H47+海南精准学!H47+实时查!H47+目标准!H47+'SMART LEARNING HOLDING'!H47+'SMART AI LIMITED'!H47+'HK01'!H47-(-SUMIFS(合并抵消!$J:$J,合并抵消!$E:$E,$E47,合并抵消!$A:$A,H$2)+SUMIFS(合并抵消!$K:$K,合并抵消!$E:$E,$E47,合并抵消!$A:$A,H$2)) | I47: =浙江精准学!I47+知识跳跳!I47+海南精准学!I47+实时查!I47+目标准!I47+'SMART LEARNING HOLDING'!I47+'SMART AI LIMITED'!I47+'HK01'!I47-(-SUMIFS(合并抵消!$J:$J,合并抵消!$E:$E,$E47,合并抵消!$A:$A,I$2)+SUMIFS(合并抵消!$K:$K,合并抵消!$E:$E,$E47,合并抵消!$A:$A,I$2)) | J47: =浙江精准学!J47+知识跳跳!J47+海南精准学!J47+实时查!J47+目标准!J47+'SMART LEARNING HOLDING'!J47+'SMART AI LIMITED'!J47+'HK01'!J47-(-SUMIFS(合并抵消!$J:$J,合并抵消!$E:$E,$E47,合并抵消!$A:$A,J$2)+SUMIFS(合并抵消!$K:$K,合并抵消!$E:$E,$E47,合并抵消!$A:$A,J$2)) | K47: =浙江精准学!K47+知识跳跳!K47+海南精准学!K47+实时查!K47+目标准!K47+'SMART LEARNING HOLDING'!K47+'SMART AI LIMITED'!K47+'HK01'!K47-(-SUMIFS(合并抵消!$J:$J,合并抵消!$E:$E,$E47,合并抵消!$A:$A,K$2)+SUMIFS(合并抵消!$K:$K,合并抵消!$E:$E,$E47,合并抵消!$A:$A,K$2)) | L47: =浙江精准学!L47+知识跳跳!L47+海南精准学!L47+实时查!L47+目标准!L47+'SMART LEARNING HOLDING'!L47+'SMART AI LIMITED'!L47+'HK01'!L47-(-SUMIFS(合并抵消!$J:$J,合并抵消!$E:$E,$E47,合并抵消!$A:$A,L$2)+SUMIFS(合并抵消!$K:$K,合并抵消!$E:$E,$E47,合并抵消!$A:$A,L$2)) | M47: =浙江精准学!M47+知识跳跳!M47+海南精准学!M47+实时查!M47+目标准!M47+'SMART LEARNING HOLDING'!M47+'SMART AI LIMITED'!M47+'HK01'!M47-(-SUMIFS(合并抵消!$J:$J,合并抵消!$E:$E,$E47,合并抵消!$A:$A,M$2)+SUMIFS(合并抵消!$K:$K,合并抵消!$E:$E,$E47,合并抵消!$A:$A,M$2)) | ... Q47: =浙江精准学!Q47+知识跳跳!Q47+海南精准学!Q47+实时查!Q47+目标准!Q47+'SMART LEARNING HOLDING'!Q47+'SMART AI LIMITED'!Q47+'HK01'!Q47-(-SUMIFS(合并抵消!$J:$J,合并抵消!$E:$E,$E47,合并抵消!$A:$A,Q$2)+SUMIFS(合并抵消!$K:$K,合并抵消!$E:$E,$E47,合并抵消!$A:$A,Q$2)) | R47: =SUM(F47:Q47)
A48: 硬件支出 | B48: 其他硬件成本 | C48: 其他硬件成本 | D48: 电容笔 | E48: Q1101 | F48: =浙江精准学!F48+知识跳跳!F48+海南精准学!F48+实时查!F48+目标准!F48+'SMART LEARNING HOLDING'!F48+'SMART AI LIMITED'!F48+'HK01'!F48-(-SUMIFS(合并抵消!$J:$J,合并抵消!$E:$E,$E48,合并抵消!$A:$A,F$2)+SUMIFS(合并抵消!$K:$K,合并抵消!$E:$E,$E48,合并抵消!$A:$A,F$2)) | G48: =浙江精准学!G48+知识跳跳!G48+海南精准学!G48+实时查!G48+目标准!G48+'SMART LEARNING HOLDING'!G48+'SMART AI LIMITED'!G48+'HK01'!G48-(-SUMIFS(合并抵消!$J:$J,合并抵消!$E:$E,$E48,合并抵消!$A:$A,G$2)+SUMIFS(合并抵消!$K:$K,合并抵消!$E:$E,$E48,合并抵消!$A:$A,G$2)) | H48: =浙江精准学!H48+知识跳跳!H48+海南精准学!H48+实时查!H48+目标准!H48+'SMART LEARNING HOLDING'!H48+'SMART AI LIMITED'!H48+'HK01'!H48-(-SUMIFS(合并抵消!$J:$J,合并抵消!$E:$E,$E48,合并抵消!$A:$A,H$2)+SUMIFS(合并抵消!$K:$K,合并抵消!$E:$E,$E48,合并抵消!$A:$A,H$2)) | I48: =浙江精准学!I48+知识跳跳!I48+海南精准学!I48+实时查!I48+目标准!I48+'SMART LEARNING HOLDING'!I48+'SMART AI LIMITED'!I48+'HK01'!I48-(-SUMIFS(合并抵消!$J:$J,合并抵消!$E:$E,$E48,合并抵消!$A:$A,I$2)+SUMIFS(合并抵消!$K:$K,合并抵消!$E:$E,$E48,合并抵消!$A:$A,I$2)) | J48: =浙江精准学!J48+知识跳跳!J48+海南精准学!J48+实时查!J48+目标准!J48+'SMART LEARNING HOLDING'!J48+'SMART AI LIMITED'!J48+'HK01'!J48-(-SUMIFS(合并抵消!$J:$J,合并抵消!$E:$E,$E48,合并抵消!$A:$A,J$2)+SUMIFS(合并抵消!$K:$K,合并抵消!$E:$E,$E48,合并抵消!$A:$A,J$2)) | K48: =浙江精准学!K48+知识跳跳!K48+海南精准学!K48+实时查!K48+目标准!K48+'SMART LEARNING HOLDING'!K48+'SMART AI LIMITED'!K48+'HK01'!K48-(-SUMIFS(合并抵消!$J:$J,合并抵消!$E:$E,$E48,合并抵消!$A:$A,K$2)+SUMIFS(合并抵消!$K:$K,合并抵消!$E:$E,$E48,合并抵消!$A:$A,K$2)) | L48: =浙江精准学!L48+知识跳跳!L48+海南精准学!L48+实时查!L48+目标准!L48+'SMART LEARNING HOLDING'!L48+'SMART AI LIMITED'!L48+'HK01'!L48-(-SUMIFS(合并抵消!$J:$J,合并抵消!$E:$E,$E48,合并抵消!$A:$A,L$2)+SUMIFS(合并抵消!$K:$K,合并抵消!$E:$E,$E48,合并抵消!$A:$A,L$2)) | M48: =浙江精准学!M48+知识跳跳!M48+海南精准学!M48+实时查!M48+目标准!M48+'SMART LEARNING HOLDING'!M48+'SMART AI LIMITED'!M48+'HK01'!M48-(-SUMIFS(合并抵消!$J:$J,合并抵消!$E:$E,$E48,合并抵消!$A:$A,M$2)+SUMIFS(合并抵消!$K:$K,合并抵消!$E:$E,$E48,合并抵消!$A:$A,M$2)) | ... Q48: =浙江精准学!Q48+知识跳跳!Q48+海南精准学!Q48+实时查!Q48+目标准!Q48+'SMART LEARNING HOLDING'!Q48+'SMART AI LIMITED'!Q48+'HK01'!Q48-(-SUMIFS(合并抵消!$J:$J,合并抵消!$E:$E,$E48,合并抵消!$A:$A,Q$2)+SUMIFS(合并抵消!$K:$K,合并抵消!$E:$E,$E48,合并抵消!$A:$A,Q$2)) | R48: =SUM(F48:Q48)
A49: 硬件支出 | B49: 其他硬件成本 | D49: 支架 | E49: Q1102 | F49: =浙江精准学!F49+知识跳跳!F49+海南精准学!F49+实时查!F49+目标准!F49+'SMART LEARNING HOLDING'!F49+'SMART AI LIMITED'!F49+'HK01'!F49-(-SUMIFS(合并抵消!$J:$J,合并抵消!$E:$E,$E49,合并抵消!$A:$A,F$2)+SUMIFS(合并抵消!$K:$K,合并抵消!$E:$E,$E49,合并抵消!$A:$A,F$2)) | G49: =浙江精准学!G49+知识跳跳!G49+海南精准学!G49+实时查!G49+目标准!G49+'SMART LEARNING HOLDING'!G49+'SMART AI LIMITED'!G49+'HK01'!G49-(-SUMIFS(合并抵消!$J:$J,合并抵消!$E:$E,$E49,合并抵消!$A:$A,G$2)+SUMIFS(合并抵消!$K:$K,合并抵消!$E:$E,$E49,合并抵消!$A:$A,G$2)) | H49: =浙江精准学!H49+知识跳跳!H49+海南精准学!H49+实时查!H49+目标准!H49+'SMART LEARNING HOLDING'!H49+'SMART AI LIMITED'!H49+'HK01'!H49-(-SUMIFS(合并抵消!$J:$J,合并抵消!$E:$E,$E49,合并抵消!$A:$A,H$2)+SUMIFS(合并抵消!$K:$K,合并抵消!$E:$E,$E49,合并抵消!$A:$A,H$2)) | I49: =浙江精准学!I49+知识跳跳!I49+海南精准学!I49+实时查!I49+目标准!I49+'SMART LEARNING HOLDING'!I49+'SMART AI LIMITED'!I49+'HK01'!I49-(-SUMIFS(合并抵消!$J:$J,合并抵消!$E:$E,$E49,合并抵消!$A:$A,I$2)+SUMIFS(合并抵消!$K:$K,合并抵消!$E:$E,$E49,合并抵消!$A:$A,I$2)) | J49: =浙江精准学!J49+知识跳跳!J49+海南精准学!J49+实时查!J49+目标准!J49+'SMART LEARNING HOLDING'!J49+'SMART AI LIMITED'!J49+'HK01'!J49-(-SUMIFS(合并抵消!$J:$J,合并抵消!$E:$E,$E49,合并抵消!$A:$A,J$2)+SUMIFS(合并抵消!$K:$K,合并抵消!$E:$E,$E49,合并抵消!$A:$A,J$2)) | K49: =浙江精准学!K49+知识跳跳!K49+海南精准学!K49+实时查!K49+目标准!K49+'SMART LEARNING HOLDING'!K49+'SMART AI LIMITED'!K49+'HK01'!K49-(-SUMIFS(合并抵消!$J:$J,合并抵消!$E:$E,$E49,合并抵消!$A:$A,K$2)+SUMIFS(合并抵消!$K:$K,合并抵消!$E:$E,$E49,合并抵消!$A:$A,K$2)) | L49: =浙江精准学!L49+知识跳跳!L49+海南精准学!L49+实时查!L49+目标准!L49+'SMART LEARNING HOLDING'!L49+'SMART AI LIMITED'!L49+'HK01'!L49-(-SUMIFS(合并抵消!$J:$J,合并抵消!$E:$E,$E49,合并抵消!$A:$A,L$2)+SUMIFS(合并抵消!$K:$K,合并抵消!$E:$E,$E49,合并抵消!$A:$A,L$2)) | M49: =浙江精准学!M49+知识跳跳!M49+海南精准学!M49+实时查!M49+目标准!M49+'SMART LEARNING HOLDING'!M49+'SMART AI LIMITED'!M49+'HK01'!M49-(-SUMIFS(合并抵消!$J:$J,合并抵消!$E:$E,$E49,合并抵消!$A:$A,M$2)+SUMIFS(合并抵消!$K:$K,合并抵消!$E:$E,$E49,合并抵消!$A:$A,M$2)) | ... Q49: =浙江精准学!Q49+知识跳跳!Q49+海南精准学!Q49+实时查!Q49+目标准!Q49+'SMART LEARNING HOLDING'!Q49+'SMART AI LIMITED'!Q49+'HK01'!Q49-(-SUMIFS(合并抵消!$J:$J,合并抵消!$E:$E,$E49,合并抵消!$A:$A,Q$2)+SUMIFS(合并抵消!$K:$K,合并抵消!$E:$E,$E49,合并抵消!$A:$A,Q$2)) | R49: =SUM(F49:Q49)
A50: 硬件支出合计 | F50: =SUM(F36:F49) | G50: =SUM(G36:G49) | H50: =SUM(H36:H49) | I50: =SUM(I36:I49) | J50: =SUM(J36:J49) | K50: =SUM(K36:K49) | L50: =SUM(L36:L49) | M50: =SUM(M36:M49) | ... Q50: =SUM(Q36:Q49) | R50: =SUM(F50:Q50)
A51: 制造费用 | B51: 制造费用 | C51: 制造费用 | D51: 西溪首座仓库租金 | E51: Q3201 | F51: =浙江精准学!F51+知识跳跳!F51+海南精准学!F51+实时查!F51+目标准!F51+'SMART LEARNING HOLDING'!F51+'SMART AI LIMITED'!F51+'HK01'!F51-(-SUMIFS(合并抵消!$J:$J,合并抵消!$E:$E,$E51,合并抵消!$A:$A,F$2)+SUMIFS(合并抵消!$K:$K,合并抵消!$E:$E,$E51,合并抵消!$A:$A,F$2)) | G51: =浙江精准学!G51+知识跳跳!G51+海南精准学!G51+实时查!G51+目标准!G51+'SMART LEARNING HOLDING'!G51+'SMART AI LIMITED'!G51+'HK01'!G51-(-SUMIFS(合并抵消!$J:$J,合并抵消!$E:$E,$E51,合并抵消!$A:$A,G$2)+SUMIFS(合并抵消!$K:$K,合并抵消!$E:$E,$E51,合并抵消!$A:$A,G$2)) | H51: =浙江精准学!H51+知识跳跳!H51+海南精准学!H51+实时查!H51+目标准!H51+'SMART LEARNING HOLDING'!H51+'SMART AI LIMITED'!H51+'HK01'!H51-(-SUMIFS(合并抵消!$J:$J,合并抵消!$E:$E,$E51,合并抵消!$A:$A,H$2)+SUMIFS(合并抵消!$K:$K,合并抵消!$E:$E,$E51,合并抵消!$A:$A,H$2)) | I51: =浙江精准学!I51+知识跳跳!I51+海南精准学!I51+实时查!I51+目标准!I51+'SMART LEARNING HOLDING'!I51+'SMART AI LIMITED'!I51+'HK01'!I51-(-SUMIFS(合并抵消!$J:$J,合并抵消!$E:$E,$E51,合并抵消!$A:$A,I$2)+SUMIFS(合并抵消!$K:$K,合并抵消!$E:$E,$E51,合并抵消!$A:$A,I$2)) | J51: =浙江精准学!J51+知识跳跳!J51+海南精准学!J51+实时查!J51+目标准!J51+'SMART LEARNING HOLDING'!J51+'SMART AI LIMITED'!J51+'HK01'!J51-(-SUMIFS(合并抵消!$J:$J,合并抵消!$E:$E,$E51,合并抵消!$A:$A,J$2)+SUMIFS(合并抵消!$K:$K,合并抵消!$E:$E,$E51,合并抵消!$A:$A,J$2)) | K51: =浙江精准学!K51+知识跳跳!K51+海南精准学!K51+实时查!K51+目标准!K51+'SMART LEARNING HOLDING'!K51+'SMART AI LIMITED'!K51+'HK01'!K51-(-SUMIFS(合并抵消!$J:$J,合并抵消!$E:$E,$E51,合并抵消!$A:$A,K$2)+SUMIFS(合并抵消!$K:$K,合并抵消!$E:$E,$E51,合并抵消!$A:$A,K$2)) | L51: =浙江精准学!L51+知识跳跳!L51+海南精准学!L51+实时查!L51+目标准!L51+'SMART LEARNING HOLDING'!L51+'SMART AI LIMITED'!L51+'HK01'!L51-(-SUMIFS(合并抵消!$J:$J,合并抵消!$E:$E,$E51,合并抵消!$A:$A,L$2)+SUMIFS(合并抵消!$K:$K,合并抵消!$E:$E,$E51,合并抵消!$A:$A,L$2)) | M51: =浙江精准学!M51+知识跳跳!M51+海南精准学!M51+实时查!M51+目标准!M51+'SMART LEARNING HOLDING'!M51+'SMART AI LIMITED'!M51+'HK01'!M51-(-SUMIFS(合并抵消!$J:$J,合并抵消!$E:$E,$E51,合并抵消!$A:$A,M$2)+SUMIFS(合并抵消!$K:$K,合并抵消!$E:$E,$E51,合并抵消!$A:$A,M$2)) | ... Q51: =浙江精准学!Q51+知识跳跳!Q51+海南精准学!Q51+实时查!Q51+目标准!Q51+'SMART LEARNING HOLDING'!Q51+'SMART AI LIMITED'!Q51+'HK01'!Q51-(-SUMIFS(合并抵消!$J:$J,合并抵消!$E:$E,$E51,合并抵消!$A:$A,Q$2)+SUMIFS(合并抵消!$K:$K,合并抵消!$E:$E,$E51,合并抵消!$A:$A,Q$2)) | R51: =SUM(F51:Q51)
A52: 制造费用 | B52: 制造费用 | D52: 西溪首座仓库物业水电费 | E52: Q3202 | F52: =浙江精准学!F52+知识跳跳!F52+海南精准学!F52+实时查!F52+目标准!F52+'SMART LEARNING HOLDING'!F52+'SMART AI LIMITED'!F52+'HK01'!F52-(-SUMIFS(合并抵消!$J:$J,合并抵消!$E:$E,$E52,合并抵消!$A:$A,F$2)+SUMIFS(合并抵消!$K:$K,合并抵消!$E:$E,$E52,合并抵消!$A:$A,F$2)) | G52: =浙江精准学!G52+知识跳跳!G52+海南精准学!G52+实时查!G52+目标准!G52+'SMART LEARNING HOLDING'!G52+'SMART AI LIMITED'!G52+'HK01'!G52-(-SUMIFS(合并抵消!$J:$J,合并抵消!$E:$E,$E52,合并抵消!$A:$A,G$2)+SUMIFS(合并抵消!$K:$K,合并抵消!$E:$E,$E52,合并抵消!$A:$A,G$2)) | H52: =浙江精准学!H52+知识跳跳!H52+海南精准学!H52+实时查!H52+目标准!H52+'SMART LEARNING HOLDING'!H52+'SMART AI LIMITED'!H52+'HK01'!H52-(-SUMIFS(合并抵消!$J:$J,合并抵消!$E:$E,$E52,合并抵消!$A:$A,H$2)+SUMIFS(合并抵消!$K:$K,合并抵消!$E:$E,$E52,合并抵消!$A:$A,H$2)) | I52: =浙江精准学!I52+知识跳跳!I52+海南精准学!I52+实时查!I52+目标准!I52+'SMART LEARNING HOLDING'!I52+'SMART AI LIMITED'!I52+'HK01'!I52-(-SUMIFS(合并抵消!$J:$J,合并抵消!$E:$E,$E52,合并抵消!$A:$A,I$2)+SUMIFS(合并抵消!$K:$K,合并抵消!$E:$E,$E52,合并抵消!$A:$A,I$2)) | J52: =浙江精准学!J52+知识跳跳!J52+海南精准学!J52+实时查!J52+目标准!J52+'SMART LEARNING HOLDING'!J52+'SMART AI LIMITED'!J52+'HK01'!J52-(-SUMIFS(合并抵消!$J:$J,合并抵消!$E:$E,$E52,合并抵消!$A:$A,J$2)+SUMIFS(合并抵消!$K:$K,合并抵消!$E:$E,$E52,合并抵消!$A:$A,J$2)) | K52: =浙江精准学!K52+知识跳跳!K52+海南精准学!K52+实时查!K52+目标准!K52+'SMART LEARNING HOLDING'!K52+'SMART AI LIMITED'!K52+'HK01'!K52-(-SUMIFS(合并抵消!$J:$J,合并抵消!$E:$E,$E52,合并抵消!$A:$A,K$2)+SUMIFS(合并抵消!$K:$K,合并抵消!$E:$E,$E52,合并抵消!$A:$A,K$2)) | L52: =浙江精准学!L52+知识跳跳!L52+海南精准学!L52+实时查!L52+目标准!L52+'SMART LEARNING HOLDING'!L52+'SMART AI LIMITED'!L52+'HK01'!L52-(-SUMIFS(合并抵消!$J:$J,合并抵消!$E:$E,$E52,合并抵消!$A:$A,L$2)+SUMIFS(合并抵消!$K:$K,合并抵消!$E:$E,$E52,合并抵消!$A:$A,L$2)) | M52: =浙江精准学!M52+知识跳跳!M52+海南精准学!M52+实时查!M52+目标准!M52+'SMART LEARNING HOLDING'!M52+'SMART AI LIMITED'!M52+'HK01'!M52-(-SUMIFS(合并抵消!$J:$J,合并抵消!$E:$E,$E52,合并抵消!$A:$A,M$2)+SUMIFS(合并抵消!$K:$K,合并抵消!$E:$E,$E52,合并抵消!$A:$A,M$2)) | ... Q52: =浙江精准学!Q52+知识跳跳!Q52+海南精准学!Q52+实时查!Q52+目标准!Q52+'SMART LEARNING HOLDING'!Q52+'SMART AI LIMITED'!Q52+'HK01'!Q52-(-SUMIFS(合并抵消!$J:$J,合并抵消!$E:$E,$E52,合并抵消!$A:$A,Q$2)+SUMIFS(合并抵消!$K:$K,合并抵消!$E:$E,$E52,合并抵消!$A:$A,Q$2)) | R52: =SUM(F52:Q52)
A53: 制造费用 | B53: 制造费用 | D53: 西溪首座仓库装修费 | E53: Q3203 | F53: =浙江精准学!F53+知识跳跳!F53+海南精准学!F53+实时查!F53+目标准!F53+'SMART LEARNING HOLDING'!F53+'SMART AI LIMITED'!F53+'HK01'!F53-(-SUMIFS(合并抵消!$J:$J,合并抵消!$E:$E,$E53,合并抵消!$A:$A,F$2)+SUMIFS(合并抵消!$K:$K,合并抵消!$E:$E,$E53,合并抵消!$A:$A,F$2)) | G53: =浙江精准学!G53+知识跳跳!G53+海南精准学!G53+实时查!G53+目标准!G53+'SMART LEARNING HOLDING'!G53+'SMART AI LIMITED'!G53+'HK01'!G53-(-SUMIFS(合并抵消!$J:$J,合并抵消!$E:$E,$E53,合并抵消!$A:$A,G$2)+SUMIFS(合并抵消!$K:$K,合并抵消!$E:$E,$E53,合并抵消!$A:$A,G$2)) | H53: =浙江精准学!H53+知识跳跳!H53+海南精准学!H53+实时查!H53+目标准!H53+'SMART LEARNING HOLDING'!H53+'SMART AI LIMITED'!H53+'HK01'!H53-(-SUMIFS(合并抵消!$J:$J,合并抵消!$E:$E,$E53,合并抵消!$A:$A,H$2)+SUMIFS(合并抵消!$K:$K,合并抵消!$E:$E,$E53,合并抵消!$A:$A,H$2)) | I53: =浙江精准学!I53+知识跳跳!I53+海南精准学!I53+实时查!I53+目标准!I53+'SMART LEARNING HOLDING'!I53+'SMART AI LIMITED'!I53+'HK01'!I53-(-SUMIFS(合并抵消!$J:$J,合并抵消!$E:$E,$E53,合并抵消!$A:$A,I$2)+SUMIFS(合并抵消!$K:$K,合并抵消!$E:$E,$E53,合并抵消!$A:$A,I$2)) | J53: =浙江精准学!J53+知识跳跳!J53+海南精准学!J53+实时查!J53+目标准!J53+'SMART LEARNING HOLDING'!J53+'SMART AI LIMITED'!J53+'HK01'!J53-(-SUMIFS(合并抵消!$J:$J,合并抵消!$E:$E,$E53,合并抵消!$A:$A,J$2)+SUMIFS(合并抵消!$K:$K,合并抵消!$E:$E,$E53,合并抵消!$A:$A,J$2)) | K53: =浙江精准学!K53+知识跳跳!K53+海南精准学!K53+实时查!K53+目标准!K53+'SMART LEARNING HOLDING'!K53+'SMART AI LIMITED'!K53+'HK01'!K53-(-SUMIFS(合并抵消!$J:$J,合并抵消!$E:$E,$E53,合并抵消!$A:$A,K$2)+SUMIFS(合并抵消!$K:$K,合并抵消!$E:$E,$E53,合并抵消!$A:$A,K$2)) | L53: =浙江精准学!L53+知识跳跳!L53+海南精准学!L53+实时查!L53+目标准!L53+'SMART LEARNING HOLDING'!L53+'SMART AI LIMITED'!L53+'HK01'!L53-(-SUMIFS(合并抵消!$J:$J,合并抵消!$E:$E,$E53,合并抵消!$A:$A,L$2)+SUMIFS(合并抵消!$K:$K,合并抵消!$E:$E,$E53,合并抵消!$A:$A,L$2)) | M53: =浙江精准学!M53+知识跳跳!M53+海南精准学!M53+实时查!M53+目标准!M53+'SMART LEARNING HOLDING'!M53+'SMART AI LIMITED'!M53+'HK01'!M53-(-SUMIFS(合并抵消!$J:$J,合并抵消!$E:$E,$E53,合并抵消!$A:$A,M$2)+SUMIFS(合并抵消!$K:$K,合并抵消!$E:$E,$E53,合并抵消!$A:$A,M$2)) | ... Q53: =浙江精准学!Q53+知识跳跳!Q53+海南精准学!Q53+实时查!Q53+目标准!Q53+'SMART LEARNING HOLDING'!Q53+'SMART AI LIMITED'!Q53+'HK01'!Q53-(-SUMIFS(合并抵消!$J:$J,合并抵消!$E:$E,$E53,合并抵消!$A:$A,Q$2)+SUMIFS(合并抵消!$K:$K,合并抵消!$E:$E,$E53,合并抵消!$A:$A,Q$2)) | R53: =SUM(F53:Q53)
A54: 制造费用 | B54: 制造费用 | D54: 运输费 | E54: Q3204 | F54: =浙江精准学!F54+知识跳跳!F54+海南精准学!F54+实时查!F54+目标准!F54+'SMART LEARNING HOLDING'!F54+'SMART AI LIMITED'!F54+'HK01'!F54-(-SUMIFS(合并抵消!$J:$J,合并抵消!$E:$E,$E54,合并抵消!$A:$A,F$2)+SUMIFS(合并抵消!$K:$K,合并抵消!$E:$E,$E54,合并抵消!$A:$A,F$2)) | G54: =浙江精准学!G54+知识跳跳!G54+海南精准学!G54+实时查!G54+目标准!G54+'SMART LEARNING HOLDING'!G54+'SMART AI LIMITED'!G54+'HK01'!G54-(-SUMIFS(合并抵消!$J:$J,合并抵消!$E:$E,$E54,合并抵消!$A:$A,G$2)+SUMIFS(合并抵消!$K:$K,合并抵消!$E:$E,$E54,合并抵消!$A:$A,G$2)) | H54: =浙江精准学!H54+知识跳跳!H54+海南精准学!H54+实时查!H54+目标准!H54+'SMART LEARNING HOLDING'!H54+'SMART AI LIMITED'!H54+'HK01'!H54-(-SUMIFS(合并抵消!$J:$J,合并抵消!$E:$E,$E54,合并抵消!$A:$A,H$2)+SUMIFS(合并抵消!$K:$K,合并抵消!$E:$E,$E54,合并抵消!$A:$A,H$2)) | I54: =浙江精准学!I54+知识跳跳!I54+海南精准学!I54+实时查!I54+目标准!I54+'SMART LEARNING HOLDING'!I54+'SMART AI LIMITED'!I54+'HK01'!I54-(-SUMIFS(合并抵消!$J:$J,合并抵消!$E:$E,$E54,合并抵消!$A:$A,I$2)+SUMIFS(合并抵消!$K:$K,合并抵消!$E:$E,$E54,合并抵消!$A:$A,I$2)) | J54: =浙江精准学!J54+知识跳跳!J54+海南精准学!J54+实时查!J54+目标准!J54+'SMART LEARNING HOLDING'!J54+'SMART AI LIMITED'!J54+'HK01'!J54-(-SUMIFS(合并抵消!$J:$J,合并抵消!$E:$E,$E54,合并抵消!$A:$A,J$2)+SUMIFS(合并抵消!$K:$K,合并抵消!$E:$E,$E54,合并抵消!$A:$A,J$2)) | K54: =浙江精准学!K54+知识跳跳!K54+海南精准学!K54+实时查!K54+目标准!K54+'SMART LEARNING HOLDING'!K54+'SMART AI LIMITED'!K54+'HK01'!K54-(-SUMIFS(合并抵消!$J:$J,合并抵消!$E:$E,$E54,合并抵消!$A:$A,K$2)+SUMIFS(合并抵消!$K:$K,合并抵消!$E:$E,$E54,合并抵消!$A:$A,K$2)) | L54: =浙江精准学!L54+知识跳跳!L54+海南精准学!L54+实时查!L54+目标准!L54+'SMART LEARNING HOLDING'!L54+'SMART AI LIMITED'!L54+'HK01'!L54-(-SUMIFS(合并抵消!$J:$J,合并抵消!$E:$E,$E54,合并抵消!$A:$A,L$2)+SUMIFS(合并抵消!$K:$K,合并抵消!$E:$E,$E54,合并抵消!$A:$A,L$2)) | M54: =浙江精准学!M54+知识跳跳!M54+海南精准学!M54+实时查!M54+目标准!M54+'SMART LEARNING HOLDING'!M54+'SMART AI LIMITED'!M54+'HK01'!M54-(-SUMIFS(合并抵消!$J:$J,合并抵消!$E:$E,$E54,合并抵消!$A:$A,M$2)+SUMIFS(合并抵消!$K:$K,合并抵消!$E:$E,$E54,合并抵消!$A:$A,M$2)) | ... Q54: =浙江精准学!Q54+知识跳跳!Q54+海南精准学!Q54+实时查!Q54+目标准!Q54+'SMART LEARNING HOLDING'!Q54+'SMART AI LIMITED'!Q54+'HK01'!Q54-(-SUMIFS(合并抵消!$J:$J,合并抵消!$E:$E,$E54,合并抵消!$A:$A,Q$2)+SUMIFS(合并抵消!$K:$K,合并抵消!$E:$E,$E54,合并抵消!$A:$A,Q$2)) | R54: =SUM(F54:Q54)
A55: 制造费用 | B55: 制造费用 | D55: 低值易耗品采购 | E55: Q3205 | F55: =浙江精准学!F55+知识跳跳!F55+海南精准学!F55+实时查!F55+目标准!F55+'SMART LEARNING HOLDING'!F55+'SMART AI LIMITED'!F55+'HK01'!F55-(-SUMIFS(合并抵消!$J:$J,合并抵消!$E:$E,$E55,合并抵消!$A:$A,F$2)+SUMIFS(合并抵消!$K:$K,合并抵消!$E:$E,$E55,合并抵消!$A:$A,F$2)) | G55: =浙江精准学!G55+知识跳跳!G55+海南精准学!G55+实时查!G55+目标准!G55+'SMART LEARNING HOLDING'!G55+'SMART AI LIMITED'!G55+'HK01'!G55-(-SUMIFS(合并抵消!$J:$J,合并抵消!$E:$E,$E55,合并抵消!$A:$A,G$2)+SUMIFS(合并抵消!$K:$K,合并抵消!$E:$E,$E55,合并抵消!$A:$A,G$2)) | H55: =浙江精准学!H55+知识跳跳!H55+海南精准学!H55+实时查!H55+目标准!H55+'SMART LEARNING HOLDING'!H55+'SMART AI LIMITED'!H55+'HK01'!H55-(-SUMIFS(合并抵消!$J:$J,合并抵消!$E:$E,$E55,合并抵消!$A:$A,H$2)+SUMIFS(合并抵消!$K:$K,合并抵消!$E:$E,$E55,合并抵消!$A:$A,H$2)) | I55: =浙江精准学!I55+知识跳跳!I55+海南精准学!I55+实时查!I55+目标准!I55+'SMART LEARNING HOLDING'!I55+'SMART AI LIMITED'!I55+'HK01'!I55-(-SUMIFS(合并抵消!$J:$J,合并抵消!$E:$E,$E55,合并抵消!$A:$A,I$2)+SUMIFS(合并抵消!$K:$K,合并抵消!$E:$E,$E55,合并抵消!$A:$A,I$2)) | J55: =浙江精准学!J55+知识跳跳!J55+海南精准学!J55+实时查!J55+目标准!J55+'SMART LEARNING HOLDING'!J55+'SMART AI LIMITED'!J55+'HK01'!J55-(-SUMIFS(合并抵消!$J:$J,合并抵消!$E:$E,$E55,合并抵消!$A:$A,J$2)+SUMIFS(合并抵消!$K:$K,合并抵消!$E:$E,$E55,合并抵消!$A:$A,J$2)) | K55: =浙江精准学!K55+知识跳跳!K55+海南精准学!K55+实时查!K55+目标准!K55+'SMART LEARNING HOLDING'!K55+'SMART AI LIMITED'!K55+'HK01'!K55-(-SUMIFS(合并抵消!$J:$J,合并抵消!$E:$E,$E55,合并抵消!$A:$A,K$2)+SUMIFS(合并抵消!$K:$K,合并抵消!$E:$E,$E55,合并抵消!$A:$A,K$2)) | L55: =浙江精准学!L55+知识跳跳!L55+海南精准学!L55+实时查!L55+目标准!L55+'SMART LEARNING HOLDING'!L55+'SMART AI LIMITED'!L55+'HK01'!L55-(-SUMIFS(合并抵消!$J:$J,合并抵消!$E:$E,$E55,合并抵消!$A:$A,L$2)+SUMIFS(合并抵消!$K:$K,合并抵消!$E:$E,$E55,合并抵消!$A:$A,L$2)) | M55: =浙江精准学!M55+知识跳跳!M55+海南精准学!M55+实时查!M55+目标准!M55+'SMART LEARNING HOLDING'!M55+'SMART AI LIMITED'!M55+'HK01'!M55-(-SUMIFS(合并抵消!$J:$J,合并抵消!$E:$E,$E55,合并抵消!$A:$A,M$2)+SUMIFS(合并抵消!$K:$K,合并抵消!$E:$E,$E55,合并抵消!$A:$A,M$2)) | ... Q55: =浙江精准学!Q55+知识跳跳!Q55+海南精准学!Q55+实时查!Q55+目标准!Q55+'SMART LEARNING HOLDING'!Q55+'SMART AI LIMITED'!Q55+'HK01'!Q55-(-SUMIFS(合并抵消!$J:$J,合并抵消!$E:$E,$E55,合并抵消!$A:$A,Q$2)+SUMIFS(合并抵消!$K:$K,合并抵消!$E:$E,$E55,合并抵消!$A:$A,Q$2)) | R55: =SUM(F55:Q55)
A56: 制造费用 | B56: 制造费用 | D56: 生产成本-员工报销 | E56: Q3206 | F56: =浙江精准学!F56+知识跳跳!F56+海南精准学!F56+实时查!F56+目标准!F56+'SMART LEARNING HOLDING'!F56+'SMART AI LIMITED'!F56+'HK01'!F56-(-SUMIFS(合并抵消!$J:$J,合并抵消!$E:$E,$E56,合并抵消!$A:$A,F$2)+SUMIFS(合并抵消!$K:$K,合并抵消!$E:$E,$E56,合并抵消!$A:$A,F$2)) | G56: =浙江精准学!G56+知识跳跳!G56+海南精准学!G56+实时查!G56+目标准!G56+'SMART LEARNING HOLDING'!G56+'SMART AI LIMITED'!G56+'HK01'!G56-(-SUMIFS(合并抵消!$J:$J,合并抵消!$E:$E,$E56,合并抵消!$A:$A,G$2)+SUMIFS(合并抵消!$K:$K,合并抵消!$E:$E,$E56,合并抵消!$A:$A,G$2)) | H56: =浙江精准学!H56+知识跳跳!H56+海南精准学!H56+实时查!H56+目标准!H56+'SMART LEARNING HOLDING'!H56+'SMART AI LIMITED'!H56+'HK01'!H56-(-SUMIFS(合并抵消!$J:$J,合并抵消!$E:$E,$E56,合并抵消!$A:$A,H$2)+SUMIFS(合并抵消!$K:$K,合并抵消!$E:$E,$E56,合并抵消!$A:$A,H$2)) | I56: =浙江精准学!I56+知识跳跳!I56+海南精准学!I56+实时查!I56+目标准!I56+'SMART LEARNING HOLDING'!I56+'SMART AI LIMITED'!I56+'HK01'!I56-(-SUMIFS(合并抵消!$J:$J,合并抵消!$E:$E,$E56,合并抵消!$A:$A,I$2)+SUMIFS(合并抵消!$K:$K,合并抵消!$E:$E,$E56,合并抵消!$A:$A,I$2)) | J56: =浙江精准学!J56+知识跳跳!J56+海南精准学!J56+实时查!J56+目标准!J56+'SMART LEARNING HOLDING'!J56+'SMART AI LIMITED'!J56+'HK01'!J56-(-SUMIFS(合并抵消!$J:$J,合并抵消!$E:$E,$E56,合并抵消!$A:$A,J$2)+SUMIFS(合并抵消!$K:$K,合并抵消!$E:$E,$E56,合并抵消!$A:$A,J$2)) | K56: =浙江精准学!K56+知识跳跳!K56+海南精准学!K56+实时查!K56+目标准!K56+'SMART LEARNING HOLDING'!K56+'SMART AI LIMITED'!K56+'HK01'!K56-(-SUMIFS(合并抵消!$J:$J,合并抵消!$E:$E,$E56,合并抵消!$A:$A,K$2)+SUMIFS(合并抵消!$K:$K,合并抵消!$E:$E,$E56,合并抵消!$A:$A,K$2)) | L56: =浙江精准学!L56+知识跳跳!L56+海南精准学!L56+实时查!L56+目标准!L56+'SMART LEARNING HOLDING'!L56+'SMART AI LIMITED'!L56+'HK01'!L56-(-SUMIFS(合并抵消!$J:$J,合并抵消!$E:$E,$E56,合并抵消!$A:$A,L$2)+SUMIFS(合并抵消!$K:$K,合并抵消!$E:$E,$E56,合并抵消!$A:$A,L$2)) | M56: =浙江精准学!M56+知识跳跳!M56+海南精准学!M56+实时查!M56+目标准!M56+'SMART LEARNING HOLDING'!M56+'SMART AI LIMITED'!M56+'HK01'!M56-(-SUMIFS(合并抵消!$J:$J,合并抵消!$E:$E,$E56,合并抵消!$A:$A,M$2)+SUMIFS(合并抵消!$K:$K,合并抵消!$E:$E,$E56,合并抵消!$A:$A,M$2)) | ... Q56: =浙江精准学!Q56+知识跳跳!Q56+海南精准学!Q56+实时查!Q56+目标准!Q56+'SMART LEARNING HOLDING'!Q56+'SMART AI LIMITED'!Q56+'HK01'!Q56-(-SUMIFS(合并抵消!$J:$J,合并抵消!$E:$E,$E56,合并抵消!$A:$A,Q$2)+SUMIFS(合并抵消!$K:$K,合并抵消!$E:$E,$E56,合并抵消!$A:$A,Q$2)) | R56: =SUM(F56:Q56)
A57: 制造费用 | B57: 制造费用 | D57: 包机膜 | E57: Q3207 | F57: =浙江精准学!F57+知识跳跳!F57+海南精准学!F57+实时查!F57+目标准!F57+'SMART LEARNING HOLDING'!F57+'SMART AI LIMITED'!F57+'HK01'!F57-(-SUMIFS(合并抵消!$J:$J,合并抵消!$E:$E,$E57,合并抵消!$A:$A,F$2)+SUMIFS(合并抵消!$K:$K,合并抵消!$E:$E,$E57,合并抵消!$A:$A,F$2)) | G57: =浙江精准学!G57+知识跳跳!G57+海南精准学!G57+实时查!G57+目标准!G57+'SMART LEARNING HOLDING'!G57+'SMART AI LIMITED'!G57+'HK01'!G57-(-SUMIFS(合并抵消!$J:$J,合并抵消!$E:$E,$E57,合并抵消!$A:$A,G$2)+SUMIFS(合并抵消!$K:$K,合并抵消!$E:$E,$E57,合并抵消!$A:$A,G$2)) | H57: =浙江精准学!H57+知识跳跳!H57+海南精准学!H57+实时查!H57+目标准!H57+'SMART LEARNING HOLDING'!H57+'SMART AI LIMITED'!H57+'HK01'!H57-(-SUMIFS(合并抵消!$J:$J,合并抵消!$E:$E,$E57,合并抵消!$A:$A,H$2)+SUMIFS(合并抵消!$K:$K,合并抵消!$E:$E,$E57,合并抵消!$A:$A,H$2)) | I57: =浙江精准学!I57+知识跳跳!I57+海南精准学!I57+实时查!I57+目标准!I57+'SMART LEARNING HOLDING'!I57+'SMART AI LIMITED'!I57+'HK01'!I57-(-SUMIFS(合并抵消!$J:$J,合并抵消!$E:$E,$E57,合并抵消!$A:$A,I$2)+SUMIFS(合并抵消!$K:$K,合并抵消!$E:$E,$E57,合并抵消!$A:$A,I$2)) | J57: =浙江精准学!J57+知识跳跳!J57+海南精准学!J57+实时查!J57+目标准!J57+'SMART LEARNING HOLDING'!J57+'SMART AI LIMITED'!J57+'HK01'!J57-(-SUMIFS(合并抵消!$J:$J,合并抵消!$E:$E,$E57,合并抵消!$A:$A,J$2)+SUMIFS(合并抵消!$K:$K,合并抵消!$E:$E,$E57,合并抵消!$A:$A,J$2)) | K57: =浙江精准学!K57+知识跳跳!K57+海南精准学!K57+实时查!K57+目标准!K57+'SMART LEARNING HOLDING'!K57+'SMART AI LIMITED'!K57+'HK01'!K57-(-SUMIFS(合并抵消!$J:$J,合并抵消!$E:$E,$E57,合并抵消!$A:$A,K$2)+SUMIFS(合并抵消!$K:$K,合并抵消!$E:$E,$E57,合并抵消!$A:$A,K$2)) | L57: =浙江精准学!L57+知识跳跳!L57+海南精准学!L57+实时查!L57+目标准!L57+'SMART LEARNING HOLDING'!L57+'SMART AI LIMITED'!L57+'HK01'!L57-(-SUMIFS(合并抵消!$J:$J,合并抵消!$E:$E,$E57,合并抵消!$A:$A,L$2)+SUMIFS(合并抵消!$K:$K,合并抵消!$E:$E,$E57,合并抵消!$A:$A,L$2)) | M57: =浙江精准学!M57+知识跳跳!M57+海南精准学!M57+实时查!M57+目标准!M57+'SMART LEARNING HOLDING'!M57+'SMART AI LIMITED'!M57+'HK01'!M57-(-SUMIFS(合并抵消!$J:$J,合并抵消!$E:$E,$E57,合并抵消!$A:$A,M$2)+SUMIFS(合并抵消!$K:$K,合并抵消!$E:$E,$E57,合并抵消!$A:$A,M$2)) | ... Q57: =浙江精准学!Q57+知识跳跳!Q57+海南精准学!Q57+实时查!Q57+目标准!Q57+'SMART LEARNING HOLDING'!Q57+'SMART AI LIMITED'!Q57+'HK01'!Q57-(-SUMIFS(合并抵消!$J:$J,合并抵消!$E:$E,$E57,合并抵消!$A:$A,Q$2)+SUMIFS(合并抵消!$K:$K,合并抵消!$E:$E,$E57,合并抵消!$A:$A,Q$2)) | R57: =SUM(F57:Q57)
A58: 制造费用 | B58: 制造费用 | D58: 贴纸/说明书 | E58: Q3208 | F58: =浙江精准学!F58+知识跳跳!F58+海南精准学!F58+实时查!F58+目标准!F58+'SMART LEARNING HOLDING'!F58+'SMART AI LIMITED'!F58+'HK01'!F58-(-SUMIFS(合并抵消!$J:$J,合并抵消!$E:$E,$E58,合并抵消!$A:$A,F$2)+SUMIFS(合并抵消!$K:$K,合并抵消!$E:$E,$E58,合并抵消!$A:$A,F$2)) | G58: =浙江精准学!G58+知识跳跳!G58+海南精准学!G58+实时查!G58+目标准!G58+'SMART LEARNING HOLDING'!G58+'SMART AI LIMITED'!G58+'HK01'!G58-(-SUMIFS(合并抵消!$J:$J,合并抵消!$E:$E,$E58,合并抵消!$A:$A,G$2)+SUMIFS(合并抵消!$K:$K,合并抵消!$E:$E,$E58,合并抵消!$A:$A,G$2)) | H58: =浙江精准学!H58+知识跳跳!H58+海南精准学!H58+实时查!H58+目标准!H58+'SMART LEARNING HOLDING'!H58+'SMART AI LIMITED'!H58+'HK01'!H58-(-SUMIFS(合并抵消!$J:$J,合并抵消!$E:$E,$E58,合并抵消!$A:$A,H$2)+SUMIFS(合并抵消!$K:$K,合并抵消!$E:$E,$E58,合并抵消!$A:$A,H$2)) | I58: =浙江精准学!I58+知识跳跳!I58+海南精准学!I58+实时查!I58+目标准!I58+'SMART LEARNING HOLDING'!I58+'SMART AI LIMITED'!I58+'HK01'!I58-(-SUMIFS(合并抵消!$J:$J,合并抵消!$E:$E,$E58,合并抵消!$A:$A,I$2)+SUMIFS(合并抵消!$K:$K,合并抵消!$E:$E,$E58,合并抵消!$A:$A,I$2)) | J58: =浙江精准学!J58+知识跳跳!J58+海南精准学!J58+实时查!J58+目标准!J58+'SMART LEARNING HOLDING'!J58+'SMART AI LIMITED'!J58+'HK01'!J58-(-SUMIFS(合并抵消!$J:$J,合并抵消!$E:$E,$E58,合并抵消!$A:$A,J$2)+SUMIFS(合并抵消!$K:$K,合并抵消!$E:$E,$E58,合并抵消!$A:$A,J$2)) | K58: =浙江精准学!K58+知识跳跳!K58+海南精准学!K58+实时查!K58+目标准!K58+'SMART LEARNING HOLDING'!K58+'SMART AI LIMITED'!K58+'HK01'!K58-(-SUMIFS(合并抵消!$J:$J,合并抵消!$E:$E,$E58,合并抵消!$A:$A,K$2)+SUMIFS(合并抵消!$K:$K,合并抵消!$E:$E,$E58,合并抵消!$A:$A,K$2)) | L58: =浙江精准学!L58+知识跳跳!L58+海南精准学!L58+实时查!L58+目标准!L58+'SMART LEARNING HOLDING'!L58+'SMART AI LIMITED'!L58+'HK01'!L58-(-SUMIFS(合并抵消!$J:$J,合并抵消!$E:$E,$E58,合并抵消!$A:$A,L$2)+SUMIFS(合并抵消!$K:$K,合并抵消!$E:$E,$E58,合并抵消!$A:$A,L$2)) | M58: =浙江精准学!M58+知识跳跳!M58+海南精准学!M58+实时查!M58+目标准!M58+'SMART LEARNING HOLDING'!M58+'SMART AI LIMITED'!M58+'HK01'!M58-(-SUMIFS(合并抵消!$J:$J,合并抵消!$E:$E,$E58,合并抵消!$A:$A,M$2)+SUMIFS(合并抵消!$K:$K,合并抵消!$E:$E,$E58,合并抵消!$A:$A,M$2)) | ... Q58: =浙江精准学!Q58+知识跳跳!Q58+海南精准学!Q58+实时查!Q58+目标准!Q58+'SMART LEARNING HOLDING'!Q58+'SMART AI LIMITED'!Q58+'HK01'!Q58-(-SUMIFS(合并抵消!$J:$J,合并抵消!$E:$E,$E58,合并抵消!$A:$A,Q$2)+SUMIFS(合并抵消!$K:$K,合并抵消!$E:$E,$E58,合并抵消!$A:$A,Q$2)) | R58: =SUM(F58:Q58)
A59: 制造费用 | B59: 制造费用 | D59: 笔尖 | E59: Q3209 | F59: =浙江精准学!F59+知识跳跳!F59+海南精准学!F59+实时查!F59+目标准!F59+'SMART LEARNING HOLDING'!F59+'SMART AI LIMITED'!F59+'HK01'!F59-(-SUMIFS(合并抵消!$J:$J,合并抵消!$E:$E,$E59,合并抵消!$A:$A,F$2)+SUMIFS(合并抵消!$K:$K,合并抵消!$E:$E,$E59,合并抵消!$A:$A,F$2)) | G59: =浙江精准学!G59+知识跳跳!G59+海南精准学!G59+实时查!G59+目标准!G59+'SMART LEARNING HOLDING'!G59+'SMART AI LIMITED'!G59+'HK01'!G59-(-SUMIFS(合并抵消!$J:$J,合并抵消!$E:$E,$E59,合并抵消!$A:$A,G$2)+SUMIFS(合并抵消!$K:$K,合并抵消!$E:$E,$E59,合并抵消!$A:$A,G$2)) | H59: =浙江精准学!H59+知识跳跳!H59+海南精准学!H59+实时查!H59+目标准!H59+'SMART LEARNING HOLDING'!H59+'SMART AI LIMITED'!H59+'HK01'!H59-(-SUMIFS(合并抵消!$J:$J,合并抵消!$E:$E,$E59,合并抵消!$A:$A,H$2)+SUMIFS(合并抵消!$K:$K,合并抵消!$E:$E,$E59,合并抵消!$A:$A,H$2)) | I59: =浙江精准学!I59+知识跳跳!I59+海南精准学!I59+实时查!I59+目标准!I59+'SMART LEARNING HOLDING'!I59+'SMART AI LIMITED'!I59+'HK01'!I59-(-SUMIFS(合并抵消!$J:$J,合并抵消!$E:$E,$E59,合并抵消!$A:$A,I$2)+SUMIFS(合并抵消!$K:$K,合并抵消!$E:$E,$E59,合并抵消!$A:$A,I$2)) | J59: =浙江精准学!J59+知识跳跳!J59+海南精准学!J59+实时查!J59+目标准!J59+'SMART LEARNING HOLDING'!J59+'SMART AI LIMITED'!J59+'HK01'!J59-(-SUMIFS(合并抵消!$J:$J,合并抵消!$E:$E,$E59,合并抵消!$A:$A,J$2)+SUMIFS(合并抵消!$K:$K,合并抵消!$E:$E,$E59,合并抵消!$A:$A,J$2)) | K59: =浙江精准学!K59+知识跳跳!K59+海南精准学!K59+实时查!K59+目标准!K59+'SMART LEARNING HOLDING'!K59+'SMART AI LIMITED'!K59+'HK01'!K59-(-SUMIFS(合并抵消!$J:$J,合并抵消!$E:$E,$E59,合并抵消!$A:$A,K$2)+SUMIFS(合并抵消!$K:$K,合并抵消!$E:$E,$E59,合并抵消!$A:$A,K$2)) | L59: =浙江精准学!L59+知识跳跳!L59+海南精准学!L59+实时查!L59+目标准!L59+'SMART LEARNING HOLDING'!L59+'SMART AI LIMITED'!L59+'HK01'!L59-(-SUMIFS(合并抵消!$J:$J,合并抵消!$E:$E,$E59,合并抵消!$A:$A,L$2)+SUMIFS(合并抵消!$K:$K,合并抵消!$E:$E,$E59,合并抵消!$A:$A,L$2)) | M59: =浙江精准学!M59+知识跳跳!M59+海南精准学!M59+实时查!M59+目标准!M59+'SMART LEARNING HOLDING'!M59+'SMART AI LIMITED'!M59+'HK01'!M59-(-SUMIFS(合并抵消!$J:$J,合并抵消!$E:$E,$E59,合并抵消!$A:$A,M$2)+SUMIFS(合并抵消!$K:$K,合并抵消!$E:$E,$E59,合并抵消!$A:$A,M$2)) | ... Q59: =浙江精准学!Q59+知识跳跳!Q59+海南精准学!Q59+实时查!Q59+目标准!Q59+'SMART LEARNING HOLDING'!Q59+'SMART AI LIMITED'!Q59+'HK01'!Q59-(-SUMIFS(合并抵消!$J:$J,合并抵消!$E:$E,$E59,合并抵消!$A:$A,Q$2)+SUMIFS(合并抵消!$K:$K,合并抵消!$E:$E,$E59,合并抵消!$A:$A,Q$2)) | R59: =SUM(F59:Q59)
A60: 制造费用 | B60: 制造费用 | D60: 华泰租金 | E60: Q3210 | F60: =浙江精准学!F60+知识跳跳!F60+海南精准学!F60+实时查!F60+目标准!F60+'SMART LEARNING HOLDING'!F60+'SMART AI LIMITED'!F60+'HK01'!F60-(-SUMIFS(合并抵消!$J:$J,合并抵消!$E:$E,$E60,合并抵消!$A:$A,F$2)+SUMIFS(合并抵消!$K:$K,合并抵消!$E:$E,$E60,合并抵消!$A:$A,F$2)) | G60: =浙江精准学!G60+知识跳跳!G60+海南精准学!G60+实时查!G60+目标准!G60+'SMART LEARNING HOLDING'!G60+'SMART AI LIMITED'!G60+'HK01'!G60-(-SUMIFS(合并抵消!$J:$J,合并抵消!$E:$E,$E60,合并抵消!$A:$A,G$2)+SUMIFS(合并抵消!$K:$K,合并抵消!$E:$E,$E60,合并抵消!$A:$A,G$2)) | H60: =浙江精准学!H60+知识跳跳!H60+海南精准学!H60+实时查!H60+目标准!H60+'SMART LEARNING HOLDING'!H60+'SMART AI LIMITED'!H60+'HK01'!H60-(-SUMIFS(合并抵消!$J:$J,合并抵消!$E:$E,$E60,合并抵消!$A:$A,H$2)+SUMIFS(合并抵消!$K:$K,合并抵消!$E:$E,$E60,合并抵消!$A:$A,H$2)) | I60: =浙江精准学!I60+知识跳跳!I60+海南精准学!I60+实时查!I60+目标准!I60+'SMART LEARNING HOLDING'!I60+'SMART AI LIMITED'!I60+'HK01'!I60-(-SUMIFS(合并抵消!$J:$J,合并抵消!$E:$E,$E60,合并抵消!$A:$A,I$2)+SUMIFS(合并抵消!$K:$K,合并抵消!$E:$E,$E60,合并抵消!$A:$A,I$2)) | J60: =浙江精准学!J60+知识跳跳!J60+海南精准学!J60+实时查!J60+目标准!J60+'SMART LEARNING HOLDING'!J60+'SMART AI LIMITED'!J60+'HK01'!J60-(-SUMIFS(合并抵消!$J:$J,合并抵消!$E:$E,$E60,合并抵消!$A:$A,J$2)+SUMIFS(合并抵消!$K:$K,合并抵消!$E:$E,$E60,合并抵消!$A:$A,J$2)) | K60: =浙江精准学!K60+知识跳跳!K60+海南精准学!K60+实时查!K60+目标准!K60+'SMART LEARNING HOLDING'!K60+'SMART AI LIMITED'!K60+'HK01'!K60-(-SUMIFS(合并抵消!$J:$J,合并抵消!$E:$E,$E60,合并抵消!$A:$A,K$2)+SUMIFS(合并抵消!$K:$K,合并抵消!$E:$E,$E60,合并抵消!$A:$A,K$2)) | L60: =浙江精准学!L60+知识跳跳!L60+海南精准学!L60+实时查!L60+目标准!L60+'SMART LEARNING HOLDING'!L60+'SMART AI LIMITED'!L60+'HK01'!L60-(-SUMIFS(合并抵消!$J:$J,合并抵消!$E:$E,$E60,合并抵消!$A:$A,L$2)+SUMIFS(合并抵消!$K:$K,合并抵消!$E:$E,$E60,合并抵消!$A:$A,L$2)) | M60: =浙江精准学!M60+知识跳跳!M60+海南精准学!M60+实时查!M60+目标准!M60+'SMART LEARNING HOLDING'!M60+'SMART AI LIMITED'!M60+'HK01'!M60-(-SUMIFS(合并抵消!$J:$J,合并抵消!$E:$E,$E60,合并抵消!$A:$A,M$2)+SUMIFS(合并抵消!$K:$K,合并抵消!$E:$E,$E60,合并抵消!$A:$A,M$2)) | ... Q60: =浙江精准学!Q60+知识跳跳!Q60+海南精准学!Q60+实时查!Q60+目标准!Q60+'SMART LEARNING HOLDING'!Q60+'SMART AI LIMITED'!Q60+'HK01'!Q60-(-SUMIFS(合并抵消!$J:$J,合并抵消!$E:$E,$E60,合并抵消!$A:$A,Q$2)+SUMIFS(合并抵消!$K:$K,合并抵消!$E:$E,$E60,合并抵消!$A:$A,Q$2)) | R60: =SUM(F60:Q60)
A61: 制造费用 | B61: 制造费用 | D61: 华泰水电费 | E61: Q3211 | F61: =浙江精准学!F61+知识跳跳!F61+海南精准学!F61+实时查!F61+目标准!F61+'SMART LEARNING HOLDING'!F61+'SMART AI LIMITED'!F61+'HK01'!F61-(-SUMIFS(合并抵消!$J:$J,合并抵消!$E:$E,$E61,合并抵消!$A:$A,F$2)+SUMIFS(合并抵消!$K:$K,合并抵消!$E:$E,$E61,合并抵消!$A:$A,F$2)) | G61: =浙江精准学!G61+知识跳跳!G61+海南精准学!G61+实时查!G61+目标准!G61+'SMART LEARNING HOLDING'!G61+'SMART AI LIMITED'!G61+'HK01'!G61-(-SUMIFS(合并抵消!$J:$J,合并抵消!$E:$E,$E61,合并抵消!$A:$A,G$2)+SUMIFS(合并抵消!$K:$K,合并抵消!$E:$E,$E61,合并抵消!$A:$A,G$2)) | H61: =浙江精准学!H61+知识跳跳!H61+海南精准学!H61+实时查!H61+目标准!H61+'SMART LEARNING HOLDING'!H61+'SMART AI LIMITED'!H61+'HK01'!H61-(-SUMIFS(合并抵消!$J:$J,合并抵消!$E:$E,$E61,合并抵消!$A:$A,H$2)+SUMIFS(合并抵消!$K:$K,合并抵消!$E:$E,$E61,合并抵消!$A:$A,H$2)) | I61: =浙江精准学!I61+知识跳跳!I61+海南精准学!I61+实时查!I61+目标准!I61+'SMART LEARNING HOLDING'!I61+'SMART AI LIMITED'!I61+'HK01'!I61-(-SUMIFS(合并抵消!$J:$J,合并抵消!$E:$E,$E61,合并抵消!$A:$A,I$2)+SUMIFS(合并抵消!$K:$K,合并抵消!$E:$E,$E61,合并抵消!$A:$A,I$2)) | J61: =浙江精准学!J61+知识跳跳!J61+海南精准学!J61+实时查!J61+目标准!J61+'SMART LEARNING HOLDING'!J61+'SMART AI LIMITED'!J61+'HK01'!J61-(-SUMIFS(合并抵消!$J:$J,合并抵消!$E:$E,$E61,合并抵消!$A:$A,J$2)+SUMIFS(合并抵消!$K:$K,合并抵消!$E:$E,$E61,合并抵消!$A:$A,J$2)) | K61: =浙江精准学!K61+知识跳跳!K61+海南精准学!K61+实时查!K61+目标准!K61+'SMART LEARNING HOLDING'!K61+'SMART AI LIMITED'!K61+'HK01'!K61-(-SUMIFS(合并抵消!$J:$J,合并抵消!$E:$E,$E61,合并抵消!$A:$A,K$2)+SUMIFS(合并抵消!$K:$K,合并抵消!$E:$E,$E61,合并抵消!$A:$A,K$2)) | L61: =浙江精准学!L61+知识跳跳!L61+海南精准学!L61+实时查!L61+目标准!L61+'SMART LEARNING HOLDING'!L61+'SMART AI LIMITED'!L61+'HK01'!L61-(-SUMIFS(合并抵消!$J:$J,合并抵消!$E:$E,$E61,合并抵消!$A:$A,L$2)+SUMIFS(合并抵消!$K:$K,合并抵消!$E:$E,$E61,合并抵消!$A:$A,L$2)) | M61: =浙江精准学!M61+知识跳跳!M61+海南精准学!M61+实时查!M61+目标准!M61+'SMART LEARNING HOLDING'!M61+'SMART AI LIMITED'!M61+'HK01'!M61-(-SUMIFS(合并抵消!$J:$J,合并抵消!$E:$E,$E61,合并抵消!$A:$A,M$2)+SUMIFS(合并抵消!$K:$K,合并抵消!$E:$E,$E61,合并抵消!$A:$A,M$2)) | ... Q61: =浙江精准学!Q61+知识跳跳!Q61+海南精准学!Q61+实时查!Q61+目标准!Q61+'SMART LEARNING HOLDING'!Q61+'SMART AI LIMITED'!Q61+'HK01'!Q61-(-SUMIFS(合并抵消!$J:$J,合并抵消!$E:$E,$E61,合并抵消!$A:$A,Q$2)+SUMIFS(合并抵消!$K:$K,合并抵消!$E:$E,$E61,合并抵消!$A:$A,Q$2))
A62: 制造费用 | B62: 制造费用 | D62: 华泰装修费 | E62: Q3212 | F62: =浙江精准学!F62+知识跳跳!F62+海南精准学!F62+实时查!F62+目标准!F62+'SMART LEARNING HOLDING'!F62+'SMART AI LIMITED'!F62+'HK01'!F62-(-SUMIFS(合并抵消!$J:$J,合并抵消!$E:$E,$E62,合并抵消!$A:$A,F$2)+SUMIFS(合并抵消!$K:$K,合并抵消!$E:$E,$E62,合并抵消!$A:$A,F$2)) | G62: =浙江精准学!G62+知识跳跳!G62+海南精准学!G62+实时查!G62+目标准!G62+'SMART LEARNING HOLDING'!G62+'SMART AI LIMITED'!G62+'HK01'!G62-(-SUMIFS(合并抵消!$J:$J,合并抵消!$E:$E,$E62,合并抵消!$A:$A,G$2)+SUMIFS(合并抵消!$K:$K,合并抵消!$E:$E,$E62,合并抵消!$A:$A,G$2)) | H62: =浙江精准学!H62+知识跳跳!H62+海南精准学!H62+实时查!H62+目标准!H62+'SMART LEARNING HOLDING'!H62+'SMART AI LIMITED'!H62+'HK01'!H62-(-SUMIFS(合并抵消!$J:$J,合并抵消!$E:$E,$E62,合并抵消!$A:$A,H$2)+SUMIFS(合并抵消!$K:$K,合并抵消!$E:$E,$E62,合并抵消!$A:$A,H$2)) | I62: =浙江精准学!I62+知识跳跳!I62+海南精准学!I62+实时查!I62+目标准!I62+'SMART LEARNING HOLDING'!I62+'SMART AI LIMITED'!I62+'HK01'!I62-(-SUMIFS(合并抵消!$J:$J,合并抵消!$E:$E,$E62,合并抵消!$A:$A,I$2)+SUMIFS(合并抵消!$K:$K,合并抵消!$E:$E,$E62,合并抵消!$A:$A,I$2)) | J62: =浙江精准学!J62+知识跳跳!J62+海南精准学!J62+实时查!J62+目标准!J62+'SMART LEARNING HOLDING'!J62+'SMART AI LIMITED'!J62+'HK01'!J62-(-SUMIFS(合并抵消!$J:$J,合并抵消!$E:$E,$E62,合并抵消!$A:$A,J$2)+SUMIFS(合并抵消!$K:$K,合并抵消!$E:$E,$E62,合并抵消!$A:$A,J$2)) | K62: =浙江精准学!K62+知识跳跳!K62+海南精准学!K62+实时查!K62+目标准!K62+'SMART LEARNING HOLDING'!K62+'SMART AI LIMITED'!K62+'HK01'!K62-(-SUMIFS(合并抵消!$J:$J,合并抵消!$E:$E,$E62,合并抵消!$A:$A,K$2)+SUMIFS(合并抵消!$K:$K,合并抵消!$E:$E,$E62,合并抵消!$A:$A,K$2)) | L62: =浙江精准学!L62+知识跳跳!L62+海南精准学!L62+实时查!L62+目标准!L62+'SMART LEARNING HOLDING'!L62+'SMART AI LIMITED'!L62+'HK01'!L62-(-SUMIFS(合并抵消!$J:$J,合并抵消!$E:$E,$E62,合并抵消!$A:$A,L$2)+SUMIFS(合并抵消!$K:$K,合并抵消!$E:$E,$E62,合并抵消!$A:$A,L$2)) | M62: =浙江精准学!M62+知识跳跳!M62+海南精准学!M62+实时查!M62+目标准!M62+'SMART LEARNING HOLDING'!M62+'SMART AI LIMITED'!M62+'HK01'!M62-(-SUMIFS(合并抵消!$J:$J,合并抵消!$E:$E,$E62,合并抵消!$A:$A,M$2)+SUMIFS(合并抵消!$K:$K,合并抵消!$E:$E,$E62,合并抵消!$A:$A,M$2)) | ... Q62: =浙江精准学!Q62+知识跳跳!Q62+海南精准学!Q62+实时查!Q62+目标准!Q62+'SMART LEARNING HOLDING'!Q62+'SMART AI LIMITED'!Q62+'HK01'!Q62-(-SUMIFS(合并抵消!$J:$J,合并抵消!$E:$E,$E62,合并抵消!$A:$A,Q$2)+SUMIFS(合并抵消!$K:$K,合并抵消!$E:$E,$E62,合并抵消!$A:$A,Q$2)) | R62: =SUM(F62:Q62)
A63: 制造费用合计 | F63: =SUM(F51:F62) | G63: =SUM(G51:G62) | H63: =SUM(H51:H62) | I63: =SUM(I51:I62) | J63: =SUM(J51:J62) | K63: =SUM(K51:K62) | L63: =SUM(L51:L62) | M63: =SUM(M51:M62) | ... Q63: =SUM(Q51:Q62) | R63: =SUM(F63:Q63)
A64: 自习室支出 | B64: 自习室支出 | C64: 自习室支出 | D64: 人力成本 | F64: =浙江精准学!F64+知识跳跳!F64+海南精准学!F64+实时查!F64+目标准!F64+'SMART LEARNING HOLDING'!F64+'SMART AI LIMITED'!F64+'HK01'!F64-(-SUMIFS(合并抵消!$J:$J,合并抵消!$E:$E,$E64,合并抵消!$A:$A,F$2)+SUMIFS(合并抵消!$K:$K,合并抵消!$E:$E,$E64,合并抵消!$A:$A,F$2)) | G64: =浙江精准学!G64+知识跳跳!G64+海南精准学!G64+实时查!G64+目标准!G64+'SMART LEARNING HOLDING'!G64+'SMART AI LIMITED'!G64+'HK01'!G64-(-SUMIFS(合并抵消!$J:$J,合并抵消!$E:$E,$E64,合并抵消!$A:$A,G$2)+SUMIFS(合并抵消!$K:$K,合并抵消!$E:$E,$E64,合并抵消!$A:$A,G$2)) | H64: =浙江精准学!H64+知识跳跳!H64+海南精准学!H64+实时查!H64+目标准!H64+'SMART LEARNING HOLDING'!H64+'SMART AI LIMITED'!H64+'HK01'!H64-(-SUMIFS(合并抵消!$J:$J,合并抵消!$E:$E,$E64,合并抵消!$A:$A,H$2)+SUMIFS(合并抵消!$K:$K,合并抵消!$E:$E,$E64,合并抵消!$A:$A,H$2)) | I64: =浙江精准学!I64+知识跳跳!I64+海南精准学!I64+实时查!I64+目标准!I64+'SMART LEARNING HOLDING'!I64+'SMART AI LIMITED'!I64+'HK01'!I64-(-SUMIFS(合并抵消!$J:$J,合并抵消!$E:$E,$E64,合并抵消!$A:$A,I$2)+SUMIFS(合并抵消!$K:$K,合并抵消!$E:$E,$E64,合并抵消!$A:$A,I$2)) | J64: =浙江精准学!J64+知识跳跳!J64+海南精准学!J64+实时查!J64+目标准!J64+'SMART LEARNING HOLDING'!J64+'SMART AI LIMITED'!J64+'HK01'!J64-(-SUMIFS(合并抵消!$J:$J,合并抵消!$E:$E,$E64,合并抵消!$A:$A,J$2)+SUMIFS(合并抵消!$K:$K,合并抵消!$E:$E,$E64,合并抵消!$A:$A,J$2)) | K64: =浙江精准学!K64+知识跳跳!K64+海南精准学!K64+实时查!K64+目标准!K64+'SMART LEARNING HOLDING'!K64+'SMART AI LIMITED'!K64+'HK01'!K64-(-SUMIFS(合并抵消!$J:$J,合并抵消!$E:$E,$E64,合并抵消!$A:$A,K$2)+SUMIFS(合并抵消!$K:$K,合并抵消!$E:$E,$E64,合并抵消!$A:$A,K$2)) | L64: =浙江精准学!L64+知识跳跳!L64+海南精准学!L64+实时查!L64+目标准!L64+'SMART LEARNING HOLDING'!L64+'SMART AI LIMITED'!L64+'HK01'!L64-(-SUMIFS(合并抵消!$J:$J,合并抵消!$E:$E,$E64,合并抵消!$A:$A,L$2)+SUMIFS(合并抵消!$K:$K,合并抵消!$E:$E,$E64,合并抵消!$A:$A,L$2)) | M64: =浙江精准学!M64+知识跳跳!M64+海南精准学!M64+实时查!M64+目标准!M64+'SMART LEARNING HOLDING'!M64+'SMART AI LIMITED'!M64+'HK01'!M64-(-SUMIFS(合并抵消!$J:$J,合并抵消!$E:$E,$E64,合并抵消!$A:$A,M$2)+SUMIFS(合并抵消!$K:$K,合并抵消!$E:$E,$E64,合并抵消!$A:$A,M$2)) | ... Q64: =浙江精准学!Q64+知识跳跳!Q64+海南精准学!Q64+实时查!Q64+目标准!Q64+'SMART LEARNING HOLDING'!Q64+'SMART AI LIMITED'!Q64+'HK01'!Q64-(-SUMIFS(合并抵消!$J:$J,合并抵消!$E:$E,$E64,合并抵消!$A:$A,Q$2)+SUMIFS(合并抵消!$K:$K,合并抵消!$E:$E,$E64,合并抵消!$A:$A,Q$2)) | R64: =SUM(F64:Q64)
A65: 自习室支出 | B65: 自习室支出 | D65: 装修支出 | F65: =浙江精准学!F65+知识跳跳!F65+海南精准学!F65+实时查!F65+目标准!F65+'SMART LEARNING HOLDING'!F65+'SMART AI LIMITED'!F65+'HK01'!F65-(-SUMIFS(合并抵消!$J:$J,合并抵消!$E:$E,$E65,合并抵消!$A:$A,F$2)+SUMIFS(合并抵消!$K:$K,合并抵消!$E:$E,$E65,合并抵消!$A:$A,F$2)) | G65: =浙江精准学!G65+知识跳跳!G65+海南精准学!G65+实时查!G65+目标准!G65+'SMART LEARNING HOLDING'!G65+'SMART AI LIMITED'!G65+'HK01'!G65-(-SUMIFS(合并抵消!$J:$J,合并抵消!$E:$E,$E65,合并抵消!$A:$A,G$2)+SUMIFS(合并抵消!$K:$K,合并抵消!$E:$E,$E65,合并抵消!$A:$A,G$2)) | H65: =浙江精准学!H65+知识跳跳!H65+海南精准学!H65+实时查!H65+目标准!H65+'SMART LEARNING HOLDING'!H65+'SMART AI LIMITED'!H65+'HK01'!H65-(-SUMIFS(合并抵消!$J:$J,合并抵消!$E:$E,$E65,合并抵消!$A:$A,H$2)+SUMIFS(合并抵消!$K:$K,合并抵消!$E:$E,$E65,合并抵消!$A:$A,H$2)) | I65: =浙江精准学!I65+知识跳跳!I65+海南精准学!I65+实时查!I65+目标准!I65+'SMART LEARNING HOLDING'!I65+'SMART AI LIMITED'!I65+'HK01'!I65-(-SUMIFS(合并抵消!$J:$J,合并抵消!$E:$E,$E65,合并抵消!$A:$A,I$2)+SUMIFS(合并抵消!$K:$K,合并抵消!$E:$E,$E65,合并抵消!$A:$A,I$2)) | J65: =浙江精准学!J65+知识跳跳!J65+海南精准学!J65+实时查!J65+目标准!J65+'SMART LEARNING HOLDING'!J65+'SMART AI LIMITED'!J65+'HK01'!J65-(-SUMIFS(合并抵消!$J:$J,合并抵消!$E:$E,$E65,合并抵消!$A:$A,J$2)+SUMIFS(合并抵消!$K:$K,合并抵消!$E:$E,$E65,合并抵消!$A:$A,J$2)) | K65: =浙江精准学!K65+知识跳跳!K65+海南精准学!K65+实时查!K65+目标准!K65+'SMART LEARNING HOLDING'!K65+'SMART AI LIMITED'!K65+'HK01'!K65-(-SUMIFS(合并抵消!$J:$J,合并抵消!$E:$E,$E65,合并抵消!$A:$A,K$2)+SUMIFS(合并抵消!$K:$K,合并抵消!$E:$E,$E65,合并抵消!$A:$A,K$2)) | L65: =浙江精准学!L65+知识跳跳!L65+海南精准学!L65+实时查!L65+目标准!L65+'SMART LEARNING HOLDING'!L65+'SMART AI LIMITED'!L65+'HK01'!L65-(-SUMIFS(合并抵消!$J:$J,合并抵消!$E:$E,$E65,合并抵消!$A:$A,L$2)+SUMIFS(合并抵消!$K:$K,合并抵消!$E:$E,$E65,合并抵消!$A:$A,L$2)) | M65: =浙江精准学!M65+知识跳跳!M65+海南精准学!M65+实时查!M65+目标准!M65+'SMART LEARNING HOLDING'!M65+'SMART AI LIMITED'!M65+'HK01'!M65-(-SUMIFS(合并抵消!$J:$J,合并抵消!$E:$E,$E65,合并抵消!$A:$A,M$2)+SUMIFS(合并抵消!$K:$K,合并抵消!$E:$E,$E65,合并抵消!$A:$A,M$2)) | ... Q65: =浙江精准学!Q65+知识跳跳!Q65+海南精准学!Q65+实时查!Q65+目标准!Q65+'SMART LEARNING HOLDING'!Q65+'SMART AI LIMITED'!Q65+'HK01'!Q65-(-SUMIFS(合并抵消!$J:$J,合并抵消!$E:$E,$E65,合并抵消!$A:$A,Q$2)+SUMIFS(合并抵消!$K:$K,合并抵消!$E:$E,$E65,合并抵消!$A:$A,Q$2)) | R65: =SUM(F65:Q65)
A66: 自习室支出 | B66: 自习室支出 | D66: 推广费用 | F66: =浙江精准学!F66+知识跳跳!F66+海南精准学!F66+实时查!F66+目标准!F66+'SMART LEARNING HOLDING'!F66+'SMART AI LIMITED'!F66+'HK01'!F66-(-SUMIFS(合并抵消!$J:$J,合并抵消!$E:$E,$E66,合并抵消!$A:$A,F$2)+SUMIFS(合并抵消!$K:$K,合并抵消!$E:$E,$E66,合并抵消!$A:$A,F$2)) | G66: =浙江精准学!G66+知识跳跳!G66+海南精准学!G66+实时查!G66+目标准!G66+'SMART LEARNING HOLDING'!G66+'SMART AI LIMITED'!G66+'HK01'!G66-(-SUMIFS(合并抵消!$J:$J,合并抵消!$E:$E,$E66,合并抵消!$A:$A,G$2)+SUMIFS(合并抵消!$K:$K,合并抵消!$E:$E,$E66,合并抵消!$A:$A,G$2)) | H66: =浙江精准学!H66+知识跳跳!H66+海南精准学!H66+实时查!H66+目标准!H66+'SMART LEARNING HOLDING'!H66+'SMART AI LIMITED'!H66+'HK01'!H66-(-SUMIFS(合并抵消!$J:$J,合并抵消!$E:$E,$E66,合并抵消!$A:$A,H$2)+SUMIFS(合并抵消!$K:$K,合并抵消!$E:$E,$E66,合并抵消!$A:$A,H$2)) | I66: =浙江精准学!I66+知识跳跳!I66+海南精准学!I66+实时查!I66+目标准!I66+'SMART LEARNING HOLDING'!I66+'SMART AI LIMITED'!I66+'HK01'!I66-(-SUMIFS(合并抵消!$J:$J,合并抵消!$E:$E,$E66,合并抵消!$A:$A,I$2)+SUMIFS(合并抵消!$K:$K,合并抵消!$E:$E,$E66,合并抵消!$A:$A,I$2)) | J66: =浙江精准学!J66+知识跳跳!J66+海南精准学!J66+实时查!J66+目标准!J66+'SMART LEARNING HOLDING'!J66+'SMART AI LIMITED'!J66+'HK01'!J66-(-SUMIFS(合并抵消!$J:$J,合并抵消!$E:$E,$E66,合并抵消!$A:$A,J$2)+SUMIFS(合并抵消!$K:$K,合并抵消!$E:$E,$E66,合并抵消!$A:$A,J$2)) | K66: =浙江精准学!K66+知识跳跳!K66+海南精准学!K66+实时查!K66+目标准!K66+'SMART LEARNING HOLDING'!K66+'SMART AI LIMITED'!K66+'HK01'!K66-(-SUMIFS(合并抵消!$J:$J,合并抵消!$E:$E,$E66,合并抵消!$A:$A,K$2)+SUMIFS(合并抵消!$K:$K,合并抵消!$E:$E,$E66,合并抵消!$A:$A,K$2)) | L66: =浙江精准学!L66+知识跳跳!L66+海南精准学!L66+实时查!L66+目标准!L66+'SMART LEARNING HOLDING'!L66+'SMART AI LIMITED'!L66+'HK01'!L66-(-SUMIFS(合并抵消!$J:$J,合并抵消!$E:$E,$E66,合并抵消!$A:$A,L$2)+SUMIFS(合并抵消!$K:$K,合并抵消!$E:$E,$E66,合并抵消!$A:$A,L$2)) | M66: =浙江精准学!M66+知识跳跳!M66+海南精准学!M66+实时查!M66+目标准!M66+'SMART LEARNING HOLDING'!M66+'SMART AI LIMITED'!M66+'HK01'!M66-(-SUMIFS(合并抵消!$J:$J,合并抵消!$E:$E,$E66,合并抵消!$A:$A,M$2)+SUMIFS(合并抵消!$K:$K,合并抵消!$E:$E,$E66,合并抵消!$A:$A,M$2)) | ... Q66: =浙江精准学!Q66+知识跳跳!Q66+海南精准学!Q66+实时查!Q66+目标准!Q66+'SMART LEARNING HOLDING'!Q66+'SMART AI LIMITED'!Q66+'HK01'!Q66-(-SUMIFS(合并抵消!$J:$J,合并抵消!$E:$E,$E66,合并抵消!$A:$A,Q$2)+SUMIFS(合并抵消!$K:$K,合并抵消!$E:$E,$E66,合并抵消!$A:$A,Q$2)) | R66: =SUM(F66:Q66)
A67: 自习室支出 | B67: 自习室支出 | D67: 管理系统 | F67: =浙江精准学!F67+知识跳跳!F67+海南精准学!F67+实时查!F67+目标准!F67+'SMART LEARNING HOLDING'!F67+'SMART AI LIMITED'!F67+'HK01'!F67-(-SUMIFS(合并抵消!$J:$J,合并抵消!$E:$E,$E67,合并抵消!$A:$A,F$2)+SUMIFS(合并抵消!$K:$K,合并抵消!$E:$E,$E67,合并抵消!$A:$A,F$2)) | G67: =浙江精准学!G67+知识跳跳!G67+海南精准学!G67+实时查!G67+目标准!G67+'SMART LEARNING HOLDING'!G67+'SMART AI LIMITED'!G67+'HK01'!G67-(-SUMIFS(合并抵消!$J:$J,合并抵消!$E:$E,$E67,合并抵消!$A:$A,G$2)+SUMIFS(合并抵消!$K:$K,合并抵消!$E:$E,$E67,合并抵消!$A:$A,G$2)) | H67: =浙江精准学!H67+知识跳跳!H67+海南精准学!H67+实时查!H67+目标准!H67+'SMART LEARNING HOLDING'!H67+'SMART AI LIMITED'!H67+'HK01'!H67-(-SUMIFS(合并抵消!$J:$J,合并抵消!$E:$E,$E67,合并抵消!$A:$A,H$2)+SUMIFS(合并抵消!$K:$K,合并抵消!$E:$E,$E67,合并抵消!$A:$A,H$2)) | I67: =浙江精准学!I67+知识跳跳!I67+海南精准学!I67+实时查!I67+目标准!I67+'SMART LEARNING HOLDING'!I67+'SMART AI LIMITED'!I67+'HK01'!I67-(-SUMIFS(合并抵消!$J:$J,合并抵消!$E:$E,$E67,合并抵消!$A:$A,I$2)+SUMIFS(合并抵消!$K:$K,合并抵消!$E:$E,$E67,合并抵消!$A:$A,I$2)) | J67: =浙江精准学!J67+知识跳跳!J67+海南精准学!J67+实时查!J67+目标准!J67+'SMART LEARNING HOLDING'!J67+'SMART AI LIMITED'!J67+'HK01'!J67-(-SUMIFS(合并抵消!$J:$J,合并抵消!$E:$E,$E67,合并抵消!$A:$A,J$2)+SUMIFS(合并抵消!$K:$K,合并抵消!$E:$E,$E67,合并抵消!$A:$A,J$2)) | K67: =浙江精准学!K67+知识跳跳!K67+海南精准学!K67+实时查!K67+目标准!K67+'SMART LEARNING HOLDING'!K67+'SMART AI LIMITED'!K67+'HK01'!K67-(-SUMIFS(合并抵消!$J:$J,合并抵消!$E:$E,$E67,合并抵消!$A:$A,K$2)+SUMIFS(合并抵消!$K:$K,合并抵消!$E:$E,$E67,合并抵消!$A:$A,K$2)) | L67: =浙江精准学!L67+知识跳跳!L67+海南精准学!L67+实时查!L67+目标准!L67+'SMART LEARNING HOLDING'!L67+'SMART AI LIMITED'!L67+'HK01'!L67-(-SUMIFS(合并抵消!$J:$J,合并抵消!$E:$E,$E67,合并抵消!$A:$A,L$2)+SUMIFS(合并抵消!$K:$K,合并抵消!$E:$E,$E67,合并抵消!$A:$A,L$2)) | M67: =浙江精准学!M67+知识跳跳!M67+海南精准学!M67+实时查!M67+目标准!M67+'SMART LEARNING HOLDING'!M67+'SMART AI LIMITED'!M67+'HK01'!M67-(-SUMIFS(合并抵消!$J:$J,合并抵消!$E:$E,$E67,合并抵消!$A:$A,M$2)+SUMIFS(合并抵消!$K:$K,合并抵消!$E:$E,$E67,合并抵消!$A:$A,M$2)) | ... Q67: =浙江精准学!Q67+知识跳跳!Q67+海南精准学!Q67+实时查!Q67+目标准!Q67+'SMART LEARNING HOLDING'!Q67+'SMART AI LIMITED'!Q67+'HK01'!Q67-(-SUMIFS(合并抵消!$J:$J,合并抵消!$E:$E,$E67,合并抵消!$A:$A,Q$2)+SUMIFS(合并抵消!$K:$K,合并抵消!$E:$E,$E67,合并抵消!$A:$A,Q$2)) | R67: =SUM(F67:Q67)
A68: 自习室支出 | B68: 自习室支出 | D68: 其他经营支出 | F68: =浙江精准学!F68+知识跳跳!F68+海南精准学!F68+实时查!F68+目标准!F68+'SMART LEARNING HOLDING'!F68+'SMART AI LIMITED'!F68+'HK01'!F68-(-SUMIFS(合并抵消!$J:$J,合并抵消!$E:$E,$E68,合并抵消!$A:$A,F$2)+SUMIFS(合并抵消!$K:$K,合并抵消!$E:$E,$E68,合并抵消!$A:$A,F$2)) | G68: =浙江精准学!G68+知识跳跳!G68+海南精准学!G68+实时查!G68+目标准!G68+'SMART LEARNING HOLDING'!G68+'SMART AI LIMITED'!G68+'HK01'!G68-(-SUMIFS(合并抵消!$J:$J,合并抵消!$E:$E,$E68,合并抵消!$A:$A,G$2)+SUMIFS(合并抵消!$K:$K,合并抵消!$E:$E,$E68,合并抵消!$A:$A,G$2)) | H68: =浙江精准学!H68+知识跳跳!H68+海南精准学!H68+实时查!H68+目标准!H68+'SMART LEARNING HOLDING'!H68+'SMART AI LIMITED'!H68+'HK01'!H68-(-SUMIFS(合并抵消!$J:$J,合并抵消!$E:$E,$E68,合并抵消!$A:$A,H$2)+SUMIFS(合并抵消!$K:$K,合并抵消!$E:$E,$E68,合并抵消!$A:$A,H$2)) | I68: =浙江精准学!I68+知识跳跳!I68+海南精准学!I68+实时查!I68+目标准!I68+'SMART LEARNING HOLDING'!I68+'SMART AI LIMITED'!I68+'HK01'!I68-(-SUMIFS(合并抵消!$J:$J,合并抵消!$E:$E,$E68,合并抵消!$A:$A,I$2)+SUMIFS(合并抵消!$K:$K,合并抵消!$E:$E,$E68,合并抵消!$A:$A,I$2)) | J68: =浙江精准学!J68+知识跳跳!J68+海南精准学!J68+实时查!J68+目标准!J68+'SMART LEARNING HOLDING'!J68+'SMART AI LIMITED'!J68+'HK01'!J68-(-SUMIFS(合并抵消!$J:$J,合并抵消!$E:$E,$E68,合并抵消!$A:$A,J$2)+SUMIFS(合并抵消!$K:$K,合并抵消!$E:$E,$E68,合并抵消!$A:$A,J$2)) | K68: =浙江精准学!K68+知识跳跳!K68+海南精准学!K68+实时查!K68+目标准!K68+'SMART LEARNING HOLDING'!K68+'SMART AI LIMITED'!K68+'HK01'!K68-(-SUMIFS(合并抵消!$J:$J,合并抵消!$E:$E,$E68,合并抵消!$A:$A,K$2)+SUMIFS(合并抵消!$K:$K,合并抵消!$E:$E,$E68,合并抵消!$A:$A,K$2)) | L68: =浙江精准学!L68+知识跳跳!L68+海南精准学!L68+实时查!L68+目标准!L68+'SMART LEARNING HOLDING'!L68+'SMART AI LIMITED'!L68+'HK01'!L68-(-SUMIFS(合并抵消!$J:$J,合并抵消!$E:$E,$E68,合并抵消!$A:$A,L$2)+SUMIFS(合并抵消!$K:$K,合并抵消!$E:$E,$E68,合并抵消!$A:$A,L$2)) | M68: =浙江精准学!M68+知识跳跳!M68+海南精准学!M68+实时查!M68+目标准!M68+'SMART LEARNING HOLDING'!M68+'SMART AI LIMITED'!M68+'HK01'!M68-(-SUMIFS(合并抵消!$J:$J,合并抵消!$E:$E,$E68,合并抵消!$A:$A,M$2)+SUMIFS(合并抵消!$K:$K,合并抵消!$E:$E,$E68,合并抵消!$A:$A,M$2)) | ... Q68: =浙江精准学!Q68+知识跳跳!Q68+海南精准学!Q68+实时查!Q68+目标准!Q68+'SMART LEARNING HOLDING'!Q68+'SMART AI LIMITED'!Q68+'HK01'!Q68-(-SUMIFS(合并抵消!$J:$J,合并抵消!$E:$E,$E68,合并抵消!$A:$A,Q$2)+SUMIFS(合并抵消!$K:$K,合并抵消!$E:$E,$E68,合并抵消!$A:$A,Q$2)) | R68: =SUM(F68:Q68)
A69: 自习室支出合计 | F69: =SUM('SMART AI LIMITED:HK01'!F64:F68) | G69: =SUM('SMART AI LIMITED:HK01'!G64:G68) | H69: =SUM('SMART AI LIMITED:HK01'!H64:H68) | I69: =SUM('SMART AI LIMITED:HK01'!I64:I68) | J69: =SUM('SMART AI LIMITED:HK01'!J64:J68) | K69: =SUM('SMART AI LIMITED:HK01'!K64:K68) | L69: =SUM('SMART AI LIMITED:HK01'!L64:L68) | M69: =SUM('SMART AI LIMITED:HK01'!M64:M68) | ... Q69: =SUM('SMART AI LIMITED:HK01'!Q64:Q68) | R69: =SUM(F69:Q69)
A70: 研发支出 | B70: 产品开发-MAX | C70: 产品开发-MAX | D70: 检测费 | E70: Q1201 | F70: =浙江精准学!F70+知识跳跳!F70+海南精准学!F70+实时查!F70+目标准!F70+'SMART LEARNING HOLDING'!F70+'SMART AI LIMITED'!F70+'HK01'!F70-(-SUMIFS(合并抵消!$J:$J,合并抵消!$E:$E,$E70,合并抵消!$A:$A,F$2)+SUMIFS(合并抵消!$K:$K,合并抵消!$E:$E,$E70,合并抵消!$A:$A,F$2)) | G70: =浙江精准学!G70+知识跳跳!G70+海南精准学!G70+实时查!G70+目标准!G70+'SMART LEARNING HOLDING'!G70+'SMART AI LIMITED'!G70+'HK01'!G70-(-SUMIFS(合并抵消!$J:$J,合并抵消!$E:$E,$E70,合并抵消!$A:$A,G$2)+SUMIFS(合并抵消!$K:$K,合并抵消!$E:$E,$E70,合并抵消!$A:$A,G$2)) | H70: =浙江精准学!H70+知识跳跳!H70+海南精准学!H70+实时查!H70+目标准!H70+'SMART LEARNING HOLDING'!H70+'SMART AI LIMITED'!H70+'HK01'!H70-(-SUMIFS(合并抵消!$J:$J,合并抵消!$E:$E,$E70,合并抵消!$A:$A,H$2)+SUMIFS(合并抵消!$K:$K,合并抵消!$E:$E,$E70,合并抵消!$A:$A,H$2)) | I70: =浙江精准学!I70+知识跳跳!I70+海南精准学!I70+实时查!I70+目标准!I70+'SMART LEARNING HOLDING'!I70+'SMART AI LIMITED'!I70+'HK01'!I70-(-SUMIFS(合并抵消!$J:$J,合并抵消!$E:$E,$E70,合并抵消!$A:$A,I$2)+SUMIFS(合并抵消!$K:$K,合并抵消!$E:$E,$E70,合并抵消!$A:$A,I$2)) | J70: =浙江精准学!J70+知识跳跳!J70+海南精准学!J70+实时查!J70+目标准!J70+'SMART LEARNING HOLDING'!J70+'SMART AI LIMITED'!J70+'HK01'!J70-(-SUMIFS(合并抵消!$J:$J,合并抵消!$E:$E,$E70,合并抵消!$A:$A,J$2)+SUMIFS(合并抵消!$K:$K,合并抵消!$E:$E,$E70,合并抵消!$A:$A,J$2)) | K70: =浙江精准学!K70+知识跳跳!K70+海南精准学!K70+实时查!K70+目标准!K70+'SMART LEARNING HOLDING'!K70+'SMART AI LIMITED'!K70+'HK01'!K70-(-SUMIFS(合并抵消!$J:$J,合并抵消!$E:$E,$E70,合并抵消!$A:$A,K$2)+SUMIFS(合并抵消!$K:$K,合并抵消!$E:$E,$E70,合并抵消!$A:$A,K$2)) | L70: =浙江精准学!L70+知识跳跳!L70+海南精准学!L70+实时查!L70+目标准!L70+'SMART LEARNING HOLDING'!L70+'SMART AI LIMITED'!L70+'HK01'!L70-(-SUMIFS(合并抵消!$J:$J,合并抵消!$E:$E,$E70,合并抵消!$A:$A,L$2)+SUMIFS(合并抵消!$K:$K,合并抵消!$E:$E,$E70,合并抵消!$A:$A,L$2)) | M70: =浙江精准学!M70+知识跳跳!M70+海南精准学!M70+实时查!M70+目标准!M70+'SMART LEARNING HOLDING'!M70+'SMART AI LIMITED'!M70+'HK01'!M70-(-SUMIFS(合并抵消!$J:$J,合并抵消!$E:$E,$E70,合并抵消!$A:$A,M$2)+SUMIFS(合并抵消!$K:$K,合并抵消!$E:$E,$E70,合并抵消!$A:$A,M$2)) | ... Q70: =浙江精准学!Q70+知识跳跳!Q70+海南精准学!Q70+实时查!Q70+目标准!Q70+'SMART LEARNING HOLDING'!Q70+'SMART AI LIMITED'!Q70+'HK01'!Q70-(-SUMIFS(合并抵消!$J:$J,合并抵消!$E:$E,$E70,合并抵消!$A:$A,Q$2)+SUMIFS(合并抵消!$K:$K,合并抵消!$E:$E,$E70,合并抵消!$A:$A,Q$2)) | R70: =SUM(F70:Q70)
A71: 研发支出 | B71: 产品开发-MAX | D71: 认证费 | E71: Q1202 | F71: =浙江精准学!F71+知识跳跳!F71+海南精准学!F71+实时查!F71+目标准!F71+'SMART LEARNING HOLDING'!F71+'SMART AI LIMITED'!F71+'HK01'!F71-(-SUMIFS(合并抵消!$J:$J,合并抵消!$E:$E,$E71,合并抵消!$A:$A,F$2)+SUMIFS(合并抵消!$K:$K,合并抵消!$E:$E,$E71,合并抵消!$A:$A,F$2)) | G71: =浙江精准学!G71+知识跳跳!G71+海南精准学!G71+实时查!G71+目标准!G71+'SMART LEARNING HOLDING'!G71+'SMART AI LIMITED'!G71+'HK01'!G71-(-SUMIFS(合并抵消!$J:$J,合并抵消!$E:$E,$E71,合并抵消!$A:$A,G$2)+SUMIFS(合并抵消!$K:$K,合并抵消!$E:$E,$E71,合并抵消!$A:$A,G$2)) | H71: =浙江精准学!H71+知识跳跳!H71+海南精准学!H71+实时查!H71+目标准!H71+'SMART LEARNING HOLDING'!H71+'SMART AI LIMITED'!H71+'HK01'!H71-(-SUMIFS(合并抵消!$J:$J,合并抵消!$E:$E,$E71,合并抵消!$A:$A,H$2)+SUMIFS(合并抵消!$K:$K,合并抵消!$E:$E,$E71,合并抵消!$A:$A,H$2)) | I71: =浙江精准学!I71+知识跳跳!I71+海南精准学!I71+实时查!I71+目标准!I71+'SMART LEARNING HOLDING'!I71+'SMART AI LIMITED'!I71+'HK01'!I71-(-SUMIFS(合并抵消!$J:$J,合并抵消!$E:$E,$E71,合并抵消!$A:$A,I$2)+SUMIFS(合并抵消!$K:$K,合并抵消!$E:$E,$E71,合并抵消!$A:$A,I$2)) | J71: =浙江精准学!J71+知识跳跳!J71+海南精准学!J71+实时查!J71+目标准!J71+'SMART LEARNING HOLDING'!J71+'SMART AI LIMITED'!J71+'HK01'!J71-(-SUMIFS(合并抵消!$J:$J,合并抵消!$E:$E,$E71,合并抵消!$A:$A,J$2)+SUMIFS(合并抵消!$K:$K,合并抵消!$E:$E,$E71,合并抵消!$A:$A,J$2)) | K71: =浙江精准学!K71+知识跳跳!K71+海南精准学!K71+实时查!K71+目标准!K71+'SMART LEARNING HOLDING'!K71+'SMART AI LIMITED'!K71+'HK01'!K71-(-SUMIFS(合并抵消!$J:$J,合并抵消!$E:$E,$E71,合并抵消!$A:$A,K$2)+SUMIFS(合并抵消!$K:$K,合并抵消!$E:$E,$E71,合并抵消!$A:$A,K$2)) | L71: =浙江精准学!L71+知识跳跳!L71+海南精准学!L71+实时查!L71+目标准!L71+'SMART LEARNING HOLDING'!L71+'SMART AI LIMITED'!L71+'HK01'!L71-(-SUMIFS(合并抵消!$J:$J,合并抵消!$E:$E,$E71,合并抵消!$A:$A,L$2)+SUMIFS(合并抵消!$K:$K,合并抵消!$E:$E,$E71,合并抵消!$A:$A,L$2)) | M71: =浙江精准学!M71+知识跳跳!M71+海南精准学!M71+实时查!M71+目标准!M71+'SMART LEARNING HOLDING'!M71+'SMART AI LIMITED'!M71+'HK01'!M71-(-SUMIFS(合并抵消!$J:$J,合并抵消!$E:$E,$E71,合并抵消!$A:$A,M$2)+SUMIFS(合并抵消!$K:$K,合并抵消!$E:$E,$E71,合并抵消!$A:$A,M$2)) | ... Q71: =浙江精准学!Q71+知识跳跳!Q71+海南精准学!Q71+实时查!Q71+目标准!Q71+'SMART LEARNING HOLDING'!Q71+'SMART AI LIMITED'!Q71+'HK01'!Q71-(-SUMIFS(合并抵消!$J:$J,合并抵消!$E:$E,$E71,合并抵消!$A:$A,Q$2)+SUMIFS(合并抵消!$K:$K,合并抵消!$E:$E,$E71,合并抵消!$A:$A,Q$2)) | R71: =SUM(F71:Q71)
A72: 研发支出 | B72: 产品开发-MAX | D72: 设计费 | E72: Q1203 | F72: =浙江精准学!F72+知识跳跳!F72+海南精准学!F72+实时查!F72+目标准!F72+'SMART LEARNING HOLDING'!F72+'SMART AI LIMITED'!F72+'HK01'!F72-(-SUMIFS(合并抵消!$J:$J,合并抵消!$E:$E,$E72,合并抵消!$A:$A,F$2)+SUMIFS(合并抵消!$K:$K,合并抵消!$E:$E,$E72,合并抵消!$A:$A,F$2)) | G72: =浙江精准学!G72+知识跳跳!G72+海南精准学!G72+实时查!G72+目标准!G72+'SMART LEARNING HOLDING'!G72+'SMART AI LIMITED'!G72+'HK01'!G72-(-SUMIFS(合并抵消!$J:$J,合并抵消!$E:$E,$E72,合并抵消!$A:$A,G$2)+SUMIFS(合并抵消!$K:$K,合并抵消!$E:$E,$E72,合并抵消!$A:$A,G$2)) | H72: =浙江精准学!H72+知识跳跳!H72+海南精准学!H72+实时查!H72+目标准!H72+'SMART LEARNING HOLDING'!H72+'SMART AI LIMITED'!H72+'HK01'!H72-(-SUMIFS(合并抵消!$J:$J,合并抵消!$E:$E,$E72,合并抵消!$A:$A,H$2)+SUMIFS(合并抵消!$K:$K,合并抵消!$E:$E,$E72,合并抵消!$A:$A,H$2)) | I72: =浙江精准学!I72+知识跳跳!I72+海南精准学!I72+实时查!I72+目标准!I72+'SMART LEARNING HOLDING'!I72+'SMART AI LIMITED'!I72+'HK01'!I72-(-SUMIFS(合并抵消!$J:$J,合并抵消!$E:$E,$E72,合并抵消!$A:$A,I$2)+SUMIFS(合并抵消!$K:$K,合并抵消!$E:$E,$E72,合并抵消!$A:$A,I$2)) | J72: =浙江精准学!J72+知识跳跳!J72+海南精准学!J72+实时查!J72+目标准!J72+'SMART LEARNING HOLDING'!J72+'SMART AI LIMITED'!J72+'HK01'!J72-(-SUMIFS(合并抵消!$J:$J,合并抵消!$E:$E,$E72,合并抵消!$A:$A,J$2)+SUMIFS(合并抵消!$K:$K,合并抵消!$E:$E,$E72,合并抵消!$A:$A,J$2)) | K72: =浙江精准学!K72+知识跳跳!K72+海南精准学!K72+实时查!K72+目标准!K72+'SMART LEARNING HOLDING'!K72+'SMART AI LIMITED'!K72+'HK01'!K72-(-SUMIFS(合并抵消!$J:$J,合并抵消!$E:$E,$E72,合并抵消!$A:$A,K$2)+SUMIFS(合并抵消!$K:$K,合并抵消!$E:$E,$E72,合并抵消!$A:$A,K$2)) | L72: =浙江精准学!L72+知识跳跳!L72+海南精准学!L72+实时查!L72+目标准!L72+'SMART LEARNING HOLDING'!L72+'SMART AI LIMITED'!L72+'HK01'!L72-(-SUMIFS(合并抵消!$J:$J,合并抵消!$E:$E,$E72,合并抵消!$A:$A,L$2)+SUMIFS(合并抵消!$K:$K,合并抵消!$E:$E,$E72,合并抵消!$A:$A,L$2)) | M72: =浙江精准学!M72+知识跳跳!M72+海南精准学!M72+实时查!M72+目标准!M72+'SMART LEARNING HOLDING'!M72+'SMART AI LIMITED'!M72+'HK01'!M72-(-SUMIFS(合并抵消!$J:$J,合并抵消!$E:$E,$E72,合并抵消!$A:$A,M$2)+SUMIFS(合并抵消!$K:$K,合并抵消!$E:$E,$E72,合并抵消!$A:$A,M$2)) | ... Q72: =浙江精准学!Q72+知识跳跳!Q72+海南精准学!Q72+实时查!Q72+目标准!Q72+'SMART LEARNING HOLDING'!Q72+'SMART AI LIMITED'!Q72+'HK01'!Q72-(-SUMIFS(合并抵消!$J:$J,合并抵消!$E:$E,$E72,合并抵消!$A:$A,Q$2)+SUMIFS(合并抵消!$K:$K,合并抵消!$E:$E,$E72,合并抵消!$A:$A,Q$2)) | R72: =SUM(F72:Q72)
A73: 研发支出 | B73: 产品开发-MAX | D73: OTA费用 | E73: Q1204 | F73: =浙江精准学!F73+知识跳跳!F73+海南精准学!F73+实时查!F73+目标准!F73+'SMART LEARNING HOLDING'!F73+'SMART AI LIMITED'!F73+'HK01'!F73-(-SUMIFS(合并抵消!$J:$J,合并抵消!$E:$E,$E73,合并抵消!$A:$A,F$2)+SUMIFS(合并抵消!$K:$K,合并抵消!$E:$E,$E73,合并抵消!$A:$A,F$2)) | G73: =浙江精准学!G73+知识跳跳!G73+海南精准学!G73+实时查!G73+目标准!G73+'SMART LEARNING HOLDING'!G73+'SMART AI LIMITED'!G73+'HK01'!G73-(-SUMIFS(合并抵消!$J:$J,合并抵消!$E:$E,$E73,合并抵消!$A:$A,G$2)+SUMIFS(合并抵消!$K:$K,合并抵消!$E:$E,$E73,合并抵消!$A:$A,G$2)) | H73: =浙江精准学!H73+知识跳跳!H73+海南精准学!H73+实时查!H73+目标准!H73+'SMART LEARNING HOLDING'!H73+'SMART AI LIMITED'!H73+'HK01'!H73-(-SUMIFS(合并抵消!$J:$J,合并抵消!$E:$E,$E73,合并抵消!$A:$A,H$2)+SUMIFS(合并抵消!$K:$K,合并抵消!$E:$E,$E73,合并抵消!$A:$A,H$2)) | I73: =浙江精准学!I73+知识跳跳!I73+海南精准学!I73+实时查!I73+目标准!I73+'SMART LEARNING HOLDING'!I73+'SMART AI LIMITED'!I73+'HK01'!I73-(-SUMIFS(合并抵消!$J:$J,合并抵消!$E:$E,$E73,合并抵消!$A:$A,I$2)+SUMIFS(合并抵消!$K:$K,合并抵消!$E:$E,$E73,合并抵消!$A:$A,I$2)) | J73: =浙江精准学!J73+知识跳跳!J73+海南精准学!J73+实时查!J73+目标准!J73+'SMART LEARNING HOLDING'!J73+'SMART AI LIMITED'!J73+'HK01'!J73-(-SUMIFS(合并抵消!$J:$J,合并抵消!$E:$E,$E73,合并抵消!$A:$A,J$2)+SUMIFS(合并抵消!$K:$K,合并抵消!$E:$E,$E73,合并抵消!$A:$A,J$2)) | K73: =浙江精准学!K73+知识跳跳!K73+海南精准学!K73+实时查!K73+目标准!K73+'SMART LEARNING HOLDING'!K73+'SMART AI LIMITED'!K73+'HK01'!K73-(-SUMIFS(合并抵消!$J:$J,合并抵消!$E:$E,$E73,合并抵消!$A:$A,K$2)+SUMIFS(合并抵消!$K:$K,合并抵消!$E:$E,$E73,合并抵消!$A:$A,K$2)) | L73: =浙江精准学!L73+知识跳跳!L73+海南精准学!L73+实时查!L73+目标准!L73+'SMART LEARNING HOLDING'!L73+'SMART AI LIMITED'!L73+'HK01'!L73-(-SUMIFS(合并抵消!$J:$J,合并抵消!$E:$E,$E73,合并抵消!$A:$A,L$2)+SUMIFS(合并抵消!$K:$K,合并抵消!$E:$E,$E73,合并抵消!$A:$A,L$2)) | M73: =浙江精准学!M73+知识跳跳!M73+海南精准学!M73+实时查!M73+目标准!M73+'SMART LEARNING HOLDING'!M73+'SMART AI LIMITED'!M73+'HK01'!M73-(-SUMIFS(合并抵消!$J:$J,合并抵消!$E:$E,$E73,合并抵消!$A:$A,M$2)+SUMIFS(合并抵消!$K:$K,合并抵消!$E:$E,$E73,合并抵消!$A:$A,M$2)) | ... Q73: =浙江精准学!Q73+知识跳跳!Q73+海南精准学!Q73+实时查!Q73+目标准!Q73+'SMART LEARNING HOLDING'!Q73+'SMART AI LIMITED'!Q73+'HK01'!Q73-(-SUMIFS(合并抵消!$J:$J,合并抵消!$E:$E,$E73,合并抵消!$A:$A,Q$2)+SUMIFS(合并抵消!$K:$K,合并抵消!$E:$E,$E73,合并抵消!$A:$A,Q$2)) | R73: =SUM(F73:Q73)
A74: 研发支出 | B74: 产品开发-MAX | D74: 模具费用 | E74: Q1205 | F74: =浙江精准学!F74+知识跳跳!F74+海南精准学!F74+实时查!F74+目标准!F74+'SMART LEARNING HOLDING'!F74+'SMART AI LIMITED'!F74+'HK01'!F74-(-SUMIFS(合并抵消!$J:$J,合并抵消!$E:$E,$E74,合并抵消!$A:$A,F$2)+SUMIFS(合并抵消!$K:$K,合并抵消!$E:$E,$E74,合并抵消!$A:$A,F$2)) | G74: =浙江精准学!G74+知识跳跳!G74+海南精准学!G74+实时查!G74+目标准!G74+'SMART LEARNING HOLDING'!G74+'SMART AI LIMITED'!G74+'HK01'!G74-(-SUMIFS(合并抵消!$J:$J,合并抵消!$E:$E,$E74,合并抵消!$A:$A,G$2)+SUMIFS(合并抵消!$K:$K,合并抵消!$E:$E,$E74,合并抵消!$A:$A,G$2)) | H74: =浙江精准学!H74+知识跳跳!H74+海南精准学!H74+实时查!H74+目标准!H74+'SMART LEARNING HOLDING'!H74+'SMART AI LIMITED'!H74+'HK01'!H74-(-SUMIFS(合并抵消!$J:$J,合并抵消!$E:$E,$E74,合并抵消!$A:$A,H$2)+SUMIFS(合并抵消!$K:$K,合并抵消!$E:$E,$E74,合并抵消!$A:$A,H$2)) | I74: =浙江精准学!I74+知识跳跳!I74+海南精准学!I74+实时查!I74+目标准!I74+'SMART LEARNING HOLDING'!I74+'SMART AI LIMITED'!I74+'HK01'!I74-(-SUMIFS(合并抵消!$J:$J,合并抵消!$E:$E,$E74,合并抵消!$A:$A,I$2)+SUMIFS(合并抵消!$K:$K,合并抵消!$E:$E,$E74,合并抵消!$A:$A,I$2)) | J74: =浙江精准学!J74+知识跳跳!J74+海南精准学!J74+实时查!J74+目标准!J74+'SMART LEARNING HOLDING'!J74+'SMART AI LIMITED'!J74+'HK01'!J74-(-SUMIFS(合并抵消!$J:$J,合并抵消!$E:$E,$E74,合并抵消!$A:$A,J$2)+SUMIFS(合并抵消!$K:$K,合并抵消!$E:$E,$E74,合并抵消!$A:$A,J$2)) | K74: =浙江精准学!K74+知识跳跳!K74+海南精准学!K74+实时查!K74+目标准!K74+'SMART LEARNING HOLDING'!K74+'SMART AI LIMITED'!K74+'HK01'!K74-(-SUMIFS(合并抵消!$J:$J,合并抵消!$E:$E,$E74,合并抵消!$A:$A,K$2)+SUMIFS(合并抵消!$K:$K,合并抵消!$E:$E,$E74,合并抵消!$A:$A,K$2)) | L74: =浙江精准学!L74+知识跳跳!L74+海南精准学!L74+实时查!L74+目标准!L74+'SMART LEARNING HOLDING'!L74+'SMART AI LIMITED'!L74+'HK01'!L74-(-SUMIFS(合并抵消!$J:$J,合并抵消!$E:$E,$E74,合并抵消!$A:$A,L$2)+SUMIFS(合并抵消!$K:$K,合并抵消!$E:$E,$E74,合并抵消!$A:$A,L$2)) | M74: =浙江精准学!M74+知识跳跳!M74+海南精准学!M74+实时查!M74+目标准!M74+'SMART LEARNING HOLDING'!M74+'SMART AI LIMITED'!M74+'HK01'!M74-(-SUMIFS(合并抵消!$J:$J,合并抵消!$E:$E,$E74,合并抵消!$A:$A,M$2)+SUMIFS(合并抵消!$K:$K,合并抵消!$E:$E,$E74,合并抵消!$A:$A,M$2)) | ... Q74: =浙江精准学!Q74+知识跳跳!Q74+海南精准学!Q74+实时查!Q74+目标准!Q74+'SMART LEARNING HOLDING'!Q74+'SMART AI LIMITED'!Q74+'HK01'!Q74-(-SUMIFS(合并抵消!$J:$J,合并抵消!$E:$E,$E74,合并抵消!$A:$A,Q$2)+SUMIFS(合并抵消!$K:$K,合并抵消!$E:$E,$E74,合并抵消!$A:$A,Q$2)) | R74: =SUM(F74:Q74)
A75: 研发支出 | B75: 产品开发-MAX | D75: TCL研发费 | E75: Q1206 | F75: =浙江精准学!F75+知识跳跳!F75+海南精准学!F75+实时查!F75+目标准!F75+'SMART LEARNING HOLDING'!F75+'SMART AI LIMITED'!F75+'HK01'!F75-(-SUMIFS(合并抵消!$J:$J,合并抵消!$E:$E,$E75,合并抵消!$A:$A,F$2)+SUMIFS(合并抵消!$K:$K,合并抵消!$E:$E,$E75,合并抵消!$A:$A,F$2)) | G75: =浙江精准学!G75+知识跳跳!G75+海南精准学!G75+实时查!G75+目标准!G75+'SMART LEARNING HOLDING'!G75+'SMART AI LIMITED'!G75+'HK01'!G75-(-SUMIFS(合并抵消!$J:$J,合并抵消!$E:$E,$E75,合并抵消!$A:$A,G$2)+SUMIFS(合并抵消!$K:$K,合并抵消!$E:$E,$E75,合并抵消!$A:$A,G$2)) | H75: =浙江精准学!H75+知识跳跳!H75+海南精准学!H75+实时查!H75+目标准!H75+'SMART LEARNING HOLDING'!H75+'SMART AI LIMITED'!H75+'HK01'!H75-(-SUMIFS(合并抵消!$J:$J,合并抵消!$E:$E,$E75,合并抵消!$A:$A,H$2)+SUMIFS(合并抵消!$K:$K,合并抵消!$E:$E,$E75,合并抵消!$A:$A,H$2)) | I75: =浙江精准学!I75+知识跳跳!I75+海南精准学!I75+实时查!I75+目标准!I75+'SMART LEARNING HOLDING'!I75+'SMART AI LIMITED'!I75+'HK01'!I75-(-SUMIFS(合并抵消!$J:$J,合并抵消!$E:$E,$E75,合并抵消!$A:$A,I$2)+SUMIFS(合并抵消!$K:$K,合并抵消!$E:$E,$E75,合并抵消!$A:$A,I$2)) | J75: =浙江精准学!J75+知识跳跳!J75+海南精准学!J75+实时查!J75+目标准!J75+'SMART LEARNING HOLDING'!J75+'SMART AI LIMITED'!J75+'HK01'!J75-(-SUMIFS(合并抵消!$J:$J,合并抵消!$E:$E,$E75,合并抵消!$A:$A,J$2)+SUMIFS(合并抵消!$K:$K,合并抵消!$E:$E,$E75,合并抵消!$A:$A,J$2)) | K75: =浙江精准学!K75+知识跳跳!K75+海南精准学!K75+实时查!K75+目标准!K75+'SMART LEARNING HOLDING'!K75+'SMART AI LIMITED'!K75+'HK01'!K75-(-SUMIFS(合并抵消!$J:$J,合并抵消!$E:$E,$E75,合并抵消!$A:$A,K$2)+SUMIFS(合并抵消!$K:$K,合并抵消!$E:$E,$E75,合并抵消!$A:$A,K$2)) | L75: =浙江精准学!L75+知识跳跳!L75+海南精准学!L75+实时查!L75+目标准!L75+'SMART LEARNING HOLDING'!L75+'SMART AI LIMITED'!L75+'HK01'!L75-(-SUMIFS(合并抵消!$J:$J,合并抵消!$E:$E,$E75,合并抵消!$A:$A,L$2)+SUMIFS(合并抵消!$K:$K,合并抵消!$E:$E,$E75,合并抵消!$A:$A,L$2)) | M75: =浙江精准学!M75+知识跳跳!M75+海南精准学!M75+实时查!M75+目标准!M75+'SMART LEARNING HOLDING'!M75+'SMART AI LIMITED'!M75+'HK01'!M75-(-SUMIFS(合并抵消!$J:$J,合并抵消!$E:$E,$E75,合并抵消!$A:$A,M$2)+SUMIFS(合并抵消!$K:$K,合并抵消!$E:$E,$E75,合并抵消!$A:$A,M$2)) | ... Q75: =浙江精准学!Q75+知识跳跳!Q75+海南精准学!Q75+实时查!Q75+目标准!Q75+'SMART LEARNING HOLDING'!Q75+'SMART AI LIMITED'!Q75+'HK01'!Q75-(-SUMIFS(合并抵消!$J:$J,合并抵消!$E:$E,$E75,合并抵消!$A:$A,Q$2)+SUMIFS(合并抵消!$K:$K,合并抵消!$E:$E,$E75,合并抵消!$A:$A,Q$2)) | R75: =SUM(F75:Q75)
A76: 研发支出 | B76: 产品开发-MAX | D76: 唤醒功能开发 | E76: Q1207 | F76: =浙江精准学!F76+知识跳跳!F76+海南精准学!F76+实时查!F76+目标准!F76+'SMART LEARNING HOLDING'!F76+'SMART AI LIMITED'!F76+'HK01'!F76-(-SUMIFS(合并抵消!$J:$J,合并抵消!$E:$E,$E76,合并抵消!$A:$A,F$2)+SUMIFS(合并抵消!$K:$K,合并抵消!$E:$E,$E76,合并抵消!$A:$A,F$2)) | G76: =浙江精准学!G76+知识跳跳!G76+海南精准学!G76+实时查!G76+目标准!G76+'SMART LEARNING HOLDING'!G76+'SMART AI LIMITED'!G76+'HK01'!G76-(-SUMIFS(合并抵消!$J:$J,合并抵消!$E:$E,$E76,合并抵消!$A:$A,G$2)+SUMIFS(合并抵消!$K:$K,合并抵消!$E:$E,$E76,合并抵消!$A:$A,G$2)) | H76: =浙江精准学!H76+知识跳跳!H76+海南精准学!H76+实时查!H76+目标准!H76+'SMART LEARNING HOLDING'!H76+'SMART AI LIMITED'!H76+'HK01'!H76-(-SUMIFS(合并抵消!$J:$J,合并抵消!$E:$E,$E76,合并抵消!$A:$A,H$2)+SUMIFS(合并抵消!$K:$K,合并抵消!$E:$E,$E76,合并抵消!$A:$A,H$2)) | I76: =浙江精准学!I76+知识跳跳!I76+海南精准学!I76+实时查!I76+目标准!I76+'SMART LEARNING HOLDING'!I76+'SMART AI LIMITED'!I76+'HK01'!I76-(-SUMIFS(合并抵消!$J:$J,合并抵消!$E:$E,$E76,合并抵消!$A:$A,I$2)+SUMIFS(合并抵消!$K:$K,合并抵消!$E:$E,$E76,合并抵消!$A:$A,I$2)) | J76: =浙江精准学!J76+知识跳跳!J76+海南精准学!J76+实时查!J76+目标准!J76+'SMART LEARNING HOLDING'!J76+'SMART AI LIMITED'!J76+'HK01'!J76-(-SUMIFS(合并抵消!$J:$J,合并抵消!$E:$E,$E76,合并抵消!$A:$A,J$2)+SUMIFS(合并抵消!$K:$K,合并抵消!$E:$E,$E76,合并抵消!$A:$A,J$2)) | K76: =浙江精准学!K76+知识跳跳!K76+海南精准学!K76+实时查!K76+目标准!K76+'SMART LEARNING HOLDING'!K76+'SMART AI LIMITED'!K76+'HK01'!K76-(-SUMIFS(合并抵消!$J:$J,合并抵消!$E:$E,$E76,合并抵消!$A:$A,K$2)+SUMIFS(合并抵消!$K:$K,合并抵消!$E:$E,$E76,合并抵消!$A:$A,K$2)) | L76: =浙江精准学!L76+知识跳跳!L76+海南精准学!L76+实时查!L76+目标准!L76+'SMART LEARNING HOLDING'!L76+'SMART AI LIMITED'!L76+'HK01'!L76-(-SUMIFS(合并抵消!$J:$J,合并抵消!$E:$E,$E76,合并抵消!$A:$A,L$2)+SUMIFS(合并抵消!$K:$K,合并抵消!$E:$E,$E76,合并抵消!$A:$A,L$2)) | M76: =浙江精准学!M76+知识跳跳!M76+海南精准学!M76+实时查!M76+目标准!M76+'SMART LEARNING HOLDING'!M76+'SMART AI LIMITED'!M76+'HK01'!M76-(-SUMIFS(合并抵消!$J:$J,合并抵消!$E:$E,$E76,合并抵消!$A:$A,M$2)+SUMIFS(合并抵消!$K:$K,合并抵消!$E:$E,$E76,合并抵消!$A:$A,M$2)) | ... Q76: =浙江精准学!Q76+知识跳跳!Q76+海南精准学!Q76+实时查!Q76+目标准!Q76+'SMART LEARNING HOLDING'!Q76+'SMART AI LIMITED'!Q76+'HK01'!Q76-(-SUMIFS(合并抵消!$J:$J,合并抵消!$E:$E,$E76,合并抵消!$A:$A,Q$2)+SUMIFS(合并抵消!$K:$K,合并抵消!$E:$E,$E76,合并抵消!$A:$A,Q$2)) | R76: =SUM(F76:Q76)
A77: 研发支出 | B77: 产品开发-MAX | D77: 题库费 | E77: Q1208 | F77: =浙江精准学!F77+知识跳跳!F77+海南精准学!F77+实时查!F77+目标准!F77+'SMART LEARNING HOLDING'!F77+'SMART AI LIMITED'!F77+'HK01'!F77-(-SUMIFS(合并抵消!$J:$J,合并抵消!$E:$E,$E77,合并抵消!$A:$A,F$2)+SUMIFS(合并抵消!$K:$K,合并抵消!$E:$E,$E77,合并抵消!$A:$A,F$2)) | G77: =浙江精准学!G77+知识跳跳!G77+海南精准学!G77+实时查!G77+目标准!G77+'SMART LEARNING HOLDING'!G77+'SMART AI LIMITED'!G77+'HK01'!G77-(-SUMIFS(合并抵消!$J:$J,合并抵消!$E:$E,$E77,合并抵消!$A:$A,G$2)+SUMIFS(合并抵消!$K:$K,合并抵消!$E:$E,$E77,合并抵消!$A:$A,G$2)) | H77: =浙江精准学!H77+知识跳跳!H77+海南精准学!H77+实时查!H77+目标准!H77+'SMART LEARNING HOLDING'!H77+'SMART AI LIMITED'!H77+'HK01'!H77-(-SUMIFS(合并抵消!$J:$J,合并抵消!$E:$E,$E77,合并抵消!$A:$A,H$2)+SUMIFS(合并抵消!$K:$K,合并抵消!$E:$E,$E77,合并抵消!$A:$A,H$2)) | I77: =浙江精准学!I77+知识跳跳!I77+海南精准学!I77+实时查!I77+目标准!I77+'SMART LEARNING HOLDING'!I77+'SMART AI LIMITED'!I77+'HK01'!I77-(-SUMIFS(合并抵消!$J:$J,合并抵消!$E:$E,$E77,合并抵消!$A:$A,I$2)+SUMIFS(合并抵消!$K:$K,合并抵消!$E:$E,$E77,合并抵消!$A:$A,I$2)) | J77: =浙江精准学!J77+知识跳跳!J77+海南精准学!J77+实时查!J77+目标准!J77+'SMART LEARNING HOLDING'!J77+'SMART AI LIMITED'!J77+'HK01'!J77-(-SUMIFS(合并抵消!$J:$J,合并抵消!$E:$E,$E77,合并抵消!$A:$A,J$2)+SUMIFS(合并抵消!$K:$K,合并抵消!$E:$E,$E77,合并抵消!$A:$A,J$2)) | K77: =浙江精准学!K77+知识跳跳!K77+海南精准学!K77+实时查!K77+目标准!K77+'SMART LEARNING HOLDING'!K77+'SMART AI LIMITED'!K77+'HK01'!K77-(-SUMIFS(合并抵消!$J:$J,合并抵消!$E:$E,$E77,合并抵消!$A:$A,K$2)+SUMIFS(合并抵消!$K:$K,合并抵消!$E:$E,$E77,合并抵消!$A:$A,K$2)) | L77: =浙江精准学!L77+知识跳跳!L77+海南精准学!L77+实时查!L77+目标准!L77+'SMART LEARNING HOLDING'!L77+'SMART AI LIMITED'!L77+'HK01'!L77-(-SUMIFS(合并抵消!$J:$J,合并抵消!$E:$E,$E77,合并抵消!$A:$A,L$2)+SUMIFS(合并抵消!$K:$K,合并抵消!$E:$E,$E77,合并抵消!$A:$A,L$2)) | M77: =浙江精准学!M77+知识跳跳!M77+海南精准学!M77+实时查!M77+目标准!M77+'SMART LEARNING HOLDING'!M77+'SMART AI LIMITED'!M77+'HK01'!M77-(-SUMIFS(合并抵消!$J:$J,合并抵消!$E:$E,$E77,合并抵消!$A:$A,M$2)+SUMIFS(合并抵消!$K:$K,合并抵消!$E:$E,$E77,合并抵消!$A:$A,M$2)) | ... Q77: =浙江精准学!Q77+知识跳跳!Q77+海南精准学!Q77+实时查!Q77+目标准!Q77+'SMART LEARNING HOLDING'!Q77+'SMART AI LIMITED'!Q77+'HK01'!Q77-(-SUMIFS(合并抵消!$J:$J,合并抵消!$E:$E,$E77,合并抵消!$A:$A,Q$2)+SUMIFS(合并抵消!$K:$K,合并抵消!$E:$E,$E77,合并抵消!$A:$A,Q$2)) | R77: =SUM(F77:Q77)
A78: 研发支出 | B78: 产品开发-PRO | C78: 产品开发-PRO | D78: 检测费 | E78: Q1301 | F78: =浙江精准学!F78+知识跳跳!F78+海南精准学!F78+实时查!F78+目标准!F78+'SMART LEARNING HOLDING'!F78+'SMART AI LIMITED'!F78+'HK01'!F78-(-SUMIFS(合并抵消!$J:$J,合并抵消!$E:$E,$E78,合并抵消!$A:$A,F$2)+SUMIFS(合并抵消!$K:$K,合并抵消!$E:$E,$E78,合并抵消!$A:$A,F$2)) | G78: =浙江精准学!G78+知识跳跳!G78+海南精准学!G78+实时查!G78+目标准!G78+'SMART LEARNING HOLDING'!G78+'SMART AI LIMITED'!G78+'HK01'!G78-(-SUMIFS(合并抵消!$J:$J,合并抵消!$E:$E,$E78,合并抵消!$A:$A,G$2)+SUMIFS(合并抵消!$K:$K,合并抵消!$E:$E,$E78,合并抵消!$A:$A,G$2)) | H78: =浙江精准学!H78+知识跳跳!H78+海南精准学!H78+实时查!H78+目标准!H78+'SMART LEARNING HOLDING'!H78+'SMART AI LIMITED'!H78+'HK01'!H78-(-SUMIFS(合并抵消!$J:$J,合并抵消!$E:$E,$E78,合并抵消!$A:$A,H$2)+SUMIFS(合并抵消!$K:$K,合并抵消!$E:$E,$E78,合并抵消!$A:$A,H$2)) | I78: =浙江精准学!I78+知识跳跳!I78+海南精准学!I78+实时查!I78+目标准!I78+'SMART LEARNING HOLDING'!I78+'SMART AI LIMITED'!I78+'HK01'!I78-(-SUMIFS(合并抵消!$J:$J,合并抵消!$E:$E,$E78,合并抵消!$A:$A,I$2)+SUMIFS(合并抵消!$K:$K,合并抵消!$E:$E,$E78,合并抵消!$A:$A,I$2)) | J78: =浙江精准学!J78+知识跳跳!J78+海南精准学!J78+实时查!J78+目标准!J78+'SMART LEARNING HOLDING'!J78+'SMART AI LIMITED'!J78+'HK01'!J78-(-SUMIFS(合并抵消!$J:$J,合并抵消!$E:$E,$E78,合并抵消!$A:$A,J$2)+SUMIFS(合并抵消!$K:$K,合并抵消!$E:$E,$E78,合并抵消!$A:$A,J$2)) | K78: =浙江精准学!K78+知识跳跳!K78+海南精准学!K78+实时查!K78+目标准!K78+'SMART LEARNING HOLDING'!K78+'SMART AI LIMITED'!K78+'HK01'!K78-(-SUMIFS(合并抵消!$J:$J,合并抵消!$E:$E,$E78,合并抵消!$A:$A,K$2)+SUMIFS(合并抵消!$K:$K,合并抵消!$E:$E,$E78,合并抵消!$A:$A,K$2)) | L78: =浙江精准学!L78+知识跳跳!L78+海南精准学!L78+实时查!L78+目标准!L78+'SMART LEARNING HOLDING'!L78+'SMART AI LIMITED'!L78+'HK01'!L78-(-SUMIFS(合并抵消!$J:$J,合并抵消!$E:$E,$E78,合并抵消!$A:$A,L$2)+SUMIFS(合并抵消!$K:$K,合并抵消!$E:$E,$E78,合并抵消!$A:$A,L$2)) | M78: =浙江精准学!M78+知识跳跳!M78+海南精准学!M78+实时查!M78+目标准!M78+'SMART LEARNING HOLDING'!M78+'SMART AI LIMITED'!M78+'HK01'!M78-(-SUMIFS(合并抵消!$J:$J,合并抵消!$E:$E,$E78,合并抵消!$A:$A,M$2)+SUMIFS(合并抵消!$K:$K,合并抵消!$E:$E,$E78,合并抵消!$A:$A,M$2)) | ... Q78: =浙江精准学!Q78+知识跳跳!Q78+海南精准学!Q78+实时查!Q78+目标准!Q78+'SMART LEARNING HOLDING'!Q78+'SMART AI LIMITED'!Q78+'HK01'!Q78-(-SUMIFS(合并抵消!$J:$J,合并抵消!$E:$E,$E78,合并抵消!$A:$A,Q$2)+SUMIFS(合并抵消!$K:$K,合并抵消!$E:$E,$E78,合并抵消!$A:$A,Q$2)) | R78: =SUM(F78:Q78)
A79: 研发支出 | B79: 产品开发-PRO | D79: 认证费 | E79: Q1302 | F79: =浙江精准学!F79+知识跳跳!F79+海南精准学!F79+实时查!F79+目标准!F79+'SMART LEARNING HOLDING'!F79+'SMART AI LIMITED'!F79+'HK01'!F79-(-SUMIFS(合并抵消!$J:$J,合并抵消!$E:$E,$E79,合并抵消!$A:$A,F$2)+SUMIFS(合并抵消!$K:$K,合并抵消!$E:$E,$E79,合并抵消!$A:$A,F$2)) | G79: =浙江精准学!G79+知识跳跳!G79+海南精准学!G79+实时查!G79+目标准!G79+'SMART LEARNING HOLDING'!G79+'SMART AI LIMITED'!G79+'HK01'!G79-(-SUMIFS(合并抵消!$J:$J,合并抵消!$E:$E,$E79,合并抵消!$A:$A,G$2)+SUMIFS(合并抵消!$K:$K,合并抵消!$E:$E,$E79,合并抵消!$A:$A,G$2)) | H79: =浙江精准学!H79+知识跳跳!H79+海南精准学!H79+实时查!H79+目标准!H79+'SMART LEARNING HOLDING'!H79+'SMART AI LIMITED'!H79+'HK01'!H79-(-SUMIFS(合并抵消!$J:$J,合并抵消!$E:$E,$E79,合并抵消!$A:$A,H$2)+SUMIFS(合并抵消!$K:$K,合并抵消!$E:$E,$E79,合并抵消!$A:$A,H$2)) | I79: =浙江精准学!I79+知识跳跳!I79+海南精准学!I79+实时查!I79+目标准!I79+'SMART LEARNING HOLDING'!I79+'SMART AI LIMITED'!I79+'HK01'!I79-(-SUMIFS(合并抵消!$J:$J,合并抵消!$E:$E,$E79,合并抵消!$A:$A,I$2)+SUMIFS(合并抵消!$K:$K,合并抵消!$E:$E,$E79,合并抵消!$A:$A,I$2)) | J79: =浙江精准学!J79+知识跳跳!J79+海南精准学!J79+实时查!J79+目标准!J79+'SMART LEARNING HOLDING'!J79+'SMART AI LIMITED'!J79+'HK01'!J79-(-SUMIFS(合并抵消!$J:$J,合并抵消!$E:$E,$E79,合并抵消!$A:$A,J$2)+SUMIFS(合并抵消!$K:$K,合并抵消!$E:$E,$E79,合并抵消!$A:$A,J$2)) | K79: =浙江精准学!K79+知识跳跳!K79+海南精准学!K79+实时查!K79+目标准!K79+'SMART LEARNING HOLDING'!K79+'SMART AI LIMITED'!K79+'HK01'!K79-(-SUMIFS(合并抵消!$J:$J,合并抵消!$E:$E,$E79,合并抵消!$A:$A,K$2)+SUMIFS(合并抵消!$K:$K,合并抵消!$E:$E,$E79,合并抵消!$A:$A,K$2)) | L79: =浙江精准学!L79+知识跳跳!L79+海南精准学!L79+实时查!L79+目标准!L79+'SMART LEARNING HOLDING'!L79+'SMART AI LIMITED'!L79+'HK01'!L79-(-SUMIFS(合并抵消!$J:$J,合并抵消!$E:$E,$E79,合并抵消!$A:$A,L$2)+SUMIFS(合并抵消!$K:$K,合并抵消!$E:$E,$E79,合并抵消!$A:$A,L$2)) | M79: =浙江精准学!M79+知识跳跳!M79+海南精准学!M79+实时查!M79+目标准!M79+'SMART LEARNING HOLDING'!M79+'SMART AI LIMITED'!M79+'HK01'!M79-(-SUMIFS(合并抵消!$J:$J,合并抵消!$E:$E,$E79,合并抵消!$A:$A,M$2)+SUMIFS(合并抵消!$K:$K,合并抵消!$E:$E,$E79,合并抵消!$A:$A,M$2)) | ... Q79: =浙江精准学!Q79+知识跳跳!Q79+海南精准学!Q79+实时查!Q79+目标准!Q79+'SMART LEARNING HOLDING'!Q79+'SMART AI LIMITED'!Q79+'HK01'!Q79-(-SUMIFS(合并抵消!$J:$J,合并抵消!$E:$E,$E79,合并抵消!$A:$A,Q$2)+SUMIFS(合并抵消!$K:$K,合并抵消!$E:$E,$E79,合并抵消!$A:$A,Q$2)) | R79: =SUM(F79:Q79)
A80: 研发支出 | B80: 产品开发-PRO | D80: 设计费 | E80: Q1303 | F80: =浙江精准学!F80+知识跳跳!F80+海南精准学!F80+实时查!F80+目标准!F80+'SMART LEARNING HOLDING'!F80+'SMART AI LIMITED'!F80+'HK01'!F80-(-SUMIFS(合并抵消!$J:$J,合并抵消!$E:$E,$E80,合并抵消!$A:$A,F$2)+SUMIFS(合并抵消!$K:$K,合并抵消!$E:$E,$E80,合并抵消!$A:$A,F$2)) | G80: =浙江精准学!G80+知识跳跳!G80+海南精准学!G80+实时查!G80+目标准!G80+'SMART LEARNING HOLDING'!G80+'SMART AI LIMITED'!G80+'HK01'!G80-(-SUMIFS(合并抵消!$J:$J,合并抵消!$E:$E,$E80,合并抵消!$A:$A,G$2)+SUMIFS(合并抵消!$K:$K,合并抵消!$E:$E,$E80,合并抵消!$A:$A,G$2)) | H80: =浙江精准学!H80+知识跳跳!H80+海南精准学!H80+实时查!H80+目标准!H80+'SMART LEARNING HOLDING'!H80+'SMART AI LIMITED'!H80+'HK01'!H80-(-SUMIFS(合并抵消!$J:$J,合并抵消!$E:$E,$E80,合并抵消!$A:$A,H$2)+SUMIFS(合并抵消!$K:$K,合并抵消!$E:$E,$E80,合并抵消!$A:$A,H$2)) | I80: =浙江精准学!I80+知识跳跳!I80+海南精准学!I80+实时查!I80+目标准!I80+'SMART LEARNING HOLDING'!I80+'SMART AI LIMITED'!I80+'HK01'!I80-(-SUMIFS(合并抵消!$J:$J,合并抵消!$E:$E,$E80,合并抵消!$A:$A,I$2)+SUMIFS(合并抵消!$K:$K,合并抵消!$E:$E,$E80,合并抵消!$A:$A,I$2)) | J80: =浙江精准学!J80+知识跳跳!J80+海南精准学!J80+实时查!J80+目标准!J80+'SMART LEARNING HOLDING'!J80+'SMART AI LIMITED'!J80+'HK01'!J80-(-SUMIFS(合并抵消!$J:$J,合并抵消!$E:$E,$E80,合并抵消!$A:$A,J$2)+SUMIFS(合并抵消!$K:$K,合并抵消!$E:$E,$E80,合并抵消!$A:$A,J$2)) | K80: =浙江精准学!K80+知识跳跳!K80+海南精准学!K80+实时查!K80+目标准!K80+'SMART LEARNING HOLDING'!K80+'SMART AI LIMITED'!K80+'HK01'!K80-(-SUMIFS(合并抵消!$J:$J,合并抵消!$E:$E,$E80,合并抵消!$A:$A,K$2)+SUMIFS(合并抵消!$K:$K,合并抵消!$E:$E,$E80,合并抵消!$A:$A,K$2)) | L80: =浙江精准学!L80+知识跳跳!L80+海南精准学!L80+实时查!L80+目标准!L80+'SMART LEARNING HOLDING'!L80+'SMART AI LIMITED'!L80+'HK01'!L80-(-SUMIFS(合并抵消!$J:$J,合并抵消!$E:$E,$E80,合并抵消!$A:$A,L$2)+SUMIFS(合并抵消!$K:$K,合并抵消!$E:$E,$E80,合并抵消!$A:$A,L$2)) | M80: =浙江精准学!M80+知识跳跳!M80+海南精准学!M80+实时查!M80+目标准!M80+'SMART LEARNING HOLDING'!M80+'SMART AI LIMITED'!M80+'HK01'!M80-(-SUMIFS(合并抵消!$J:$J,合并抵消!$E:$E,$E80,合并抵消!$A:$A,M$2)+SUMIFS(合并抵消!$K:$K,合并抵消!$E:$E,$E80,合并抵消!$A:$A,M$2)) | ... Q80: =浙江精准学!Q80+知识跳跳!Q80+海南精准学!Q80+实时查!Q80+目标准!Q80+'SMART LEARNING HOLDING'!Q80+'SMART AI LIMITED'!Q80+'HK01'!Q80-(-SUMIFS(合并抵消!$J:$J,合并抵消!$E:$E,$E80,合并抵消!$A:$A,Q$2)+SUMIFS(合并抵消!$K:$K,合并抵消!$E:$E,$E80,合并抵消!$A:$A,Q$2)) | R80: =SUM(F80:Q80)
A81: 研发支出 | B81: 产品开发-PRO | D81: OTA费用 | E81: Q1304 | F81: =浙江精准学!F81+知识跳跳!F81+海南精准学!F81+实时查!F81+目标准!F81+'SMART LEARNING HOLDING'!F81+'SMART AI LIMITED'!F81+'HK01'!F81-(-SUMIFS(合并抵消!$J:$J,合并抵消!$E:$E,$E81,合并抵消!$A:$A,F$2)+SUMIFS(合并抵消!$K:$K,合并抵消!$E:$E,$E81,合并抵消!$A:$A,F$2)) | G81: =浙江精准学!G81+知识跳跳!G81+海南精准学!G81+实时查!G81+目标准!G81+'SMART LEARNING HOLDING'!G81+'SMART AI LIMITED'!G81+'HK01'!G81-(-SUMIFS(合并抵消!$J:$J,合并抵消!$E:$E,$E81,合并抵消!$A:$A,G$2)+SUMIFS(合并抵消!$K:$K,合并抵消!$E:$E,$E81,合并抵消!$A:$A,G$2)) | H81: =浙江精准学!H81+知识跳跳!H81+海南精准学!H81+实时查!H81+目标准!H81+'SMART LEARNING HOLDING'!H81+'SMART AI LIMITED'!H81+'HK01'!H81-(-SUMIFS(合并抵消!$J:$J,合并抵消!$E:$E,$E81,合并抵消!$A:$A,H$2)+SUMIFS(合并抵消!$K:$K,合并抵消!$E:$E,$E81,合并抵消!$A:$A,H$2)) | I81: =浙江精准学!I81+知识跳跳!I81+海南精准学!I81+实时查!I81+目标准!I81+'SMART LEARNING HOLDING'!I81+'SMART AI LIMITED'!I81+'HK01'!I81-(-SUMIFS(合并抵消!$J:$J,合并抵消!$E:$E,$E81,合并抵消!$A:$A,I$2)+SUMIFS(合并抵消!$K:$K,合并抵消!$E:$E,$E81,合并抵消!$A:$A,I$2)) | J81: =浙江精准学!J81+知识跳跳!J81+海南精准学!J81+实时查!J81+目标准!J81+'SMART LEARNING HOLDING'!J81+'SMART AI LIMITED'!J81+'HK01'!J81-(-SUMIFS(合并抵消!$J:$J,合并抵消!$E:$E,$E81,合并抵消!$A:$A,J$2)+SUMIFS(合并抵消!$K:$K,合并抵消!$E:$E,$E81,合并抵消!$A:$A,J$2)) | K81: =浙江精准学!K81+知识跳跳!K81+海南精准学!K81+实时查!K81+目标准!K81+'SMART LEARNING HOLDING'!K81+'SMART AI LIMITED'!K81+'HK01'!K81-(-SUMIFS(合并抵消!$J:$J,合并抵消!$E:$E,$E81,合并抵消!$A:$A,K$2)+SUMIFS(合并抵消!$K:$K,合并抵消!$E:$E,$E81,合并抵消!$A:$A,K$2)) | L81: =浙江精准学!L81+知识跳跳!L81+海南精准学!L81+实时查!L81+目标准!L81+'SMART LEARNING HOLDING'!L81+'SMART AI LIMITED'!L81+'HK01'!L81-(-SUMIFS(合并抵消!$J:$J,合并抵消!$E:$E,$E81,合并抵消!$A:$A,L$2)+SUMIFS(合并抵消!$K:$K,合并抵消!$E:$E,$E81,合并抵消!$A:$A,L$2)) | M81: =浙江精准学!M81+知识跳跳!M81+海南精准学!M81+实时查!M81+目标准!M81+'SMART LEARNING HOLDING'!M81+'SMART AI LIMITED'!M81+'HK01'!M81-(-SUMIFS(合并抵消!$J:$J,合并抵消!$E:$E,$E81,合并抵消!$A:$A,M$2)+SUMIFS(合并抵消!$K:$K,合并抵消!$E:$E,$E81,合并抵消!$A:$A,M$2)) | ... Q81: =浙江精准学!Q81+知识跳跳!Q81+海南精准学!Q81+实时查!Q81+目标准!Q81+'SMART LEARNING HOLDING'!Q81+'SMART AI LIMITED'!Q81+'HK01'!Q81-(-SUMIFS(合并抵消!$J:$J,合并抵消!$E:$E,$E81,合并抵消!$A:$A,Q$2)+SUMIFS(合并抵消!$K:$K,合并抵消!$E:$E,$E81,合并抵消!$A:$A,Q$2)) | R81: =SUM(F81:Q81)
A82: 研发支出 | B82: 产品开发-PRO | D82: 模具费用 | E82: Q1305 | F82: =浙江精准学!F82+知识跳跳!F82+海南精准学!F82+实时查!F82+目标准!F82+'SMART LEARNING HOLDING'!F82+'SMART AI LIMITED'!F82+'HK01'!F82-(-SUMIFS(合并抵消!$J:$J,合并抵消!$E:$E,$E82,合并抵消!$A:$A,F$2)+SUMIFS(合并抵消!$K:$K,合并抵消!$E:$E,$E82,合并抵消!$A:$A,F$2)) | G82: =浙江精准学!G82+知识跳跳!G82+海南精准学!G82+实时查!G82+目标准!G82+'SMART LEARNING HOLDING'!G82+'SMART AI LIMITED'!G82+'HK01'!G82-(-SUMIFS(合并抵消!$J:$J,合并抵消!$E:$E,$E82,合并抵消!$A:$A,G$2)+SUMIFS(合并抵消!$K:$K,合并抵消!$E:$E,$E82,合并抵消!$A:$A,G$2)) | H82: =浙江精准学!H82+知识跳跳!H82+海南精准学!H82+实时查!H82+目标准!H82+'SMART LEARNING HOLDING'!H82+'SMART AI LIMITED'!H82+'HK01'!H82-(-SUMIFS(合并抵消!$J:$J,合并抵消!$E:$E,$E82,合并抵消!$A:$A,H$2)+SUMIFS(合并抵消!$K:$K,合并抵消!$E:$E,$E82,合并抵消!$A:$A,H$2)) | I82: =浙江精准学!I82+知识跳跳!I82+海南精准学!I82+实时查!I82+目标准!I82+'SMART LEARNING HOLDING'!I82+'SMART AI LIMITED'!I82+'HK01'!I82-(-SUMIFS(合并抵消!$J:$J,合并抵消!$E:$E,$E82,合并抵消!$A:$A,I$2)+SUMIFS(合并抵消!$K:$K,合并抵消!$E:$E,$E82,合并抵消!$A:$A,I$2)) | J82: =浙江精准学!J82+知识跳跳!J82+海南精准学!J82+实时查!J82+目标准!J82+'SMART LEARNING HOLDING'!J82+'SMART AI LIMITED'!J82+'HK01'!J82-(-SUMIFS(合并抵消!$J:$J,合并抵消!$E:$E,$E82,合并抵消!$A:$A,J$2)+SUMIFS(合并抵消!$K:$K,合并抵消!$E:$E,$E82,合并抵消!$A:$A,J$2)) | K82: =浙江精准学!K82+知识跳跳!K82+海南精准学!K82+实时查!K82+目标准!K82+'SMART LEARNING HOLDING'!K82+'SMART AI LIMITED'!K82+'HK01'!K82-(-SUMIFS(合并抵消!$J:$J,合并抵消!$E:$E,$E82,合并抵消!$A:$A,K$2)+SUMIFS(合并抵消!$K:$K,合并抵消!$E:$E,$E82,合并抵消!$A:$A,K$2)) | L82: =浙江精准学!L82+知识跳跳!L82+海南精准学!L82+实时查!L82+目标准!L82+'SMART LEARNING HOLDING'!L82+'SMART AI LIMITED'!L82+'HK01'!L82-(-SUMIFS(合并抵消!$J:$J,合并抵消!$E:$E,$E82,合并抵消!$A:$A,L$2)+SUMIFS(合并抵消!$K:$K,合并抵消!$E:$E,$E82,合并抵消!$A:$A,L$2)) | M82: =浙江精准学!M82+知识跳跳!M82+海南精准学!M82+实时查!M82+目标准!M82+'SMART LEARNING HOLDING'!M82+'SMART AI LIMITED'!M82+'HK01'!M82-(-SUMIFS(合并抵消!$J:$J,合并抵消!$E:$E,$E82,合并抵消!$A:$A,M$2)+SUMIFS(合并抵消!$K:$K,合并抵消!$E:$E,$E82,合并抵消!$A:$A,M$2)) | ... Q82: =浙江精准学!Q82+知识跳跳!Q82+海南精准学!Q82+实时查!Q82+目标准!Q82+'SMART LEARNING HOLDING'!Q82+'SMART AI LIMITED'!Q82+'HK01'!Q82-(-SUMIFS(合并抵消!$J:$J,合并抵消!$E:$E,$E82,合并抵消!$A:$A,Q$2)+SUMIFS(合并抵消!$K:$K,合并抵消!$E:$E,$E82,合并抵消!$A:$A,Q$2)) | R82: =SUM(F82:Q82)
A83: 研发支出 | B83: 产品开发-PRO | D83: BOE研发费 | E83: Q1306 | F83: =浙江精准学!F83+知识跳跳!F83+海南精准学!F83+实时查!F83+目标准!F83+'SMART LEARNING HOLDING'!F83+'SMART AI LIMITED'!F83+'HK01'!F83-(-SUMIFS(合并抵消!$J:$J,合并抵消!$E:$E,$E83,合并抵消!$A:$A,F$2)+SUMIFS(合并抵消!$K:$K,合并抵消!$E:$E,$E83,合并抵消!$A:$A,F$2)) | G83: =浙江精准学!G83+知识跳跳!G83+海南精准学!G83+实时查!G83+目标准!G83+'SMART LEARNING HOLDING'!G83+'SMART AI LIMITED'!G83+'HK01'!G83-(-SUMIFS(合并抵消!$J:$J,合并抵消!$E:$E,$E83,合并抵消!$A:$A,G$2)+SUMIFS(合并抵消!$K:$K,合并抵消!$E:$E,$E83,合并抵消!$A:$A,G$2)) | H83: =浙江精准学!H83+知识跳跳!H83+海南精准学!H83+实时查!H83+目标准!H83+'SMART LEARNING HOLDING'!H83+'SMART AI LIMITED'!H83+'HK01'!H83-(-SUMIFS(合并抵消!$J:$J,合并抵消!$E:$E,$E83,合并抵消!$A:$A,H$2)+SUMIFS(合并抵消!$K:$K,合并抵消!$E:$E,$E83,合并抵消!$A:$A,H$2)) | I83: =浙江精准学!I83+知识跳跳!I83+海南精准学!I83+实时查!I83+目标准!I83+'SMART LEARNING HOLDING'!I83+'SMART AI LIMITED'!I83+'HK01'!I83-(-SUMIFS(合并抵消!$J:$J,合并抵消!$E:$E,$E83,合并抵消!$A:$A,I$2)+SUMIFS(合并抵消!$K:$K,合并抵消!$E:$E,$E83,合并抵消!$A:$A,I$2)) | J83: =浙江精准学!J83+知识跳跳!J83+海南精准学!J83+实时查!J83+目标准!J83+'SMART LEARNING HOLDING'!J83+'SMART AI LIMITED'!J83+'HK01'!J83-(-SUMIFS(合并抵消!$J:$J,合并抵消!$E:$E,$E83,合并抵消!$A:$A,J$2)+SUMIFS(合并抵消!$K:$K,合并抵消!$E:$E,$E83,合并抵消!$A:$A,J$2)) | K83: =浙江精准学!K83+知识跳跳!K83+海南精准学!K83+实时查!K83+目标准!K83+'SMART LEARNING HOLDING'!K83+'SMART AI LIMITED'!K83+'HK01'!K83-(-SUMIFS(合并抵消!$J:$J,合并抵消!$E:$E,$E83,合并抵消!$A:$A,K$2)+SUMIFS(合并抵消!$K:$K,合并抵消!$E:$E,$E83,合并抵消!$A:$A,K$2)) | L83: =浙江精准学!L83+知识跳跳!L83+海南精准学!L83+实时查!L83+目标准!L83+'SMART LEARNING HOLDING'!L83+'SMART AI LIMITED'!L83+'HK01'!L83-(-SUMIFS(合并抵消!$J:$J,合并抵消!$E:$E,$E83,合并抵消!$A:$A,L$2)+SUMIFS(合并抵消!$K:$K,合并抵消!$E:$E,$E83,合并抵消!$A:$A,L$2)) | M83: =浙江精准学!M83+知识跳跳!M83+海南精准学!M83+实时查!M83+目标准!M83+'SMART LEARNING HOLDING'!M83+'SMART AI LIMITED'!M83+'HK01'!M83-(-SUMIFS(合并抵消!$J:$J,合并抵消!$E:$E,$E83,合并抵消!$A:$A,M$2)+SUMIFS(合并抵消!$K:$K,合并抵消!$E:$E,$E83,合并抵消!$A:$A,M$2)) | ... Q83: =浙江精准学!Q83+知识跳跳!Q83+海南精准学!Q83+实时查!Q83+目标准!Q83+'SMART LEARNING HOLDING'!Q83+'SMART AI LIMITED'!Q83+'HK01'!Q83-(-SUMIFS(合并抵消!$J:$J,合并抵消!$E:$E,$E83,合并抵消!$A:$A,Q$2)+SUMIFS(合并抵消!$K:$K,合并抵消!$E:$E,$E83,合并抵消!$A:$A,Q$2)) | R83: =SUM(F83:Q83)
A84: 研发支出 | B84: 产品开发-PRO | D84: 题库费 | E84: Q1307 | F84: =浙江精准学!F84+知识跳跳!F84+海南精准学!F84+实时查!F84+目标准!F84+'SMART LEARNING HOLDING'!F84+'SMART AI LIMITED'!F84+'HK01'!F84-(-SUMIFS(合并抵消!$J:$J,合并抵消!$E:$E,$E84,合并抵消!$A:$A,F$2)+SUMIFS(合并抵消!$K:$K,合并抵消!$E:$E,$E84,合并抵消!$A:$A,F$2)) | G84: =浙江精准学!G84+知识跳跳!G84+海南精准学!G84+实时查!G84+目标准!G84+'SMART LEARNING HOLDING'!G84+'SMART AI LIMITED'!G84+'HK01'!G84-(-SUMIFS(合并抵消!$J:$J,合并抵消!$E:$E,$E84,合并抵消!$A:$A,G$2)+SUMIFS(合并抵消!$K:$K,合并抵消!$E:$E,$E84,合并抵消!$A:$A,G$2)) | H84: =浙江精准学!H84+知识跳跳!H84+海南精准学!H84+实时查!H84+目标准!H84+'SMART LEARNING HOLDING'!H84+'SMART AI LIMITED'!H84+'HK01'!H84-(-SUMIFS(合并抵消!$J:$J,合并抵消!$E:$E,$E84,合并抵消!$A:$A,H$2)+SUMIFS(合并抵消!$K:$K,合并抵消!$E:$E,$E84,合并抵消!$A:$A,H$2)) | I84: =浙江精准学!I84+知识跳跳!I84+海南精准学!I84+实时查!I84+目标准!I84+'SMART LEARNING HOLDING'!I84+'SMART AI LIMITED'!I84+'HK01'!I84-(-SUMIFS(合并抵消!$J:$J,合并抵消!$E:$E,$E84,合并抵消!$A:$A,I$2)+SUMIFS(合并抵消!$K:$K,合并抵消!$E:$E,$E84,合并抵消!$A:$A,I$2)) | J84: =浙江精准学!J84+知识跳跳!J84+海南精准学!J84+实时查!J84+目标准!J84+'SMART LEARNING HOLDING'!J84+'SMART AI LIMITED'!J84+'HK01'!J84-(-SUMIFS(合并抵消!$J:$J,合并抵消!$E:$E,$E84,合并抵消!$A:$A,J$2)+SUMIFS(合并抵消!$K:$K,合并抵消!$E:$E,$E84,合并抵消!$A:$A,J$2)) | K84: =浙江精准学!K84+知识跳跳!K84+海南精准学!K84+实时查!K84+目标准!K84+'SMART LEARNING HOLDING'!K84+'SMART AI LIMITED'!K84+'HK01'!K84-(-SUMIFS(合并抵消!$J:$J,合并抵消!$E:$E,$E84,合并抵消!$A:$A,K$2)+SUMIFS(合并抵消!$K:$K,合并抵消!$E:$E,$E84,合并抵消!$A:$A,K$2)) | L84: =浙江精准学!L84+知识跳跳!L84+海南精准学!L84+实时查!L84+目标准!L84+'SMART LEARNING HOLDING'!L84+'SMART AI LIMITED'!L84+'HK01'!L84-(-SUMIFS(合并抵消!$J:$J,合并抵消!$E:$E,$E84,合并抵消!$A:$A,L$2)+SUMIFS(合并抵消!$K:$K,合并抵消!$E:$E,$E84,合并抵消!$A:$A,L$2)) | M84: =浙江精准学!M84+知识跳跳!M84+海南精准学!M84+实时查!M84+目标准!M84+'SMART LEARNING HOLDING'!M84+'SMART AI LIMITED'!M84+'HK01'!M84-(-SUMIFS(合并抵消!$J:$J,合并抵消!$E:$E,$E84,合并抵消!$A:$A,M$2)+SUMIFS(合并抵消!$K:$K,合并抵消!$E:$E,$E84,合并抵消!$A:$A,M$2)) | ... Q84: =浙江精准学!Q84+知识跳跳!Q84+海南精准学!Q84+实时查!Q84+目标准!Q84+'SMART LEARNING HOLDING'!Q84+'SMART AI LIMITED'!Q84+'HK01'!Q84-(-SUMIFS(合并抵消!$J:$J,合并抵消!$E:$E,$E84,合并抵消!$A:$A,Q$2)+SUMIFS(合并抵消!$K:$K,合并抵消!$E:$E,$E84,合并抵消!$A:$A,Q$2)) | R84: =SUM(F84:Q84)
A85: 研发支出 | B85: 其他产品开发 | C85: 其他产品开发 | D85: 产品开发-员工报销 | E85: Q1402 | F85: =浙江精准学!F85+知识跳跳!F85+海南精准学!F85+实时查!F85+目标准!F85+'SMART LEARNING HOLDING'!F85+'SMART AI LIMITED'!F85+'HK01'!F85-(-SUMIFS(合并抵消!$J:$J,合并抵消!$E:$E,$E85,合并抵消!$A:$A,F$2)+SUMIFS(合并抵消!$K:$K,合并抵消!$E:$E,$E85,合并抵消!$A:$A,F$2)) | G85: =浙江精准学!G85+知识跳跳!G85+海南精准学!G85+实时查!G85+目标准!G85+'SMART LEARNING HOLDING'!G85+'SMART AI LIMITED'!G85+'HK01'!G85-(-SUMIFS(合并抵消!$J:$J,合并抵消!$E:$E,$E85,合并抵消!$A:$A,G$2)+SUMIFS(合并抵消!$K:$K,合并抵消!$E:$E,$E85,合并抵消!$A:$A,G$2)) | H85: =浙江精准学!H85+知识跳跳!H85+海南精准学!H85+实时查!H85+目标准!H85+'SMART LEARNING HOLDING'!H85+'SMART AI LIMITED'!H85+'HK01'!H85-(-SUMIFS(合并抵消!$J:$J,合并抵消!$E:$E,$E85,合并抵消!$A:$A,H$2)+SUMIFS(合并抵消!$K:$K,合并抵消!$E:$E,$E85,合并抵消!$A:$A,H$2)) | I85: =浙江精准学!I85+知识跳跳!I85+海南精准学!I85+实时查!I85+目标准!I85+'SMART LEARNING HOLDING'!I85+'SMART AI LIMITED'!I85+'HK01'!I85-(-SUMIFS(合并抵消!$J:$J,合并抵消!$E:$E,$E85,合并抵消!$A:$A,I$2)+SUMIFS(合并抵消!$K:$K,合并抵消!$E:$E,$E85,合并抵消!$A:$A,I$2)) | J85: =浙江精准学!J85+知识跳跳!J85+海南精准学!J85+实时查!J85+目标准!J85+'SMART LEARNING HOLDING'!J85+'SMART AI LIMITED'!J85+'HK01'!J85-(-SUMIFS(合并抵消!$J:$J,合并抵消!$E:$E,$E85,合并抵消!$A:$A,J$2)+SUMIFS(合并抵消!$K:$K,合并抵消!$E:$E,$E85,合并抵消!$A:$A,J$2)) | K85: =浙江精准学!K85+知识跳跳!K85+海南精准学!K85+实时查!K85+目标准!K85+'SMART LEARNING HOLDING'!K85+'SMART AI LIMITED'!K85+'HK01'!K85-(-SUMIFS(合并抵消!$J:$J,合并抵消!$E:$E,$E85,合并抵消!$A:$A,K$2)+SUMIFS(合并抵消!$K:$K,合并抵消!$E:$E,$E85,合并抵消!$A:$A,K$2)) | L85: =浙江精准学!L85+知识跳跳!L85+海南精准学!L85+实时查!L85+目标准!L85+'SMART LEARNING HOLDING'!L85+'SMART AI LIMITED'!L85+'HK01'!L85-(-SUMIFS(合并抵消!$J:$J,合并抵消!$E:$E,$E85,合并抵消!$A:$A,L$2)+SUMIFS(合并抵消!$K:$K,合并抵消!$E:$E,$E85,合并抵消!$A:$A,L$2)) | M85: =浙江精准学!M85+知识跳跳!M85+海南精准学!M85+实时查!M85+目标准!M85+'SMART LEARNING HOLDING'!M85+'SMART AI LIMITED'!M85+'HK01'!M85-(-SUMIFS(合并抵消!$J:$J,合并抵消!$E:$E,$E85,合并抵消!$A:$A,M$2)+SUMIFS(合并抵消!$K:$K,合并抵消!$E:$E,$E85,合并抵消!$A:$A,M$2)) | ... Q85: =浙江精准学!Q85+知识跳跳!Q85+海南精准学!Q85+实时查!Q85+目标准!Q85+'SMART LEARNING HOLDING'!Q85+'SMART AI LIMITED'!Q85+'HK01'!Q85-(-SUMIFS(合并抵消!$J:$J,合并抵消!$E:$E,$E85,合并抵消!$A:$A,Q$2)+SUMIFS(合并抵消!$K:$K,合并抵消!$E:$E,$E85,合并抵消!$A:$A,Q$2)) | R85: =SUM(F85:Q85)
A86: 研发支出 | B86: 其他产品开发 | D86: 软件使用费 | E86: Q1401 | F86: =浙江精准学!F86+知识跳跳!F86+海南精准学!F86+实时查!F86+目标准!F86+'SMART LEARNING HOLDING'!F86+'SMART AI LIMITED'!F86+'HK01'!F86-(-SUMIFS(合并抵消!$J:$J,合并抵消!$E:$E,$E86,合并抵消!$A:$A,F$2)+SUMIFS(合并抵消!$K:$K,合并抵消!$E:$E,$E86,合并抵消!$A:$A,F$2)) | G86: =浙江精准学!G86+知识跳跳!G86+海南精准学!G86+实时查!G86+目标准!G86+'SMART LEARNING HOLDING'!G86+'SMART AI LIMITED'!G86+'HK01'!G86-(-SUMIFS(合并抵消!$J:$J,合并抵消!$E:$E,$E86,合并抵消!$A:$A,G$2)+SUMIFS(合并抵消!$K:$K,合并抵消!$E:$E,$E86,合并抵消!$A:$A,G$2)) | H86: =浙江精准学!H86+知识跳跳!H86+海南精准学!H86+实时查!H86+目标准!H86+'SMART LEARNING HOLDING'!H86+'SMART AI LIMITED'!H86+'HK01'!H86-(-SUMIFS(合并抵消!$J:$J,合并抵消!$E:$E,$E86,合并抵消!$A:$A,H$2)+SUMIFS(合并抵消!$K:$K,合并抵消!$E:$E,$E86,合并抵消!$A:$A,H$2)) | I86: =浙江精准学!I86+知识跳跳!I86+海南精准学!I86+实时查!I86+目标准!I86+'SMART LEARNING HOLDING'!I86+'SMART AI LIMITED'!I86+'HK01'!I86-(-SUMIFS(合并抵消!$J:$J,合并抵消!$E:$E,$E86,合并抵消!$A:$A,I$2)+SUMIFS(合并抵消!$K:$K,合并抵消!$E:$E,$E86,合并抵消!$A:$A,I$2)) | J86: =浙江精准学!J86+知识跳跳!J86+海南精准学!J86+实时查!J86+目标准!J86+'SMART LEARNING HOLDING'!J86+'SMART AI LIMITED'!J86+'HK01'!J86-(-SUMIFS(合并抵消!$J:$J,合并抵消!$E:$E,$E86,合并抵消!$A:$A,J$2)+SUMIFS(合并抵消!$K:$K,合并抵消!$E:$E,$E86,合并抵消!$A:$A,J$2)) | K86: =浙江精准学!K86+知识跳跳!K86+海南精准学!K86+实时查!K86+目标准!K86+'SMART LEARNING HOLDING'!K86+'SMART AI LIMITED'!K86+'HK01'!K86-(-SUMIFS(合并抵消!$J:$J,合并抵消!$E:$E,$E86,合并抵消!$A:$A,K$2)+SUMIFS(合并抵消!$K:$K,合并抵消!$E:$E,$E86,合并抵消!$A:$A,K$2)) | L86: =浙江精准学!L86+知识跳跳!L86+海南精准学!L86+实时查!L86+目标准!L86+'SMART LEARNING HOLDING'!L86+'SMART AI LIMITED'!L86+'HK01'!L86-(-SUMIFS(合并抵消!$J:$J,合并抵消!$E:$E,$E86,合并抵消!$A:$A,L$2)+SUMIFS(合并抵消!$K:$K,合并抵消!$E:$E,$E86,合并抵消!$A:$A,L$2)) | M86: =浙江精准学!M86+知识跳跳!M86+海南精准学!M86+实时查!M86+目标准!M86+'SMART LEARNING HOLDING'!M86+'SMART AI LIMITED'!M86+'HK01'!M86-(-SUMIFS(合并抵消!$J:$J,合并抵消!$E:$E,$E86,合并抵消!$A:$A,M$2)+SUMIFS(合并抵消!$K:$K,合并抵消!$E:$E,$E86,合并抵消!$A:$A,M$2)) | ... Q86: =浙江精准学!Q86+知识跳跳!Q86+海南精准学!Q86+实时查!Q86+目标准!Q86+'SMART LEARNING HOLDING'!Q86+'SMART AI LIMITED'!Q86+'HK01'!Q86-(-SUMIFS(合并抵消!$J:$J,合并抵消!$E:$E,$E86,合并抵消!$A:$A,Q$2)+SUMIFS(合并抵消!$K:$K,合并抵消!$E:$E,$E86,合并抵消!$A:$A,Q$2)) | R86: =SUM(F86:Q86)
A87: 研发支出 | B87: 服务器算法充值 | C87: 服务器算法充值 | D87: 阿里云充值费用 | E87: Q1501 | F87: =浙江精准学!F87+知识跳跳!F87+海南精准学!F87+实时查!F87+目标准!F87+'SMART LEARNING HOLDING'!F87+'SMART AI LIMITED'!F87+'HK01'!F87-(-SUMIFS(合并抵消!$J:$J,合并抵消!$E:$E,$E87,合并抵消!$A:$A,F$2)+SUMIFS(合并抵消!$K:$K,合并抵消!$E:$E,$E87,合并抵消!$A:$A,F$2)) | G87: =浙江精准学!G87+知识跳跳!G87+海南精准学!G87+实时查!G87+目标准!G87+'SMART LEARNING HOLDING'!G87+'SMART AI LIMITED'!G87+'HK01'!G87-(-SUMIFS(合并抵消!$J:$J,合并抵消!$E:$E,$E87,合并抵消!$A:$A,G$2)+SUMIFS(合并抵消!$K:$K,合并抵消!$E:$E,$E87,合并抵消!$A:$A,G$2)) | H87: =浙江精准学!H87+知识跳跳!H87+海南精准学!H87+实时查!H87+目标准!H87+'SMART LEARNING HOLDING'!H87+'SMART AI LIMITED'!H87+'HK01'!H87-(-SUMIFS(合并抵消!$J:$J,合并抵消!$E:$E,$E87,合并抵消!$A:$A,H$2)+SUMIFS(合并抵消!$K:$K,合并抵消!$E:$E,$E87,合并抵消!$A:$A,H$2)) | I87: =浙江精准学!I87+知识跳跳!I87+海南精准学!I87+实时查!I87+目标准!I87+'SMART LEARNING HOLDING'!I87+'SMART AI LIMITED'!I87+'HK01'!I87-(-SUMIFS(合并抵消!$J:$J,合并抵消!$E:$E,$E87,合并抵消!$A:$A,I$2)+SUMIFS(合并抵消!$K:$K,合并抵消!$E:$E,$E87,合并抵消!$A:$A,I$2)) | J87: =浙江精准学!J87+知识跳跳!J87+海南精准学!J87+实时查!J87+目标准!J87+'SMART LEARNING HOLDING'!J87+'SMART AI LIMITED'!J87+'HK01'!J87-(-SUMIFS(合并抵消!$J:$J,合并抵消!$E:$E,$E87,合并抵消!$A:$A,J$2)+SUMIFS(合并抵消!$K:$K,合并抵消!$E:$E,$E87,合并抵消!$A:$A,J$2)) | K87: =浙江精准学!K87+知识跳跳!K87+海南精准学!K87+实时查!K87+目标准!K87+'SMART LEARNING HOLDING'!K87+'SMART AI LIMITED'!K87+'HK01'!K87-(-SUMIFS(合并抵消!$J:$J,合并抵消!$E:$E,$E87,合并抵消!$A:$A,K$2)+SUMIFS(合并抵消!$K:$K,合并抵消!$E:$E,$E87,合并抵消!$A:$A,K$2)) | L87: =浙江精准学!L87+知识跳跳!L87+海南精准学!L87+实时查!L87+目标准!L87+'SMART LEARNING HOLDING'!L87+'SMART AI LIMITED'!L87+'HK01'!L87-(-SUMIFS(合并抵消!$J:$J,合并抵消!$E:$E,$E87,合并抵消!$A:$A,L$2)+SUMIFS(合并抵消!$K:$K,合并抵消!$E:$E,$E87,合并抵消!$A:$A,L$2)) | M87: =浙江精准学!M87+知识跳跳!M87+海南精准学!M87+实时查!M87+目标准!M87+'SMART LEARNING HOLDING'!M87+'SMART AI LIMITED'!M87+'HK01'!M87-(-SUMIFS(合并抵消!$J:$J,合并抵消!$E:$E,$E87,合并抵消!$A:$A,M$2)+SUMIFS(合并抵消!$K:$K,合并抵消!$E:$E,$E87,合并抵消!$A:$A,M$2)) | ... Q87: =浙江精准学!Q87+知识跳跳!Q87+海南精准学!Q87+实时查!Q87+目标准!Q87+'SMART LEARNING HOLDING'!Q87+'SMART AI LIMITED'!Q87+'HK01'!Q87-(-SUMIFS(合并抵消!$J:$J,合并抵消!$E:$E,$E87,合并抵消!$A:$A,Q$2)+SUMIFS(合并抵消!$K:$K,合并抵消!$E:$E,$E87,合并抵消!$A:$A,Q$2)) | R87: =SUM(F87:Q87)
A88: 研发支出 | B88: 服务器算法充值 | D88: 微软充值费用 | E88: Q1502 | F88: =浙江精准学!F88+知识跳跳!F88+海南精准学!F88+实时查!F88+目标准!F88+'SMART LEARNING HOLDING'!F88+'SMART AI LIMITED'!F88+'HK01'!F88-(-SUMIFS(合并抵消!$J:$J,合并抵消!$E:$E,$E88,合并抵消!$A:$A,F$2)+SUMIFS(合并抵消!$K:$K,合并抵消!$E:$E,$E88,合并抵消!$A:$A,F$2)) | G88: =浙江精准学!G88+知识跳跳!G88+海南精准学!G88+实时查!G88+目标准!G88+'SMART LEARNING HOLDING'!G88+'SMART AI LIMITED'!G88+'HK01'!G88-(-SUMIFS(合并抵消!$J:$J,合并抵消!$E:$E,$E88,合并抵消!$A:$A,G$2)+SUMIFS(合并抵消!$K:$K,合并抵消!$E:$E,$E88,合并抵消!$A:$A,G$2)) | H88: =浙江精准学!H88+知识跳跳!H88+海南精准学!H88+实时查!H88+目标准!H88+'SMART LEARNING HOLDING'!H88+'SMART AI LIMITED'!H88+'HK01'!H88-(-SUMIFS(合并抵消!$J:$J,合并抵消!$E:$E,$E88,合并抵消!$A:$A,H$2)+SUMIFS(合并抵消!$K:$K,合并抵消!$E:$E,$E88,合并抵消!$A:$A,H$2)) | I88: =浙江精准学!I88+知识跳跳!I88+海南精准学!I88+实时查!I88+目标准!I88+'SMART LEARNING HOLDING'!I88+'SMART AI LIMITED'!I88+'HK01'!I88-(-SUMIFS(合并抵消!$J:$J,合并抵消!$E:$E,$E88,合并抵消!$A:$A,I$2)+SUMIFS(合并抵消!$K:$K,合并抵消!$E:$E,$E88,合并抵消!$A:$A,I$2)) | J88: =浙江精准学!J88+知识跳跳!J88+海南精准学!J88+实时查!J88+目标准!J88+'SMART LEARNING HOLDING'!J88+'SMART AI LIMITED'!J88+'HK01'!J88-(-SUMIFS(合并抵消!$J:$J,合并抵消!$E:$E,$E88,合并抵消!$A:$A,J$2)+SUMIFS(合并抵消!$K:$K,合并抵消!$E:$E,$E88,合并抵消!$A:$A,J$2)) | K88: =浙江精准学!K88+知识跳跳!K88+海南精准学!K88+实时查!K88+目标准!K88+'SMART LEARNING HOLDING'!K88+'SMART AI LIMITED'!K88+'HK01'!K88-(-SUMIFS(合并抵消!$J:$J,合并抵消!$E:$E,$E88,合并抵消!$A:$A,K$2)+SUMIFS(合并抵消!$K:$K,合并抵消!$E:$E,$E88,合并抵消!$A:$A,K$2)) | L88: =浙江精准学!L88+知识跳跳!L88+海南精准学!L88+实时查!L88+目标准!L88+'SMART LEARNING HOLDING'!L88+'SMART AI LIMITED'!L88+'HK01'!L88-(-SUMIFS(合并抵消!$J:$J,合并抵消!$E:$E,$E88,合并抵消!$A:$A,L$2)+SUMIFS(合并抵消!$K:$K,合并抵消!$E:$E,$E88,合并抵消!$A:$A,L$2)) | M88: =浙江精准学!M88+知识跳跳!M88+海南精准学!M88+实时查!M88+目标准!M88+'SMART LEARNING HOLDING'!M88+'SMART AI LIMITED'!M88+'HK01'!M88-(-SUMIFS(合并抵消!$J:$J,合并抵消!$E:$E,$E88,合并抵消!$A:$A,M$2)+SUMIFS(合并抵消!$K:$K,合并抵消!$E:$E,$E88,合并抵消!$A:$A,M$2)) | ... Q88: =浙江精准学!Q88+知识跳跳!Q88+海南精准学!Q88+实时查!Q88+目标准!Q88+'SMART LEARNING HOLDING'!Q88+'SMART AI LIMITED'!Q88+'HK01'!Q88-(-SUMIFS(合并抵消!$J:$J,合并抵消!$E:$E,$E88,合并抵消!$A:$A,Q$2)+SUMIFS(合并抵消!$K:$K,合并抵消!$E:$E,$E88,合并抵消!$A:$A,Q$2)) | R88: =SUM(F88:Q88)
A89: 研发支出 | B89: 服务器算法充值 | D89: kimi充值费用 | E89: Q1503 | F89: =浙江精准学!F89+知识跳跳!F89+海南精准学!F89+实时查!F89+目标准!F89+'SMART LEARNING HOLDING'!F89+'SMART AI LIMITED'!F89+'HK01'!F89-(-SUMIFS(合并抵消!$J:$J,合并抵消!$E:$E,$E89,合并抵消!$A:$A,F$2)+SUMIFS(合并抵消!$K:$K,合并抵消!$E:$E,$E89,合并抵消!$A:$A,F$2)) | G89: =浙江精准学!G89+知识跳跳!G89+海南精准学!G89+实时查!G89+目标准!G89+'SMART LEARNING HOLDING'!G89+'SMART AI LIMITED'!G89+'HK01'!G89-(-SUMIFS(合并抵消!$J:$J,合并抵消!$E:$E,$E89,合并抵消!$A:$A,G$2)+SUMIFS(合并抵消!$K:$K,合并抵消!$E:$E,$E89,合并抵消!$A:$A,G$2)) | H89: =浙江精准学!H89+知识跳跳!H89+海南精准学!H89+实时查!H89+目标准!H89+'SMART LEARNING HOLDING'!H89+'SMART AI LIMITED'!H89+'HK01'!H89-(-SUMIFS(合并抵消!$J:$J,合并抵消!$E:$E,$E89,合并抵消!$A:$A,H$2)+SUMIFS(合并抵消!$K:$K,合并抵消!$E:$E,$E89,合并抵消!$A:$A,H$2)) | I89: =浙江精准学!I89+知识跳跳!I89+海南精准学!I89+实时查!I89+目标准!I89+'SMART LEARNING HOLDING'!I89+'SMART AI LIMITED'!I89+'HK01'!I89-(-SUMIFS(合并抵消!$J:$J,合并抵消!$E:$E,$E89,合并抵消!$A:$A,I$2)+SUMIFS(合并抵消!$K:$K,合并抵消!$E:$E,$E89,合并抵消!$A:$A,I$2)) | J89: =浙江精准学!J89+知识跳跳!J89+海南精准学!J89+实时查!J89+目标准!J89+'SMART LEARNING HOLDING'!J89+'SMART AI LIMITED'!J89+'HK01'!J89-(-SUMIFS(合并抵消!$J:$J,合并抵消!$E:$E,$E89,合并抵消!$A:$A,J$2)+SUMIFS(合并抵消!$K:$K,合并抵消!$E:$E,$E89,合并抵消!$A:$A,J$2)) | K89: =浙江精准学!K89+知识跳跳!K89+海南精准学!K89+实时查!K89+目标准!K89+'SMART LEARNING HOLDING'!K89+'SMART AI LIMITED'!K89+'HK01'!K89-(-SUMIFS(合并抵消!$J:$J,合并抵消!$E:$E,$E89,合并抵消!$A:$A,K$2)+SUMIFS(合并抵消!$K:$K,合并抵消!$E:$E,$E89,合并抵消!$A:$A,K$2)) | L89: =浙江精准学!L89+知识跳跳!L89+海南精准学!L89+实时查!L89+目标准!L89+'SMART LEARNING HOLDING'!L89+'SMART AI LIMITED'!L89+'HK01'!L89-(-SUMIFS(合并抵消!$J:$J,合并抵消!$E:$E,$E89,合并抵消!$A:$A,L$2)+SUMIFS(合并抵消!$K:$K,合并抵消!$E:$E,$E89,合并抵消!$A:$A,L$2)) | M89: =浙江精准学!M89+知识跳跳!M89+海南精准学!M89+实时查!M89+目标准!M89+'SMART LEARNING HOLDING'!M89+'SMART AI LIMITED'!M89+'HK01'!M89-(-SUMIFS(合并抵消!$J:$J,合并抵消!$E:$E,$E89,合并抵消!$A:$A,M$2)+SUMIFS(合并抵消!$K:$K,合并抵消!$E:$E,$E89,合并抵消!$A:$A,M$2)) | ... Q89: =浙江精准学!Q89+知识跳跳!Q89+海南精准学!Q89+实时查!Q89+目标准!Q89+'SMART LEARNING HOLDING'!Q89+'SMART AI LIMITED'!Q89+'HK01'!Q89-(-SUMIFS(合并抵消!$J:$J,合并抵消!$E:$E,$E89,合并抵消!$A:$A,Q$2)+SUMIFS(合并抵消!$K:$K,合并抵消!$E:$E,$E89,合并抵消!$A:$A,Q$2)) | R89: =SUM(F89:Q89)
A90: 研发支出 | B90: 服务器算法充值 | D90: 智普AI充值费用 | E90: Q1504 | F90: =浙江精准学!F90+知识跳跳!F90+海南精准学!F90+实时查!F90+目标准!F90+'SMART LEARNING HOLDING'!F90+'SMART AI LIMITED'!F90+'HK01'!F90-(-SUMIFS(合并抵消!$J:$J,合并抵消!$E:$E,$E90,合并抵消!$A:$A,F$2)+SUMIFS(合并抵消!$K:$K,合并抵消!$E:$E,$E90,合并抵消!$A:$A,F$2)) | G90: =浙江精准学!G90+知识跳跳!G90+海南精准学!G90+实时查!G90+目标准!G90+'SMART LEARNING HOLDING'!G90+'SMART AI LIMITED'!G90+'HK01'!G90-(-SUMIFS(合并抵消!$J:$J,合并抵消!$E:$E,$E90,合并抵消!$A:$A,G$2)+SUMIFS(合并抵消!$K:$K,合并抵消!$E:$E,$E90,合并抵消!$A:$A,G$2)) | H90: =浙江精准学!H90+知识跳跳!H90+海南精准学!H90+实时查!H90+目标准!H90+'SMART LEARNING HOLDING'!H90+'SMART AI LIMITED'!H90+'HK01'!H90-(-SUMIFS(合并抵消!$J:$J,合并抵消!$E:$E,$E90,合并抵消!$A:$A,H$2)+SUMIFS(合并抵消!$K:$K,合并抵消!$E:$E,$E90,合并抵消!$A:$A,H$2)) | I90: =浙江精准学!I90+知识跳跳!I90+海南精准学!I90+实时查!I90+目标准!I90+'SMART LEARNING HOLDING'!I90+'SMART AI LIMITED'!I90+'HK01'!I90-(-SUMIFS(合并抵消!$J:$J,合并抵消!$E:$E,$E90,合并抵消!$A:$A,I$2)+SUMIFS(合并抵消!$K:$K,合并抵消!$E:$E,$E90,合并抵消!$A:$A,I$2)) | J90: =浙江精准学!J90+知识跳跳!J90+海南精准学!J90+实时查!J90+目标准!J90+'SMART LEARNING HOLDING'!J90+'SMART AI LIMITED'!J90+'HK01'!J90-(-SUMIFS(合并抵消!$J:$J,合并抵消!$E:$E,$E90,合并抵消!$A:$A,J$2)+SUMIFS(合并抵消!$K:$K,合并抵消!$E:$E,$E90,合并抵消!$A:$A,J$2)) | K90: =浙江精准学!K90+知识跳跳!K90+海南精准学!K90+实时查!K90+目标准!K90+'SMART LEARNING HOLDING'!K90+'SMART AI LIMITED'!K90+'HK01'!K90-(-SUMIFS(合并抵消!$J:$J,合并抵消!$E:$E,$E90,合并抵消!$A:$A,K$2)+SUMIFS(合并抵消!$K:$K,合并抵消!$E:$E,$E90,合并抵消!$A:$A,K$2)) | L90: =浙江精准学!L90+知识跳跳!L90+海南精准学!L90+实时查!L90+目标准!L90+'SMART LEARNING HOLDING'!L90+'SMART AI LIMITED'!L90+'HK01'!L90-(-SUMIFS(合并抵消!$J:$J,合并抵消!$E:$E,$E90,合并抵消!$A:$A,L$2)+SUMIFS(合并抵消!$K:$K,合并抵消!$E:$E,$E90,合并抵消!$A:$A,L$2)) | M90: =浙江精准学!M90+知识跳跳!M90+海南精准学!M90+实时查!M90+目标准!M90+'SMART LEARNING HOLDING'!M90+'SMART AI LIMITED'!M90+'HK01'!M90-(-SUMIFS(合并抵消!$J:$J,合并抵消!$E:$E,$E90,合并抵消!$A:$A,M$2)+SUMIFS(合并抵消!$K:$K,合并抵消!$E:$E,$E90,合并抵消!$A:$A,M$2)) | ... Q90: =浙江精准学!Q90+知识跳跳!Q90+海南精准学!Q90+实时查!Q90+目标准!Q90+'SMART LEARNING HOLDING'!Q90+'SMART AI LIMITED'!Q90+'HK01'!Q90-(-SUMIFS(合并抵消!$J:$J,合并抵消!$E:$E,$E90,合并抵消!$A:$A,Q$2)+SUMIFS(合并抵消!$K:$K,合并抵消!$E:$E,$E90,合并抵消!$A:$A,Q$2)) | R90: =SUM(F90:Q90)
A91: 研发支出 | B91: 服务器算法充值 | D91: 硅基流动充值费用 | E91: Q1506 | F91: =浙江精准学!F91+知识跳跳!F91+海南精准学!F91+实时查!F91+目标准!F91+'SMART LEARNING HOLDING'!F91+'SMART AI LIMITED'!F91+'HK01'!F91-(-SUMIFS(合并抵消!$J:$J,合并抵消!$E:$E,$E91,合并抵消!$A:$A,F$2)+SUMIFS(合并抵消!$K:$K,合并抵消!$E:$E,$E91,合并抵消!$A:$A,F$2)) | G91: =浙江精准学!G91+知识跳跳!G91+海南精准学!G91+实时查!G91+目标准!G91+'SMART LEARNING HOLDING'!G91+'SMART AI LIMITED'!G91+'HK01'!G91-(-SUMIFS(合并抵消!$J:$J,合并抵消!$E:$E,$E91,合并抵消!$A:$A,G$2)+SUMIFS(合并抵消!$K:$K,合并抵消!$E:$E,$E91,合并抵消!$A:$A,G$2)) | H91: =浙江精准学!H91+知识跳跳!H91+海南精准学!H91+实时查!H91+目标准!H91+'SMART LEARNING HOLDING'!H91+'SMART AI LIMITED'!H91+'HK01'!H91-(-SUMIFS(合并抵消!$J:$J,合并抵消!$E:$E,$E91,合并抵消!$A:$A,H$2)+SUMIFS(合并抵消!$K:$K,合并抵消!$E:$E,$E91,合并抵消!$A:$A,H$2)) | I91: =浙江精准学!I91+知识跳跳!I91+海南精准学!I91+实时查!I91+目标准!I91+'SMART LEARNING HOLDING'!I91+'SMART AI LIMITED'!I91+'HK01'!I91-(-SUMIFS(合并抵消!$J:$J,合并抵消!$E:$E,$E91,合并抵消!$A:$A,I$2)+SUMIFS(合并抵消!$K:$K,合并抵消!$E:$E,$E91,合并抵消!$A:$A,I$2)) | J91: =浙江精准学!J91+知识跳跳!J91+海南精准学!J91+实时查!J91+目标准!J91+'SMART LEARNING HOLDING'!J91+'SMART AI LIMITED'!J91+'HK01'!J91-(-SUMIFS(合并抵消!$J:$J,合并抵消!$E:$E,$E91,合并抵消!$A:$A,J$2)+SUMIFS(合并抵消!$K:$K,合并抵消!$E:$E,$E91,合并抵消!$A:$A,J$2)) | K91: =浙江精准学!K91+知识跳跳!K91+海南精准学!K91+实时查!K91+目标准!K91+'SMART LEARNING HOLDING'!K91+'SMART AI LIMITED'!K91+'HK01'!K91-(-SUMIFS(合并抵消!$J:$J,合并抵消!$E:$E,$E91,合并抵消!$A:$A,K$2)+SUMIFS(合并抵消!$K:$K,合并抵消!$E:$E,$E91,合并抵消!$A:$A,K$2)) | L91: =浙江精准学!L91+知识跳跳!L91+海南精准学!L91+实时查!L91+目标准!L91+'SMART LEARNING HOLDING'!L91+'SMART AI LIMITED'!L91+'HK01'!L91-(-SUMIFS(合并抵消!$J:$J,合并抵消!$E:$E,$E91,合并抵消!$A:$A,L$2)+SUMIFS(合并抵消!$K:$K,合并抵消!$E:$E,$E91,合并抵消!$A:$A,L$2)) | M91: =浙江精准学!M91+知识跳跳!M91+海南精准学!M91+实时查!M91+目标准!M91+'SMART LEARNING HOLDING'!M91+'SMART AI LIMITED'!M91+'HK01'!M91-(-SUMIFS(合并抵消!$J:$J,合并抵消!$E:$E,$E91,合并抵消!$A:$A,M$2)+SUMIFS(合并抵消!$K:$K,合并抵消!$E:$E,$E91,合并抵消!$A:$A,M$2)) | ... Q91: =浙江精准学!Q91+知识跳跳!Q91+海南精准学!Q91+实时查!Q91+目标准!Q91+'SMART LEARNING HOLDING'!Q91+'SMART AI LIMITED'!Q91+'HK01'!Q91-(-SUMIFS(合并抵消!$J:$J,合并抵消!$E:$E,$E91,合并抵消!$A:$A,Q$2)+SUMIFS(合并抵消!$K:$K,合并抵消!$E:$E,$E91,合并抵消!$A:$A,Q$2)) | R91: =SUM(F91:Q91)
A92: 研发支出 | B92: 服务器算法充值 | D92: 无问芯穹充值费用 | E92: Q1507 | F92: =浙江精准学!F92+知识跳跳!F92+海南精准学!F92+实时查!F92+目标准!F92+'SMART LEARNING HOLDING'!F92+'SMART AI LIMITED'!F92+'HK01'!F92-(-SUMIFS(合并抵消!$J:$J,合并抵消!$E:$E,$E92,合并抵消!$A:$A,F$2)+SUMIFS(合并抵消!$K:$K,合并抵消!$E:$E,$E92,合并抵消!$A:$A,F$2)) | G92: =浙江精准学!G92+知识跳跳!G92+海南精准学!G92+实时查!G92+目标准!G92+'SMART LEARNING HOLDING'!G92+'SMART AI LIMITED'!G92+'HK01'!G92-(-SUMIFS(合并抵消!$J:$J,合并抵消!$E:$E,$E92,合并抵消!$A:$A,G$2)+SUMIFS(合并抵消!$K:$K,合并抵消!$E:$E,$E92,合并抵消!$A:$A,G$2)) | H92: =浙江精准学!H92+知识跳跳!H92+海南精准学!H92+实时查!H92+目标准!H92+'SMART LEARNING HOLDING'!H92+'SMART AI LIMITED'!H92+'HK01'!H92-(-SUMIFS(合并抵消!$J:$J,合并抵消!$E:$E,$E92,合并抵消!$A:$A,H$2)+SUMIFS(合并抵消!$K:$K,合并抵消!$E:$E,$E92,合并抵消!$A:$A,H$2)) | I92: =浙江精准学!I92+知识跳跳!I92+海南精准学!I92+实时查!I92+目标准!I92+'SMART LEARNING HOLDING'!I92+'SMART AI LIMITED'!I92+'HK01'!I92-(-SUMIFS(合并抵消!$J:$J,合并抵消!$E:$E,$E92,合并抵消!$A:$A,I$2)+SUMIFS(合并抵消!$K:$K,合并抵消!$E:$E,$E92,合并抵消!$A:$A,I$2)) | J92: =浙江精准学!J92+知识跳跳!J92+海南精准学!J92+实时查!J92+目标准!J92+'SMART LEARNING HOLDING'!J92+'SMART AI LIMITED'!J92+'HK01'!J92-(-SUMIFS(合并抵消!$J:$J,合并抵消!$E:$E,$E92,合并抵消!$A:$A,J$2)+SUMIFS(合并抵消!$K:$K,合并抵消!$E:$E,$E92,合并抵消!$A:$A,J$2)) | K92: =浙江精准学!K92+知识跳跳!K92+海南精准学!K92+实时查!K92+目标准!K92+'SMART LEARNING HOLDING'!K92+'SMART AI LIMITED'!K92+'HK01'!K92-(-SUMIFS(合并抵消!$J:$J,合并抵消!$E:$E,$E92,合并抵消!$A:$A,K$2)+SUMIFS(合并抵消!$K:$K,合并抵消!$E:$E,$E92,合并抵消!$A:$A,K$2)) | L92: =浙江精准学!L92+知识跳跳!L92+海南精准学!L92+实时查!L92+目标准!L92+'SMART LEARNING HOLDING'!L92+'SMART AI LIMITED'!L92+'HK01'!L92-(-SUMIFS(合并抵消!$J:$J,合并抵消!$E:$E,$E92,合并抵消!$A:$A,L$2)+SUMIFS(合并抵消!$K:$K,合并抵消!$E:$E,$E92,合并抵消!$A:$A,L$2)) | M92: =浙江精准学!M92+知识跳跳!M92+海南精准学!M92+实时查!M92+目标准!M92+'SMART LEARNING HOLDING'!M92+'SMART AI LIMITED'!M92+'HK01'!M92-(-SUMIFS(合并抵消!$J:$J,合并抵消!$E:$E,$E92,合并抵消!$A:$A,M$2)+SUMIFS(合并抵消!$K:$K,合并抵消!$E:$E,$E92,合并抵消!$A:$A,M$2)) | ... Q92: =浙江精准学!Q92+知识跳跳!Q92+海南精准学!Q92+实时查!Q92+目标准!Q92+'SMART LEARNING HOLDING'!Q92+'SMART AI LIMITED'!Q92+'HK01'!Q92-(-SUMIFS(合并抵消!$J:$J,合并抵消!$E:$E,$E92,合并抵消!$A:$A,Q$2)+SUMIFS(合并抵消!$K:$K,合并抵消!$E:$E,$E92,合并抵消!$A:$A,Q$2)) | R92: =SUM(F92:Q92)
A93: 研发支出 | B93: 服务器算法充值 | D93: 其他服务器算法充值 | E93: Q1505 | F93: =浙江精准学!F93+知识跳跳!F93+海南精准学!F93+实时查!F93+目标准!F93+'SMART LEARNING HOLDING'!F93+'SMART AI LIMITED'!F93+'HK01'!F93-(-SUMIFS(合并抵消!$J:$J,合并抵消!$E:$E,$E93,合并抵消!$A:$A,F$2)+SUMIFS(合并抵消!$K:$K,合并抵消!$E:$E,$E93,合并抵消!$A:$A,F$2)) | G93: =浙江精准学!G93+知识跳跳!G93+海南精准学!G93+实时查!G93+目标准!G93+'SMART LEARNING HOLDING'!G93+'SMART AI LIMITED'!G93+'HK01'!G93-(-SUMIFS(合并抵消!$J:$J,合并抵消!$E:$E,$E93,合并抵消!$A:$A,G$2)+SUMIFS(合并抵消!$K:$K,合并抵消!$E:$E,$E93,合并抵消!$A:$A,G$2)) | H93: =浙江精准学!H93+知识跳跳!H93+海南精准学!H93+实时查!H93+目标准!H93+'SMART LEARNING HOLDING'!H93+'SMART AI LIMITED'!H93+'HK01'!H93-(-SUMIFS(合并抵消!$J:$J,合并抵消!$E:$E,$E93,合并抵消!$A:$A,H$2)+SUMIFS(合并抵消!$K:$K,合并抵消!$E:$E,$E93,合并抵消!$A:$A,H$2)) | I93: =浙江精准学!I93+知识跳跳!I93+海南精准学!I93+实时查!I93+目标准!I93+'SMART LEARNING HOLDING'!I93+'SMART AI LIMITED'!I93+'HK01'!I93-(-SUMIFS(合并抵消!$J:$J,合并抵消!$E:$E,$E93,合并抵消!$A:$A,I$2)+SUMIFS(合并抵消!$K:$K,合并抵消!$E:$E,$E93,合并抵消!$A:$A,I$2)) | J93: =浙江精准学!J93+知识跳跳!J93+海南精准学!J93+实时查!J93+目标准!J93+'SMART LEARNING HOLDING'!J93+'SMART AI LIMITED'!J93+'HK01'!J93-(-SUMIFS(合并抵消!$J:$J,合并抵消!$E:$E,$E93,合并抵消!$A:$A,J$2)+SUMIFS(合并抵消!$K:$K,合并抵消!$E:$E,$E93,合并抵消!$A:$A,J$2)) | K93: =浙江精准学!K93+知识跳跳!K93+海南精准学!K93+实时查!K93+目标准!K93+'SMART LEARNING HOLDING'!K93+'SMART AI LIMITED'!K93+'HK01'!K93-(-SUMIFS(合并抵消!$J:$J,合并抵消!$E:$E,$E93,合并抵消!$A:$A,K$2)+SUMIFS(合并抵消!$K:$K,合并抵消!$E:$E,$E93,合并抵消!$A:$A,K$2)) | L93: =浙江精准学!L93+知识跳跳!L93+海南精准学!L93+实时查!L93+目标准!L93+'SMART LEARNING HOLDING'!L93+'SMART AI LIMITED'!L93+'HK01'!L93-(-SUMIFS(合并抵消!$J:$J,合并抵消!$E:$E,$E93,合并抵消!$A:$A,L$2)+SUMIFS(合并抵消!$K:$K,合并抵消!$E:$E,$E93,合并抵消!$A:$A,L$2)) | M93: =浙江精准学!M93+知识跳跳!M93+海南精准学!M93+实时查!M93+目标准!M93+'SMART LEARNING HOLDING'!M93+'SMART AI LIMITED'!M93+'HK01'!M93-(-SUMIFS(合并抵消!$J:$J,合并抵消!$E:$E,$E93,合并抵消!$A:$A,M$2)+SUMIFS(合并抵消!$K:$K,合并抵消!$E:$E,$E93,合并抵消!$A:$A,M$2)) | ... Q93: =浙江精准学!Q93+知识跳跳!Q93+海南精准学!Q93+实时查!Q93+目标准!Q93+'SMART LEARNING HOLDING'!Q93+'SMART AI LIMITED'!Q93+'HK01'!Q93-(-SUMIFS(合并抵消!$J:$J,合并抵消!$E:$E,$E93,合并抵消!$A:$A,Q$2)+SUMIFS(合并抵消!$K:$K,合并抵消!$E:$E,$E93,合并抵消!$A:$A,Q$2)) | R93: =SUM(F93:Q93)
A94: 研发支出 | B94: 研发-服务费 | C94: 研发-服务费 | D94: 设计外包服务费 | E94: Q1601 | F94: =浙江精准学!F94+知识跳跳!F94+海南精准学!F94+实时查!F94+目标准!F94+'SMART LEARNING HOLDING'!F94+'SMART AI LIMITED'!F94+'HK01'!F94-(-SUMIFS(合并抵消!$J:$J,合并抵消!$E:$E,$E94,合并抵消!$A:$A,F$2)+SUMIFS(合并抵消!$K:$K,合并抵消!$E:$E,$E94,合并抵消!$A:$A,F$2)) | G94: =浙江精准学!G94+知识跳跳!G94+海南精准学!G94+实时查!G94+目标准!G94+'SMART LEARNING HOLDING'!G94+'SMART AI LIMITED'!G94+'HK01'!G94-(-SUMIFS(合并抵消!$J:$J,合并抵消!$E:$E,$E94,合并抵消!$A:$A,G$2)+SUMIFS(合并抵消!$K:$K,合并抵消!$E:$E,$E94,合并抵消!$A:$A,G$2)) | H94: =浙江精准学!H94+知识跳跳!H94+海南精准学!H94+实时查!H94+目标准!H94+'SMART LEARNING HOLDING'!H94+'SMART AI LIMITED'!H94+'HK01'!H94-(-SUMIFS(合并抵消!$J:$J,合并抵消!$E:$E,$E94,合并抵消!$A:$A,H$2)+SUMIFS(合并抵消!$K:$K,合并抵消!$E:$E,$E94,合并抵消!$A:$A,H$2)) | I94: =浙江精准学!I94+知识跳跳!I94+海南精准学!I94+实时查!I94+目标准!I94+'SMART LEARNING HOLDING'!I94+'SMART AI LIMITED'!I94+'HK01'!I94-(-SUMIFS(合并抵消!$J:$J,合并抵消!$E:$E,$E94,合并抵消!$A:$A,I$2)+SUMIFS(合并抵消!$K:$K,合并抵消!$E:$E,$E94,合并抵消!$A:$A,I$2)) | J94: =浙江精准学!J94+知识跳跳!J94+海南精准学!J94+实时查!J94+目标准!J94+'SMART LEARNING HOLDING'!J94+'SMART AI LIMITED'!J94+'HK01'!J94-(-SUMIFS(合并抵消!$J:$J,合并抵消!$E:$E,$E94,合并抵消!$A:$A,J$2)+SUMIFS(合并抵消!$K:$K,合并抵消!$E:$E,$E94,合并抵消!$A:$A,J$2)) | K94: =浙江精准学!K94+知识跳跳!K94+海南精准学!K94+实时查!K94+目标准!K94+'SMART LEARNING HOLDING'!K94+'SMART AI LIMITED'!K94+'HK01'!K94-(-SUMIFS(合并抵消!$J:$J,合并抵消!$E:$E,$E94,合并抵消!$A:$A,K$2)+SUMIFS(合并抵消!$K:$K,合并抵消!$E:$E,$E94,合并抵消!$A:$A,K$2)) | L94: =浙江精准学!L94+知识跳跳!L94+海南精准学!L94+实时查!L94+目标准!L94+'SMART LEARNING HOLDING'!L94+'SMART AI LIMITED'!L94+'HK01'!L94-(-SUMIFS(合并抵消!$J:$J,合并抵消!$E:$E,$E94,合并抵消!$A:$A,L$2)+SUMIFS(合并抵消!$K:$K,合并抵消!$E:$E,$E94,合并抵消!$A:$A,L$2)) | M94: =浙江精准学!M94+知识跳跳!M94+海南精准学!M94+实时查!M94+目标准!M94+'SMART LEARNING HOLDING'!M94+'SMART AI LIMITED'!M94+'HK01'!M94-(-SUMIFS(合并抵消!$J:$J,合并抵消!$E:$E,$E94,合并抵消!$A:$A,M$2)+SUMIFS(合并抵消!$K:$K,合并抵消!$E:$E,$E94,合并抵消!$A:$A,M$2)) | ... Q94: =浙江精准学!Q94+知识跳跳!Q94+海南精准学!Q94+实时查!Q94+目标准!Q94+'SMART LEARNING HOLDING'!Q94+'SMART AI LIMITED'!Q94+'HK01'!Q94-(-SUMIFS(合并抵消!$J:$J,合并抵消!$E:$E,$E94,合并抵消!$A:$A,Q$2)+SUMIFS(合并抵消!$K:$K,合并抵消!$E:$E,$E94,合并抵消!$A:$A,Q$2)) | R94: =SUM(F94:Q94)
A95: 研发支出 | B95: 研发-服务费 | D95: AI技术外包服务费 | E95: Q1602 | F95: =浙江精准学!F95+知识跳跳!F95+海南精准学!F95+实时查!F95+目标准!F95+'SMART LEARNING HOLDING'!F95+'SMART AI LIMITED'!F95+'HK01'!F95-(-SUMIFS(合并抵消!$J:$J,合并抵消!$E:$E,$E95,合并抵消!$A:$A,F$2)+SUMIFS(合并抵消!$K:$K,合并抵消!$E:$E,$E95,合并抵消!$A:$A,F$2)) | G95: =浙江精准学!G95+知识跳跳!G95+海南精准学!G95+实时查!G95+目标准!G95+'SMART LEARNING HOLDING'!G95+'SMART AI LIMITED'!G95+'HK01'!G95-(-SUMIFS(合并抵消!$J:$J,合并抵消!$E:$E,$E95,合并抵消!$A:$A,G$2)+SUMIFS(合并抵消!$K:$K,合并抵消!$E:$E,$E95,合并抵消!$A:$A,G$2)) | H95: =浙江精准学!H95+知识跳跳!H95+海南精准学!H95+实时查!H95+目标准!H95+'SMART LEARNING HOLDING'!H95+'SMART AI LIMITED'!H95+'HK01'!H95-(-SUMIFS(合并抵消!$J:$J,合并抵消!$E:$E,$E95,合并抵消!$A:$A,H$2)+SUMIFS(合并抵消!$K:$K,合并抵消!$E:$E,$E95,合并抵消!$A:$A,H$2)) | I95: =浙江精准学!I95+知识跳跳!I95+海南精准学!I95+实时查!I95+目标准!I95+'SMART LEARNING HOLDING'!I95+'SMART AI LIMITED'!I95+'HK01'!I95-(-SUMIFS(合并抵消!$J:$J,合并抵消!$E:$E,$E95,合并抵消!$A:$A,I$2)+SUMIFS(合并抵消!$K:$K,合并抵消!$E:$E,$E95,合并抵消!$A:$A,I$2)) | J95: =浙江精准学!J95+知识跳跳!J95+海南精准学!J95+实时查!J95+目标准!J95+'SMART LEARNING HOLDING'!J95+'SMART AI LIMITED'!J95+'HK01'!J95-(-SUMIFS(合并抵消!$J:$J,合并抵消!$E:$E,$E95,合并抵消!$A:$A,J$2)+SUMIFS(合并抵消!$K:$K,合并抵消!$E:$E,$E95,合并抵消!$A:$A,J$2)) | K95: =浙江精准学!K95+知识跳跳!K95+海南精准学!K95+实时查!K95+目标准!K95+'SMART LEARNING HOLDING'!K95+'SMART AI LIMITED'!K95+'HK01'!K95-(-SUMIFS(合并抵消!$J:$J,合并抵消!$E:$E,$E95,合并抵消!$A:$A,K$2)+SUMIFS(合并抵消!$K:$K,合并抵消!$E:$E,$E95,合并抵消!$A:$A,K$2)) | L95: =浙江精准学!L95+知识跳跳!L95+海南精准学!L95+实时查!L95+目标准!L95+'SMART LEARNING HOLDING'!L95+'SMART AI LIMITED'!L95+'HK01'!L95-(-SUMIFS(合并抵消!$J:$J,合并抵消!$E:$E,$E95,合并抵消!$A:$A,L$2)+SUMIFS(合并抵消!$K:$K,合并抵消!$E:$E,$E95,合并抵消!$A:$A,L$2)) | M95: =浙江精准学!M95+知识跳跳!M95+海南精准学!M95+实时查!M95+目标准!M95+'SMART LEARNING HOLDING'!M95+'SMART AI LIMITED'!M95+'HK01'!M95-(-SUMIFS(合并抵消!$J:$J,合并抵消!$E:$E,$E95,合并抵消!$A:$A,M$2)+SUMIFS(合并抵消!$K:$K,合并抵消!$E:$E,$E95,合并抵消!$A:$A,M$2)) | ... Q95: =浙江精准学!Q95+知识跳跳!Q95+海南精准学!Q95+实时查!Q95+目标准!Q95+'SMART LEARNING HOLDING'!Q95+'SMART AI LIMITED'!Q95+'HK01'!Q95-(-SUMIFS(合并抵消!$J:$J,合并抵消!$E:$E,$E95,合并抵消!$A:$A,Q$2)+SUMIFS(合并抵消!$K:$K,合并抵消!$E:$E,$E95,合并抵消!$A:$A,Q$2)) | R95: =SUM(F95:Q95)
A96: 研发支出 | B96: 研发-服务费 | D96: 知识产权服务费 | E96: Q1603 | F96: =浙江精准学!F96+知识跳跳!F96+海南精准学!F96+实时查!F96+目标准!F96+'SMART LEARNING HOLDING'!F96+'SMART AI LIMITED'!F96+'HK01'!F96-(-SUMIFS(合并抵消!$J:$J,合并抵消!$E:$E,$E96,合并抵消!$A:$A,F$2)+SUMIFS(合并抵消!$K:$K,合并抵消!$E:$E,$E96,合并抵消!$A:$A,F$2)) | G96: =浙江精准学!G96+知识跳跳!G96+海南精准学!G96+实时查!G96+目标准!G96+'SMART LEARNING HOLDING'!G96+'SMART AI LIMITED'!G96+'HK01'!G96-(-SUMIFS(合并抵消!$J:$J,合并抵消!$E:$E,$E96,合并抵消!$A:$A,G$2)+SUMIFS(合并抵消!$K:$K,合并抵消!$E:$E,$E96,合并抵消!$A:$A,G$2)) | H96: =浙江精准学!H96+知识跳跳!H96+海南精准学!H96+实时查!H96+目标准!H96+'SMART LEARNING HOLDING'!H96+'SMART AI LIMITED'!H96+'HK01'!H96-(-SUMIFS(合并抵消!$J:$J,合并抵消!$E:$E,$E96,合并抵消!$A:$A,H$2)+SUMIFS(合并抵消!$K:$K,合并抵消!$E:$E,$E96,合并抵消!$A:$A,H$2)) | I96: =浙江精准学!I96+知识跳跳!I96+海南精准学!I96+实时查!I96+目标准!I96+'SMART LEARNING HOLDING'!I96+'SMART AI LIMITED'!I96+'HK01'!I96-(-SUMIFS(合并抵消!$J:$J,合并抵消!$E:$E,$E96,合并抵消!$A:$A,I$2)+SUMIFS(合并抵消!$K:$K,合并抵消!$E:$E,$E96,合并抵消!$A:$A,I$2)) | J96: =浙江精准学!J96+知识跳跳!J96+海南精准学!J96+实时查!J96+目标准!J96+'SMART LEARNING HOLDING'!J96+'SMART AI LIMITED'!J96+'HK01'!J96-(-SUMIFS(合并抵消!$J:$J,合并抵消!$E:$E,$E96,合并抵消!$A:$A,J$2)+SUMIFS(合并抵消!$K:$K,合并抵消!$E:$E,$E96,合并抵消!$A:$A,J$2)) | K96: =浙江精准学!K96+知识跳跳!K96+海南精准学!K96+实时查!K96+目标准!K96+'SMART LEARNING HOLDING'!K96+'SMART AI LIMITED'!K96+'HK01'!K96-(-SUMIFS(合并抵消!$J:$J,合并抵消!$E:$E,$E96,合并抵消!$A:$A,K$2)+SUMIFS(合并抵消!$K:$K,合并抵消!$E:$E,$E96,合并抵消!$A:$A,K$2)) | L96: =浙江精准学!L96+知识跳跳!L96+海南精准学!L96+实时查!L96+目标准!L96+'SMART LEARNING HOLDING'!L96+'SMART AI LIMITED'!L96+'HK01'!L96-(-SUMIFS(合并抵消!$J:$J,合并抵消!$E:$E,$E96,合并抵消!$A:$A,L$2)+SUMIFS(合并抵消!$K:$K,合并抵消!$E:$E,$E96,合并抵消!$A:$A,L$2)) | M96: =浙江精准学!M96+知识跳跳!M96+海南精准学!M96+实时查!M96+目标准!M96+'SMART LEARNING HOLDING'!M96+'SMART AI LIMITED'!M96+'HK01'!M96-(-SUMIFS(合并抵消!$J:$J,合并抵消!$E:$E,$E96,合并抵消!$A:$A,M$2)+SUMIFS(合并抵消!$K:$K,合并抵消!$E:$E,$E96,合并抵消!$A:$A,M$2)) | ... Q96: =浙江精准学!Q96+知识跳跳!Q96+海南精准学!Q96+实时查!Q96+目标准!Q96+'SMART LEARNING HOLDING'!Q96+'SMART AI LIMITED'!Q96+'HK01'!Q96-(-SUMIFS(合并抵消!$J:$J,合并抵消!$E:$E,$E96,合并抵消!$A:$A,Q$2)+SUMIFS(合并抵消!$K:$K,合并抵消!$E:$E,$E96,合并抵消!$A:$A,Q$2)) | R96: =SUM(F96:Q96)
A97: 研发支出 | B97: 研发-其他费用 | C97: 研发-费用报销 | D97: 研发员工报销 | E97: Q1701 | F97: =浙江精准学!F97+知识跳跳!F97+海南精准学!F97+实时查!F97+目标准!F97+'SMART LEARNING HOLDING'!F97+'SMART AI LIMITED'!F97+'HK01'!F97-(-SUMIFS(合并抵消!$J:$J,合并抵消!$E:$E,$E97,合并抵消!$A:$A,F$2)+SUMIFS(合并抵消!$K:$K,合并抵消!$E:$E,$E97,合并抵消!$A:$A,F$2)) | G97: =浙江精准学!G97+知识跳跳!G97+海南精准学!G97+实时查!G97+目标准!G97+'SMART LEARNING HOLDING'!G97+'SMART AI LIMITED'!G97+'HK01'!G97-(-SUMIFS(合并抵消!$J:$J,合并抵消!$E:$E,$E97,合并抵消!$A:$A,G$2)+SUMIFS(合并抵消!$K:$K,合并抵消!$E:$E,$E97,合并抵消!$A:$A,G$2)) | H97: =浙江精准学!H97+知识跳跳!H97+海南精准学!H97+实时查!H97+目标准!H97+'SMART LEARNING HOLDING'!H97+'SMART AI LIMITED'!H97+'HK01'!H97-(-SUMIFS(合并抵消!$J:$J,合并抵消!$E:$E,$E97,合并抵消!$A:$A,H$2)+SUMIFS(合并抵消!$K:$K,合并抵消!$E:$E,$E97,合并抵消!$A:$A,H$2)) | I97: =浙江精准学!I97+知识跳跳!I97+海南精准学!I97+实时查!I97+目标准!I97+'SMART LEARNING HOLDING'!I97+'SMART AI LIMITED'!I97+'HK01'!I97-(-SUMIFS(合并抵消!$J:$J,合并抵消!$E:$E,$E97,合并抵消!$A:$A,I$2)+SUMIFS(合并抵消!$K:$K,合并抵消!$E:$E,$E97,合并抵消!$A:$A,I$2)) | J97: =浙江精准学!J97+知识跳跳!J97+海南精准学!J97+实时查!J97+目标准!J97+'SMART LEARNING HOLDING'!J97+'SMART AI LIMITED'!J97+'HK01'!J97-(-SUMIFS(合并抵消!$J:$J,合并抵消!$E:$E,$E97,合并抵消!$A:$A,J$2)+SUMIFS(合并抵消!$K:$K,合并抵消!$E:$E,$E97,合并抵消!$A:$A,J$2)) | K97: =浙江精准学!K97+知识跳跳!K97+海南精准学!K97+实时查!K97+目标准!K97+'SMART LEARNING HOLDING'!K97+'SMART AI LIMITED'!K97+'HK01'!K97-(-SUMIFS(合并抵消!$J:$J,合并抵消!$E:$E,$E97,合并抵消!$A:$A,K$2)+SUMIFS(合并抵消!$K:$K,合并抵消!$E:$E,$E97,合并抵消!$A:$A,K$2)) | L97: =浙江精准学!L97+知识跳跳!L97+海南精准学!L97+实时查!L97+目标准!L97+'SMART LEARNING HOLDING'!L97+'SMART AI LIMITED'!L97+'HK01'!L97-(-SUMIFS(合并抵消!$J:$J,合并抵消!$E:$E,$E97,合并抵消!$A:$A,L$2)+SUMIFS(合并抵消!$K:$K,合并抵消!$E:$E,$E97,合并抵消!$A:$A,L$2)) | M97: =浙江精准学!M97+知识跳跳!M97+海南精准学!M97+实时查!M97+目标准!M97+'SMART LEARNING HOLDING'!M97+'SMART AI LIMITED'!M97+'HK01'!M97-(-SUMIFS(合并抵消!$J:$J,合并抵消!$E:$E,$E97,合并抵消!$A:$A,M$2)+SUMIFS(合并抵消!$K:$K,合并抵消!$E:$E,$E97,合并抵消!$A:$A,M$2)) | ... Q97: =浙江精准学!Q97+知识跳跳!Q97+海南精准学!Q97+实时查!Q97+目标准!Q97+'SMART LEARNING HOLDING'!Q97+'SMART AI LIMITED'!Q97+'HK01'!Q97-(-SUMIFS(合并抵消!$J:$J,合并抵消!$E:$E,$E97,合并抵消!$A:$A,Q$2)+SUMIFS(合并抵消!$K:$K,合并抵消!$E:$E,$E97,合并抵消!$A:$A,Q$2)) | R97: =SUM(F97:Q97)
A98: 研发支出合计 | F98: =SUM(F70:F97) | G98: =SUM(G70:G97) | H98: =SUM(H70:H97) | I98: =SUM(I70:I97) | J98: =SUM(J70:J97) | K98: =SUM(K70:K97) | L98: =SUM(L70:L97) | M98: =SUM(M70:M97) | ... Q98: =SUM(Q70:Q97) | R98: =SUM(F98:Q98)
A99: 销售费用 | B99: 品牌建设 | C99: 品牌建设 | D99: 媒体采购 | E99: Q1801 | F99: =浙江精准学!F99+知识跳跳!F99+海南精准学!F99+实时查!F99+目标准!F99+'SMART LEARNING HOLDING'!F99+'SMART AI LIMITED'!F99+'HK01'!F99-(-SUMIFS(合并抵消!$J:$J,合并抵消!$E:$E,$E99,合并抵消!$A:$A,F$2)+SUMIFS(合并抵消!$K:$K,合并抵消!$E:$E,$E99,合并抵消!$A:$A,F$2)) | G99: =浙江精准学!G99+知识跳跳!G99+海南精准学!G99+实时查!G99+目标准!G99+'SMART LEARNING HOLDING'!G99+'SMART AI LIMITED'!G99+'HK01'!G99-(-SUMIFS(合并抵消!$J:$J,合并抵消!$E:$E,$E99,合并抵消!$A:$A,G$2)+SUMIFS(合并抵消!$K:$K,合并抵消!$E:$E,$E99,合并抵消!$A:$A,G$2)) | H99: =浙江精准学!H99+知识跳跳!H99+海南精准学!H99+实时查!H99+目标准!H99+'SMART LEARNING HOLDING'!H99+'SMART AI LIMITED'!H99+'HK01'!H99-(-SUMIFS(合并抵消!$J:$J,合并抵消!$E:$E,$E99,合并抵消!$A:$A,H$2)+SUMIFS(合并抵消!$K:$K,合并抵消!$E:$E,$E99,合并抵消!$A:$A,H$2)) | I99: =浙江精准学!I99+知识跳跳!I99+海南精准学!I99+实时查!I99+目标准!I99+'SMART LEARNING HOLDING'!I99+'SMART AI LIMITED'!I99+'HK01'!I99-(-SUMIFS(合并抵消!$J:$J,合并抵消!$E:$E,$E99,合并抵消!$A:$A,I$2)+SUMIFS(合并抵消!$K:$K,合并抵消!$E:$E,$E99,合并抵消!$A:$A,I$2)) | J99: =浙江精准学!J99+知识跳跳!J99+海南精准学!J99+实时查!J99+目标准!J99+'SMART LEARNING HOLDING'!J99+'SMART AI LIMITED'!J99+'HK01'!J99-(-SUMIFS(合并抵消!$J:$J,合并抵消!$E:$E,$E99,合并抵消!$A:$A,J$2)+SUMIFS(合并抵消!$K:$K,合并抵消!$E:$E,$E99,合并抵消!$A:$A,J$2)) | K99: =浙江精准学!K99+知识跳跳!K99+海南精准学!K99+实时查!K99+目标准!K99+'SMART LEARNING HOLDING'!K99+'SMART AI LIMITED'!K99+'HK01'!K99-(-SUMIFS(合并抵消!$J:$J,合并抵消!$E:$E,$E99,合并抵消!$A:$A,K$2)+SUMIFS(合并抵消!$K:$K,合并抵消!$E:$E,$E99,合并抵消!$A:$A,K$2)) | L99: =浙江精准学!L99+知识跳跳!L99+海南精准学!L99+实时查!L99+目标准!L99+'SMART LEARNING HOLDING'!L99+'SMART AI LIMITED'!L99+'HK01'!L99-(-SUMIFS(合并抵消!$J:$J,合并抵消!$E:$E,$E99,合并抵消!$A:$A,L$2)+SUMIFS(合并抵消!$K:$K,合并抵消!$E:$E,$E99,合并抵消!$A:$A,L$2)) | M99: =浙江精准学!M99+知识跳跳!M99+海南精准学!M99+实时查!M99+目标准!M99+'SMART LEARNING HOLDING'!M99+'SMART AI LIMITED'!M99+'HK01'!M99-(-SUMIFS(合并抵消!$J:$J,合并抵消!$E:$E,$E99,合并抵消!$A:$A,M$2)+SUMIFS(合并抵消!$K:$K,合并抵消!$E:$E,$E99,合并抵消!$A:$A,M$2)) | ... Q99: =浙江精准学!Q99+知识跳跳!Q99+海南精准学!Q99+实时查!Q99+目标准!Q99+'SMART LEARNING HOLDING'!Q99+'SMART AI LIMITED'!Q99+'HK01'!Q99-(-SUMIFS(合并抵消!$J:$J,合并抵消!$E:$E,$E99,合并抵消!$A:$A,Q$2)+SUMIFS(合并抵消!$K:$K,合并抵消!$E:$E,$E99,合并抵消!$A:$A,Q$2)) | R99: =SUM(F99:Q99)
A100: 销售费用 | B100: 品牌建设 | D100: 舆情服务 | E100: Q1802 | F100: =浙江精准学!F100+知识跳跳!F100+海南精准学!F100+实时查!F100+目标准!F100+'SMART LEARNING HOLDING'!F100+'SMART AI LIMITED'!F100+'HK01'!F100-(-SUMIFS(合并抵消!$J:$J,合并抵消!$E:$E,$E100,合并抵消!$A:$A,F$2)+SUMIFS(合并抵消!$K:$K,合并抵消!$E:$E,$E100,合并抵消!$A:$A,F$2)) | G100: =浙江精准学!G100+知识跳跳!G100+海南精准学!G100+实时查!G100+目标准!G100+'SMART LEARNING HOLDING'!G100+'SMART AI LIMITED'!G100+'HK01'!G100-(-SUMIFS(合并抵消!$J:$J,合并抵消!$E:$E,$E100,合并抵消!$A:$A,G$2)+SUMIFS(合并抵消!$K:$K,合并抵消!$E:$E,$E100,合并抵消!$A:$A,G$2)) | H100: =浙江精准学!H100+知识跳跳!H100+海南精准学!H100+实时查!H100+目标准!H100+'SMART LEARNING HOLDING'!H100+'SMART AI LIMITED'!H100+'HK01'!H100-(-SUMIFS(合并抵消!$J:$J,合并抵消!$E:$E,$E100,合并抵消!$A:$A,H$2)+SUMIFS(合并抵消!$K:$K,合并抵消!$E:$E,$E100,合并抵消!$A:$A,H$2)) | I100: =浙江精准学!I100+知识跳跳!I100+海南精准学!I100+实时查!I100+目标准!I100+'SMART LEARNING HOLDING'!I100+'SMART AI LIMITED'!I100+'HK01'!I100-(-SUMIFS(合并抵消!$J:$J,合并抵消!$E:$E,$E100,合并抵消!$A:$A,I$2)+SUMIFS(合并抵消!$K:$K,合并抵消!$E:$E,$E100,合并抵消!$A:$A,I$2)) | J100: =浙江精准学!J100+知识跳跳!J100+海南精准学!J100+实时查!J100+目标准!J100+'SMART LEARNING HOLDING'!J100+'SMART AI LIMITED'!J100+'HK01'!J100-(-SUMIFS(合并抵消!$J:$J,合并抵消!$E:$E,$E100,合并抵消!$A:$A,J$2)+SUMIFS(合并抵消!$K:$K,合并抵消!$E:$E,$E100,合并抵消!$A:$A,J$2)) | K100: =浙江精准学!K100+知识跳跳!K100+海南精准学!K100+实时查!K100+目标准!K100+'SMART LEARNING HOLDING'!K100+'SMART AI LIMITED'!K100+'HK01'!K100-(-SUMIFS(合并抵消!$J:$J,合并抵消!$E:$E,$E100,合并抵消!$A:$A,K$2)+SUMIFS(合并抵消!$K:$K,合并抵消!$E:$E,$E100,合并抵消!$A:$A,K$2)) | L100: =浙江精准学!L100+知识跳跳!L100+海南精准学!L100+实时查!L100+目标准!L100+'SMART LEARNING HOLDING'!L100+'SMART AI LIMITED'!L100+'HK01'!L100-(-SUMIFS(合并抵消!$J:$J,合并抵消!$E:$E,$E100,合并抵消!$A:$A,L$2)+SUMIFS(合并抵消!$K:$K,合并抵消!$E:$E,$E100,合并抵消!$A:$A,L$2)) | M100: =浙江精准学!M100+知识跳跳!M100+海南精准学!M100+实时查!M100+目标准!M100+'SMART LEARNING HOLDING'!M100+'SMART AI LIMITED'!M100+'HK01'!M100-(-SUMIFS(合并抵消!$J:$J,合并抵消!$E:$E,$E100,合并抵消!$A:$A,M$2)+SUMIFS(合并抵消!$K:$K,合并抵消!$E:$E,$E100,合并抵消!$A:$A,M$2)) | ... Q100: =浙江精准学!Q100+知识跳跳!Q100+海南精准学!Q100+实时查!Q100+目标准!Q100+'SMART LEARNING HOLDING'!Q100+'SMART AI LIMITED'!Q100+'HK01'!Q100-(-SUMIFS(合并抵消!$J:$J,合并抵消!$E:$E,$E100,合并抵消!$A:$A,Q$2)+SUMIFS(合并抵消!$K:$K,合并抵消!$E:$E,$E100,合并抵消!$A:$A,Q$2)) | R100: =SUM(F100:Q100)
...

Sheet 浙江精准学
A1: 公司：浙江精准学
A2: 一级 | B2: 二级 | C2: 二级 | D2: 三级 | E2: 三级科目对应编码 | F2: 1月 | G2: 2月 | H2: 3月 | I2: 4月 | J2: 5月 | K2: 6月 | L2: 7月 | M2: 8月 | N2: 9月 | O2: 10月 | P2: 11月 | Q2: 12月 | R2: 本年合计
A3: 收入 | B3: 业务收入 | C3: 业务收入 | D3: 平台硬件销售收入 | E3: Q0101 | F3: =SUMIFS('1月数据源'!I:I,'1月数据源'!D:D,E3,'1月数据源'!F:F,"浙江精准学科技有限公司")-SUMIFS('1月数据源'!J:J,'1月数据源'!D:D,E3,'1月数据源'!F:F,"浙江精准学科技有限公司") | G3: =SUMIFS('2月数据源'!I:I,'2月数据源'!D:D,E3,'2月数据源'!F:F,"浙江精准学科技有限公司")-SUMIFS('2月数据源'!J:J,'2月数据源'!D:D,E3,'2月数据源'!F:F,"浙江精准学科技有限公司") | H3: =SUMIFS('3月数据源'!I:I,'3月数据源'!D:D,E3,'3月数据源'!F:F,"浙江精准学科技有限公司")-SUMIFS('3月数据源'!J:J,'3月数据源'!D:D,E3,'3月数据源'!F:F,"浙江精准学科技有限公司") | I3: =SUMIFS('4月数据源'!I:I,'4月数据源'!D:D,E3,'4月数据源'!F:F,"浙江精准学科技有限公司")-SUMIFS('4月数据源'!J:J,'4月数据源'!D:D,E3,'4月数据源'!F:F,"浙江精准学科技有限公司") | J3: =SUMIFS('5月数据源'!I:I,'5月数据源'!D:D,E3,'5月数据源'!F:F,"浙江精准学科技有限公司")-SUMIFS('5月数据源'!J:J,'5月数据源'!D:D,E3,'5月数据源'!F:F,"浙江精准学科技有限公司") | K3: =SUMIFS('6月数据源'!$I:$I,'6月数据源'!$D:$D,$E3,'6月数据源'!$F:$F,"浙江精准学科技有限公司")-SUMIFS('6月数据源'!$J:$J,'6月数据源'!$D:$D,$E3,'6月数据源'!$F:$F,"浙江精准学科技有限公司") | L3: =SUMIFS('7月数据源'!$I:$I,'7月数据源'!$D:$D,$E3,'7月数据源'!$F:$F,"浙江精准学科技有限公司")-SUMIFS('7月数据源'!$J:$J,'7月数据源'!$D:$D,$E3,'7月数据源'!$F:$F,"浙江精准学科技有限公司") | M3: =SUMIFS('8月数据源'!$I:$I,'8月数据源'!$D:$D,$E3,'8月数据源'!$F:$F,"浙江精准学科技有限公司")-SUMIFS('8月数据源'!$J:$J,'8月数据源'!$D:$D,$E3,'8月数据源'!$F:$F,"浙江精准学科技有限公司") | N3: =SUMIFS('9月数据源'!$I:$I,'9月数据源'!$D:$D,$E3,'9月数据源'!$F:$F,"浙江精准学科技有限公司")-SUMIFS('9月数据源'!$J:$J,'9月数据源'!$D:$D,$E3,'9月数据源'!$F:$F,"浙江精准学科技有限公司") | O3: =SUMIFS('10月数据源'!$I:$I,'10月数据源'!$D:$D,$E3,'10月数据源'!$F:$F,"浙江精准学科技有限公司")-SUMIFS('10月数据源'!$J:$J,'10月数据源'!$D:$D,$E3,'10月数据源'!$F:$F,"浙江精准学科技有限公司") | P3: =SUMIFS('11月数据源'!$I:$I,'11月数据源'!$D:$D,$E3,'11月数据源'!$F:$F,"浙江精准学科技有限公司")-SUMIFS('11月数据源'!$J:$J,'11月数据源'!$D:$D,$E3,'11月数据源'!$F:$F,"浙江精准学科技有限公司") | Q3: =SUMIFS('12月数据源'!$I:$I,'12月数据源'!$D:$D,$E3,'12月数据源'!$F:$F,"浙江精准学科技有限公司")-SUMIFS('12月数据源'!$J:$J,'12月数据源'!$D:$D,$E3,'12月数据源'!$F:$F,"浙江精准学科技有限公司")
